Workbook
Name Discount: #REF!
Name Discount: #REF!
Name Discount: #REF!
Name Discount: #REF!
Name Discount: #REF!
Name Discount: #REF!
Name Discount: #REF!
Name Discount: #REF!
Name Discount: #REF!
Name Discount: #REF!
Name Discount: #REF!
Name Discount: #REF!
Name Discount: #REF!
Name Discount: #REF!
Name Discount: #REF!

Sheet Cost Data
A1: Division | B1: 2
B2: 01 00 00 | C2: General Requirements
B3: 01 11 00 | C3: Preconstruction Costs | D3: ='1'!K24 -> 0
B4: 01 31 00 | C4: Project Management and Coordination | D4: ='1'!K35 -> 165000
B5: 01 41 00 | C5: Permits | D5: ='1'!K67 -> 3000
B6: 01 45 00 | C6: Quality Control | D6: ='1'!K76 -> 8000
B7: 01 51 00 | C7: Temporary Utilities | D7: ='1'!K87 -> 15000
B8: 01 52 00 | C8: Construction Facilities | D8: ='1'!K97 -> 35468.079
B9: 01 54 00 | C9: Construction Aids | D9: ='1'!K105 -> 203313.04
B10: 01 56 00 | C10: Temporary Barriers & Enclosures | D10: ='1'!K128 -> 25000
B11: 01 74 00 | C11: Cleaning & Waste Management | D11: ='1'!K136 -> 54500
A13: Division | B13: 2
B15: 02 00 00 | C15: Existing Conditions
B16: 02 41 00 | C16: Demolition | D16: ='2'!K26 -> 0
B17: 02 82 00 | C17: Asbestos Remediation | D17: ='2'!K37 -> 0
B18: 02 83 00 | C18: Trenching | D18: ='2'!K48 -> 0
A21: Division | B21: 3
B22: 03 00 00 | C22: Concrete
B23: 03 11 00 | C23: Concrete Forming | D23: ='3'!K26 -> 302400
B24: 03 20 00 | C24: Concrete Reinforcing | D24: ='3'!K37 -> 0
B25: 03 30 00 | C25: Cast-in-Place Concrete | D25: ='3'!K50 -> 177795.86
B26: 03 35 00 | C26: Concrete Finishing | D26: ='3'!K59 -> 44527
B27: 03 40 00 | C27: Precast Concrete | D27: ='3'!K70 -> 77850
B28: 03 60 00 | C28: Grouting | D28: ='3'!K79 -> 68035
A31: Division | B31: 4
B32: 04 00 00 | C32: Masonry
B33: 04 20 00 | C33: Unit Masonry | D33: ='4'!K26 -> 140360
B34: 04 43 00 | C34: Stone Masonry | D34: ='4'!K37 -> 0
A36: Division | B36: 5
B37: 05 00 00 | C37: Metals
B38: 05 12 00 | C38: Structural Steel Framing | D38: ='5'!K26 -> 141400
B39: 05 20 00 | C39: Metal Joists | D39: ='5'!K37 -> 0
B40: 05 30 00 | C40: Metal Decking | D40: ='5'!K45 -> 0
B41: 05 51 00 | C41: Metal Stairs | D41: ='5'!K54 -> 0
B42: 05 52 00 | C42: Metal Railings | D42: ='5'!K65 -> 73570
B43: 05 59 00 | C43: Metal Specialties | D43: ='5'!K74 -> 0
A46: Division | B46: 6
B47: 06 00 00 | C47: Wood, Plastics, and Composites
B48: 06 11 00 | C48: Framing | D48: ='6'!K19 -> 571330
B49: 06 20 00 | C49: Finish Carpentry | D49: ='6'!K36 -> 1261823.7
B50: 06 22 00 | C50: Millwork | D50: ='6'!K47 -> 425900
B51: 06 41 00 | C51: Architechtural Wood Casework | D51: ='6'!K55 -> 0
B52: 06 42 00 | C52: Wood Paneling | D52: ='6'!K64 -> 0
B53: 06 43 00 | C53: Wood Stairs and Railings | D53: ='6'!K75 -> 0
B54: 06 46 00 | C54: Wood Trim | D54: ='6'!K84 -> 315803.89
B55: 06 48 00 | C55: Wood Frames | D55: ='6'!K91 -> 0
A58: Division | B58: 7
B59: 07 00 00 | C59: Thermal and Moisture Protection
B60: 07 21 00 | C60: Thermal Insulation | D60: ='7'!K16 -> 237835
B61: 07 24 00 | C61: EIFS | D61: ='7'!K22 -> 271678.01
B62: 07 31 00 | C62: Shingles | D62: ='7'!K27 -> 81750
B63: 07 42 00 | C63: Wall Panels | D63: ='7'!K33 -> 0
B64: 07 46 00 | C64: Siding | D64: ='7'!K39 -> 561708
B65: 07 52 00 | C65: Modified Bituminous Membrane Roofing | D65: ='7'!K45 -> 0
B66: 07 53 00 | C66: Elastomeric Membrane Roofing | D66: ='7'!K50 -> 0
B67: 07 62 00 | C67: Sheet Metal Flashing and Trim | D67: ='7'!K55 -> 0
B68: 07 63 00 | C68: Sheet Metal Roofing Specialties | D68: ='7'!K60 -> 0
B69: 07 64 00 | C69: Sheet Metal Wall Cladding | D69: ='7'!K66 -> 0
B70: 07 72 00 | C70: Roof Accessories | D70: ='7'!K72 -> 0
B71: 07 81 00 | C71: Applied Fireproofing | D71: ='7'!K78 -> 26550
B72: 07 90 00 | C72: Joint Protection | D72: ='7'!K84 -> 0
A74: Division | B74: 8
B75: 08 00 00 | C75: Openings
B76: 08 11 00 | C76: Metal Doors and Frames | D76: ='8'!K18 -> 89875
B77: 08 14 00 | C77: Wood Doors | D77: ='8'!K24 -> 0
B78: 08 31 00 | C78: Access Doors and Panels | D78: ='8'!K29 -> 8000
B79: 08 32 00 | C79: Sliding Gates | D79: ='8'!K35 -> 0
B80: 08 33 00 | C80: Coiling Doors and Drilles | D80: ='8'!K41 -> 10984.51
B81: 08 34 00 | C81: Special Function Doors | D81: ='8'!K47 -> 0
B82: 08 38 00 | C82: Traffic Doors | D82: ='8'!K52 -> 0
B83: 08 41 00 | C83: Entrances and Storefronts | D83: ='8'!K57 -> 39425
B84: 08 44 00 | C84: Curtain Wall and Glazed Assemblies | D84: ='8'!K62 -> 0
B85: 08 50 00 | C85: Windows | D85: ='8'!K69 -> 126145.3
B86: 08 70 00 | C86: Hardware | D86: ='8'!K75 -> 0
B87: 08 81 00 | C87: Glass Glazing | D87: ='8'!K81 -> 0
B88: 08 83 00 | C88: Mirrors | D88: ='8'!K87 -> 0
B89: 08 87 00 | C89: Glazing Surface Films | D89: ='8'!K93 -> 0
B90: 08 91 00 | C90: Louvers | D90: ='8'!K99 -> 0
A92: Division | B92: 9
B93: 09 00 00 | C93: Finishes
B94: 09 20 00 | C94: Plaster and Gypsum Board | D94: ='9'!K18 -> 1139222
B95: 09 30 00 | C95: Tiling | D95: ='9'!K26 -> 0
B96: 09 50 00 | C96: Ceiling | D96: ='9'!K32 -> 0
B97: 09 60 00 | C97: Flooring | D97: ='9'!K47 -> 411100
B98: 09 72 00 | C98: Wall Coverings | D98: ='9'!K53 -> 0
B99: 09 91 00 | C99: Painting | D99: ='9'!K62 -> 197003
A102: Division | B102: 10
B103: 10 00 00 | C103: Specialties
B104: 10 11 00 | C104: Visual Display Units | D104: ='10'!K17 -> 0
B105: 10 14 00 | C105: Signage | D105: ='10'!K25 -> 10950
B106: 10 20 00 | C106: Interior Specialties | D106: ='10'!K38 -> 11989.39
B107: 10 44 00 | C107: Fire Protection Specialties | D107: ='10'!K44 -> 0
B108: 10 51 00 | C108: Lockers | D108: ='10'!K51 -> 31062.37
B109: 10 57 00 | C109: Wardrobe and Closet Specialties | D109: ='10'!K57 -> 32532
B110: 10 70 00 | C110: Exterior Specialties | D110: ='10'!K63 -> 1640
A112: Division | B112: 11
B113: 11 00 00 | C113: Equipment
B114: 11 11 00 | C114: Vehicle Service Equipment | D114: ='11'!K24 -> 0
B115: 11 13 00 | C115: Loading Dock Equipment | D115: ='11'!K35 -> 0
B116: 11 30 00 | C116: Residential Equipment | D116: ='11'!K43 -> 200600
...

Sheet Cost Report
B1: Division | C1: Sub - Division | D1: Discription | E1: Cost
B2: 01 00 00 | D2: General Requirements | E2: ='Estimate Summary'!H15 -> 584281.12
B3: 01 11 00 | D3: Preconstruction Costs | E3: ='1'!K24 -> 0
B4: 01 31 00 | D4: Project Management and Coordination | E4: ='1'!K35 -> 165000
B5: 01 31 00 | C5: 01 31 01 | D5: Senior Construction Manager | E5: ='1'!K27 -> 0
B6: 01 31 00 | C6: 01 31 02 | D6: Senior Estimator | E6: ='1'!K28 -> 0
B7: 01 31 00 | C7: 01 31 03 | D7: Senior Project Manager | E7: ='1'!K29 -> 0
B8: 01 31 00 | C8: 01 31 04 | D8: Project Coordinator | E8: ='1'!K30 -> 0
B9: 01 31 00 | C9: 01 31 05 | D9: Project Superintendent | E9: ='1'!K31 -> 165000
B10: 01 31 00 | C10: 01 31 06 | D10: Project Foreman | E10: ='1'!K32 -> 0
B11: 01 32 00 | C11: 01 32 00 | D11: Travel
B12: 01 41 00 | D12: Permits | E12: ='1'!K67 -> 3000
B13: 01 45 00 | D13: Quality Control | E13: ='1'!K76 -> 8000
B14: 01 51 00 | D14: Temporary Utilities | E14: ='1'!K87 -> 15000
B15: 01 52 00 | D15: Construction Facilities | E15: ='1'!K97 -> 35468.079
B16: 01 52 00 | C16: 01 52 01 | D16: Construction Field Office | E16: ='1'!K90 -> 12375
B17: 01 52 00 | C17: 01 52 02 | D17: Sanitary Facilities | E17: ='1'!K92 -> 12000
B18: 01 52 00 | C18: 01 52 03 | D18: Drawing Reprographics | E18: ='1'!K93 -> 5503.0789
B19: 01 52 00 | C19: 01 52 04 | D19: First-Aid / Safety | E19: ='1'!K94 -> 3750
B20: 01 52 00 | C20: 01 52 05 | D20: Job Sign | E20: ='1'!K95 -> 0
B21: 01 54 00 | D21: Construction Aids | E21: ='1'!K105 -> 203313.04
B22: 01 55 00 | C22: 01 55 00 | D22: Winter Conditions
B23: 01 56 00 | D23: Temporary Barriers & Enclosures | E23: ='1'!K128 -> 25000
B24: 01 74 00 | D24: Cleaning & Waste Management | E24: ='1'!K136 -> 54500
B25: 01 74 00 | C25: 01 74 01 | D25: Progress Cleaning | E25: ='1'!K131 -> 0
B26: 01 74 00 | C26: 01 74 02 | D26: Site Maintenance | E26: ='1'!K132 -> 14400
B27: 01 74 00 | C27: 01 74 03 | D27: Construction Waste Mgmt & Disposal | E27: ='1'!K133 -> 16500
B28: 01 74 00 | C28: 01 74 04 | D28: Final Cleaning | E28: ='1'!K134 -> 23600
B29: 02 00 00 | D29: Existing Conditions | E29: ='Estimate Summary'!H17 -> 0
B30: 02 41 00 | D30: Demolition | E30: ='2'!K26 -> 0
B31: 02 82 00 | D31: Asbestos Remediation | E31: ='2'!K37 -> 0
B32: 02 83 00 | D32: Trenching | E32: ='2'!K48 -> 0
B33: 03 00 00 | D33: Concrete | E33: ='Estimate Summary'!H19 -> 670607.86
B34: 03 11 00 | D34: Concrete Forming | E34: ='3'!K26 -> 302400
B35: 03 20 00 | D35: Concrete Reinforcing | E35: ='3'!K37 -> 0
B36: 03 30 00 | D36: Cast-in-Place Concrete | E36: ='3'!K50 -> 177795.86
B37: 03 35 00 | D37: Concrete Finishing | E37: ='3'!K59 -> 44527
B38: 03 40 00 | D38: Precast Concrete | E38: ='3'!K70 -> 77850
B39: 03 60 00 | D39: Foundation Materials | E39: ='3'!K79 -> 68035
B40: 03 60 00 | C40: 03 60 01 | D40: Insulation | E40: ='3'!K73 -> 15640
B41: 03 60 00 | C41: 03 60 02 | D41: Vapour Barrier | E41: ='3'!K74 -> 8235
B42: 04 00 00 | D42: Masonry | E42: ='Estimate Summary'!H21 -> 140360
B43: 04 20 00 | D43: Unit Masonry | E43: ='4'!K26 -> 140360
B44: 04 43 00 | D44: Stone Masonry | E44: ='4'!K37 -> 0
B45: 05 00 00 | D45: Metals | E45: ='Estimate Summary'!H23 -> 214970
B46: 05 12 00 | D46: Structural Steel Framing | E46: ='5'!K26 -> 141400
B47: 05 20 00 | D47: Metal Joists | E47: ='5'!K37 -> 0
B48: 05 30 00 | D48: Metal Decking | E48: ='5'!K45 -> 0
B49: 05 51 00 | D49: Metal Stairs | E49: ='5'!K54 -> 0
B50: 05 52 00 | D50: Metal Railings | E50: ='5'!K65 -> 73570
B51: 05 59 00 | D51: Metal Specialties | E51: ='5'!K74 -> 0
B52: 06 00 00 | D52: Wood, Plastics, and Composites | E52: ='Estimate Summary'!H25 -> 2574857.6
B53: 06 11 00 | D53: Framing Labour | E53: ='6'!K19 -> 571330
B54: 06 20 00 | D54: Framing Material | E54: ='6'!K36 -> 1261823.7
B55: 06 22 00 | D55: Millwork | E55: ='6'!K47 -> 425900
B56: 06 41 00 | D56: Architechtural Wood Casework | E56: ='6'!K55 -> 0
B57: 06 42 00 | D57: Wood Paneling | E57: ='6'!K64 -> 0
B58: 06 43 00 | D58: Wood Stairs and Railings | E58: ='6'!K75 -> 0
B59: 06 46 00 | D59: Wood Trim | E59: ='6'!K84 -> 315803.89
B60: 06 48 00 | D60: Wood Frames | E60: ='6'!K91 -> 0
B61: 07 00 00 | D61: Thermal and Moisture Protection | E61: ='Estimate Summary'!H27 -> 1179521
B62: 07 21 00 | D62: Thermal Insulation | E62: ='7'!K16 -> 237835
B63: 07 24 00 | D63: EIFS | E63: ='7'!K22 -> 271678.01
B64: 07 31 00 | D64: Shingles | E64: ='7'!K27 -> 81750
B65: 07 42 00 | D65: Wall Panels | E65: ='7'!K33 -> 0
B66: 07 46 00 | D66: Siding | E66: ='7'!K39 -> 561708
B67: 07 52 00 | D67: Modified Bituminous Membrane Roofing | E67: ='7'!K45 -> 0
B68: 07 53 00 | D68: Elastomeric Membrane Roofing | E68: ='7'!K50 -> 0
B69: 07 62 00 | D69: Sheet Metal Flashing and Trim | E69: ='7'!K55 -> 0
B70: 07 63 00 | D70: Sheet Metal Roofing Specialties | E70: ='7'!K60 -> 0
B71: 07 64 00 | D71: Sheet Metal Wall Cladding | E71: ='7'!K66 -> 0
B72: 07 72 00 | D72: Roof Accessories | E72: ='7'!K72 -> 0
B73: 07 81 00 | D73: Applied Fireproofing | E73: ='7'!K78 -> 26550
B74: 07 90 00 | D74: Joint Protection | E74: ='7'!K84 -> 0
B75: 08 00 00 | D75: Openings | E75: ='Estimate Summary'!H29 -> 274429.81
B76: 08 11 00 | D76: Metal Doors and Frames | E76: ='8'!K18 -> 89875
B77: 08 14 00 | D77: Wood Doors | E77: ='8'!K24 -> 0
B78: 08 31 00 | D78: Access Doors and Panels | E78: ='8'!K29 -> 8000
B79: 08 32 00 | D79: Sliding Gates | E79: ='8'!K35 -> 0
B80: 08 33 00 | D80: Coiling Doors and Drilles | E80: ='8'!K41 -> 10984.51
B81: 08 34 00 | D81: Special Function Doors | E81: ='8'!K47 -> 0
B82: 08 38 00 | D82: Traffic Doors | E82: ='8'!K52 -> 0
B83: 08 41 00 | D83: Entrances and Storefronts | E83: ='8'!K57 -> 39425
B84: 08 44 00 | D84: Curtain Wall and Glazed Assemblies | E84: ='8'!K62 -> 0
B85: 08 50 00 | D85: Windows | E85: ='8'!K69 -> 126145.3
B86: 08 70 00 | D86: Hardware | E86: ='8'!K75 -> 0
B87: 08 81 00 | D87: Glass Glazing | E87: ='8'!K81 -> 0
B88: 08 83 00 | D88: Mirrors | E88: ='8'!K87 -> 0
B89: 08 87 00 | D89: Glazing Surface Films | E89: ='8'!K93 -> 0
B90: 08 91 00 | D90: Louvers | E90: ='8'!K99 -> 0
B91: 09 00 00 | D91: Finishes | E91: ='Estimate Summary'!H31 -> 1747325
B92: 09 20 00 | D92: Plaster and Gypsum Board | E92: ='9'!K18 -> 1139222
B93: 09 30 00 | D93: Tiling | E93: ='9'!K26 -> 0
B94: 09 50 00 | D94: Ceiling | E94: ='9'!K32 -> 0
B95: 09 60 00 | D95: Flooring | E95: ='9'!K47 -> 411100
B96: 09 60 00 | C96: 09 61 00 | D96: Concrete Floor Polishing | E96: ='9'!K35 -> 121100
B97: 09 60 00 | C97: 09 62 00 | D97: Specialty Flooring | E97: ='9'!K37 -> 0
B98: 09 60 00 | C98: 09 64 00 | D98: Wood Flooring | E98: ='9'!K38 -> 0
B99: 09 60 00 | C99: 09 65 00 | D99: VCT | E99: ='9'!K39 -> 0
B100: 09 60 00 | C100: 09 67 00 | D100: LVT | E100: ='9'!K40 -> 290000
...

Sheet DATA
B2: Quarter | C2: Column1 | D2: Province | H2: Project Definition | J2: Contract Type | K2: Payment Method | M2: A | N2: >5M
B3: Q1 | D3: NB | H3: Multi Residential | J3: CCDC 2 | K3: Stipulated Price | M3: B | N3: 2-5M
B4: Q2 | D4: PEI | H4: Office | J4: CCDC 5B | K4: Fixed Fee | M4: C | N4: 500K - 2M | R4: Status | T4: Result
B5: Q3 | D5: NS | H5: Retail | J5: CCDC 5A | M5: D | N5: 100K - 500K | R5: Awarded | T5: Successful
B6: Q4 | D6: Other | H6: Food | J6: Design Build | M6: E | N6: less than 100K | R6: Not Awarded | T6: Unsuccessful
R7: Pending
A10: Closing Date | B10: Budget Year | C10: Quarter | D10: Province | E10: City/Town | F10: Estimate Number | G10: Estimate Name | H10: Type of Construction | I10: Area | J10: Contract Type | K10: Payment Method | L10: Estimate Price | M10: Price Category | N10: Schedule | O10: Soft Cost | P10: Cost per Week | Q10: Margin | R10: Status | S10: Bid Docs | T10: Successful / Unsuccessful
A11: =+'Estimate Summary'!B3 -> 45379 | B11: =+'Estimate Summary'!B7 -> 2024 | C11: =+'Estimate Summary'!B8 -> Q2 | D11: =+'Estimate Summary'!B5 -> NB | E11: ='Estimate Summary'!B6 -> Moncton | F11: ='Estimate Summary'!B4 -> 2989 | G11: ='Estimate Summary'!D5 -> 2500 Mountain Road Multi-Res | H11: =+'Estimate Summary'!F8 -> 0 | I11: =+'Estimate Summary'!D11 -> 65592 | J11: ='Estimate Summary'!D7 -> CCDC 5B | K11: =+'Estimate Summary'!D8 -> Fixed Fee | L11: =+'Estimate Summary'!D75 -> 11119373 | M11: =IF(L11<100000,"E",IF(L11<500000,"D",IF(L11<2000000,"C",IF(L11<5000000,"B",IF(L11>=5000000,"A"))))) -> A | N11: ='Estimate Summary'!D81 -> 60 | O11: ='Estimate Summary'!D82 -> 737710.08 | P11: ='Estimate Summary'!E82 -> 12295.168 | Q11: ='Estimate Summary'!D84 -> 0.066344575 | R11: ='Estimate Summary'!F6 -> 0 | S11: ='Estimate Summary'!F5 -> 0 | T11: ='Estimate Summary'!F7 -> 0

Sheet Estimate Version Comparison
B2: ='Estimate Summary'!D5 -> 2500 Mountain Road Multi-Res | I2: CLIENT SUMMARY
B3: ='Estimate Summary'!D6 -> Ashish Goel
B4: Date: | C4: ='Estimate Summary'!B3 -> 45379
G7: ='Estimate Summary'!B3 -> 45379 | H7: ='Estimate Summary'!G8 -> 0
B8: 01 00 00 | C8: General Requirements | E8: =SUM(D9:D17) -> 0 | H8: =SUM(G9:G17) -> 509281.12 | J8: =IF(H8>E8,"Increase","Decrease or No Change") -> Increase | K8: =H8-E8 -> 509281.12
B9: 01 11 00 | C9: Preconstruction Costs | D9: 0 | G9: ='1'!K24 -> 0
B10: 01 31 00 | C10: Project Management and Coordination | D10: 0 | G10: ='1'!K35 -> 165000
B11: 01 41 00 | C11: Permits | D11: 0 | G11: ='1'!K67 -> 3000
B12: 01 45 00 | C12: Quality Control | D12: 0 | G12: ='1'!K76 -> 8000
B13: 01 51 00 | C13: Temporary Utilities | D13: 0 | G13: ='1'!K87 -> 15000
B14: 01 52 00 | C14: Construction Facilities | D14: 0 | G14: ='1'!K97 -> 35468.079
B15: 01 54 00 | C15: Construction Aids | D15: 0 | G15: ='1'!K105 -> 203313.04
B16: 01 56 00 | C16: Temporary Barriers & Enclosures | D16: 0 | G16: ='1'!K128 -> 25000
B17: 01 74 00 | C17: Cleaning & Waste Management | D17: 0 | G17: ='1'!K136 -> 54500
B19: 02 00 00 | C19: Existing Conditions | E19: =SUM(D20:D22) -> 0 | H19: =SUM(G20:G22) -> 0 | J19: =IF(H19>E19,"Increase","Decrease or No Change") -> Decrease or No Change | K19: =H19-E19 -> 0
B20: 02 41 00 | C20: Demolition | D20: 0 | G20: ='2'!K13 -> 0
B21: 02 82 00 | C21: Asbestos Remediation | D21: 0 | G21: ='2'!K37 -> 0
B22: 02 83 00 | C22: Trenching | D22: 0 | G22: ='2'!K48 -> 0
B24: 03 00 00 | C24: Concrete | E24: =SUM(D25:D29) -> 0 | H24: =SUM(G25:G29) -> 670607.86 | J24: =IF(H24>E24,"Increase","Decrease or No Change") -> Increase | K24: =H24-E24 -> 670607.86
B25: 03 11 00 | C25: Concrete Forming | D25: 0 | G25: ='3'!K26 -> 302400
B26: 03 20 00 | C26: Concrete Reinforcing | D26: 0 | G26: ='3'!K37 -> 0
B27: 03 30 00 | C27: Cast-in-Place Concrete | D27: 0 | G27: ='3'!K50+'3'!K59 -> 222322.86
B28: 03 40 00 | C28: Precast Concrete | D28: 0 | G28: ='3'!K70 -> 77850
B29: 03 60 00 | C29: Grouting | D29: 0 | G29: ='3'!K79 -> 68035
B31: 04 00 00 | C31: Masonry | E31: =SUM(D32:D33) -> 0 | H31: =SUM(G32:G33) -> 140360 | J31: =IF(H31>E31,"Increase","Decrease or No Change") -> Increase | K31: =H31-E31 -> 140360
B32: 04 20 00 | C32: Unit Masonry | D32: 0 | G32: ='4'!K26 -> 140360
B33: 04 40 00 | C33: Stone Assemblies | D33: 0 | G33: ='4'!K37 -> 0
B35: 05 00 00 | C35: Metals | E35: =SUM(D36:D39) -> 0 | H35: =SUM(G36:G39) -> 214970 | J35: =IF(H35>E35,"Increase","Decrease or No Change") -> Increase | K35: =H35-E35 -> 214970
B36: 05 12 00 | C36: Structural Steel Framing | D36: 0 | G36: ='5'!K26 -> 141400
B37: 05 20 00 | C37: Metal Joists | D37: 0 | G37: ='5'!K37 -> 0
B38: 05 30 00 | C38: Metal Decking | D38: 0 | G38: ='5'!K45 -> 0
B39: 05 50 00 | C39: Metal Fabrications | D39: 0 | G39: ='5'!K54+'5'!K65+'5'!K74 -> 73570
B41: 06 00 00 | C41: Wood, Plastics, and Composites | E41: =SUM(D42:D45) -> 0 | H41: =SUM(G42:G45) -> 2574857.6 | J41: =IF(H41>E41,"Increase","Decrease or No Change") -> Increase | K41: =H41-E41 -> 2574857.6
B42: 06 11 00 | C42: Framing Labour | D42: 0 | G42: ='6'!K19 -> 571330
B43: 06 11 00 | C43: Framing Material | D43: 0 | G43: ='6'!K36 -> 1261823.7
B44: 06 22 00 | C44: Millwork | D44: 0 | G44: ='6'!K47 -> 425900
B45: 06 40 00 | C45: Architectural Woodwork | D45: 0 | G45: ='6'!K55+'6'!K64+'6'!K75+'6'!K84+'6'!K91 -> 315803.89
B47: 07 00 00 | C47: Thermal and Moisture Protection | E47: =SUM(D48:D57) -> 0 | H47: =SUM(G48:G57) -> 1179521 | J47: =IF(H47>E47,"Increase","Decrease or No Change") -> Increase | K47: =H47-E47 -> 1179521
B48: 07 21 00 | C48: Thermal Insulation | D48: 0 | G48: ='7'!K16 -> 237835
B49: 07 24 00 | C49: EIFS | D49: 0 | G49: ='7'!K22 -> 271678.01
B50: 07 31 00 | C50: Shingles | D50: 0 | G50: ='7'!K27 -> 81750
B51: 07 42 00 | C51: Wall Panels | D51: 0 | G51: ='7'!K33 -> 0
B52: 07 46 00 | C52: Siding | D52: 0 | G52: ='7'!K39 -> 561708
B53: 07 50 00 | C53: Membrane Roofing | D53: 0 | G53: ='7'!K45+'7'!K50 -> 0
B54: 07 60 00 | C54: Flashing and Sheet Metal | D54: 0 | G54: ='7'!K55+'7'!K60+'7'!K66 -> 0
B55: 07 72 00 | C55: Roof Accessories | D55: 0 | G55: ='7'!K72 -> 0
B56: 07 80 00 | C56: Smoke and Fire Protection | D56: 0 | G56: ='7'!K78 -> 26550
B57: 07 90 00 | C57: Joint Protection | D57: 0 | G57: ='7'!K84 -> 0
B59: 08 00 00 | C59: Openings | E59: =SUM(D60:D66) -> 0 | H59: =SUM(G60:G66) -> 274429.81 | J59: =IF(H59>E59,"Increase","Decrease or No Change") -> Increase | K59: =H59-E59 -> 274429.81
B60: 08 10 00 | C60: Doors and Frames | D60: 0 | G60: ='8'!K18+'8'!K24 -> 89875
B61: 08 30 00 | C61: Speciality Doors and Frames | D61: 0 | G61: ='8'!K29+'8'!K35+'8'!K41+'8'!K47+'8'!K52 -> 18984.51
B62: 08 40 00 | C62: Store Fronts and Curtainwalls | D62: 0 | G62: ='8'!K57+'8'!K62 -> 39425
B63: 08 50 00 | C63: Windows | D63: 0 | G63: ='8'!K69 -> 126145.3
B64: 08 70 00 | C64: Hardeware | D64: 0 | G64: ='8'!K75 -> 0
B65: 08 80 00 | C65: Glazing | D65: 0 | G65: ='8'!K81+'8'!K87+'8'!K93 -> 0
B66: 08 90 00 | C66: Louvers | D66: 0 | G66: ='8'!K99 -> 0
B68: 09 00 00 | C68: Finishes | E68: =SUM(D69:D74) -> 0 | H68: =SUM(G69:G74) -> 1747325 | J68: =IF(H68>E68,"Increase","Decrease or No Change") -> Increase | K68: =H68-E68 -> 1747325
B69: 09 20 00 | C69: Plaster and Gypsum Board | D69: 0 | G69: ='9'!K18 -> 1139222
B70: 09 30 00 | C70: Tiling | D70: 0 | G70: ='9'!K26 -> 0
B71: 09 50 00 | C71: Ceiling | D71: 0 | G71: ='9'!K32 -> 0
B72: 09 60 00 | C72: Flooring | D72: 0 | G72: ='9'!K47 -> 411100
B73: 09 70 00 | C73: Wall Finishes | D73: 0 | G73: ='9'!K53 -> 0
B74: 09 90 00 | C74: Painting | D74: 0 | G74: ='9'!K62 -> 197003
B76: 10 00 00 | C76: Specialties | E76: =SUM(D77:D82) -> 0 | H76: =SUM(G77:G82) -> 55641.76 | J76: =IF(H76>E76,"Increase","Decrease or No Change") -> Increase | K76: =H76-E76 -> 55641.76
B77: 10 11 00 | C77: Visual Display Units | D77: 0 | G77: ='10'!K17 -> 0
B78: 10 14 00 | C78: Signage | D78: 0 | G78: ='10'!K25 -> 10950
B79: 10 20 00 | C79: Interior Specialties | D79: 0 | G79: ='10'!K38 -> 11989.39
B80: 10 40 00 | C80: Safety Specialties | D80: 0 | G80: ='10'!K44 -> 0
B81: 10 50 00 | C81: Storage Specialties | D81: 0 | G81: ='10'!K51 -> 31062.37
B82: 10 70 00 | C82: Exterior Specialties | D82: 0 | G82: ='10'!K63 -> 1640
B86: 11 00 00 | C86: Equipment | E86: =SUM(D87:D90) -> 0 | H86: =SUM(G87:G90) -> 200600
B87: 11 10 00 | C87: Vehicle Equipment | D87: 0 | G87: ='11'!K24+'11'!K35 -> 0
B88: 11 30 00 | C88: Residential Equipment | D88: 0 | G88: ='11'!K43 -> 200600 | J88: =IF(H88>E88,"Increase","Decrease or No Change") -> Decrease or No Change | K88: =H88-E88 -> 0
B89: 11 40 00 | C89: Food Service Equipment | D89: 0 | G89: ='11'!K52+'11'!K63 -> 0
B90: 11 50 00 | C90: Educational & Lab Equipment | D90: 0 | G90: ='11'!K72+'11'!K79 -> 0
B92: 12 00 00 | C92: Furnishings | E92: =SUM(D93:D94) -> 0 | H92: =SUM(G93:G94) -> 41300 | J92: =IF(H92>E92,"Increase","Decrease or No Change") -> Increase | K92: =H92-E92 -> 41300
B93: 12 20 00 | C93: Window Treatments | D93: 0 | G93: ='12'!K24+'12'!K35 -> 41300
B94: 12 30 00 | C94: Casework | D94: 0 | G94: ='12'!K43+'12'!K52+'12'!K63+'12'!K72 -> 0
B96: 13 00 00 | C96: Special Construction | E96: ='Estimate Summary'!E39 -> 0 | H96: ='Estimate Summary'!H39 -> 121400 | J96: =IF(H96>E96,"Increase","Decrease or No Change") -> Increase | K96: =H96-E96 -> 121400
B98: 14 00 00 | C98: Conveying Equipment | E98: =SUM(D99:D100) -> 0 | H98: =SUM(G99:G100) -> 0 | J98: =IF(H98>E98,"Increase","Decrease or No Change") -> Decrease or No Change | K98: =H98-E98 -> 0
B99: 14 20 00 | C99: Elevators | D99: 0 | G99: ='14'!K24 -> 0
B100: 14 40 00 | C100: Lifts | D100: 0 | G100: ='14'!K35+'14'!K43 -> 0
B102: 21 00 00 | C102: Fire Suppression | E102: =D103 -> 0 | H102: =G103 -> 212000 | J102: =IF(H103>E102,"Increase","Decrease or No Change") -> Decrease or No Change | K102: =H103-E102 -> 0
B103: 21 10 00 | C103: Water-Based Fire-Suppression System | D103: 0 | G103: ='21'!K24 -> 212000
B105: 22 00 00 | C105: Plumbing | E105: =SUM(D106:D108) -> 0 | H105: =SUM(G106:G108) -> 674850 | J105: =IF(H106>E105,"Increase","Decrease or No Change") -> Decrease or No Change | K105: =H106-E105 -> 0
B106: 22 10 00 | C106: Plumbing Piping | D106: 0 | G106: ='22'!K24 -> 674850
B107: 22 30 00 | C107: Plumbing Equipment | D107: 0 | G107: ='22'!K35 -> 0
B108: 22 40 00 | C108: Plumbing Fixtures | D108: 0 | G108: ='22'!K46+'22'!K67+'22'!K74 -> 0
B110: 23 00 00 | C110: HVAC | E110: =SUM(D111:D118) -> 0 | H110: =SUM(G111:G118) -> 467650 | J110: =IF(H111>E110,"Increase","Decrease or No Change") -> Decrease or No Change | K110: =H111-E110 -> 0
B111: 23 07 00 | C111: HVAC Insulation | D111: 0 | G111: ='23'!K18 -> 467650
B112: 23 08 00 | C112: Commissioning of HVAC | D112: 0 | G112: ='23'!K25 -> 0
B113: 23 09 00 | C113: Instrumentation and Control for HVAC | D113: 0 | G113: ='23'!K31 -> 0
B114: 23 10 00 | C114: Facility Fuel System | D114: 0 | G114: ='23'!K38+'23'!K46 -> 0
B115: 23 20 00 | C115: HVAC Piping and Pumps | D115: 0 | G115: ='23'!K53+'23'!K58 -> 0
B116: 23 30 00 | C116: HVAC Air Distribution | D116: 0 | G116: ='23'!K73 -> 0
B117: 23 70 00 | C117: Central HVAC Equipment | D117: 0 | G117: ='23'!K79 -> 0
B118: 23 80 00 | C118: Decentralized HVAC Equipment | D118: 0 | G118: ='23'!K85+'23'!K91 -> 0
B120: 25 00 00 | C120: Integrated Automation | E120: ='Estimate Summary'!E49 -> 0 | H120: ='Estimate Summary'!H49 -> 0 | J120: =IF(H120>E120,"Increase","Decrease or No Change") -> Decrease or No Change | K120: =H120-E120 -> 0
B122: 26 00 00 | C122: Electrical | E122: =SUM(D123:D125) -> 0 | H122: =SUM(G123:G125) -> 822897 | J122: =IF(H123>E122,"Increase","Decrease or No Change") -> Decrease or No Change | K122: =H123-E122 -> 0
B123: 26 09 00 | C123: Sub Contractor Cost | D123: 0 | G123: ='26'!K26 -> 770000
...

Sheet Client  Detailed Summary 
B3: ='Estimate Summary'!D5 -> 2500 Mountain Road Multi-Res | F3: CLIENT SUMMARY
B5: Date: | C5: 45421
B7: 01 00 00 | C7: General Requirements | H7: =SUM(G8:G18) -> 584281.12
B8: 01 11 00 | C8: Preconstruction Costs | G8: ='1'!K24 -> 0
B9: 01 31 00 | C9: Project Management and Coordination | G9: ='1'!K35 -> 165000
B10: 01 32 00 | C10: Insurance | G10: ='1'!K45+'1'!K56 -> 0 | H10: By Client
B11: 01 41 00 | C11: Permits | G11: ='1'!K67 -> 3000 | H11: By Client
B12: 01 45 00 | C12: Quality Control | G12: ='1'!K76 -> 8000
B13: 01 51 00 | C13: Temporary Utilities | G13: ='1'!K87 -> 15000
B14: 01 52 00 | C14: Construction Facilities | G14: ='1'!K97 -> 35468.079
B15: 01 54 00 | C15: Security | G15: ='1'!K100 -> 30000
B16: 01 54 00 | C16: Construction Aids & Winter Conditions | G16: ='1'!K105+'1'!K120-G15 -> 248313.04
B17: 01 56 00 | C17: Temporary Barriers & Enclosures | G17: ='1'!K128 -> 25000
B18: 01 74 00 | C18: Cleaning & Waste Management | G18: ='1'!K136 -> 54500
B20: 02 00 00 | C20: Existing Conditions | H20: =SUM(G21:G23) -> 0
B21: 02 41 00 | C21: Demolition | G21: ='2'!K26 -> 0
B22: 02 82 00 | C22: Asbestos Remediation | G22: ='2'!K37 -> 0
B23: 02 83 00 | C23: Trenching | G23: ='2'!K48 -> 0
B25: 03 00 00 | C25: Concrete | H25: =SUM(G26:G30) -> 670607.86
B26: 03 11 00 | C26: Concrete Forming | G26: ='3'!K26 -> 302400
B27: 03 20 00 | C27: Concrete Reinforcing | G27: ='3'!K37 -> 0
B28: 03 30 00 | C28: Cast-in-Place Concrete | G28: ='3'!K50+'3'!K59 -> 222322.86
B29: 03 40 00 | C29: Precast Concrete | G29: ='3'!K70 -> 77850
B30: 03 60 00 | C30: Grouting | G30: ='3'!K79 -> 68035
B32: 04 00 00 | C32: Masonry | H32: =SUM(G33:G34) -> 140360
B33: 04 20 00 | C33: Exterior Stone Veneer | G33: ='4'!K26 -> 140360
B34: 04 40 00 | C34: Stone Assemblies | G34: ='4'!K37 -> 0
B36: 05 00 00 | C36: Metals | H36: =SUM(G37:G40) -> 214970
B37: 05 12 00 | C37: Structural Steel Framing | G37: ='5'!K26 -> 141400
B38: 05 20 00 | C38: Metal Joists | G38: ='5'!K37 -> 0
B39: 05 30 00 | C39: Metal Decking | G39: ='5'!K45 -> 0
B40: 05 50 00 | C40: Balcony Handrails | G40: ='5'!K54+'5'!K65+'5'!K74 -> 73570
B42: 06 00 00 | C42: Wood, Plastics, and Composites | H42: =SUM(G43:G46) -> 2574857.6
B43: 06 11 00 | C43: Framing Labour | G43: ='6'!K19 -> 571330
B44: 06 11 00 | C44: Framing Material | G44: ='6'!K36 -> 1261823.7
B45: 06 22 00 | C45: Millwork | G45: ='6'!K47 -> 425900
B46: 06 40 00 | C46: Architectural Woodwork | G46: ='6'!K55+'6'!K64+'6'!K75+'6'!K84+'6'!K91 -> 315803.89
B48: 07 00 00 | C48: Thermal and Moisture Protection | H48: =SUM(G49:G58) -> 1179521
B49: 07 21 00 | C49: Thermal Insulation | G49: ='7'!K16 -> 237835
B50: 07 24 00 | C50: Acoustiboard floor soundproofing | G50: ='7'!K22 -> 271678.01
B51: 07 31 00 | C51: Shingles | G51: ='7'!K27 -> 81750
B52: 07 42 00 | C52: Wall Panels | G52: ='7'!K33 -> 0
B53: 07 46 00 | C53: Siding | G53: ='7'!K39 -> 561708
B54: 07 50 00 | C54: Membrane Roofing | G54: ='7'!K45+'7'!K50 -> 0
B55: 07 60 00 | C55: Flashing and Sheet Metal | G55: ='7'!K55+'7'!K60+'7'!K66 -> 0
B56: 07 72 00 | C56: Roof Accessories | G56: ='7'!K72 -> 0
B57: 07 80 00 | C57: Smoke and Fire Protection | G57: ='7'!K78 -> 26550
B58: 07 90 00 | C58: Joint Protection | G58: ='7'!K84 -> 0
B60: 08 00 00 | C60: Openings | H60: =SUM(G61:G67) -> 274429.81
B61: 08 10 00 | C61: Doors and Frames | G61: ='8'!K18+'8'!K24 -> 89875
B62: 08 30 00 | C62: Speciality Doors and Frames | G62: ='8'!K29+'8'!K35+'8'!K41+'8'!K47+'8'!K52 -> 18984.51
B63: 08 40 00 | C63: Aluminum Doors and Glazing | G63: ='8'!K57+'8'!K62 -> 39425
B64: 08 50 00 | C64: Windows | G64: ='8'!K69 -> 126145.3
B65: 08 70 00 | C65: Hardeware | G65: ='8'!K75 -> 0
B66: 08 80 00 | C66: Glazing | G66: ='8'!K81+'8'!K87+'8'!K93 -> 0
B67: 08 90 00 | C67: Louvers | G67: ='8'!K99 -> 0
B69: 09 00 00 | C69: Finishes | H69: =SUM(G70:G75) -> 1747325
B70: 09 20 00 | C70: Plaster and Gypsum Board | G70: ='9'!K18 -> 1139222
B71: 09 30 00 | C71: Tiling | G71: ='9'!K26 -> 0
B72: 09 50 00 | C72: Ceiling | G72: ='9'!K32 -> 0
B73: 09 60 00 | C73: Flooring | G73: ='9'!K47 -> 411100
B74: 09 70 00 | C74: Wall Finishes | G74: ='9'!K53 -> 0
B75: 09 90 00 | C75: Painting | G75: ='9'!K62 -> 197003
B77: 10 00 00 | C77: Specialties | H77: =SUM(G78:G83) -> 88173.76
B78: 10 11 00 | C78: Visual Display Units | G78: ='10'!K17 -> 0
B79: 10 14 00 | C79: Mailbox | G79: ='10'!K25 -> 10950
B80: 10 20 00 | C80: Washroom Specialties | G80: ='10'!K38 -> 11989.39
B81: 10 40 00 | C81: Closet shelving | G81: ='10'!K57 -> 32532
B82: 10 50 00 | C82: Storage Specialties | G82: ='10'!K51 -> 31062.37
B83: 10 70 00 | C83: Bike Rack | G83: ='10'!K63 -> 1640
B85: 11 00 00 | C85: Equipment | H85: =SUM(G86:G89) -> 200600
B86: 11 10 00 | C86: Vehicle Equipment | G86: ='11'!K24+'11'!K35 -> 0
B87: 11 30 00 | C87: Appliances | G87: ='11'!K43 -> 200600
B88: 11 40 00 | C88: Food Service Equipment | G88: ='11'!K52+'11'!K63 -> 0
B89: 11 50 00 | C89: Educational & Lab Equipment | G89: ='11'!K72+'11'!K79 -> 0
B91: 12 00 00 | C91: Furnishings | H91: =SUM(G92:G93) -> 41300
B92: 12 20 00 | C92: Window Treatments | G92: ='12'!K24+'12'!K35 -> 41300
B93: 12 30 00 | C93: Casework | G93: ='12'!K43+'12'!K52+'12'!K63+'12'!K72 -> 0
B95: 13 00 00 | C95: Solar Panel Addition | H95: =SUM(G96:G98) -> 121400
C96: Solar Panel System | G96: ='13'!J11+'13'!K16 -> 96400
C97: Framing | G97: ='13'!J12 -> 25000
C98: Electrical | G98: ='13'!J13 -> 0
B100: 14 00 00 | C100: Conveying Equipment | H100: =SUM(G101:G102) -> 155285
B101: 14 20 00 | C101: Elevators | G101: ='Estimate Summary'!H41 -> 155285
B102: 14 40 00 | C102: Lifts | G102: ='14'!K35+'14'!K43 -> 0
B104: 21 00 00 | C104: Fire Suppression | H104: =G105 -> 212000
B105: 21 10 00 | C105: Water-Based Fire-Suppression System | G105: ='21'!K24 -> 212000
B107: 22 00 00 | C107: Plumbing | H107: =SUM(G108:G110) -> 674850
B108: 22 10 00 | C108: Plumbing | G108: ='22'!K24 -> 674850
B109: 22 30 00 | C109: Plumbing Equipment | G109: ='22'!K35 -> 0
B110: 22 40 00 | C110: Plumbing Fixtures | G110: ='22'!K46+'22'!K67+'22'!K74 -> 0
B112: 23 00 00 | C112: HVAC | H112: =SUM(G113:G120) -> 467650
B113: 23 07 00 | C113: HVAC | G113: ='23'!K18 -> 467650
B114: 23 08 00 | C114: Commissioning of HVAC | G114: ='23'!K25 -> 0
B115: 23 09 00 | C115: Instrumentation and Control for HVAC | G115: ='23'!K31 -> 0
B116: 23 10 00 | C116: Facility Fuel System | G116: ='23'!K38+'23'!K46 -> 0
B117: 23 20 00 | C117: HVAC Piping and Pumps | G117: ='23'!K53+'23'!K58 -> 0
B118: 23 30 00 | C118: HVAC Air Distribution | G118: ='23'!K73 -> 0
B119: 23 70 00 | C119: Central HVAC Equipment | G119: ='23'!K79 -> 0
B120: 23 80 00 | C120: Decentralized HVAC Equipment | G120: ='23'!K85+'23'!K91 -> 0
...

Sheet Estimate Summary
A2: Project Information
A3: Closing Date : | B3: 45379
A4: Estimate # E- | B4: 2989 | C4: Area: | D4: 65592
A5: Province : | B5: NB | C5: Estimate Name : | D5: 2500 Mountain Road Multi-Res | E5: Bid Documents :
A6: City/Town : | B6: Moncton | C6: Client : | D6: Ashish Goel | E6: Status :
A7: Budget Year : | B7: 2024 | C7: Contract Type : | D7: CCDC 5B | E7: Result:
A8: Quarter: | B8: Q2 | C8: Payment Method : | D8: Fixed Fee
C11: Area: | D11: =D4 -> 65592 | E11: Sq. Ft. | K11: Belle Foret | L11: 77648 | M11: SF
A13: CODE | B13: DESCRIPTION | D13: M&E $$ | E13: M-HRS | F13: LAB $$ | G13: SUB CONT. | H13: Total | K13: Comparable Project
C14: % | I14: $/SF
A15: 01 00 00 | B15: General Requirements | C15: =H15/D$66 -> 0.05517354 | D15: =SUM('1'!F139:F140) -> 401881.12 | E15: =SUM('1'!G139:G140) -> 241 | F15: =SUM('1'!I139:I140) -> 179400 | G15: =SUM('1'!J139:J140) -> 3000 | H15: =D15+F15+G15 -> 584281.12 | I15: =ROUNDUP(H15/D$11,1)&"$/SF" -> 9$/SF | K15: =669794.47+187000 -> 856794.47 | L15: =K15/$L$11 -> 11.03434
A17: 02 00 00 | B17: Existing Conditions | C17: =H17/D$66 -> 0 | D17: =SUM('2'!F51:F52) -> 0 | E17: =SUM('2'!G51:G52) -> 0 | F17: =SUM('2'!I51:I52) -> 0 | G17: =SUM('2'!J51:J52) -> 0 | H17: =D17+F17+G17 -> 0 | I17: =ROUNDUP(H17/D$11,1)&"$/SF" -> 0$/SF
A19: 03 00 00 | B19: Concrete | C19: =H19/D$66 -> 0.063325356 | D19: =SUM('3'!F82:F83) -> 236330.86 | E19: =SUM('3'!G82:G83) -> 158.33333 | F19: =SUM('3'!I82:I83) -> 9500 | G19: =SUM('3'!J82:J83) -> 424777 | H19: =D19+F19+G19 -> 670607.86 | I19: =ROUNDUP(H19/D$11,1)&"$/SF" -> 10.3$/SF | K19: 1469856 | L19: =K19/$L$11 -> 18.929734
A21: 04 00 00 | B21: Masonry | C21: =H21/D$66 -> 0.013254164 | D21: =SUM('4'!F68:F69) -> 0 | E21: =SUM('4'!G68:G69) -> 0 | F21: =SUM('4'!I68:I69) -> 0 | G21: =SUM('4'!J68:J69) -> 140360 | H21: =D21+F21+G21 -> 140360 | I21: =ROUNDUP(H21/D$11,1)&"$/SF" -> 2.2$/SF | K21: 240000 | L21: =K21/$L$11 -> 3.0908716
A23: 05 00 00 | B23: Metals | C23: =H23/D$66 -> 0.020299571 | D23: =SUM('5'!F77:F78) -> 800 | E23: =SUM('5'!G77:G78) -> 0 | F23: =SUM('5'!I77:I78) -> 0 | G23: =SUM('5'!J77:J78) -> 214170 | H23: =D23+F23+G23 -> 214970 | I23: =ROUNDUP(H23/D$11,1)&"$/SF" -> 3.3$/SF | K23: 141945.5 | L23: =K23/$L$11 -> 1.8280638
A25: 06 00 00 | B25: Wood, Plastics, and Composites | C25: =H25/D$66 -> 0.24314324 | D25: =SUM('6'!F94:F95) -> 551103.89 | E25: =SUM('6'!G94:G95) -> 0 | F25: =SUM('6'!I94:I95) -> 0 | G25: =SUM('6'!J94:J95) -> 2023753.7 | H25: =D25+F25+G25 -> 2574857.6 | I25: =ROUNDUP(H25/D$11,1)&"$/SF" -> 39.3$/SF | K25: 2971859.6 | L25: =K25/$L$11 -> 38.273486
A27: 07 00 00 | B27: Thermal and Moisture Protection | C27: =H27/D$66 -> 0.11138191 | D27: =SUM('7'!F93:F94) -> 545786.81 | E27: =SUM('7'!G93:G94) -> 59077.8 | F27: =SUM('7'!I93:I94) -> 99349.2 | G27: =SUM('7'!J93:J94) -> 534385 | H27: =D27+F27+G27 -> 1179521 | I27: =ROUNDUP(H27/D$11,1)&"$/SF" -> 18$/SF | K27: 1267203.6 | L27: =K27/$L$11 -> 16.319849
A29: 08 00 00 | B29: Openings | C29: =H29/D$66 -> 0.025914348 | D29: =SUM('8'!F108:F109) -> 8000 | E29: =SUM('8'!G108:G109) -> 0 | F29: =SUM('8'!I108:I109) -> 0 | G29: =SUM('8'!J108:J109) -> 266429.81 | H29: =D29+F29+G29 -> 274429.81 | I29: =ROUNDUP(H29/D$11,1)&"$/SF" -> 4.2$/SF | K29: 508342.1 | L29: =K29/$L$11 -> 6.5467507
A31: 09 00 00 | B31: Finishes | C31: =H31/D$66 -> 0.16499952 | D31: =SUM('9'!F65:F66) -> 121100 | E31: =SUM('9'!G65:G66) -> 0 | F31: =SUM('9'!I65:I66) -> 0 | G31: =SUM('9'!J65:J66) -> 1626225 | H31: =D31+F31+G31 -> 1747325 | I31: =ROUNDUP(H31/D$11,1)&"$/SF" -> 26.7$/SF | K31: 1804882.8 | L31: =K31/$L$11 -> 23.24442
A33: 10 00 00 | B33: Specialties | C33: =H33/D$66 -> 0.0083262291 | D33: =SUM('10'!F74:F75) -> 13329.39 | E33: =SUM('10'!G74:G75) -> 5 | F33: =SUM('10'!I74:I75) -> 300 | G33: =SUM('10'!J74:J75) -> 74544.37 | H33: =D33+F33+G33 -> 88173.76 | I33: =ROUNDUP(H33/D$11,1)&"$/SF" -> 1.4$/SF | K33: 101680 | L33: =K33/$L$11 -> 1.3094993
A35: 11 00 00 | B35: Equipment | C35: =H35/D$66 -> 0.018942615 | D35: =SUM('11'!F99:F100) -> 200600 | E35: =SUM('11'!G99:G100) -> 0 | F35: =SUM('11'!I99:I100) -> 0 | G35: =SUM('11'!J99:J100) -> 0 | H35: =D35+F35+G35 -> 200600 | I35: =ROUNDUP(H35/D$11,1)&"$/SF" -> 3.1$/SF | K35: 234000 | L35: =K35/$L$11 -> 3.0135998
A37: 12 00 00 | B37: Furnishings | C37: =H37/D$66 -> 0.0038999501 | D37: =SUM('12'!F99:F100) -> 41300 | E37: =SUM('12'!G99:G100) -> 0 | F37: =SUM('12'!I99:I100) -> 0 | G37: =SUM('12'!J99:J100) -> 0 | H37: =D37+F37+G37 -> 41300 | I37: =ROUNDUP(H37/D$11,1)&"$/SF" -> 0.7$/SF | K37: 47669 | L37: =K37/$L$11 -> 0.6139115
A39: 13 00 00 | B39: Special Construction | C39: =H39/D$66 -> 0.011463776 | D39: =+SUM('13'!F99:F100) -> 10000 | E39: =SUM('13'!G99:G100) -> 0 | F39: =SUM('13'!I99:I100) -> 0 | G39: =SUM('13'!J99:J100) -> 111400 | H39: =D39+F39+G39 -> 121400 | I39: =ROUNDUP(H39/D$11,1)&"$/SF" -> 1.9$/SF
A41: 14 00 00 | B41: Conveying Equipment | C41: =H41/D$66 -> 0.014663529 | D41: =SUM('14'!F99:F100) -> 0 | E41: =SUM('14'!G99:G100) -> 0 | F41: =SUM('14'!I99:I100) -> 0 | G41: =SUM('14'!J99:J100) -> 155285 | H41: =D41+F41+G41 -> 155285 | I41: =ROUNDUP(H41/D$11,1)&"$/SF" -> 2.4$/SF | K41: 324859 | L41: =K41/$L$11 -> 4.1837394
A43: 21 00 00 | B43: Fire Suppression | C43: =H43/D$66 -> 0.020019114 | D43: =SUM('21'!F99:F100) -> 0 | E43: =SUM('21'!G99:G100) -> 0 | F43: =SUM('21'!I99:I100) -> 0 | G43: =SUM('21'!J99:J100) -> 212000 | H43: =D43+F43+G43 -> 212000 | I43: =ROUNDUP(H43/D$11,1)&"$/SF" -> 3.3$/SF | K43: 256043.6 | L43: =K43/$L$11 -> 3.2974912
A45: 22 00 00 | B45: Plumbing | C45: =H45/D$66 -> 0.06372594 | D45: =SUM('22'!F94:F95) -> 0 | E45: =SUM('22'!G94:G95) -> 0 | F45: =SUM('22'!I94:I95) -> 0 | G45: =SUM('22'!J94:J95) -> 674850 | H45: =D45+F45+G45 -> 674850 | I45: =ROUNDUP(H45/D$11,1)&"$/SF" -> 10.3$/SF | K45: 813490.08 | L45: =K45/$L$11 -> 10.476639
A47: 23 00 00 | B47: HVAC | C47: =H47/D$66 -> 0.044160089 | D47: =SUM('23'!F102:F103) -> 0 | E47: =SUM('23'!G102:G103) -> 0 | F47: =SUM('23'!I102:I103) -> 0 | G47: =SUM('23'!J102:J103) -> 467650 | H47: =D47+F47+G47 -> 467650 | I47: =ROUNDUP(H47/D$11,1)&"$/SF" -> 7.2$/SF | K47: 641638.63 | L47: =K47/$L$11 -> 8.2634276
A49: 25 00 00 | B49: Integrated Automation | C49: =H49/D$66 -> 0 | D49: =SUM('25'!F54:F55) -> 0 | E49: =SUM('25'!G54:G55) -> 0 | F49: =SUM('25'!I54:I55) -> 0 | G49: =SUM('25'!J54:J55) -> 0 | H49: =D49+F49+G49 -> 0 | I49: =ROUNDUP(H49/D$11,1)&"$/SF" -> 0$/SF
A51: 26 00 00 | B51: Electrical | C51: =H51/D$66 -> 0.077705986 | D51: =SUM('26'!F58:F59) -> 52897 | E51: =SUM('26'!G58:G59) -> 0 | F51: =SUM('26'!I58:I59) -> 0 | G51: =SUM('26'!J58:J59) -> 770000 | H51: =D51+F51+G51 -> 822897 | I51: =ROUNDUP(H51/D$11,1)&"$/SF" -> 12.6$/SF | K51: 1110432.1 | L51: =K51/$L$11 -> 14.300846
A53: 27 00 00 | B53: Communications | C53: =H53/D$66 -> 0 | D53: =SUM('27'!F99:F100) -> 0 | E53: =SUM('27'!G99:G100) -> 0 | F53: =SUM('27'!I99:I100) -> 0 | G53: =SUM('27'!J99:J100) -> 0 | H53: =D53+F53+G53 -> 0 | I53: =ROUNDUP(H53/D$11,1)&"$/SF" -> 0$/SF
A55: 28 00 00 | B55: Electronic Safety and Security | C55: =H55/D$66 -> 0 | D55: =SUM('28'!F55:F56) -> 0 | E55: =SUM('28'!G55:G56) -> 0 | F55: =SUM('28'!I55:I56) -> 0 | G55: =SUM('28'!J55:J56) -> 0 | H55: =D55+F55+G55 -> 0 | I55: =ROUNDUP(H55/D$11,1)&"$/SF" -> 0$/SF
A57: 31 00 00 | B57: Earthwork | C57: =H57/D$66 -> 0.025335511 | D57: =SUM('31'!F69:F70) -> 40000 | E57: =SUM('31'!G69:G70) -> 0 | F57: =SUM('31'!I69:I70) -> 0 | G57: =SUM('31'!J69:J70) -> 228300 | H57: =D57+F57+G57 -> 268300 | I57: =ROUNDUP(H57/D$11,1)&"$/SF" -> 4.1$/SF | K57: 771509.48 | L57: =K57/$L$11 -> 9.9359865
A59: 32 00 00 | B59: Exterior Improvements | C59: =H59/D$66 -> 0.014265603 | D59: =SUM('32'!F97:F98) -> 0 | E59: =SUM('32'!G97:G98) -> 0 | F59: =SUM('32'!I97:I98) -> 0 | G59: =SUM('32'!J97:J98) -> 151071.01 | H59: =D59+F59+G59 -> 151071.01 | I59: =ROUNDUP(H59/D$11,1)&"$/SF" -> 2.4$/SF | K59: 211970 | L59: =K59/$L$11 -> 2.7298836
A61: 33 00 00 | B61: Utilities | C61: =H61/D$66 -> 0 | D61: =SUM('33'!F57:F58) -> 0 | E61: =SUM('33'!G57:G58) -> 0 | F61: =SUM('33'!I57:I58) -> 0 | G61: =SUM('33'!J57:J58) -> 0 | H61: =D61+F61+G61 -> 0 | I61: =ROUNDUP(H61/D$11,1)&"$/SF" -> 0$/SF
B64: Sub Totals>>>>>> | C64: =SUM(C15:C63) -> 1 | D64: =SUM(D15:D63) -> 2223129.1 | E64: =SUM(E15:E63) -> 59482.133 | F64: =SUM(F15:F63) -> 288549.2 | G64: =SUM(G15:G63) -> 8078200.9 | H64: =SUM(H15:H63) -> 10589879 | I64: =ROUNDUP(H64/D$11,1)&"$/SF" -> 161.5$/SF
B66: Total Construction Cost>>>>>> | D66: =D64+F64+G64 -> 10589879
N67: Total Job | O67: 12246313
B68: OH&P>>>>>> | D68: =(D66*E68) -> 529493.96 | E68: 0.05 | K68: =D68/59 -> 8974.4738 | N68: Ready to award / Awarded | O68: ='3'!M13+'3'!J14+'5'!M14+'6'!J33+'6'!J11+'7'!M76+'7'!M36+'8'!M13+'8'!M38+'9'!J11+'9'!J57+'9'!K47+'10'!M48+'10'!M54+'13'!M15+'14'!J12+'21'!J12+'22'!J14+'23'!J12+'26'!J16+'31'!M31+'3'!M40+'5'!M58+'8'!K69 -> 8049129.9
F69: HST | G69: TOTAL | N69: % | O69: =O68/O67 -> 0.65726967
F70: 0.15
B71: Estimated Price | D71: =D68+D66 -> 11119373 | F71: =D71*F70 -> 1667906 | G71: =D71+F71 -> 12787279
K73: Budget
F74: HST | G74: TOTAL | K74: 11301598
B75: Total (HST excluded) | D75: =D71+D73 -> 11119373 | F75: =D75*F70 -> 1667906 | G75: =D75+F75 -> 12787279 | K75: Difference
K76: =K74-D75 -> 182224.98
D77: =D71/D11 -> 169.52331 | E77: /sq.ft. | F77: =D71/59 -> 188463.95
C81: Schedule | D81: 60 | E81: Weeks | G81: Job Type | H81: Target Margin
C82: Soft Cost | D82: =D68+F15+'1'!K14+'1'!K93+'1'!K38+'1'!K103 -> 737710.08 | E82: =D82/D81 -> 12295.168 | G82: A > 1,000,000 | H82: 0.1
G83: B > 500,000 | H83: 0.15
C84: Margin | D84: =D82/D71 -> 0.066344575 | G84: C > 100,000 | H84: 0.2
C85: Buyouts | D85: =D75*E85 -> 111193.73 | E85: 0.01 | G85: D < 100,000 | H85: 0.25
C86: CO's | D86: =D75*E86 -> 555968.65 | E86: 0.05
A87: Competititors on Bid | B87: =COUNTIF(A88:A96,"*") -> 0
E89: =D75*0.025 -> 277984.33
E90: =D75+E89 -> 11397357

Sheet 1
C1: ='Estimate Summary'!C1:H1 -> 0
G5: General Requirements | J5: Schedule
D6: ='Estimate Summary'!C11 -> Area: | E6: ='Estimate Summary'!D11 -> 65592 | F6: ='Estimate Summary'!E11 -> Sq. Ft. | J6: ='Estimate Summary'!D81 -> 60 | K6: Weeks
A9: CODE | B9: DESCRIPTION | C9: Materials & Equipment | G9: Labor | L9: Sub Contractor | M9: Quote Total | N9: Additional Quote Info
A10: 01 11 00 | B10: Preconstruction Costs | C10: Qty | D10: Unit | E10: U. Price | F10: Sub Total | G10: MHrs | H10: U. Price | I10: Sub Total | J10: Quote | K10: Total
A11: 01 11 13 | B11: Senior Construction Manager | D11: LS | E11: 0 | F11: =C11*E11 -> 0 | H11: 0 | I11: =G11*H11 -> 0 | K11: =F11+I11+J11 -> 0
A12: 01 11 16 | B12: Senior Estimator | D12: LS | E12: 0 | F12: =C12*E12 -> 0 | H12: 0 | I12: =G12*H12 -> 0 | K12: =F12+I12+J12 -> 0
A13: 01 11 19 | B13: Junior Estimator | D13: LS | E13: 0 | F13: =C13*E13 -> 0 | H13: 0 | I13: =G13*H13 -> 0 | K13: =F13+I13+J13 -> 0
A14: 01 11 23 | B14: Reprographics | D14: LS | E14: 0 | F14: =C14*E14 -> 0 | H14: 0 | I14: =G14*H14 -> 0 | K14: =F14+I14+J14 -> 0
A15: 01 11 26 | B15: Design Costs | D15: LS | E15: 0 | F15: =C15*E15 -> 0 | H15: 0 | I15: =G15*H15 -> 0 | K15: =F15+I15+J15 -> 0
A16: 01 11 26.13 | B16: Architectural | D16: LS | E16: 0 | F16: =C16*E16 -> 0 | H16: 0 | I16: =G16*H16 -> 0 | K16: =F16+I16+J16 -> 0
A17: 01 11 26.16 | B17: Civil | D17: LS | E17: 0 | F17: =C17*E17 -> 0 | H17: 0 | I17: =G17*H17 -> 0 | K17: =F17+I17+J17 -> 0
A18: 01 11 26.19 | B18: Structural | D18: LS | E18: 0 | F18: =C18*E18 -> 0 | H18: 0 | I18: =G18*H18 -> 0 | K18: =F18+I18+J18 -> 0
A19: 01 11 26.23 | B19: HVAC | D19: LS | E19: 0 | F19: =C19*E19 -> 0 | H19: 0 | I19: =G19*H19 -> 0 | K19: =F19+I19+J19 -> 0
A20: 01 11 26.26 | B20: Plumbing | D20: LS | E20: 0 | F20: =C20*E20 -> 0 | H20: 0 | I20: =G20*H20 -> 0 | K20: =F20+I20+J20 -> 0
A21: 01 11 26.29 | B21: Electrical | D21: LS | E21: 0 | F21: =C21*E21 -> 0 | H21: 0 | I21: =G21*H21 -> 0 | K21: =F21+I21+J21 -> 0
A22: 01 11 26.33 | B22: Geotechnical | D22: LS | E22: 0 | F22: =C22*E22 -> 0 | H22: 0 | I22: =G22*H22 -> 0 | K22: =F22+I22+J22 -> 0
J24: Sub Total | K24: =SUM(K11:K23) -> 0
A25: CODE | B25: DESCRIPTION | C25: Materials & Equipment | G25: Labor
A26: 01 31 00 | B26: Project Management and Coordination | C26: Qty | D26: Unit | E26: U. Price | F26: Sub Total | G26: MHrs | H26: U. Price | I26: Sub Total | J26: Quote | K26: Total
A27: 01 31 01 | B27: Senior Construction Manager | D27: LS | E27: 0 | F27: =C27*E27 -> 0 | H27: 0 | I27: =G27*H27 -> 0 | K27: =F27+I27+J27 -> 0
A28: 01 31 02 | B28: Senior Estimator | D28: LS | E28: 0 | F28: =C28*E28 -> 0 | H28: 0 | I28: =G28*H28 -> 0 | K28: =F28+I28+J28 -> 0
A29: 01 31 03 | B29: Senior Project Manager | C29: =J6 -> 60 | D29: LS | E29: 0 | F29: =C29*E29 -> 0 | H29: 100 | I29: =H29*G29*C29 -> 0 | K29: =F29+I29+J29 -> 0
A30: 01 31 04 | B30: Project Coordinator | C30: =J6 -> 60 | D30: LS | E30: 0 | F30: =C30*E30 -> 0 | H30: 75 | I30: =H30*G30*C30 -> 0 | K30: =F30+I30+J30 -> 0
A31: 01 31 05 | B31: Project Superintendent | C31: =J6 -> 60 | D31: LS | E31: 0 | F31: =C31*E31 -> 0 | G31: 1 | H31: 2750 | I31: =H31*G31*C31 -> 165000 | K31: =F31+I31+J31 -> 165000 | L31: Ekinox | M31: 188344 | N31: Spent to date $168k
A32: 01 31 06 | B32: Project Foreman | D32: LS | E32: 0 | F32: =C32*E32 -> 0 | H32: 0 | I32: =G32*H32 -> 0 | K32: =F32+I32+J32 -> 0
D33: LS | E33: 0 | F33: =C33*E33 -> 0 | H33: 0 | I33: =G33*H33 -> 0 | K33: =F33+I33+J33 -> 0
K34: =F34+I34+J34 -> 0
J35: Sub Total | K35: =SUM(K27:K34) -> 165000
A36: CODE | B36: DESCRIPTION
A37: 01 32 00 | B37: Insurance | D37: /$1000 | E37: Cost | F37: Rate | G37: Toll Cost | H37: Frequency | J37: Sub Total | K37: Total
A38: 01 32 01 | B38: General Liability & Contractor's Pollution Liability | C38: =SUM('Estimate Summary'!H17:H61)/1000 -> 10005.598 | D38: /$1000 | E38: 0.63 | K38: =F38 -> 0
B39: Contractor's Pollution Liability | C39: =SUM('Estimate Summary'!H17:H61)/1000 -> 10005.598 | D39: /$1000 | E39: 1.29 | K39: =F39 -> 0 | L39: By Client
B40: Builders Risk | C40: =+J6/4.5 -> 13.333333 | D40: $1000/month | E40: 0.75 | K40: =F40 -> 0 | L40: Ekinox | M40: 188344
B41: Wrap-up Liability | C41: =SUM('Estimate Summary'!H17:H61)/1000 -> 10005.598 | D41: /$1000 | E41: 1.88 | K41: =F41 -> 0
A45: 01 32 00 | J45: Sub Total | K45: =SUM(K38:K44) -> 0
A46: CODE | B46: DESCRIPTION | C46: Materials & Equipment | G46: Labor
A47: CODE | B47: DESCRIPTION
A48: 01 32 00 | B48: Travel | C48: Frequency | D48: Weeks | E48: Distance (Round Trip) | F48: Rate | G48: Toll Cost | H48: Frequency | J48: Sub Total | K48: Total
B49: PM KM | D49: =J6 -> 60 | E49: 0 | F49: 0.45 | H49: =C49*D49 -> 0 | J49: =C49*D49*E49*F49+G49*H49 -> 0 | K49: =J49+(G49*H49) -> 0
B50: Superintendent KM | D50: =J6 -> 60 | E50: 0 | F50: 0.45 | H50: =C50*D50 -> 0 | J50: =C50*D50*E50*F50+G50*H50 -> 0 | K50: =J50+(G50*H50) -> 0
B51: Hotel | D51: =J6 -> 60 | F51: 120 | J51: =C51*D51*F51 -> 0 | K51: =J51 -> 0
B52: Per Diem
B53: foreman - Mondays | D53: =J$6 -> 60 | F53: 40 | J53: =C53*D53*F53 -> 0 | K53: =J53 -> 0
B54: foreman: Tues to Thurs | D54: =J$6 -> 60 | F54: 47 | J54: =C54*D54*F54 -> 0 | K54: =J54 -> 0
B55: foreman: Fridays | D55: =J$6 -> 60 | F55: 22 | J55: =C55*D55*F55 -> 0 | K55: =J55 -> 0
A56: 01 32 00 | J56: Sub Total | K56: =SUM(K49:K55) -> 0
A57: CODE | B57: DESCRIPTION | C57: Materials & Equipment | G57: Labor
A58: 01 41 00 | B58: Permits | C58: Qty | D58: Unit | E58: U. Price | F58: Sub Total | G58: MHrs | H58: U. Price | I58: Sub Total | J58: Quote | K58: Total
A59: 01 41 00 | B59: Bldg Permit Fees | C59: =SUM('Estimate Summary'!H17:H61)/1000 -> 10005.598 | D59: /$1000 | E59: 0 | F59: =C59*E59 -> 0 | J59: 3000 | K59: =F59+I59+J59 -> 3000 | L59: By Client
B60: Moncton | C60: 8 | D60: /$1000 | E60: "+ Development Fee | G60: $100 <$500k, $150 $500k to 1M, $300 1M - 5 M, $500 > 5M
B61: Dieppe | C61: 7.5 | D61: /$1000
B62: Saint John | C62: 8.9 | D62: /$1000 | E62: $120 Base Fee
B63: Fredericton | C63: 8 | D63: /$1000
B64: Halifax | C64: 5.5 | D64: /$1000
J67: Sub Total | K67: =SUM(K59:K66) -> 3000
A68: CODE | B68: DESCRIPTION | C68: Materials & Equipment | G68: Labor
A69: 01 45 00 | B69: Quality Control | C69: Qty | D69: Unit | E69: U. Price | F69: Sub Total | G69: MHrs | H69: U. Price | I69: Sub Total | J69: Quote | K69: Total
A70: 01 45 01 | B70: Soil Investigation and Testing | C70: 1 | D70: LS | E70: 2500 | F70: =C70*E70 -> 2500 | H70: 0 | I70: =G70*H70 -> 0 | K70: =F70+I70+J70 -> 2500
A71: 01 45 02 | B71: Material Inspection and Testing | C71: 1 | D71: LS | E71: 2500 | F71: =C71*E71 -> 2500 | H71: 0 | I71: =G71*H71 -> 0 | K71: =F71+I71+J71 -> 2500 | L71: Ekinox | M71: 25768
A72: 01 45 03 | B72: Survey and Layout | C72: 1 | D72: LS | E72: 3000 | F72: =C72*E72 -> 3000 | H72: 0 | I72: =G72*H72 -> 0 | K72: =F72+I72+J72 -> 3000
A73: 01 45 04 | B73: Hazardous Idendification Inspection | D73: LS | E73: 0 | F73: =C73*E73 -> 0 | H73: 0 | I73: =G73*H73 -> 0 | K73: =F73+I73+J73 -> 0
A74: 01 45 05 | B74: Sanitary Line Video | D74: LS | E74: 0 | F74: =C74*E74 -> 0 | H74: 0 | I74: =G74*H74 -> 0 | K74: =F74+I74+J74 -> 0
J76: Sub Total | K76: =SUM(K70:K75) -> 8000
A77: CODE | B77: DESCRIPTION | C77: Materials & Equipment | G77: Labor
A78: 01 51 00 | B78: Temporary Utilities | C78: Qty | D78: Unit | E78: U. Price | F78: Sub Total | G78: MHrs | H78: U. Price | I78: Sub Total | J78: Quote | K78: Total
A79: 01 51 01 | B79: Temporary Fire Protection | D79: Week | E79: 0 | F79: =C79*E79 -> 0 | H79: 0 | I79: =G79*H79 -> 0 | K79: =F79+I79+J79 -> 0
A80: 01 51 02 | B80: Temporary Power | C80: =J6 -> 60 | D80: Week | E80: 250 | F80: =C80*E80 -> 15000 | H80: 0 | I80: =G80*H80 -> 0 | K80: =F80+I80+J80 -> 15000 | L80: Ekinox | M80: 16732.93
A81: 01 51 03 | B81: Temporary Lighting | D81: Week | E81: 0 | F81: =C81*E81 -> 0 | H81: 0 | I81: =G81*H81 -> 0 | K81: =F81+I81+J81 -> 0
A82: 01 51 04 | B82: Temporary Fuel Oil | D82: Week | E82: 0 | F82: =C82*E82 -> 0 | H82: 0 | I82: =G82*H82 -> 0 | K82: =F82+I82+J82 -> 0
A83: 01 51 05 | B83: Temp HVAC | D83: Week | E83: 0 | F83: =C83*E83 -> 0 | H83: 0 | I83: =G83*H83 -> 0 | K83: =F83+I83+J83 -> 0
A84: 01 51 06 | B84: Temporary Internet | D84: Week | E84: 0 | F84: =C84*E84 -> 0 | H84: 0 | I84: =G84*H84 -> 0 | K84: =F84+I84+J84 -> 0
A85: 01 51 07 | B85: Temporary Water | D85: Week | E85: 0 | F85: =C85*E85 -> 0 | H85: 0 | I85: =G85*H85 -> 0 | K85: =F85+I85+J85 -> 0
J87: Sub Total | K87: =SUM(K79:K86) -> 15000
A88: CODE | B88: DESCRIPTION | C88: Materials & Equipment | G88: Labor
A89: 01 52 00 | B89: Construction Facilities | C89: Qty | D89: Unit | E89: U. Price | F89: Sub Total | G89: MHrs | H89: U. Price | I89: Sub Total | J89: Quote | K89: Total
A90: 01 52 01 | B90: Construction Field Office | C90: =J6/4 -> 15 | D90: Month | E90: 825 | F90: =C90*E90 -> 12375 | H90: 0 | I90: =G90*H90 -> 0 | K90: =F90+I90+J90 -> 12375
A91: 01 52 01 | B91: Field Office One Time Charges | C91: 1 | D91: Ea | E91: 1840 | F91: =C91*E91 -> 1840 | K91: =F91+I91+J91 -> 1840
A92: 01 52 02 | B92: Sanitary Facilities | C92: =J6*4 -> 240 | D92: Week | E92: 50 | F92: =C92*E92 -> 12000 | H92: 0 | I92: =G92*H92 -> 0 | K92: =F92+I92+J92 -> 12000 | L92: Ekinox | M92: 32020
A93: 01 52 03 | B93: Drawing Reprographics | C93: =SUM('Estimate Summary'!H17:H61)/1000 -> 10005.598 | D93: M | E93: 0.55 | F93: =C93*E93 -> 5503.0789 | H93: 0 | I93: =G93*H93 -> 0 | K93: =F93+I93+J93 -> 5503.0789
A94: 01 52 04 | B94: First-Aid / Safety | C94: =J6/2 -> 30 | D94: Week | E94: 125 | F94: =C94*E94 -> 3750 | H94: 0 | I94: =G94*H94 -> 0 | K94: =F94+I94+J94 -> 3750
A95: 01 52 05 | B95: Job Sign | D95: Ea | E95: 200 | F95: =C95*E95 -> 0 | H95: 0 | I95: =G95*H95 -> 0 | K95: =F95+I95+J95 -> 0
J97: Sub Total | K97: =SUM(K90:K96) -> 35468.079
A98: CODE | B98: DESCRIPTION | C98: Materials & Equipment | G98: Labor
A99: 01 54 00 | B99: Construction Aids | C99: Qty | D99: Unit | E99: U. Price | F99: Sub Total | G99: MHrs | H99: U. Price | I99: Sub Total | J99: Quote | K99: Total
A100: 01 54 01 | B100: Security | C100: 1 | D100: LS | E100: 30000 | F100: =C100*E100 -> 30000 | H100: 0 | I100: =G100*H100 -> 0 | K100: =F100+I100+J100 -> 30000 | L100: Ekinox | M100: 30000
A101: 01 54 02 | B101: Rentals | C101: =J6/4 -> 15 | D101: LS | E101: 10000 | F101: =C101*E101 -> 150000 | H101: 0 | I101: =G101*H101 -> 0 | K101: =F101+I101+J101 -> 150000
A102: 01 54 03 | B102: Small Tools | C102: ='Estimate Summary'!E62 -> 0 | D102: Allow | E102: 0 | F102: =C102*E102 -> 0 | H102: 0 | I102: =G102*H102 -> 0 | K102: =F102+I102+J102 -> 0 | L102: Ekinox | M102: =29784+97825 -> 127609
A103: 01 54 04 | B103: Technology (Procore, Smartbid, On-screen, Imaginit, Sage 300) | C103: =SUM('Estimate Summary'!H17:H63)/1000 -> 10005.598 | D103: /$1000 | E103: 2.33 | F103: =C103*E103 -> 23313.043 | H103: 0 | I103: =G103*H103 -> 0 | K103: =F103+I103+J103 -> 23313.043
J105: Sub Total | K105: =SUM(K100:K104) -> 203313.04
A106: CODE | B106: DESCRIPTION | C106: Materials & Equipment | G106: Labor
A107: 01 55 00 | B107: Winter Conditions | C107: Qty | D107: Unit | E107: U. Price | F107: Sub Total | G107: MHrs | H107: U. Price | I107: Sub Total | J107: Quote | K107: Total
A109: 01 55 01 | B109: Winter Conditions | C109: 5 | D109: month | E109: 15000 | F109: =C109*E109 -> 75000 | K109: =F109 -> 75000 | L109: Ekinox | M109: 72459.76
A110: 01 55 02 | B110: Tarps (10) | D110: ea | E110: 73 | F110: =C110*E110 -> 0 | K110: =F110 -> 0
A111: 01 55 03 | B111: Fans | D111: month | E111: 355 | F111: =C111*E111 -> 0 | K111: =F111 -> 0
A112: 01 55 04 | B112: Fuel Cube | D112: month | E112: 609 | F112: =C112*E112 -> 0 | K112: =F112 -> 0
A113: 01 55 05 | B113: Delivery | D113: ea | E113: 98 | F113: =C113*E113 -> 0 | K113: =F113 -> 0
A114: 01 55 06 | B114: Pickup | D114: ea | E114: 98 | F114: =C114*E114 -> 0 | K114: =F114 -> 0
B115: Quantity of Fuel
C116: Tank Size | D116: L/Hr | E116: Running (Hours / Day) | F116: Litres / Day | G116: Duration (Days)
...

Sheet 2
C1: ='Estimate Summary'!C1:H1 -> 0
G5: Existing Conditions | J5: Schedule
D6: ='Estimate Summary'!C11 -> Area: | E6: ='Estimate Summary'!D11 -> 65592 | F6: ='Estimate Summary'!E11 -> Sq. Ft. | J6: ='1'!J6 -> 60 | K6: Weeks
A11: CODE | B11: DESCRIPTION | C11: Materials & Equipment | G11: Labor | L11: Sub Contractor | M11: Quote Total | N11: Additional Quote Info
A12: 02 00 00 | B12: Existing Conditions | C12: Qty | D12: Unit | E12: U. Price | F12: Sub Total | G12: MHrs | H12: U. Price | I12: Sub Total | J12: Quote | K12: Total
A13: 02 41 00 | B13: Demolition | D13: LS | E13: 0 | F13: =C13*E13 -> 0 | H13: 0 | I13: =G13*H13 -> 0 | K13: =F13+I13+J13 -> 0
D14: LS | E14: 0 | F14: =C14*E14 -> 0 | H14: 0 | I14: =G14*H14 -> 0 | K14: =F14+I14+J14 -> 0
D15: LS | E15: 0 | F15: =C15*E15 -> 0 | H15: 0 | I15: =G15*H15 -> 0 | K15: =F15+I15+J15 -> 0
D16: LS | E16: 0 | F16: =C16*E16 -> 0 | H16: 0 | I16: =G16*H16 -> 0 | K16: =F16+I16+J16 -> 0
D17: LS | E17: 0 | F17: =C17*E17 -> 0 | H17: 0 | I17: =G17*H17 -> 0 | K17: =F17+I17+J17 -> 0
D18: LS | E18: 0 | F18: =C18*E18 -> 0 | H18: 0 | I18: =G18*H18 -> 0 | K18: =F18+I18+J18 -> 0
D19: LS | E19: 0 | F19: =C19*E19 -> 0 | H19: 0 | I19: =G19*H19 -> 0 | K19: =F19+I19+J19 -> 0
D20: LS | E20: 0 | F20: =C20*E20 -> 0 | H20: 0 | I20: =G20*H20 -> 0 | K20: =F20+I20+J20 -> 0
D21: LS | E21: 0 | F21: =C21*E21 -> 0 | H21: 0 | I21: =G21*H21 -> 0 | K21: =F21+I21+J21 -> 0
D22: LS | E22: 0 | F22: =C22*E22 -> 0 | H22: 0 | I22: =G22*H22 -> 0 | K22: =F22+I22+J22 -> 0
D23: LS | E23: 0 | F23: =C23*E23 -> 0 | H23: 0 | I23: =G23*H23 -> 0 | K23: =F23+I23+J23 -> 0
D24: LS | E24: 0 | F24: =C24*E24 -> 0 | H24: 0 | I24: =G24*H24 -> 0 | K24: =F24+I24+J24 -> 0
J26: Sub Total | K26: =SUM(K13:K25) -> 0
A27: CODE | B27: DESCRIPTION | C27: Materials & Equipment | G27: Labor
A28: 02 82 00 | B28: Asbestos Remediation | C28: Qty | D28: Unit | E28: U. Price | F28: Sub Total | G28: MHrs | H28: U. Price | I28: Sub Total | J28: Quote | K28: Total
D29: LS | E29: 0 | F29: =C29*E29 -> 0 | H29: 0 | I29: =G29*H29 -> 0 | K29: =F29+I29+J29 -> 0
D30: LS | E30: 0 | F30: =C30*E30 -> 0 | H30: 0 | I30: =G30*H30 -> 0 | K30: =F30+I30+J30 -> 0
D31: LS | E31: 0 | F31: =C31*E31 -> 0 | H31: 0 | I31: =G31*H31 -> 0 | K31: =F31+I31+J31 -> 0
D32: LS | E32: 0 | F32: =C32*E32 -> 0 | H32: 0 | I32: =G32*H32 -> 0 | K32: =F32+I32+J32 -> 0
D33: LS | E33: 0 | F33: =C33*E33 -> 0 | H33: 0 | I33: =G33*H33 -> 0 | K33: =F33+I33+J33 -> 0
D34: LS | E34: 0 | F34: =C34*E34 -> 0 | H34: 0 | I34: =G34*H34 -> 0 | K34: =F34+I34+J34 -> 0
D35: LS | E35: 0 | F35: =C35*E35 -> 0 | H35: 0 | I35: =G35*H35 -> 0 | K35: =F35+I35+J35 -> 0
J37: Sub Total | K37: =SUM(K29:K36) -> 0
A38: CODE | B38: DESCRIPTION | C38: Materials & Equipment | G38: Labor
A39: 02 83 00 | B39: Trenching | C39: Qty | D39: Unit | E39: U. Price | F39: Sub Total | G39: MHrs | H39: U. Price | I39: Sub Total | J39: Quote | K39: Total
D40: LS | E40: 0 | F40: =C40*E40 -> 0 | H40: 0 | I40: =G40*H40 -> 0 | K40: =F40+I40+J40 -> 0
B41: Sanitary Trenching | D41: ft | E41: 65 | F41: =C41*E41 -> 0 | H41: 0 | I41: =G41*H41 -> 0 | K41: =F41+I41+J41 -> 0
D42: LS | E42: 0 | F42: =C42*E42 -> 0 | H42: 0 | I42: =G42*H42 -> 0 | K42: =F42+I42+J42 -> 0
B43: Conduit Trenching | D43: ft | E43: 35 | F43: =C43*E43 -> 0 | H43: 0 | I43: =G43*H43 -> 0 | K43: =F43+I43+J43 -> 0
D44: LS | E44: 0 | F44: =C44*E44 -> 0 | H44: 0 | I44: =G44*H44 -> 0 | K44: =F44+I44+J44 -> 0
D45: LS | E45: 0 | F45: =C45*E45 -> 0 | H45: 0 | I45: =G45*H45 -> 0 | K45: =F45+I45+J45 -> 0
D46: LS | E46: 0 | F46: =C46*E46 -> 0 | H46: 0 | I46: =G46*H46 -> 0 | K46: =F46+I46+J46 -> 0
J48: Sub Total | K48: =SUM(K40:K47) -> 0
F49: Material Total | G49: Total Hours | I49: Labor Total | J49: Contractor Total | K49: TOTAL
A50: $ / Sq.Ft | B50: TOTAL DIVISION 2
A51: =K51/E6 -> 0 | F51: =SUM(F13:F25,F40:F47,F29:F35) -> 0 | G51: =SUM(G13:G25,G40:G47,G29:G35) -> 0 | I51: =SUM(I13:I25,I40:I47,I29:I35) -> 0 | J51: =SUM(J13:J25,J40:J47,J29:J35) -> 0 | K51: =SUM(K48,K26,K37) -> 0

Sheet 3
C1: ='Estimate Summary'!C1:H1 -> 0
G5: Concrete | J5: Schedule
D6: ='Estimate Summary'!C11 -> Area: | E6: ='Estimate Summary'!D11 -> 65592 | F6: ='Estimate Summary'!E11 -> Sq. Ft. | J6: ='1'!J6 -> 60 | K6: Weeks
A11: CODE | B11: DESCRIPTION | C11: Materials & Equipment | G11: Labor | L11: Sub Contractor | M11: Quote Total | N11: Additional Quote Info
A12: 03 11 00 | B12: Concrete Forming | C12: Qty | D12: Unit | E12: U. Price | F12: Sub Total | G12: MHrs | H12: U. Price | I12: Sub Total | J12: Quote | K12: Total
A13: 03 11 01 | B13: Contractor Quote | K13: =F13+I13+J13 -> 0 | L13: Spent incl Rebar | M13: 561600
A14: 03 11 02.1 | B14: Footings | D14: ft | E14: 25 | F14: =C14*E14 -> 0 | H14: 0 | I14: =G14*H14 -> 0 | J14: =M14-M13 -> 302400 | K14: =F14+I14+J14 -> 302400 | L14: Optimal | M14: 864000 | N14: Can start within 2 weeks. Says 6 to 8 weeks of work left to do
A15: 03 11 02.2 | B15: Walls | D15: ft | E15: 45 | F15: =C15*E15 -> 0 | H15: 0 | I15: =G15*H15 -> 0 | K15: =F15+I15+J15 -> 0
A16: 03 11 02.3 | B16: Piers | D16: ea | E16: 150 | F16: =C16*E16 -> 0 | H16: 0 | I16: =G16*H16 -> 0 | K16: =F16+I16+J16 -> 0
D17: LS | E17: 0 | F17: =C17*E17 -> 0 | H17: 0 | I17: =G17*H17 -> 0 | K17: =F17+I17+J17 -> 0
D18: LS | E18: 0 | F18: =C18*E18 -> 0 | H18: 0 | I18: =G18*H18 -> 0 | K18: =F18+I18+J18 -> 0
D19: LS | E19: 0 | F19: =C19*E19 -> 0 | H19: 0 | I19: =G19*H19 -> 0 | K19: =F19+I19+J19 -> 0
D20: LS | E20: 0 | F20: =C20*E20 -> 0 | H20: 0 | I20: =G20*H20 -> 0 | K20: =F20+I20+J20 -> 0
J26: Sub Total | K26: =SUM(K13:K25) -> 302400
A27: CODE | B27: DESCRIPTION | C27: Materials & Equipment | G27: Labor
A28: 03 20 00 | B28: Concrete Reinforcing | C28: Qty | D28: Unit | E28: U. Price | F28: Sub Total | G28: MHrs | H28: U. Price | I28: Sub Total | J28: Quote | K28: Total
A29: 03 20 01 | B29: Contractor Quote | K29: =F29+I29+J29 -> 0 | T29: Type | U29: Width | W29: Height
A30: 03 20 02 | B30: Rebar | D30: LS | E30: 0 | F30: =C30*E30 -> 0 | H30: 0 | I30: =G30*H30 -> 0 | K30: =F30+I30+J30 -> 0 | U30: A | V30: B | W30: D | X30: Quantity | Y30: Volume m3
A31: 03 20 03 | B31: Mesh | D31: LS | E31: 0 | F31: =C31*E31 -> 0 | H31: 0 | I31: =G31*H31 -> 0 | K31: =F31+I31+J31 -> 0 | S31: Footings | T31: 1 | Y31: =U31*V31*W31*0.0000163871*X31 -> 0
D32: LS | E32: 0 | F32: =C32*E32 -> 0 | H32: 0 | I32: =G32*H32 -> 0 | K32: =F32+I32+J32 -> 0 | T32: 2 | Y32: =U32*V32*W32*0.0000163871*X32 -> 0
D33: LS | E33: 0 | F33: =C33*E33 -> 0 | H33: 0 | I33: =G33*H33 -> 0 | K33: =F33+I33+J33 -> 0 | U33: Length (FT) | V33: Width (ft) | W33: Height (ft)
D34: LS | E34: 0 | F34: =C34*E34 -> 0 | H34: 0 | I34: =G34*H34 -> 0 | K34: =F34+I34+J34 -> 0 | S34: Strip Footing | Y34: =U34*V34*W34*0.028 -> 0
D35: LS | E35: 0 | F35: =C35*E35 -> 0 | H35: 0 | I35: =G35*H35 -> 0 | K35: =F35+I35+J35 -> 0 | S35: Walls | Y35: =U35*V35*W35*0.028 -> 0
S36: Piers | Y36: =U36*V36*W36*0.028*X36 -> 0
J37: Sub Total | K37: =SUM(K29:K36) -> 0 | U37: Area (SF) | W37: Thickness (ft)
A38: CODE | B38: DESCRIPTION | C38: Materials & Equipment | G38: Labor | S38: Slab - ground floor | Y38: =U38*W38*0.028 -> 0
A39: 03 30 00 | B39: Cast-in-Place Concrete | C39: Qty | D39: Unit | E39: U. Price | F39: Sub Total | G39: MHrs | H39: U. Price | I39: Sub Total | J39: Quote | K39: Total | S39: Slab - 2nd floor | Y39: =U39*W39*0.028 -> 0
A40: 03 30 01 | B40: SOG Volume | C40: =Q86*1.1 -> 264.51333 | D40: m3 | E40: =161.42+20 -> 181.42 | F40: =C40*E40 -> 47988.008 | H40: 0 | I40: =G40*H40 -> 0 | K40: =F40+I40+J40 -> 47988.008 | L40: Spent | M40: 100052.75 | O40: 25MPA | P40: =C40+C42 -> 281.33353
B41: Structural Slab | C41: =Q87*1.1 -> 493.95341 | D41: m3 | E41: =190.58+20 -> 210.58 | F41: =C41*E41 -> 104016.71 | H41: 0 | I41: =G41*H41 -> 0 | K41: =F41+I41+J41 -> 104016.71 | L41: 2024 Prices | O41: 30MPA | P41: =C43 -> 22.956468
A42: 03 30 02 | B42: Footing Volume | C42: =(Q82+Q84)*1.1 -> 16.820207 | D42: m3 | E42: =E40 -> 181.42 | F42: =C42*E42 -> 3051.5219 | H42: 0 | I42: =G42*H42 -> 0 | K42: =F42+I42+J42 -> 3051.5219 | O42: 35MPA | P42: =C41+C44 -> 495.44854 | S42: Exterior Pads | Y42: =U42*W42*0.028 -> 0
A43: 03 30 03 | B43: Foundation Wall Volume | C43: =Q83*1.1 -> 22.956468 | D43: m3 | E43: =177.6+20 -> 197.6 | F43: =C43*E43 -> 4536.198 | H43: 0 | I43: =G43*H43 -> 0 | K43: =F43+I43+J43 -> 4536.198
A44: 03 30 04 | B44: Columns | C44: =Q85*1.1 -> 1.4951295 | D44: m3 | E44: =E41 -> 210.58 | F44: =C44*E44 -> 314.84437 | H44: 0 | I44: =G44*H44 -> 0 | K44: =F44+I44+J44 -> 314.84437
B45: Retaining Walls | C45: =Q88 -> 35.849128 | D45: m3 | E45: =E43 -> 197.6 | F45: =C45*E45 -> 7083.7877 | H45: 0 | I45: =G45*H45 -> 0 | K45: =F45+I45+J45 -> 7083.7877
B46: Retaining Footings | C46: =Q89 -> 4.0209922 | D46: m3 | E46: =E40 -> 181.42 | F46: =C46*E46 -> 729.48841 | H46: 0 | I46: =G46*H46 -> 0 | K46: =F46+I46+J46 -> 729.48841
B47: Already Spent | K47: =F47+I47+J47 -> 0
B48: Pump Hrs | C48: =SUM(C40:C46)/35 -> 23.988819 | D48: Hrs | E48: 280 | F48: =C48*E48 -> 6716.8693 | H48: 0 | I48: =G48*H48 -> 0 | K48: =F48+I48+J48 -> 6716.8693 | L48: 38M Pump | W48: Total Volume - Slab | Y48: =Y38+Y39 -> 0
A49: 03 30 04 | B49: Pump | C49: =SUM(C40:C46) -> 839.60866 | D49: m3 | E49: 4 | F49: =C49*E49 -> 3358.4346 | H49: 0 | I49: =G49*H49 -> 0 | K49: =F49+I49+J49 -> 3358.4346 | W49: Total Volume - Footing | Y49: =Y31+Y32+Y34 -> 0
J50: Sub Total | K50: =SUM(K40:K49) -> 177795.86 | W50: Total Volume - Walls | Y50: =Y35+Y36 -> 0
A51: CODE | B51: DESCRIPTION | C51: Materials & Equipment | G51: Labor | W51: Total Volume - Exterior | Y51: =Y42 -> 0
A52: 03 35 00 | B52: Concrete Finishing | C52: Qty | D52: Unit | E52: U. Price | F52: Sub Total | G52: MHrs | H52: U. Price | I52: Sub Total | J52: Quote | K52: Total
D53: LS | E53: 0 | F53: =C53*E53 -> 0 | H53: 0 | I53: =G53*H53 -> 0 | K53: =F53+I53+J53 -> 0 | N53: Coating for garage slab
B54: Slab Finishing - Ground Floor | C54: =17300*2 -> 34600 | D54: sf | E54: 2 | H54: 0 | I54: =G54*H54 -> 0 | J54: =M55 -> 44527 | K54: =F54+I54+J54 -> 44527 | L54: Texcon | M54: 46000
B55: Slab Finishing - 2nd Floor | C55: =U39 -> 0 | D55: sf | E55: 1 | F55: =C55*E55 -> 0 | H55: 0 | I55: =G55*H55 -> 0 | K55: =F55+I55+J55 -> 0 | L55: Euro | M55: 44527
D56: LS | E56: 0 | F56: =C56*E56 -> 0 | H56: 0 | I56: =G56*H56 -> 0 | K56: =F56+I56+J56 -> 0 | L56: Champion | M56: =39303+5207+6884 -> 51394
D57: LS | E57: 0 | F57: =C57*E57 -> 0 | H57: 0 | I57: =G57*H57 -> 0 | K57: =F57+I57+J57 -> 0
J59: Sub Total | K59: =SUM(K53:K58) -> 44527
A60: CODE | B60: DESCRIPTION | C60: Materials & Equipment | G60: Labor
A61: 03 40 00 | B61: Precast Concrete | C61: Qty | D61: Unit | E61: U. Price | F61: Sub Total | G61: MHrs | H61: U. Price | I61: Sub Total | J61: Quote | K61: Total
D62: LS | E62: 0 | F62: =C62*E62 -> 0 | H62: 0 | I62: =G62*H62 -> 0 | K62: =F62+I62+J62 -> 0
D63: LS | E63: 0 | F63: =C63*E63 -> 0 | H63: 0 | I63: =G63*H63 -> 0 | J63: =M63 -> 77850 | K63: =F63+I63+J63 -> 77850 | L63: APC | M63: 77850
D64: LS | E64: 0 | F64: =C64*E64 -> 0 | H64: 0 | I64: =G64*H64 -> 0 | K64: =F64+I64+J64 -> 0
D65: LS | E65: 0 | F65: =C65*E65 -> 0 | H65: 0 | I65: =G65*H65 -> 0 | K65: =F65+I65+J65 -> 0
D66: LS | E66: 0 | F66: =C66*E66 -> 0 | H66: 0 | I66: =G66*H66 -> 0 | K66: =F66+I66+J66 -> 0
D67: LS | E67: 0 | F67: =C67*E67 -> 0 | H67: 0 | I67: =G67*H67 -> 0 | K67: =F67+I67+J67 -> 0
D68: LS | E68: 0 | F68: =C68*E68 -> 0 | H68: 0 | I68: =G68*H68 -> 0 | K68: =F68+I68+J68 -> 0
J70: Sub Total | K70: =SUM(K62:K69) -> 77850
A71: CODE | B71: DESCRIPTION | C71: Materials & Equipment | G71: Labor
A72: 03 60 00 | B72: Foundation Materials | C72: Qty | D72: Unit | E72: U. Price | F72: Sub Total | G72: MHrs | H72: U. Price | I72: Sub Total | J72: Quote | K72: Total
A73: 03 60 01 | B73: Insulation | C73: =10+(660*4/8) -> 340 | D73: sheet | E73: 26 | F73: =C73*E73 -> 8840 | G73: =C73/3 -> 113.33333 | H73: 60 | I73: =G73*H73 -> 6800 | K73: =F73+I73+J73 -> 15640 | L73: Labour Spent | M73: 31200
A74: 03 60 02 | B74: Vapour Barrier | C74: 9 | D74: rolls | E74: 615 | F74: =C74*E74 -> 5535 | G74: =C74*5 -> 45 | H74: 60 | I74: =G74*H74 -> 2700 | K74: =F74+I74+J74 -> 8235 | L74: Materials Spent | M74: 33171
B75: Foundation waterproofing allowance | C75: =(670*4)+(60*10)+(40*10) -> 3680 | D75: SF | E75: 12 | F75: =C75*E75 -> 44160 | H75: 0 | I75: =G75*H75 -> 0 | K75: =F75+I75+J75 -> 44160
D76: LS | E76: 0 | F76: =C76*E76 -> 0 | H76: 0 | I76: =G76*H76 -> 0 | K76: =F76+I76+J76 -> 0
D77: LS | E77: 0 | F77: =C77*E77 -> 0 | H77: 0 | I77: =G77*H77 -> 0 | K77: =F77+I77+J77 -> 0
J79: Sub Total | K79: =SUM(K73:K78) -> 68035
F80: Material Total | G80: Total Hours | I80: Labor Total | J80: Contractor Total | K80: TOTAL
A81: $ / Sq.Ft | B81: TOTAL DIVISION 3 | Q81: M3
A82: =K82/E6 -> 10.223928 | F82: =SUM(F73:F78,F62:F69,F53:F58,F40:F49,F29:F36,F13:F25) -> 236330.86 | G82: =SUM(G73:G78,G62:G69,G53:G58,G40:G49,G29:G36,G13:G24) -> 158.33333 | I82: =SUM(I73:I78,I62:I69,I53:I58,I40:I49,I29:I36,I13:I25) -> 9500 | J82: =SUM(J73:J78,J62:J68,J53:J58,J40:J49,J29:J36,J13:J25) -> 424777 | K82: =SUM(K79,K70,K59,K50,K37,K26) -> 670607.86 | M82: 1 | N82: F1 Footing | O82: 284 | P82: CF | Q82: =CONVERT(O82,"ft^3","m^3") -> 8.0419844
M83: 2 | N83: F1 Wall | O83: 737 | P83: CF | Q83: =CONVERT(O83,"ft^3","m^3") -> 20.869516
M84: 3 | N84: Footing B | O84: 256 | P84: CF | Q84: =CONVERT(O84,"ft^3","m^3") -> 7.2491127
M85: 4 | N85: Columns | O85: 48 | P85: CF | Q85: =CONVERT(O85,"ft^3","m^3") -> 1.3592086
M86: 5 | N86: SOG | O86: 8492 | P86: CF | Q86: =CONVERT(O86,"ft^3","m^3") -> 240.46666
M87: 6 | N87: Structural Slab | O87: 15858 | P87: CF | Q87: =CONVERT(O87,"ft^3","m^3") -> 449.04855
M88: 7 | N88: Retaining Walls | O88: 1266 | Q88: =CONVERT(O88,"ft^3","m^3") -> 35.849128
M89: 8 | N89: Retaining Footing | O89: 142 | Q89: =CONVERT(O89,"ft^3","m^3") -> 4.0209922

Sheet 4
C1: ='Estimate Summary'!C1:H1 -> 0
G5: Masonry | J5: Schedule
D6: ='Estimate Summary'!C11 -> Area: | E6: ='Estimate Summary'!D11 -> 65592 | F6: ='Estimate Summary'!E11 -> Sq. Ft. | J6: ='1'!J6 -> 60 | K6: Weeks
A11: CODE | B11: DESCRIPTION | C11: Materials & Equipment | G11: Labor | L11: Sub Contractor | M11: Quote Total | N11: Additional Quote Info | O11: Previous Quotes
A12: 04 20 00 | B12: Unit Masonry | C12: Qty | D12: Unit | E12: U. Price | F12: Sub Total | G12: MHrs | H12: U. Price | I12: Sub Total | J12: Quote | K12: Total
D13: LS | E13: 0 | F13: =C13*E13 -> 0 | H13: 0 | I13: =G13*H13 -> 0 | K13: =F13+I13+J13 -> 0 | M13: Veneer | N13: Interior Blocks | O13: Ston Masonry | P13: =94000+37400 -> 131400 | Q13: Labour only for exterior. Labour + Mat for interior block walls
B14: Culture Stone | C14: =2745+545 -> 3290 | D14: SF | E14: 50 | H14: 0 | I14: =G14*H14 -> 0 | J14: =M14 -> 104000 | K14: =F14+I14+J14 -> 104000 | L14: JP Masonry | M14: 104000 | N14: 36360
D15: LS | E15: 0 | F15: =C15*E15 -> 0 | H15: 0 | I15: =G15*H15 -> 0 | K15: =F15+I15+J15 -> 0 | L15: Vintage (Late) | M15: 219495
B16: Block Walls | C16: 1600 | D16: SF | E16: 40 | H16: 0 | I16: =G16*H16 -> 0 | J16: =N14 -> 36360 | K16: =F16+I16+J16 -> 36360
D17: LS | E17: 0 | F17: =C17*E17 -> 0 | H17: 0 | I17: =G17*H17 -> 0 | K17: =F17+I17+J17 -> 0
D18: LS | E18: 0 | F18: =C18*E18 -> 0 | H18: 0 | I18: =G18*H18 -> 0 | K18: =F18+I18+J18 -> 0
D19: LS | E19: 0 | F19: =C19*E19 -> 0 | H19: 0 | I19: =G19*H19 -> 0 | K19: =F19+I19+J19 -> 0 | L19: Shaw Stone supply | M19: 51352 | N19: Screwed Vena Stone
D20: LS | E20: 0 | F20: =C20*E20 -> 0 | H20: 0 | I20: =G20*H20 -> 0 | K20: =F20+I20+J20 -> 0 | L20: AVT Install | M20: 55000
D21: LS | E21: 0 | F21: =C21*E21 -> 0 | H21: 0 | I21: =G21*H21 -> 0 | K21: =F21+I21+J21 -> 0
D22: LS | E22: 0 | F22: =C22*E22 -> 0 | H22: 0 | I22: =G22*H22 -> 0 | K22: =F22+I22+J22 -> 0
D23: LS | E23: 0 | F23: =C23*E23 -> 0 | H23: 0 | I23: =G23*H23 -> 0 | K23: =F23+I23+J23 -> 0
D24: LS | E24: 0 | F24: =C24*E24 -> 0 | H24: 0 | I24: =G24*H24 -> 0 | K24: =F24+I24+J24 -> 0
J26: Sub Total | K26: =SUM(K13:K25) -> 140360
A27: CODE | B27: DESCRIPTION | C27: Materials & Equipment | G27: Labor
A28: 04 43 00 | B28: Stone Masonry | C28: Qty | D28: Unit | E28: U. Price | F28: Sub Total | G28: MHrs | H28: U. Price | I28: Sub Total | J28: Quote | K28: Total
D29: LS | E29: 0 | F29: =C29*E29 -> 0 | H29: 0 | I29: =G29*H29 -> 0 | K29: =F29+I29+J29 -> 0
D30: LS | E30: 0 | F30: =C30*E30 -> 0 | H30: 0 | I30: =G30*H30 -> 0 | K30: =F30+I30+J30 -> 0
D31: LS | E31: 0 | F31: =C31*E31 -> 0 | H31: 0 | I31: =G31*H31 -> 0 | K31: =F31+I31+J31 -> 0
D32: LS | E32: 0 | F32: =C32*E32 -> 0 | H32: 0 | I32: =G32*H32 -> 0 | K32: =F32+I32+J32 -> 0
D33: LS | E33: 0 | F33: =C33*E33 -> 0 | H33: 0 | I33: =G33*H33 -> 0 | K33: =F33+I33+J33 -> 0
D34: LS | E34: 0 | F34: =C34*E34 -> 0 | H34: 0 | I34: =G34*H34 -> 0 | K34: =F34+I34+J34 -> 0
D35: LS | E35: 0 | F35: =C35*E35 -> 0 | H35: 0 | I35: =G35*H35 -> 0 | K35: =F35+I35+J35 -> 0
J37: Sub Total | K37: =SUM(K29:K36) -> 0
A38: CODE | B38: DESCRIPTION | C38: Materials & Equipment | G38: Labor
C39: Qty | D39: Unit | E39: U. Price | F39: Sub Total | G39: MHrs | H39: U. Price | I39: Sub Total | J39: Quote | K39: Total
D40: LS | E40: 0 | F40: =C40*E40 -> 0 | H40: 0 | I40: =G40*H40 -> 0 | K40: =F40+I40+J40 -> 0
D41: LS | E41: 0 | F41: =C41*E41 -> 0 | H41: 0 | I41: =G41*H41 -> 0 | K41: =F41+I41+J41 -> 0
D42: LS | E42: 0 | F42: =C42*E42 -> 0 | H42: 0 | I42: =G42*H42 -> 0 | K42: =F42+I42+J42 -> 0
J45: Sub Total | K45: =SUM(K40:K44) -> 0
A46: CODE | B46: DESCRIPTION | C46: Materials & Equipment | G46: Labor
C47: Qty | D47: Unit | E47: U. Price | F47: Sub Total | G47: MHrs | H47: U. Price | I47: Sub Total | J47: Quote | K47: Total
D48: LS | E48: 0 | F48: =C48*E48 -> 0 | H48: 0 | I48: =G48*H48 -> 0 | K48: =F48+I48+J48 -> 0
D49: LS | E49: 0 | F49: =C49*E49 -> 0 | H49: 0 | I49: =G49*H49 -> 0 | K49: =F49+I49+J49 -> 0
D50: LS | E50: 0 | F50: =C50*E50 -> 0 | H50: 0 | I50: =G50*H50 -> 0 | K50: =F50+I50+J50 -> 0
D51: LS | E51: 0 | F51: =C51*E51 -> 0 | H51: 0 | I51: =G51*H51 -> 0 | K51: =F51+I51+J51 -> 0
D52: LS | E52: 0 | F52: =C52*E52 -> 0 | H52: 0 | I52: =G52*H52 -> 0 | K52: =F52+I52+J52 -> 0
J54: Sub Total | K54: =SUM(K48:K53) -> 0
A55: CODE | B55: DESCRIPTION | C55: Materials & Equipment | G55: Labor
C56: Qty | D56: Unit | E56: U. Price | F56: Sub Total | G56: MHrs | H56: U. Price | I56: Sub Total | J56: Quote | K56: Total
D57: LS | E57: 0 | F57: =C57*E57 -> 0 | H57: 0 | I57: =G57*H57 -> 0 | K57: =F57+I57+J57 -> 0
D58: LS | E58: 0 | F58: =C58*E58 -> 0 | H58: 0 | I58: =G58*H58 -> 0 | K58: =F58+I58+J58 -> 0
D59: LS | E59: 0 | F59: =C59*E59 -> 0 | H59: 0 | I59: =G59*H59 -> 0 | K59: =F59+I59+J59 -> 0
D60: LS | E60: 0 | F60: =C60*E60 -> 0 | H60: 0 | I60: =G60*H60 -> 0 | K60: =F60+I60+J60 -> 0
D61: LS | E61: 0 | F61: =C61*E61 -> 0 | H61: 0 | I61: =G61*H61 -> 0 | K61: =F61+I61+J61 -> 0
D62: LS | E62: 0 | F62: =C62*E62 -> 0 | H62: 0 | I62: =G62*H62 -> 0 | K62: =F62+I62+J62 -> 0
D63: LS | E63: 0 | F63: =C63*E63 -> 0 | H63: 0 | I63: =G63*H63 -> 0 | K63: =F63+I63+J63 -> 0
J65: Sub Total | K65: =SUM(K57:K64) -> 0
F66: Material Total | G66: Total Hours | I66: Labor Total | J66: Contractor Total | K66: TOTAL
A67: $ / Sq.Ft | B67: TOTAL DIVISION 4
A68: =K68/E6 -> 2.1398951 | F68: =SUM(F57:F64,F48:F53,F40:F44,F29:F36,F13:F25) -> 0 | G68: =SUM(G57:G64,G48:G53,G40:G44,G29:G36,G13:G25) -> 0 | I68: =SUM(I57:I64,I48:I53,I40:I44,I29:I36,I13:I25) -> 0 | J68: =SUM(J57:J64,J48:J53,J40:J44,J29:J36,J13:J25) -> 140360 | K68: =K65+K54+K45+K37+K26 -> 140360

Sheet 5
C1: ='Estimate Summary'!C1:H1 -> 0
G5: Metals | J5: Schedule
D6: ='Estimate Summary'!C11 -> Area: | E6: ='Estimate Summary'!D11 -> 65592 | F6: ='Estimate Summary'!E11 -> Sq. Ft. | J6: ='1'!J6 -> 60 | K6: Weeks
A11: CODE | B11: DESCRIPTION | C11: Materials & Equipment | G11: Labor | L11: Sub Contractor | M11: Quote Total | N11: Additional Quote Info
A12: 05 12 00 | B12: Structural Steel Framing | C12: Qty | D12: Unit | E12: U. Price | F12: Sub Total | G12: MHrs | H12: U. Price | I12: Sub Total | J12: Quote | K12: Total
D13: LS | E13: 0 | F13: =C13*E13 -> 0 | H13: 0 | I13: =G13*H13 -> 0 | K13: =F13+I13+J13 -> 0
D14: LS | E14: 0 | F14: =C14*E14 -> 0 | H14: 0 | I14: =G14*H14 -> 0 | J14: =M14 -> 136100 | K14: =F14+I14+J14 -> 136100 | L14: Summit | M14: 136100 | N14: $4500 extra for brick lintels
D15: LS | E15: 0 | F15: =C15*E15 -> 0 | H15: 0 | I15: =G15*H15 -> 0 | K15: =F15+I15+J15 -> 0
B16: Brick Lintels | D16: LS | E16: 0 | F16: =C16*E16 -> 0 | H16: 0 | I16: =G16*H16 -> 0 | J16: 4500 | K16: =F16+I16+J16 -> 4500
D17: LS | E17: 0 | F17: =C17*E17 -> 0 | H17: 0 | I17: =G17*H17 -> 0 | K17: =F17+I17+J17 -> 0
B18: Metal clips for handrails | C18: 8 | D18: LS | E18: 100 | F18: =C18*E18 -> 800 | H18: 0 | I18: =G18*H18 -> 0 | K18: =F18+I18+J18 -> 800
D19: LS | E19: 0 | F19: =C19*E19 -> 0 | H19: 0 | I19: =G19*H19 -> 0 | K19: =F19+I19+J19 -> 0
D20: LS | E20: 0 | F20: =C20*E20 -> 0 | H20: 0 | I20: =G20*H20 -> 0 | K20: =F20+I20+J20 -> 0
D21: LS | E21: 0 | F21: =C21*E21 -> 0 | H21: 0 | I21: =G21*H21 -> 0 | K21: =F21+I21+J21 -> 0
D22: LS | E22: 0 | F22: =C22*E22 -> 0 | H22: 0 | I22: =G22*H22 -> 0 | K22: =F22+I22+J22 -> 0
D23: LS | E23: 0 | F23: =C23*E23 -> 0 | H23: 0 | I23: =G23*H23 -> 0 | K23: =F23+I23+J23 -> 0
D24: LS | E24: 0 | F24: =C24*E24 -> 0 | H24: 0 | I24: =G24*H24 -> 0 | K24: =F24+I24+J24 -> 0
J26: Sub Total | K26: =SUM(K13:K25) -> 141400
A27: CODE | B27: DESCRIPTION | C27: Materials & Equipment | G27: Labor
A28: 05 20 00 | B28: Metal Joists | C28: Qty | D28: Unit | E28: U. Price | F28: Sub Total | G28: MHrs | H28: U. Price | I28: Sub Total | J28: Quote | K28: Total
D29: LS | E29: 0 | F29: =C29*E29 -> 0 | H29: 0 | I29: =G29*H29 -> 0 | K29: =F29+I29+J29 -> 0
D30: LS | E30: 0 | F30: =C30*E30 -> 0 | H30: 0 | I30: =G30*H30 -> 0 | K30: =F30+I30+J30 -> 0
D31: LS | E31: 0 | F31: =C31*E31 -> 0 | H31: 0 | I31: =G31*H31 -> 0 | K31: =F31+I31+J31 -> 0
D32: LS | E32: 0 | F32: =C32*E32 -> 0 | H32: 0 | I32: =G32*H32 -> 0 | K32: =F32+I32+J32 -> 0
D33: LS | E33: 0 | F33: =C33*E33 -> 0 | H33: 0 | I33: =G33*H33 -> 0 | K33: =F33+I33+J33 -> 0
D34: LS | E34: 0 | F34: =C34*E34 -> 0 | H34: 0 | I34: =G34*H34 -> 0 | K34: =F34+I34+J34 -> 0
D35: LS | E35: 0 | F35: =C35*E35 -> 0 | H35: 0 | I35: =G35*H35 -> 0 | K35: =F35+I35+J35 -> 0
J37: Sub Total | K37: =SUM(K29:K36) -> 0
A38: CODE | B38: DESCRIPTION | C38: Materials & Equipment | G38: Labor
A39: 05 30 00 | B39: Metal Decking | C39: Qty | D39: Unit | E39: U. Price | F39: Sub Total | G39: MHrs | H39: U. Price | I39: Sub Total | J39: Quote | K39: Total
D40: LS | E40: 0 | F40: =C40*E40 -> 0 | H40: 0 | I40: =G40*H40 -> 0 | K40: =F40+I40+J40 -> 0
D41: LS | E41: 0 | F41: =C41*E41 -> 0 | H41: 0 | I41: =G41*H41 -> 0 | K41: =F41+I41+J41 -> 0
D42: LS | E42: 0 | F42: =C42*E42 -> 0 | H42: 0 | I42: =G42*H42 -> 0 | K42: =F42+I42+J42 -> 0
J45: Sub Total | K45: =SUM(K40:K44) -> 0
A46: CODE | B46: DESCRIPTION | C46: Materials & Equipment | G46: Labor
A47: 05 51 00 | B47: Metal Stairs | C47: Qty | D47: Unit | E47: U. Price | F47: Sub Total | G47: MHrs | H47: U. Price | I47: Sub Total | J47: Quote | K47: Total
D48: LS | E48: 0 | F48: =C48*E48 -> 0 | H48: 0 | I48: =G48*H48 -> 0 | K48: =F48+I48+J48 -> 0
D49: LS | E49: 0 | F49: =C49*E49 -> 0 | H49: 0 | I49: =G49*H49 -> 0 | K49: =F49+I49+J49 -> 0
D50: LS | E50: 0 | F50: =C50*E50 -> 0 | H50: 0 | I50: =G50*H50 -> 0 | K50: =F50+I50+J50 -> 0
D51: LS | E51: 0 | F51: =C51*E51 -> 0 | H51: 0 | I51: =G51*H51 -> 0 | K51: =F51+I51+J51 -> 0
D52: LS | E52: 0 | F52: =C52*E52 -> 0 | H52: 0 | I52: =G52*H52 -> 0 | K52: =F52+I52+J52 -> 0
J54: Sub Total | K54: =SUM(K48:K53) -> 0
A55: CODE | B55: DESCRIPTION | C55: Materials & Equipment | G55: Labor
A56: 05 52 00 | B56: Metal Railings | C56: Qty | D56: Unit | E56: U. Price | F56: Sub Total | G56: MHrs | H56: U. Price | I56: Sub Total | J56: Quote | K56: Total
D57: LS | E57: 0 | F57: =C57*E57 -> 0 | H57: 0 | I57: =G57*H57 -> 0 | K57: =F57+I57+J57 -> 0 | L57: ADS | M57: 67400
C58: 59 | D58: Unit | E58: =M64 -> 1752.8814 | H58: 0 | I58: =G58*H58 -> 0 | J58: =M58 -> 73570 | K58: =F58+I58+J58 -> 73570 | L58: FCG | M58: 73570
D59: LS | E59: 0 | F59: =C59*E59 -> 0 | H59: 0 | I59: =G59*H59 -> 0 | K59: =F59+I59+J59 -> 0
D60: LS | E60: 0 | F60: =C60*E60 -> 0 | H60: 0 | I60: =G60*H60 -> 0 | K60: =F60+I60+J60 -> 0
D61: LS | E61: 0 | F61: =C61*E61 -> 0 | H61: 0 | I61: =G61*H61 -> 0 | K61: =F61+I61+J61 -> 0
D62: LS | E62: 0 | F62: =C62*E62 -> 0 | H62: 0 | I62: =G62*H62 -> 0 | K62: =F62+I62+J62 -> 0
D63: LS | E63: 0 | F63: =C63*E63 -> 0 | H63: 0 | I63: =G63*H63 -> 0 | K63: =F63+I63+J63 -> 0
L64: Joyce per unit | M64: =103420/59 -> 1752.8814
J65: Sub Total | K65: =SUM(K57:K64) -> 73570
A66: CODE | B66: DESCRIPTION | C66: Materials & Equipment | G66: Labor
A67: 05 59 00 | B67: Metal Specialties | C67: Qty | D67: Unit | E67: U. Price | F67: Sub Total | G67: MHrs | H67: U. Price | I67: Sub Total | J67: Quote | K67: Total
D68: LS | E68: 0 | F68: =C68*E68 -> 0 | H68: 0 | I68: =G68*H68 -> 0 | K68: =F68+I68+J68 -> 0
D69: LS | E69: 0 | F69: =C69*E69 -> 0 | H69: 0 | I69: =G69*H69 -> 0 | K69: =F69+I69+J69 -> 0
D70: LS | E70: 0 | F70: =C70*E70 -> 0 | H70: 0 | I70: =G70*H70 -> 0 | K70: =F70+I70+J70 -> 0
D71: LS | E71: 0 | F71: =C71*E71 -> 0 | H71: 0 | I71: =G71*H71 -> 0 | K71: =F71+I71+J71 -> 0
D72: LS | E72: 0 | F72: =C72*E72 -> 0 | H72: 0 | I72: =G72*H72 -> 0 | K72: =F72+I72+J72 -> 0
J74: Sub Total | K74: =SUM(K68:K73) -> 0
F75: Material Total | G75: Total Hours | I75: Labor Total | J75: Contractor Total | K75: TOTAL
A76: $ / Sq.Ft | B76: TOTAL DIVISION 5
A77: =K77/E6 -> 3.2773814 | F77: =SUM(F68:F73,F57:F64,F48:F53,F40:F44,F29:F36,F13:F25) -> 800 | G77: =SUM(G68:G73,G57:G64,G48:G53,G40:G44,G29:G36,G13:G24) -> 0 | I77: =SUM(I68:I73,I57:I64,I48:I53,I40:I44,I29:I36,I13:I25) -> 0 | J77: =SUM(J68:J73,J57:J63,J48:J53,J40:J44,J29:J36,J13:J25) -> 214170 | K77: =SUM(,K74,K65,K54,K45,K37,K26) -> 214970

Sheet 6
C1: ='Estimate Summary'!C1:H1 -> 0
G5: Wood & Plastics | J5: Schedule
D6: ='Estimate Summary'!C11 -> Area: | E6: ='Estimate Summary'!D11 -> 65592 | F6: ='Estimate Summary'!E11 -> Sq. Ft. | J6: ='1'!J6 -> 60 | K6: Weeks
A9: CODE | B9: DESCRIPTION | C9: Materials & Equipment | G9: Labor | L9: Sub Contractor | M9: Quote Total | N9: Additional Quote Info
A10: 06 11 00 | B10: Framing Labour | C10: Qty | D10: Unit | E10: U. Price | F10: Sub Total | G10: MHrs | H10: U. Price | I10: Sub Total | J10: Quote | K10: Total
H11: 0 | I11: =G11*H11 -> 0 | J11: =M13 -> 459330 | K11: =F11+I11+J11 -> 459330 | L11: AVT | M11: 445000 | N11: Framing Only. They supply manlift, we supply crane and zoom boom
B12: Allowance for corner columns install | C12: 6 | D12: LS | E12: 500 | F12: =E12*C12 -> 3000 | H12: 0 | I12: =G12*H12 -> 0 | K12: =F12+I12+J12 -> 3000 | L12: Big Bang | M12: 545000 | N12: Framing, strapping and tyvek install
H13: 0 | I13: =G13*H13 -> 0 | K13: =F13+I13+J13 -> 0 | L13: CMS | M13: =459330 -> 459330 | N13: Includes deck install and Windows install & Solar Panel Reinforcements
B14: Crane | C14: 15 | D14: wks | E14: 7000 | F14: =E14*C14 -> 105000 | H14: 0 | I14: =G14*H14 -> 0 | K14: =F14+I14+J14 -> 105000 | L14: Gbro | M14: 569550 | N14: Includes deck install and Windows install
B15: Crane Setup/Dismantle | C15: 2 | D15: LS | E15: 2000 | F15: =E15*C15 -> 4000 | H15: 0 | I15: =G15*H15 -> 0 | K15: =F15+I15+J15 -> 4000 | L15: East Coast | M15: =350000+45000 -> 395000 | N15: Framing and concrete deck install. Additional $45k for window install
H16: 0 | I16: =G16*H16 -> 0 | K16: =F16+I16+J16 -> 0 | L16: S&J | M16: 389956.2 | N16: Includes deck install and Windows install
H17: 0 | I17: =G17*H17 -> 0 | K17: =F17+I17+J17 -> 0 | L17: Branco | M17: =469227.2+8400 -> 477627.2 | N17: Includes deck install and Windows install & Solar Panel Reinforcements
J19: Sub Total | K19: =SUM(K11:K18) -> 571330
A20: 06 20 00 | B20: Framing Materials | C20: Qty | D20: Unit | E20: U. Price | F20: Sub Total | J20: Quote | K20: Total
B22: Lumber & Fasterners Allowance | C22: 59 | D22: Unit | E22: 3250 | F22: =C22*E22 -> 191750 | K22: =F22+I22+J22 -> 191750 | L22: Belle Foret per unit | M22: =175845.44/63 -> 2791.1975 | N22: Added $ for truss bracing
B23: 2x6 Stud | D23: ft | E23: 0.81 | F23: =C23*E23 -> 0 | K23: =F23+I23+J23 -> 0
B24: 2x8 | D24: ft | E24: 1.24 | F24: =C24*E24 -> 0 | K24: =F24+I24+J24 -> 0
B25: 2x10 | D25: ft | E25: 1.61 | F25: =C25*E25 -> 0 | K25: =F25+I25+J25 -> 0
B26: 1x3 | D26: ft | E26: 0.25 | F26: =C26*E26 -> 0 | K26: =F26+I26+J26 -> 0
B27: 1x4 | D27: ft | E27: 0.37 | F27: =C27*E27 -> 0 | K27: =F27+I27+J27 -> 0 | M27: Per Unit
B28: PLYWOOD | K28: =F28+I28+J28 -> 0 | L28: Belle Foret Atlas | M28: =1362134/63 -> 21621.175
B29: 1/2" Standard | D29: EA | E29: 30.65 | F29: =C29*E29 -> 0 | K29: =F29+I29+J29 -> 0 | L29: Joyce Atlas | M29: =1361600/59 -> 23077.966
B30: 5/8" Standard | D30: EA | E30: 43.69 | F30: =C30*E30 -> 0 | K30: =F30+I30+J30 -> 0
B31: 3/4" Standard | D31: EA | E31: 47.47 | F31: =C31*E31 -> 0 | K31: =F31+I31+J31 -> 0 | M31: Walls | N31: Floors | O31: Trusses | P31: Stairs | Q31: Total | S31: Additional with solar bracing
L32: Atlas | M32: 466300 | N32: =263000+218650+43200 -> 524850 | O32: 104900 | P32: 32400 | Q32: =SUM(M32:P32) -> 1128450 | R32: Total with Trusses | S32: 19500
B33: Panel Allowance | C33: 59 | D33: EA | E33: 23077.97 | J33: =R33 -> 1070073.7 | K33: =F33+I33+J33 -> 1070073.7 | L33: T&M | M33: 1003550 | N33: Incl | O33: Not Incl | P33: Incl | Q33: 930650 | R33: =Q33+O35 -> 1070073.7
L34: Truss Peninsule
L35: Gable | M35: Not Incl | N35: 266240.78 | O35: 139423.66 | P35: Not Incl | Q35: Floor does not have boarding
J36: Sub Total | K36: =SUM(K21:K35) -> 1261823.7
A37: CODE | B37: DESCRIPTION | C37: Materials & Equipment | G37: Labor
A38: 06 22 00 | B38: Millwork | C38: Qty | D38: Unit | E38: U. Price | F38: Sub Total | G38: MHrs | H38: U. Price | I38: Sub Total | J38: Quote | K38: Total
D39: LS | E39: 0 | F39: =C39*E39 -> 0 | H39: 0 | I39: =G39*H39 -> 0 | K39: =F39+I39+J39 -> 0 | L39: Extreme Kitchen
C40: 59 | D40: Unit | E40: 6000 | H40: 0 | I40: =G40*H40 -> 0 | J40: =M40 -> 425900 | K40: =F40+I40+J40 -> 425900 | L40: Foxwood | M40: 425900 | N40: Melamine Counter top and doors
D41: LS | E41: 0 | F41: =C41*E41 -> 0 | H41: 0 | I41: =G41*H41 -> 0 | K41: =F41+I41+J41 -> 0 | L41: Royalty | M41: 633000
D42: LS | E42: 0 | F42: =C42*E42 -> 0 | H42: 0 | I42: =G42*H42 -> 0 | K42: =F42+I42+J42 -> 0 | L42: Shaw
D43: LS | E43: 0 | F43: =C43*E43 -> 0 | H43: 0 | I43: =G43*H43 -> 0 | K43: =F43+I43+J43 -> 0 | L43: Triangle | M43: 446883.98 | N43: Pricing quartz top with melamine doors
D44: LS | E44: 0 | F44: =C44*E44 -> 0 | H44: 0 | I44: =G44*H44 -> 0 | K44: =F44+I44+J44 -> 0 | L44: Laforest | M44: 604750 | N44: Soft Close +$44,250. Quartz +$372,000
D45: LS | E45: 0 | F45: =C45*E45 -> 0 | H45: 0 | I45: =G45*H45 -> 0 | K45: =F45+I45+J45 -> 0 | L45: Master Interior (Late) | M45: =194016.19+96052+83585.89+30680 -> 404334.08
J47: Sub Total | K47: =SUM(K39:K46) -> 425900
A48: CODE | B48: DESCRIPTION | C48: Materials & Equipment | G48: Labor
A49: 06 41 00 | B49: Architechtural Wood Casework | C49: Qty | D49: Unit | E49: U. Price | F49: Sub Total | G49: MHrs | H49: U. Price | I49: Sub Total | J49: Quote | K49: Total
B50: Pre-Hung Doors | C50: 59 | D50: Unit | E50: =M50 -> 0 | F50: =C50*E50 -> 0 | H50: 0 | I50: =G50*H50 -> 0 | K50: =F50+I50+J50 -> 0
D51: LS | E51: 0 | F51: =C51*E51 -> 0 | H51: 0 | I51: =G51*H51 -> 0 | K51: =F51+I51+J51 -> 0
D52: LS | E52: 0 | F52: =C52*E52 -> 0 | H52: 0 | I52: =G52*H52 -> 0 | K52: =F52+I52+J52 -> 0
J55: Sub Total | K55: =SUM(K50:K54) -> 0
A56: CODE | B56: DESCRIPTION | C56: Materials & Equipment | G56: Labor
A57: 06 42 00 | B57: Wood Paneling | C57: Qty | D57: Unit | E57: U. Price | F57: Sub Total | G57: MHrs | H57: U. Price | I57: Sub Total | J57: Quote | K57: Total
D58: LS | E58: 0 | F58: =C58*E58 -> 0 | H58: 0 | I58: =G58*H58 -> 0 | K58: =F58+I58+J58 -> 0
D59: LS | E59: 0 | F59: =C59*E59 -> 0 | H59: 0 | I59: =G59*H59 -> 0 | K59: =F59+I59+J59 -> 0
D60: LS | E60: 0 | F60: =C60*E60 -> 0 | H60: 0 | I60: =G60*H60 -> 0 | K60: =F60+I60+J60 -> 0
D61: LS | E61: 0 | F61: =C61*E61 -> 0 | H61: 0 | I61: =G61*H61 -> 0 | K61: =F61+I61+J61 -> 0
D62: LS | E62: 0 | F62: =C62*E62 -> 0 | H62: 0 | I62: =G62*H62 -> 0 | K62: =F62+I62+J62 -> 0
J64: Sub Total | K64: =SUM(K58:K63) -> 0
A65: CODE | B65: DESCRIPTION | C65: Materials & Equipment | G65: Labor
A66: 06 43 00 | B66: Wood Stairs and Railings | C66: Qty | D66: Unit | E66: U. Price | F66: Sub Total | G66: MHrs | H66: U. Price | I66: Sub Total | J66: Quote | K66: Total
D67: LS | E67: 0 | F67: =C67*E67 -> 0 | H67: 0 | I67: =G67*H67 -> 0 | K67: =F67+I67+J67 -> 0
D68: LS | E68: 0 | F68: =C68*E68 -> 0 | H68: 0 | I68: =G68*H68 -> 0 | K68: =F68+I68+J68 -> 0
D69: LS | E69: 0 | F69: =C69*E69 -> 0 | H69: 0 | I69: =G69*H69 -> 0 | K69: =F69+I69+J69 -> 0
D70: LS | E70: 0 | F70: =C70*E70 -> 0 | H70: 0 | I70: =G70*H70 -> 0 | K70: =F70+I70+J70 -> 0
D71: LS | E71: 0 | F71: =C71*E71 -> 0 | H71: 0 | I71: =G71*H71 -> 0 | K71: =F71+I71+J71 -> 0
D72: LS | E72: 0 | F72: =C72*E72 -> 0 | H72: 0 | I72: =G72*H72 -> 0 | K72: =F72+I72+J72 -> 0
D73: LS | E73: 0 | F73: =C73*E73 -> 0 | H73: 0 | I73: =G73*H73 -> 0 | K73: =F73+I73+J73 -> 0
P74: Trim LF | Q74: Suite QTY | R74: Total Trim | S74: Door Trim | T74: Total Door Trim | U74: Pre-hung Doors
J75: Sub Total | K75: =SUM(K67:K74) -> 0 | O75: Suite A Floor Trim | P75: 244 | Q75: 1 | R75: =Q75*P75 -> 244 | S75: =20*5*2 -> 200 | T75: =S75*Q75 -> 200 | U75: =S75/40 -> 5 | V75: =U75*Q75 -> 5
A76: CODE | B76: DESCRIPTION | C76: Materials & Equipment | G76: Labor | O76: Suite B Floor Trim | P76: 238 | Q76: 7 | R76: =Q76*P76 -> 1666 | S76: =6*20*2 -> 240 | T76: =S76*Q76 -> 1680 | U76: =S76/40 -> 6 | V76: =U76*Q76 -> 42
A77: 06 46 00 | B77: Wood Trim | C77: Qty | D77: Unit | E77: U. Price | F77: Sub Total | G77: MHrs | H77: U. Price | I77: Sub Total | J77: Quote | K77: Total | O77: Suite BF Trim | P77: 231 | Q77: 3 | R77: =Q77*P77 -> 693 | S77: =6*20*2 -> 240 | T77: =S77*Q77 -> 720 | U77: =S77/40 -> 6 | V77: =U77*Q77 -> 18
B78: Floor Trim | C78: =R86 -> 19179.6 | D78: LF | E78: 1.25 | H78: 0 | I78: =G78*H78 -> 0 | J78: =M78 -> 68450 | K78: =F78+I78+J78 -> 68450 | L78: GB Finish | M78: 68450 | O78: Suite C Floor Trim | P78: 227 | Q78: 4 | R78: =Q78*P78 -> 908 | S78: =7*20*2 -> 280 | T78: =S78*Q78 -> 1120 | U78: =S78/40 -> 7 | V78: =U78*Q78 -> 28
B79: Door Trim | C79: =T86 -> 19448 | D79: LF | E79: 1.03 | H79: 0 | I79: =G79*H79 -> 0 | K79: =F79+I79+J79 -> 0 | L79: S&J | M79: 92424.96 | O79: Suite D Trim | P79: 288 | Q79: 16 | R79: =Q79*P79 -> 4608 | S79: =20*6*2 -> 240 | T79: =S79*Q79 -> 3840 | U79: =S79/40 -> 6 | V79: =U79*Q79 -> 96
B80: Pre-hung doors | C80: =V86 -> 442 | D80: LS | E80: 225 | H80: 0 | I80: =G80*H80 -> 0 | K80: =F80+I80+J80 -> 0 | O80: Suite E Trim | P80: 389 | Q80: 4 | R80: =Q80*P80 -> 1556 | S80: =10*20*2 -> 400 | T80: =S80*Q80 -> 1600 | U80: =S80/40 -> 10 | V80: =U80*Q80 -> 40
D81: LS | E81: 0 | F81: =C81*E81 -> 0 | H81: 0 | I81: =G81*H81 -> 0 | K81: =F81+I81+J81 -> 0 | O81: Suite F Trim | P81: 353 | Q81: 12 | R81: =Q81*P81 -> 4236 | S81: =20*10*2 -> 400 | T81: =S81*Q81 -> 4800 | U81: =S81/40 -> 10 | V81: =U81*Q81 -> 120
C82: 59 | D82: Unit | E82: =M82 -> 4192.4389 | F82: =C82*E82 -> 247353.89 | H82: 0 | I82: =G82*H82 -> 0 | K82: =F82+I82+J82 -> 247353.89 | L82: Belle Foret per Unit | M82: =264123.65/63 -> 4192.4389 | N82: Includes pre-hung doors | O82: Suite G Trim | P82: 236 | Q82: 1 | R82: =Q82*P82 -> 236 | S82: =6*20*2 -> 240 | T82: =S82*Q82 -> 240 | U82: =S82/40 -> 6 | V82: =U82*Q82 -> 6
O83: Suite H Trim | P83: 343 | Q83: 7 | R83: =Q83*P83 -> 2401 | S83: =9*20*2 -> 360 | T83: =S83*Q83 -> 2520 | U83: =S83/40 -> 9 | V83: =U83*Q83 -> 63
J84: Sub Total | K84: =SUM(K78:K83) -> 315803.89 | O84: Suite I Trim | P84: 222 | Q84: 4 | R84: =Q84*P84 -> 888 | S84: =6*20*2 -> 240 | T84: =S84*Q84 -> 960 | U84: =S84/40 -> 6 | V84: =U84*Q84 -> 24
A85: CODE | B85: DESCRIPTION | C85: Materials & Equipment | G85: Labor | Q85: 10% Factor | R85: =SUM(R75:R84)*0.1 -> 1743.6 | T85: =SUM(T75:T84)*0.1 -> 1768
A86: 06 48 00 | B86: Wood Frames | C86: Qty | D86: Unit | E86: U. Price | F86: Sub Total | G86: MHrs | H86: U. Price | I86: Sub Total | J86: Quote | K86: Total | Q86: Total | R86: =SUM(R75:R85) -> 19179.6 | T86: =SUM(T75:T85) -> 19448 | V86: =SUM(V75:V85) -> 442
D87: LS | E87: 0 | F87: =C87*E87 -> 0 | H87: 0 | I87: =G87*H87 -> 0 | K87: =F87+I87+J87 -> 0
D88: LS | E88: 0 | F88: =C88*E88 -> 0 | H88: 0 | I88: =G88*H88 -> 0 | K88: =F88+I88+J88 -> 0
D89: LS | E89: 0 | F89: =C89*E89 -> 0 | H89: 0 | I89: =G89*H89 -> 0 | K89: =F89+I89+J89 -> 0
J91: Sub Total | K91: =SUM(K87:K90) -> 0
F92: Material Total | G92: Total Hours | I92: Labor Total | J92: Contractor Total | K92: TOTAL
A93: $ / Sq.Ft | B93: TOTAL DIVISION 6
A94: =K94/E6 -> 39.255665 | F94: =SUM(F87:F90,F78:F83,F67:F73,F58:F63,F50:F54,F39:F46,F21:F35,F11:F17) -> 551103.89 | G94: =SUM(G87:G90,G78:G83,G67:G73,G58:G63,G50:G54,G39:G46,G21:G35,G11:G17) -> 0 | I94: =SUM(I87:I90,I78:I83,I67:I73,I58:I63,I50:I54,I39:I46,I21:I35,I11:I17) -> 0 | J94: =SUM(J87:J90,J78:J83,J67:J73,J58:J63,J50:J54,J39:J46,J21:J35,J11:J17) -> 2023753.7 | K94: =SUM(K91,K84,K75,K64,K55,K47,K36,K19) -> 2574857.6

Sheet 7
C1: ='Estimate Summary'!C1:H1 -> 0
G5: Thermal & Moisture Protection | J5: Schedule
D6: ='Estimate Summary'!C11 -> Area: | E6: ='Estimate Summary'!D11 -> 65592 | F6: ='Estimate Summary'!E11 -> Sq. Ft. | J6: ='1'!J6 -> 60 | K6: Weeks
A9: CODE | B9: DESCRIPTION | C9: Materials & Equipment | G9: Labor | L9: Sub Contractor | M9: Quote Total | N9: Additional Quote Info
A10: 07 21 00 | B10: Thermal Insulation | C10: Qty | D10: Unit | E10: U. Price | F10: Sub Total | G10: MHrs | H10: U. Price | I10: Sub Total | J10: Quote | K10: Total
A11: 07 21 16 | B11: Blanket Insulation | C11: 59 | D11: Unit | E11: =M15 -> 3880.4407 | H11: 0 | I11: =G11*H11 -> 0 | J11: =M11 -> 237835 | K11: =F11+I11+J11 -> 237835 | L11: Mike's | M11: 237835 | N11: Alternative in floor insulation
A12: 07 21 26 | B12: Blown Insulation | D12: LS | E12: 0 | F12: =C12*E12 -> 0 | H12: 0 | I12: =G12*H12 -> 0 | K12: =F12+I12+J12 -> 0 | L12: Ghiro / BenJo | M12: 193676 | N12: Missing spray foam in underground garage
A13: 07 21 29 | B13: Sprayed Insulation | D13: LS | E13: 0 | F13: =C13*E13 -> 0 | H13: 0 | I13: =G13*H13 -> 0 | K13: =F13+I13+J13 -> 0 | L13: Trinity | M13: =191830+30179 -> 222009 | N13: Blown insulation only
D14: LS | E14: 0 | F14: =C14*E14 -> 0 | H14: 0 | I14: =G14*H14 -> 0 | K14: =F14+I14+J14 -> 0
L15: Joyce per unit | M15: =228946/59 -> 3880.4407
J16: Sub Total | K16: =SUM(K11:K15) -> 237835
A17: CODE | B17: DESCRIPTION | C17: Materials & Equipment | G17: Labor
A18: 07 24 00 | B18: Sound Proofing | C18: Qty | D18: Unit | E18: U. Price | F18: Sub Total | G18: SF | H18: U. Price | I18: Sub Total | J18: Quote | K18: Total
B19: Acoustiboard | C19: =E6/4*3*1.2 -> 59032.8 | D19: SF | E19: 2.88 | F19: =C19*E19 -> 170014.46 | G19: =C19 -> 59032.8 | H19: 1.5 | I19: =G19*H19 -> 88549.2 | K19: =F19+I19+J19 -> 258563.66
B20: Sealant | C20: 45 | D20: Unit | E20: 51.43 | F20: =C20*E20 -> 2314.35 | G20: =C20 -> 45 | H20: =60*4 -> 240 | I20: =G20*H20 -> 10800 | K20: =F20+I20+J20 -> 13114.35 | L20: Assuming 1 tube can do 10'
D21: LS | E21: 0 | F21: =C21*E21 -> 0 | H21: 0 | I21: =G21*H21 -> 0 | K21: =F21+I21+J21 -> 0
J22: Sub Total | K22: =SUM(K19:K21) -> 271678.01
A23: CODE | B23: DESCRIPTION | C23: Materials & Equipment | G23: Labor | O23: Previous Quote
A24: 07 31 00 | B24: Shingles | C24: Qty | D24: Unit | E24: U. Price | F24: Sub Total | G24: MHrs | H24: U. Price | I24: Sub Total | J24: Quote | K24: Total | O24: All Angles Covered | P24: 87550
C25: =E6/4 -> 16398 | D25: SF | E25: =P27 -> 5.30309 | F25: =M25 -> 81750 | H25: 0 | I25: =G25*H25 -> 0 | K25: =F25+I25+J25 -> 81750 | L25: All Angles | M25: 81750
D26: LS | E26: 0 | F26: =C26*E26 -> 0 | H26: 0 | I26: =G26*H26 -> 0 | K26: =F26+I26+J26 -> 0 | L26: Belvue | M26: 101990.13
J27: Sub Total | K27: =SUM(K25:K26) -> 81750 | L27: Eastbound | M27: 102450 | O27: Joyce per sf/floor | P27: =67275/12686 -> 5.30309
A28: CODE | B28: DESCRIPTION | C28: Materials & Equipment | G28: Labor | L28: Maximum | M28: 57500 | N28: Install only
A29: 07 42 00 | B29: Wall Panels | C29: Qty | D29: Unit | E29: U. Price | F29: Sub Total | G29: MHrs | H29: U. Price | I29: Sub Total | J29: Quote | K29: Total
D30: LS | E30: 0 | F30: =C30*E30 -> 0 | H30: 0 | I30: =G30*H30 -> 0 | K30: =F30+I30+J30 -> 0
D31: LS | E31: 0 | F31: =C31*E31 -> 0 | H31: 0 | I31: =G31*H31 -> 0 | K31: =F31+I31+J31 -> 0
D32: LS | E32: 0 | F32: =C32*E32 -> 0 | H32: 0 | I32: =G32*H32 -> 0 | K32: =F32+I32+J32 -> 0
J33: Sub Total | K33: =SUM(K30:K32) -> 0
A34: CODE | B34: DESCRIPTION | C34: Materials & Equipment | G34: Labor
A35: 07 46 00 | B35: Siding | C35: Qty | D35: Unit | E35: U. Price | F35: Sub Total | G35: MHrs | H35: U. Price | I35: Sub Total | J35: Quote | K35: Total | L35: Century
B36: Metal Siding | C36: =20027+4282 -> 24309 | D36: SF | E36: 12 | F36: =C36*E36 -> 291708 | H36: 0 | I36: =G36*H36 -> 0 | K36: =F36+I36+J36 -> 291708 | L36: Shaw Materials | M36: 192414.29
D37: LS | E37: 0 | F37: =C37*E37 -> 0 | H37: 0 | I37: =G37*H37 -> 0 | J37: =M37-55000 -> 270000 | K37: =F37+I37+J37 -> 270000 | L37: AVT Install | M37: 325000 | N37: $55k credit if no need to install brick veneer. Includes strapping install
D38: LS | E38: 0 | F38: =C38*E38 -> 0 | H38: 0 | I38: =G38*H38 -> 0 | K38: =F38+I38+J38 -> 0 | L38: Century | M38: 715000 | N38: =M38/C36 -> 29.412975 | O38: Price per sf
J39: Sub Total | K39: =SUM(K36:K38) -> 561708 | L39: Riztcor Install | M39: $550 Per square | N39: $5.50 per SF | O39: =C36*5.5 -> 133699.5
A40: CODE | B40: DESCRIPTION | C40: Materials & Equipment | G40: Labor
A41: 07 52 00 | B41: Modified Bituminous Membrane Roofing | C41: Qty | D41: Unit | E41: U. Price | F41: Sub Total | G41: MHrs | H41: U. Price | I41: Sub Total | J41: Quote | K41: Total
D42: LS | E42: 0 | F42: =C42*E42 -> 0 | H42: 0 | I42: =G42*H42 -> 0 | K42: =F42+I42+J42 -> 0
D43: LS | E43: 0 | F43: =C43*E43 -> 0 | H43: 0 | I43: =G43*H43 -> 0 | K43: =F43+I43+J43 -> 0
D44: LS | E44: 0 | F44: =C44*E44 -> 0 | H44: 0 | I44: =G44*H44 -> 0 | K44: =F44+I44+J44 -> 0
J45: Sub Total | K45: =SUM(K42:K44) -> 0
A46: CODE | B46: DESCRIPTION | C46: Materials & Equipment | G46: Labor
A47: 07 53 00 | B47: Elastomeric Membrane Roofing | C47: Qty | D47: Unit | E47: U. Price | F47: Sub Total | G47: MHrs | H47: U. Price | I47: Sub Total | J47: Quote | K47: Total
D48: LS | E48: 0 | F48: =C48*E48 -> 0 | H48: 0 | I48: =G48*H48 -> 0 | K48: =F48+I48+J48 -> 0
D49: LS | E49: 0 | F49: =C49*E49 -> 0 | H49: 0 | I49: =G49*H49 -> 0 | K49: =F49+I49+J49 -> 0
J50: Sub Total | K50: =SUM(K48:K49) -> 0
A51: CODE | B51: DESCRIPTION | C51: Materials & Equipment | G51: Labor
A52: 07 62 00 | B52: Sheet Metal Flashing and Trim | C52: Qty | D52: Unit | E52: U. Price | F52: Sub Total | G52: MHrs | H52: U. Price | I52: Sub Total | J52: Quote | K52: Total
D53: LS | E53: 0 | F53: =C53*E53 -> 0 | H53: 0 | I53: =G53*H53 -> 0 | K53: =F53+I53+J53 -> 0
D54: LS | E54: 0 | F54: =C54*E54 -> 0 | H54: 0 | I54: =G54*H54 -> 0 | K54: =F54+I54+J54 -> 0
J55: Sub Total | K55: =SUM(K53:K54) -> 0
A56: CODE | B56: DESCRIPTION | C56: Materials & Equipment | G56: Labor
A57: 07 63 00 | B57: Sheet Metal Roofing Specialties | C57: Qty | D57: Unit | E57: U. Price | F57: Sub Total | G57: MHrs | H57: U. Price | I57: Sub Total | J57: Quote | K57: Total
D58: LS | E58: 0 | F58: =C58*E58 -> 0 | H58: 0 | I58: =G58*H58 -> 0 | K58: =F58+I58+J58 -> 0
D59: LS | E59: 0 | F59: =C59*E59 -> 0 | H59: 0 | I59: =G59*H59 -> 0 | K59: =F59+I59+J59 -> 0
J60: Sub Total | K60: =SUM(K58:K59) -> 0
A61: CODE | B61: DESCRIPTION | C61: Materials & Equipment | G61: Labor
A62: 07 64 00 | B62: Sheet Metal Wall Cladding | C62: Qty | D62: Unit | E62: U. Price | F62: Sub Total | G62: MHrs | H62: U. Price | I62: Sub Total | J62: Quote | K62: Total
D63: LS | E63: 0 | F63: =C63*E63 -> 0 | H63: 0 | I63: =G63*H63 -> 0 | K63: =F63+I63+J63 -> 0
D64: LS | E64: 0 | F64: =C64*E64 -> 0 | H64: 0 | I64: =G64*H64 -> 0 | K64: =F64+I64+J64 -> 0
D65: LS | E65: 0 | F65: =C65*E65 -> 0 | H65: 0 | I65: =G65*H65 -> 0 | K65: =F65+I65+J65 -> 0
J66: Sub Total | K66: =SUM(K63:K65) -> 0
A67: CODE | B67: DESCRIPTION | C67: Materials & Equipment | G67: Labor
A68: 07 72 00 | B68: Roof Accessories | C68: Qty | D68: Unit | E68: U. Price | F68: Sub Total | G68: MHrs | H68: U. Price | I68: Sub Total | J68: Quote | K68: Total
A69: 07 72 26 | B69: Ridge Vents | D69: LS | E69: 0 | F69: =C69*E69 -> 0 | H69: 0 | I69: =G69*H69 -> 0 | K69: =F69+I69+J69 -> 0
A70: 07 72 33 | B70: Roof Hatches | D70: LS | E70: 0 | F70: =C70*E70 -> 0 | H70: 0 | I70: =G70*H70 -> 0 | K70: =F70+I70+J70 -> 0
D71: LS | E71: 0 | F71: =C71*E71 -> 0 | H71: 0 | I71: =G71*H71 -> 0 | K71: =F71+I71+J71 -> 0
J72: Sub Total | K72: =SUM(K69:K71) -> 0
A73: CODE | B73: DESCRIPTION | C73: Materials & Equipment | G73: Labor
A74: 07 81 00 | B74: Applied Fireproofing | C74: Qty | D74: Unit | E74: U. Price | F74: Sub Total | G74: MHrs | H74: U. Price | I74: Sub Total | J74: Quote | K74: Total | L74: Mike's | M74: 26550
A75: 07 84 00 | B75: Firestopping | C75: 59 | D75: Unit | E75: =M77 -> 457.14286 | H75: 0 | I75: =G75*H75 -> 0 | J75: =M74 -> 26550 | K75: =F75+I75+J75 -> 26550 | L75: Premium | M75: 48376 | P75: Insulation
B76: Underground Garage Allowance | D76: LS | E76: 0 | F76: =C76*E76 -> 0 | H76: 0 | I76: =G76*H76 -> 0 | K76: =F76+I76+J76 -> 0 | L76: Fundy | M76: 21180
L77: Belle Foret per unit | M77: =28800/63 -> 457.14286
J78: Sub Total | K78: =SUM(K75:K77) -> 26550 | L78: Joyce per unit | M78: =21180/59 -> 358.98305
A79: CODE | B79: DESCRIPTION | C79: Materials & Equipment | G79: Labor
A80: 07 90 00 | B80: Joint Protection | C80: Qty | D80: Unit | E80: U. Price | F80: Sub Total | G80: MHrs | H80: U. Price | I80: Sub Total | J80: Quote | K80: Total
D81: LS | E81: 0 | F81: =C81*E81 -> 0 | H81: 0 | I81: =G81*H81 -> 0 | K81: =F81+I81+J81 -> 0
D82: LS | E82: 0 | F82: =C82*E82 -> 0 | H82: 0 | I82: =G82*H82 -> 0 | K82: =F82+I82+J82 -> 0
J84: Sub Total | K84: =SUM(K81:K83) -> 0
A85: CODE | B85: DESCRIPTION | C85: Materials & Equipment | G85: Labor
C86: Qty | D86: Unit | E86: U. Price | F86: Sub Total | G86: MHrs | H86: U. Price | I86: Sub Total | J86: Quote | K86: Total
D87: LS | E87: 0 | F87: =C87*E87 -> 0 | H87: 0 | I87: =G87*H87 -> 0 | K87: =F87+I87+J87 -> 0
D88: LS | E88: 0 | F88: =C88*E88 -> 0 | H88: 0 | I88: =G88*H88 -> 0 | K88: =F88+I88+J88 -> 0
J90: Sub Total | K90: =SUM(K87:K89) -> 0
F91: Material Total | G91: Total Hours | I91: Labor Total | J91: Contractor Total | K91: TOTAL
A92: $ / Sq.Ft | B92: TOTAL DIVISION 7
A93: =K94/E6 -> 0 | F93: =SUM(F87:F89,F81:F83,F75:F77,F69:F71,F63:F65,F58:F59,F53:F54,F48:F49,F42:F44,F36:F38,F30:F32,F25:F26,F19:F21,F11:F15) -> 545786.81 | G93: =SUM(G87:G89,G81:G83,G75:G77,G69:G71,G63:G65,G58:G59,G53:G54,G48:G49,G42:G44,G36:G38,G30:G32,G25:G26,G19:G21,G11:G15) -> 59077.8 | I93: =SUM(I87:I89,I81:I83,I75:I77,I69:I71,I63:I65,I58:I59,I53:I54,I48:I49,I42:I44,I36:I38,I30:I32,I25:I26,I19:I21,I11:I15) -> 99349.2 | J93: =SUM(J87:J89,J81:J83,J75:J77,J69:J71,J63:J65,J58:J59,J53:J54,J48:J49,J42:J44,J36:J38,J30:J32,J25:J26,J19:J21,J11:J15) -> 534385 | K93: =K90+K84+K78+K72+K66+K60+K55+K50+K45+K39+K33+K27+K22+K16 -> 1179521

Sheet 8
C1: ='Estimate Summary'!C1:H1 -> 0
G5: Openings | J5: Schedule
D6: ='Estimate Summary'!C11 -> Area: | E6: ='Estimate Summary'!D11 -> 65592 | F6: ='Estimate Summary'!E11 -> Sq. Ft. | J6: ='1'!J6 -> 60 | K6: Weeks
A11: CODE | B11: DESCRIPTION | C11: Materials & Equipment | G11: Labor | L11: Sub Contractor | M11: Quote Total | N11: Additional Quote Info
A12: 08 11 00 | B12: Metal Doors and Frames | C12: Qty | D12: Unit | E12: U. Price | F12: Sub Total | G12: MHrs | H12: U. Price | I12: Sub Total | J12: Quote | K12: Total
A13: 08 11 13 | B13: Hollow Metal Doors and Frames | C13: 59 | D13: Unit | E13: =M17 -> 2040.8644 | H13: 0 | I13: =G13*H13 -> 0 | J13: =M13 -> 89875 | K13: =F13+I13+J13 -> 89875 | L13: Sevy | M13: =88350+1525 -> 89875
A14: 08 11 16 | B14: Aluminum Doors and Frames | D14: LS | E14: 0 | F14: =C14*E14 -> 0 | H14: 0 | I14: =G14*H14 -> 0 | K14: =F14+I14+J14 -> 0
D15: LS | E15: 0 | F15: =C15*E15 -> 0 | H15: 0 | I15: =G15*H15 -> 0 | K15: =F15+I15+J15 -> 0
D16: LS | E16: 0 | F16: =C16*E16 -> 0 | H16: 0 | I16: =G16*H16 -> 0 | K16: =F16+I16+J16 -> 0
L17: Joyce | M17: =120411/59 -> 2040.8644
J18: Sub Total | K18: =SUM(K13:K17) -> 89875
A19: CODE | B19: DESCRIPTION | C19: Materials & Equipment | G19: Labor
A20: 08 14 00 | B20: Wood Doors | C20: Qty | D20: Unit | E20: U. Price | F20: Sub Total | G20: MHrs | H20: U. Price | I20: Sub Total | J20: Quote | K20: Total
D21: LS | E21: 0 | F21: =C21*E21 -> 0 | H21: 0 | I21: =G21*H21 -> 0 | K21: =F21+I21+J21 -> 0
D22: LS | E22: 0 | F22: =C22*E22 -> 0 | H22: 0 | I22: =G22*H22 -> 0 | K22: =F22+I22+J22 -> 0
D23: LS | E23: 0 | F23: =C23*E23 -> 0 | H23: 0 | I23: =G23*H23 -> 0 | K23: =F23+I23+J23 -> 0
J24: Sub Total | K24: =SUM(K21:K23) -> 0
A25: CODE | B25: DESCRIPTION | C25: Materials & Equipment | G25: Labor
A26: 08 31 00 | B26: Access Doors and Panels | C26: Qty | D26: Unit | E26: U. Price | F26: Sub Total | G26: MHrs | H26: U. Price | I26: Sub Total | J26: Quote | K26: Total
B27: Attict Hatches | C27: 1 | D27: LS | E27: 8000 | F27: =C27*E27 -> 8000 | H27: 0 | I27: =G27*H27 -> 0 | K27: =F27+I27+J27 -> 8000
D28: LS | E28: 0 | F28: =C28*E28 -> 0 | H28: 0 | I28: =G28*H28 -> 0 | K28: =F28+I28+J28 -> 0
J29: Sub Total | K29: =SUM(K27:K28) -> 8000
A30: CODE | B30: DESCRIPTION | C30: Materials & Equipment | G30: Labor
A31: 08 32 00 | B31: Sliding Gates | C31: Qty | D31: Unit | E31: U. Price | F31: Sub Total | G31: MHrs | H31: U. Price | I31: Sub Total | J31: Quote | K31: Total
D32: LS | E32: 0 | F32: =C32*E32 -> 0 | H32: 0 | I32: =G32*H32 -> 0 | K32: =F32+I32+J32 -> 0
D33: LS | E33: 0 | F33: =C33*E33 -> 0 | H33: 0 | I33: =G33*H33 -> 0 | K33: =F33+I33+J33 -> 0
D34: LS | E34: 0 | F34: =C34*E34 -> 0 | H34: 0 | I34: =G34*H34 -> 0 | K34: =F34+I34+J34 -> 0
J35: Sub Total | K35: =SUM(K32:K34) -> 0
A36: CODE | B36: DESCRIPTION | C36: Materials & Equipment | G36: Labor
A37: 08 33 00 | B37: Coiling Doors and Drilles | C37: Qty | D37: Unit | E37: U. Price | F37: Sub Total | G37: MHrs | H37: U. Price | I37: Sub Total | J37: Quote | K37: Total
D38: LS | E38: 0 | F38: =C38*E38 -> 0 | H38: 0 | I38: =G38*H38 -> 0 | J38: =M38 -> 10984.51 | K38: =F38+I38+J38 -> 10984.51 | L38: Gagnon | M38: 10984.51
D39: LS | E39: 0 | F39: =C39*E39 -> 0 | H39: 0 | I39: =G39*H39 -> 0 | K39: =F39+I39+J39 -> 0 | L39: Iller | M39: 7273
D40: LS | E40: 0 | F40: =C40*E40 -> 0 | H40: 0 | I40: =G40*H40 -> 0 | K40: =F40+I40+J40 -> 0
J41: Sub Total | K41: =SUM(K38:K40) -> 10984.51
A42: CODE | B42: DESCRIPTION | C42: Materials & Equipment | G42: Labor
A43: 08 34 00 | B43: Special Function Doors | C43: Qty | D43: Unit | E43: U. Price | F43: Sub Total | G43: MHrs | H43: U. Price | I43: Sub Total | J43: Quote | K43: Total
D44: LS | E44: 0 | F44: =C44*E44 -> 0 | H44: 0 | I44: =G44*H44 -> 0 | K44: =F44+I44+J44 -> 0
D45: LS | E45: 0 | F45: =C45*E45 -> 0 | H45: 0 | I45: =G45*H45 -> 0 | K45: =F45+I45+J45 -> 0
D46: LS | E46: 0 | F46: =C46*E46 -> 0 | H46: 0 | I46: =G46*H46 -> 0 | K46: =F46+I46+J46 -> 0
J47: Sub Total | K47: =SUM(K44:K46) -> 0
A48: CODE | B48: DESCRIPTION | C48: Materials & Equipment | G48: Labor
A49: 08 38 00 | B49: Traffic Doors | C49: Qty | D49: Unit | E49: U. Price | F49: Sub Total | G49: MHrs | H49: U. Price | I49: Sub Total | J49: Quote | K49: Total
D50: LS | E50: 0 | F50: =C50*E50 -> 0 | H50: 0 | I50: =G50*H50 -> 0 | K50: =F50+I50+J50 -> 0
D51: LS | E51: 0 | F51: =C51*E51 -> 0 | H51: 0 | I51: =G51*H51 -> 0 | K51: =F51+I51+J51 -> 0
J52: Sub Total | K52: =SUM(K50:K51) -> 0
A53: CODE | B53: DESCRIPTION | C53: Materials & Equipment | G53: Labor
A54: 08 41 00 | B54: Entrances and Storefronts | C54: Qty | D54: Unit | E54: U. Price | F54: Sub Total | G54: MHrs | H54: U. Price | I54: Sub Total | J54: Quote | K54: Total
C55: 1 | D55: LS | E55: 35000 | H55: 0 | I55: =G55*H55 -> 0 | J55: =M55 -> 39425 | K55: =F55+I55+J55 -> 39425 | L55: FCG | M55: 39425
D56: LS | E56: 0 | F56: =C56*E56 -> 0 | H56: 0 | I56: =G56*H56 -> 0 | K56: =F56+I56+J56 -> 0 | L56: Royal | M56: 50837
J57: Sub Total | K57: =SUM(K55:K56) -> 39425
A58: CODE | B58: DESCRIPTION | C58: Materials & Equipment | G58: Labor | L58: Economy | M58: 38300
A59: 08 44 00 | B59: Curtain Wall and Glazed Assemblies | C59: Qty | D59: Unit | E59: U. Price | F59: Sub Total | G59: MHrs | H59: U. Price | I59: Sub Total | J59: Quote | K59: Total
D60: LS | E60: 0 | F60: =C60*E60 -> 0 | H60: 0 | I60: =G60*H60 -> 0 | K60: =F60+I60+J60 -> 0
D61: LS | E61: 0 | F61: =C61*E61 -> 0 | H61: 0 | I61: =G61*H61 -> 0 | K61: =F61+I61+J61 -> 0
J62: Sub Total | K62: =SUM(K60:K61) -> 0
A63: CODE | B63: DESCRIPTION | C63: Materials & Equipment | G63: Labor | M63: Option 1 | N63: Option 2
A64: 08 50 00 | B64: Windows | C64: Qty | D64: Unit | E64: U. Price | F64: Sub Total | G64: MHrs | H64: U. Price | I64: Sub Total | J64: Quote | K64: Total | L64: Global | M64: 127003.4 | N64: 126145.3 | O64: Option 1 is spec but does not meet NAFS. Option 2 offers alternative split window half operable. | T64: W1A | U64: 106
A65: 08 51 00 | B65: Metal Windows | D65: LS | E65: 0 | F65: =C65*E65 -> 0 | H65: 0 | I65: =G65*H65 -> 0 | J65: =N64 -> 126145.3 | K65: =F65+I65+J65 -> 126145.3 | L65: Atlantic | M65: 121656.5 | N65: =M65-(4*460)+(4*208) -> 120648.5 | O65: Option 2 is fixed count. Balcony doors tempered | T65: W1B | U65: 16
A66: 08 52 00 | B66: Wood Windows | D66: LS | E66: 0 | F66: =C66*E66 -> 0 | H66: 0 | I66: =G66*H66 -> 0 | K66: =F66+I66+J66 -> 0 | L66: Maritime | M66: 155674.41 | N66: 133974.46 | O66: Did not include BF unit doors | T66: W1C | U66: 17
A67: 08 53 00 | B67: Plastic Windows | C67: 59 | D67: Unit | E67: =M69 -> 5243.5793 | H67: 0 | I67: =G67*H67 -> 0 | K67: =F67+I67+J67 -> 0 | L67: Ghiro | M67: 146347.04 | N67: =(561.12*4)+M67 -> 148591.52 | O67: Option 2 is fixed count | T67: W2A | U67: 25
A68: 08 54 00 | B68: Composite Windows | D68: LS | E68: 0 | F68: =C68*E68 -> 0 | H68: 0 | I68: =G68*H68 -> 0 | K68: =F68+I68+J68 -> 0 | T68: PatioA | U68: 56
J69: Sub Total | K69: =SUM(K65:K68) -> 126145.3 | L69: Joyce | M69: =309371.18/59 -> 5243.5793 | T69: PatioB | U69: 3
A70: CODE | B70: DESCRIPTION | C70: Materials & Equipment | G70: Labor
A71: 08 70 00 | B71: Hardware | C71: Qty | D71: Unit | E71: U. Price | F71: Sub Total | G71: MHrs | H71: U. Price | I71: Sub Total | J71: Quote | K71: Total
D72: LS | E72: 0 | F72: =C72*E72 -> 0 | H72: 0 | I72: =G72*H72 -> 0 | K72: =F72+I72+J72 -> 0
D73: LS | E73: 0 | F73: =C73*E73 -> 0 | H73: 0 | I73: =G73*H73 -> 0 | K73: =F73+I73+J73 -> 0
J75: Sub Total | K75: =SUM(K72:K74) -> 0
A76: CODE | B76: DESCRIPTION | C76: Materials & Equipment | G76: Labor
A77: 08 81 00 | B77: Glass Glazing | C77: Qty | D77: Unit | E77: U. Price | F77: Sub Total | G77: MHrs | H77: U. Price | I77: Sub Total | J77: Quote | K77: Total | L77: Century
D78: LS | E78: 0 | F78: =C78*E78 -> 0 | H78: 0 | I78: =G78*H78 -> 0 | K78: =F78+I78+J78 -> 0 | L78: FCG
D79: LS | E79: 0 | F79: =C79*E79 -> 0 | H79: 0 | I79: =G79*H79 -> 0 | K79: =F79+I79+J79 -> 0
J81: Sub Total | K81: =SUM(K78:K80) -> 0
A82: CODE | B82: DESCRIPTION | C82: Materials & Equipment | G82: Labor
A83: 08 83 00 | B83: Mirrors | C83: Qty | D83: Unit | E83: U. Price | F83: Sub Total | G83: MHrs | H83: U. Price | I83: Sub Total | J83: Quote | K83: Total
D84: LS | E84: 0 | F84: =C84*E84 -> 0 | H84: 0 | I84: =G84*H84 -> 0 | K84: =F84+I84+J84 -> 0
D85: LS | E85: 0 | F85: =C85*E85 -> 0 | H85: 0 | I85: =G85*H85 -> 0 | K85: =F85+I85+J85 -> 0
J87: Sub Total | K87: =SUM(K84:K86) -> 0
A88: CODE | B88: DESCRIPTION | C88: Materials & Equipment | G88: Labor
A89: 08 87 00 | B89: Glazing Surface Films | C89: Qty | D89: Unit | E89: U. Price | F89: Sub Total | G89: MHrs | H89: U. Price | I89: Sub Total | J89: Quote | K89: Total
D90: LS | E90: 0 | F90: =C90*E90 -> 0 | H90: 0 | I90: =G90*H90 -> 0 | K90: =F90+I90+J90 -> 0
D91: LS | E91: 0 | F91: =C91*E91 -> 0 | H91: 0 | I91: =G91*H91 -> 0 | K91: =F91+I91+J91 -> 0
J93: Sub Total | K93: =SUM(K90:K92) -> 0
A94: CODE | B94: DESCRIPTION | C94: Materials & Equipment | G94: Labor
A95: 08 91 00 | B95: Louvers | C95: Qty | D95: Unit | E95: U. Price | F95: Sub Total | G95: MHrs | H95: U. Price | I95: Sub Total | J95: Quote | K95: Total
D96: LS | E96: 0 | F96: =C96*E96 -> 0 | H96: 0 | I96: =G96*H96 -> 0 | K96: =F96+I96+J96 -> 0
D97: LS | E97: 0 | F97: =C97*E97 -> 0 | H97: 0 | I97: =G97*H97 -> 0 | K97: =F97+I97+J97 -> 0
J99: Sub Total | K99: =SUM(K96:K98) -> 0
A100: CODE | B100: DESCRIPTION | C100: Materials & Equipment | G100: Labor
C101: Qty | D101: Unit | E101: U. Price | F101: Sub Total | G101: MHrs | H101: U. Price | I101: Sub Total | J101: Quote | K101: Total
D102: LS | E102: 0 | F102: =C102*E102 -> 0 | H102: 0 | I102: =G102*H102 -> 0 | K102: =F102+I102+J102 -> 0
D103: LS | E103: 0 | F103: =C103*E103 -> 0 | H103: 0 | I103: =G103*H103 -> 0 | K103: =F103+I103+J103 -> 0
J105: Sub Total | K105: =SUM(K102:K104) -> 0
F106: Material Total | G106: Total Hours | I106: Labor Total | J106: Contractor Total | K106: TOTAL
A107: $ / Sq.Ft | B107: TOTAL DIVISION 8
A108: =K109/E6 -> 0 | F108: =SUM(F102:F104,F96:F98,F90:F92,F84:F86,F78:F80,F72:F74,F65:F68,F60:F61,F55:F56,F50:F51,F44:F46,F38:F40,F32:F34,F27:F28,F21:F23,F13:F17) -> 8000 | G108: =SUM(G102:G104,G96:G98,G90:G92,G84:G86,G78:G80,G72:G74,G65:G68,G60:G61,G55:G56,G50:G51,G44:G46,G38:G40,G32:G34,G27:G28,G21:G23,G13:G17) -> 0 | I108: =SUM(I102:I104,I96:I98,I90:I92,I84:I86,I78:I80,I72:I74,I65:I68,I60:I61,I55:I56,I50:I51,I44:I46,I38:I40,I32:I34,I27:I28,I21:I23,I13:I17) -> 0 | J108: =SUM(J102:J104,J96:J98,J90:J92,J84:J86,J78:J80,J72:J74,J65:J68,J60:J61,J55:J56,J50:J51,J44:J46,J38:J40,J32:J34,J27:J28,J21:J23,J13:J17) -> 266429.81 | K108: =SUM(K105,K99,K93,K87,K81,K75,K69,K18,K24,K29,K35,K41,K47,K52,K57,K62) -> 274429.81

Sheet 9
C1: ='Estimate Summary'!C1:H1 -> 0
G5: Finishes | J5: Schedule
D6: ='Estimate Summary'!C11 -> Area: | E6: ='Estimate Summary'!D11 -> 65592 | F6: ='Estimate Summary'!E11 -> Sq. Ft. | J6: ='1'!J6 -> 60 | K6: Weeks
A9: CODE | B9: DESCRIPTION | C9: Materials & Equipment | G9: Labor | L9: Sub Contractor | M9: Quote Total | N9: Additional Quote Info | O9: Previous Quotes
A10: 09 20 00 | B10: Plaster and Gypsum Board | C10: Qty | D10: Unit | E10: U. Price | F10: Sub Total | G10: MHrs | H10: U. Price | I10: Sub Total | J10: Quote | K10: Total
D11: SF | E11: 0 | F11: =C11*E11 -> 0 | H11: 0 | I11: =G11*H11 -> 0 | J11: =M13 -> 1139222 | K11: =F11+I11+J11 -> 1139222 | L11: A1 | M11: 1209800 | N11: Price no longer valid - Merge with Arsenault | O11: A1 | P11: 1298700
D12: SF | E12: 0 | F12: =C12*E12 -> 0 | H12: 0 | I12: =G12*H12 -> 0 | K12: =F12+I12+J12 -> 0 | L12: Fundy | M12: 1138510 | N12: Frame bulkheads extra $28,640 | O12: Cheaper when using with firestopping
D13: SF | E13: 0 | F13: =C13*E13 -> 0 | H13: 0 | I13: =G13*H13 -> 0 | K13: =F13+I13+J13 -> 0 | L13: Arsenault | M13: 1139222 | N13: Revised price
D14: SF | E14: 0 | F14: =C14*E14 -> 0 | H14: 0 | I14: =G14*H14 -> 0 | K14: =F14+I14+J14 -> 0
D15: SF | E15: 0 | F15: =C15*E15 -> 0 | H15: 0 | I15: =G15*H15 -> 0 | K15: =F15+I15+J15 -> 0
D16: SF | E16: 0 | F16: =C16*E16 -> 0 | H16: 0 | I16: =G16*H16 -> 0 | K16: =F16+I16+J16 -> 0
J18: Sub Total | K18: =SUM(K11:K17) -> 1139222
A19: CODE | B19: DESCRIPTION | C19: Materials & Equipment | G19: Labor
A20: 09 30 00 | B20: Tiling | C20: Qty | D20: Unit | E20: U. Price | F20: Sub Total | G20: MHrs | H20: U. Price | I20: Sub Total | J20: Quote | K20: Total
D21: SF | E21: 0 | F21: =C21*E21 -> 0 | H21: 0 | I21: =G21*H21 -> 0 | K21: =F21+I21+J21 -> 0
D22: SF | E22: 0 | F22: =C22*E22 -> 0 | H22: 0 | I22: =G22*H22 -> 0 | K22: =F22+I22+J22 -> 0
D23: SF | E23: 0 | F23: =C23*E23 -> 0 | H23: 0 | I23: =G23*H23 -> 0 | K23: =F23+I23+J23 -> 0
D24: SF | E24: 0 | F24: =C24*E24 -> 0 | H24: 0 | I24: =G24*H24 -> 0 | K24: =F24+I24+J24 -> 0
J26: Sub Total | K26: =SUM(K21:K25) -> 0
A27: CODE | B27: DESCRIPTION | C27: Materials & Equipment | G27: Labor
A28: 09 50 00 | B28: Ceiling | C28: Qty | D28: Unit | E28: U. Price | F28: Sub Total | G28: MHrs | H28: U. Price | I28: Sub Total | J28: Quote | K28: Total
D29: SF | E29: 0 | F29: =C29*E29 -> 0 | H29: 0 | I29: =G29*H29 -> 0 | K29: =F29+I29+J29 -> 0
D30: SF | E30: 0 | F30: =C30*E30 -> 0 | H30: 0 | I30: =G30*H30 -> 0 | K30: =F30+I30+J30 -> 0
J32: Sub Total | K32: =SUM(K29:K31) -> 0
A33: CODE | B33: DESCRIPTION | C33: Materials & Equipment | G33: Labor
A34: 09 60 00 | B34: Flooring | C34: Qty | D34: Unit | E34: U. Price | F34: Sub Total | G34: MHrs | H34: U. Price | I34: Sub Total | J34: Quote | K34: Total
A35: 09 61 00 | B35: Concrete Floor Polishing | C35: 17300 | D35: SF | E35: 7 | F35: =C35*E35 -> 121100 | H35: 0 | I35: =G35*H35 -> 0 | K35: =F35+I35+J35 -> 121100 | L35: Need epoxy quotes | M35: Expert Concrete
D36: SF | E36: 0 | F36: =C36*E36 -> 0 | H36: 0 | I36: =G36*H36 -> 0 | K36: =F36+I36+J36 -> 0
A37: 09 62 00 | B37: Specialty Flooring | D37: SF | E37: 0 | F37: =C37*E37 -> 0 | H37: 0 | I37: =G37*H37 -> 0 | K37: =F37+I37+J37 -> 0
A38: 09 64 00 | B38: Wood Flooring | D38: SF | E38: 0 | F38: =C38*E38 -> 0 | H38: 0 | I38: =G38*H38 -> 0 | K38: =F38+I38+J38 -> 0
A39: 09 65 00 | B39: VCT | D39: SF | E39: 0 | F39: =C39*E39 -> 0 | H39: 0 | I39: =G39*H39 -> 0 | K39: =F39+I39+J39 -> 0 | L39: Ritchies | M39: 290000 | N39: Meets Soprema Acoustiboard requirements.
A40: 09 67 00 | B40: LVT | C40: =E6 -> 65592 | D40: SF | E40: 4.5 | H40: 0 | I40: =G40*H40 -> 0 | J40: =M39 -> 290000 | K40: =F40+I40+J40 -> 290000 | L40: Floors Plus | M40: 305400 | N40: Revised to meeet Soprema requirements
A41: 09 68 00 | B41: Carpet Tile | D41: SF | E41: 0 | F41: =C41*E41 -> 0 | H41: 0 | I41: =G41*H41 -> 0 | K41: =F41+I41+J41 -> 0 | L41: Master Interior (Late) | M41: =99821.75+94688.06+2129.9+5111.76+17921.94+21024 -> 240697.41
J47: Sub Total | K47: =SUM(K35:K46) -> 411100
A48: CODE | B48: DESCRIPTION | C48: Materials & Equipment | G48: Labor
A49: 09 72 00 | B49: Wall Coverings | C49: Qty | D49: Unit | E49: U. Price | F49: Sub Total | G49: MHrs | H49: U. Price | I49: Sub Total | J49: Quote | K49: Total
D50: SF | E50: 0 | F50: =C50*E50 -> 0 | H50: 0 | I50: =G50*H50 -> 0 | K50: =F50+I50+J50 -> 0
D51: SF | E51: 0 | F51: =C51*E51 -> 0 | H51: 0 | I51: =G51*H51 -> 0 | K51: =F51+I51+J51 -> 0
J53: Sub Total | K53: =SUM(K50:K52) -> 0
A54: CODE | B54: DESCRIPTION | C54: Materials & Equipment | G54: Labor
A55: 09 91 00 | B55: Painting | C55: Qty | D55: Unit | E55: U. Price | F55: Sub Total | G55: MHrs | H55: U. Price | I55: Sub Total | J55: Quote | K55: Total
A56: 09 91 13 | B56: Exterior Painting | D56: SF | E56: 0 | F56: =C56*E56 -> 0 | H56: 0 | I56: =G56*H56 -> 0 | K56: =F56+I56+J56 -> 0 | L56: Advantage | M56: 200000
A57: 09 91 23 | B57: Interior Painting | D57: SF | E57: 0 | F57: =C57*E57 -> 0 | H57: 0 | I57: =G57*H57 -> 0 | J57: =M59 -> 197003 | K57: =F57+I57+J57 -> 197003 | L57: D&S | M57: 331537
L58: P4X | M58: 218205
L59: PaintGenix | M59: 197003
L60: Priority
J62: Sub Total | K62: =SUM(K56:K61) -> 197003
F63: Material Total | G63: Total Hours | I63: Labor Total | J63: Contractor Total | K63: TOTAL
A64: $ / Sq.Ft | B64: TOTAL DIVISION 9
A65: =K66/'Estimate Summary'!E6 -> #VALUE! | F65: =SUM(F56:F61,F35:F46,F29:F31,F21:F25,F11:F17,F50:F52) -> 121100 | G65: =SUM(G56:G61,G35:G46,G29:G31,G21:G25,G11:G17) -> 0 | I65: =SUM(I56:I61,I35:I46,I29:I31,I21:I25,I11:I17,I50:I52) -> 0 | J65: =SUM(J56:J61,J35:J46,J29:J31,J21:J25,J11:J17,J50:J52) -> 1626225 | K65: =K62+K53+K47+K32+K26+K18 -> 1747325

Sheet 10
C1: ='Estimate Summary'!C1:H1 -> 0
G5: Specalties | J5: Schedule
D6: ='Estimate Summary'!C11 -> Area: | E6: ='Estimate Summary'!D11 -> 65592 | F6: ='Estimate Summary'!E11 -> Sq. Ft. | J6: ='1'!J6 -> 60 | K6: Weeks
A9: CODE | B9: DESCRIPTION | C9: Materials & Equipment | G9: Labor | L9: Sub Contractor | M9: Quote Total | N9: Additional Quote Info
A10: 10 11 00 | B10: Visual Display Units | C10: Qty | D10: Unit | E10: U. Price | F10: Sub Total | G10: MHrs | H10: U. Price | I10: Sub Total | J10: Quote | K10: Total
D11: LS | E11: 0 | F11: =C11*E11 -> 0 | H11: 0 | I11: =G11*H11 -> 0 | K11: =F11+I11+J11 -> 0
D12: LS | E12: 0 | F12: =C12*E12 -> 0 | H12: 0 | I12: =G12*H12 -> 0 | K12: =F12+I12+J12 -> 0
D13: LS | E13: 0 | F13: =C13*E13 -> 0 | H13: 0 | I13: =G13*H13 -> 0 | K13: =F13+I13+J13 -> 0
D14: LS | E14: 0 | F14: =C14*E14 -> 0 | H14: 0 | I14: =G14*H14 -> 0 | K14: =F14+I14+J14 -> 0
D15: LS | E15: 0 | F15: =C15*E15 -> 0 | H15: 0 | I15: =G15*H15 -> 0 | K15: =F15+I15+J15 -> 0
J17: Sub Total | K17: =SUM(K11:K16) -> 0
A18: CODE | B18: DESCRIPTION | C18: Materials & Equipment | G18: Labor
A19: 10 14 00 | B19: Signage | C19: Qty | D19: Unit | E19: U. Price | F19: Sub Total | G19: MHrs | H19: U. Price | I19: Sub Total | J19: Quote | K19: Total
D20: LS | E20: 0 | F20: =C20*E20 -> 0 | H20: 0 | I20: =G20*H20 -> 0 | K20: =F20+I20+J20 -> 0
B21: Mailbox | C21: 1 | D21: LS | E21: 5000 | H21: 0 | I21: =G21*H21 -> 0 | J21: =M21 -> 10950 | K21: =F21+I21+J21 -> 10950 | L21: Short | M21: 10950
D22: LS | E22: 0 | F22: =C22*E22 -> 0 | H22: 0 | I22: =G22*H22 -> 0 | K22: =F22+I22+J22 -> 0
D23: LS | E23: 0 | F23: =C23*E23 -> 0 | H23: 0 | I23: =G23*H23 -> 0 | K23: =F23+I23+J23 -> 0
J25: Sub Total | K25: =SUM(K20:K24) -> 10950
A26: CODE | B26: DESCRIPTION | C26: Materials & Equipment | G26: Labor
A27: 10 20 00 | B27: Interior Specialties | C27: Qty | D27: Unit | E27: U. Price | F27: Sub Total | G27: MHrs | H27: U. Price | I27: Sub Total | J27: Quote | K27: Total
A28: 10 21 00 | B28: Compartments and Cubicles | D28: LS | E28: 0 | F28: =C28*E28 -> 0 | H28: 0 | I28: =G28*H28 -> 0 | K28: =F28+I28+J28 -> 0 | L28: Short
A29: 10 21 13 | B29: Toilet Compartments | D29: LS | E29: 0 | F29: =C29*E29 -> 0 | H29: 0 | I29: =G29*H29 -> 0 | K29: =F29+I29+J29 -> 0
A30: 10 22 00 | B30: Partitions | D30: LS | E30: 0 | F30: =C30*E30 -> 0 | H30: 0 | I30: =G30*H30 -> 0 | K30: =F30+I30+J30 -> 0
A31: 10 22 19 | B31: Demountable Partitions | D31: LS | E31: 0 | F31: =C31*E31 -> 0 | H31: 0 | I31: =G31*H31 -> 0 | K31: =F31+I31+J31 -> 0 | L31: Master Interior Chrome (Late) | M31: 2296
A32: 10 22 39 | B32: Mirror | D32: LS | E32: 0 | F32: =C32*E32 -> 0 | H32: 0 | I32: =G32*H32 -> 0 | K32: =F32+I32+J32 -> 0 | L32: Master Interior Black (Late) | M32: 3116
A33: 10 22 43 | B33: Sliding Partions | C33: 59 | D33: Unit | E33: 203.21 | F33: =C33*E33 -> 11989.39 | H33: 60 | I33: =G33*H33 -> 0 | K33: =F33+I33+J33 -> 11989.39 | L33: Master Interior Mirror (Black) | M33: 5904
A34: 10 28 00 | B34: Toilet , Bath, and Laundry Accessories | D34: LS | E34: 0 | F34: =C34*E34 -> 0 | H34: 0 | I34: =G34*H34 -> 0 | K34: =F34+I34+J34 -> 0
J38: Sub Total | K38: =SUM(K28:K37) -> 11989.39
A39: CODE | B39: DESCRIPTION | C39: Materials & Equipment | G39: Labor
A40: 10 44 00 | B40: Fire Protection Specialties | C40: Qty | D40: Unit | E40: U. Price | F40: Sub Total | G40: MHrs | H40: U. Price | I40: Sub Total | J40: Quote | K40: Total
A41: 10 44 16 | B41: Fire Extinguishers | D41: LS | E41: 0 | F41: =C41*E41 -> 0 | H41: 0 | I41: =G41*H41 -> 0 | K41: =F41+I41+J41 -> 0
D42: LS | E42: 0 | F42: =C42*E42 -> 0 | H42: 0 | I42: =G42*H42 -> 0 | K42: =F42+I42+J42 -> 0
J44: Sub Total | K44: =SUM(K41:K43) -> 0
A45: CODE | B45: DESCRIPTION | C45: Materials & Equipment | G45: Labor
A46: 10 51 00 | B46: Lockers | C46: Qty | D46: Unit | E46: U. Price | F46: Sub Total | G46: MHrs | H46: U. Price | I46: Sub Total | J46: Quote | K46: Total
D47: LS | E47: 0 | F47: =C47*E47 -> 0 | H47: 0 | I47: =G47*H47 -> 0 | J47: =M48 -> 31062.37 | K47: =F47+I47+J47 -> 31062.37 | L47: Eastern | M47: 36900
D48: LS | E48: 0 | F48: =C48*E48 -> 0 | H48: 0 | I48: =G48*H48 -> 0 | K48: =F48+I48+J48 -> 0 | L48: Stor-it | M48: 31062.37
D49: LS | E49: 0 | F49: =C49*E49 -> 0 | H49: 0 | I49: =G49*H49 -> 0 | K49: =F49+I49+J49 -> 0 | L49: Maritime | M49: 57000
L50: Groundtek | M50: 52685
J51: Sub Total | K51: =SUM(K47:K50) -> 31062.37
A52: CODE | B52: DESCRIPTION | C52: Materials & Equipment | G52: Labor
A53: 10 57 00 | B53: Wardrobe and Closet Specialties | C53: Qty | D53: Unit | E53: U. Price | F53: Sub Total | G53: MHrs | H53: U. Price | I53: Sub Total | J53: Quote | K53: Total
B54: Wire shelving | D54: LS | E54: 0 | F54: =C54*E54 -> 0 | H54: 0 | I54: =G54*H54 -> 0 | J54: =M54 -> 32532 | K54: =F54+I54+J54 -> 32532 | L54: Hang It | M54: 32532
D55: LS | E55: 0 | F55: =C55*E55 -> 0 | H55: 0 | I55: =G55*H55 -> 0 | K55: =F55+I55+J55 -> 0
J57: Sub Total | K57: =SUM(K54:K56) -> 32532
A58: CODE | B58: DESCRIPTION | C58: Materials & Equipment | G58: Labor
A59: 10 70 00 | B59: Exterior Specialties | C59: Qty | D59: Unit | E59: U. Price | F59: Sub Total | G59: MHrs | H59: U. Price | I59: Sub Total | J59: Quote | K59: Total
A60: 10 73 00 | B60: Bike Rack | C60: 1 | D60: LS | E60: 2000 | F60: =M60 -> 1340 | G60: 5 | H60: 60 | I60: =G60*H60 -> 300 | K60: =F60+I60+J60 -> 1640 | L60: Eastern | M60: 1340
A61: 10 73 16 | B61: Canopies | D61: LS | E61: 0 | F61: =C61*E61 -> 0 | H61: 0 | I61: =G61*H61 -> 0 | K61: =F61+I61+J61 -> 0
A62: 10 75 00 | B62: Flagpoles
J63: Sub Total | K63: =SUM(K60:K62) -> 1640
A64: CODE | B64: DESCRIPTION | C64: Materials & Equipment | G64: Labor
C65: Qty | D65: Unit | E65: U. Price | F65: Sub Total | G65: MHrs | H65: U. Price | I65: Sub Total | J65: Quote | K65: Total
D66: LS | E66: 0 | F66: =C66*E66 -> 0 | H66: 0 | I66: =G66*H66 -> 0 | K66: =F66+I66+J66 -> 0
D67: LS | E67: 0 | F67: =C67*E67 -> 0 | H67: 0 | I67: =G67*H67 -> 0 | K67: =F67+I67+J67 -> 0
D68: LS | E68: 0 | F68: =C68*E68 -> 0 | H68: 0 | I68: =G68*H68 -> 0 | K68: =F68+I68+J68 -> 0
D69: LS | E69: 0 | F69: =C69*E69 -> 0 | H69: 0 | I69: =G69*H69 -> 0 | K69: =F69+I69+J69 -> 0
J71: Sub Total | K71: =SUM(K66:K70) -> 0
F72: Material Total | G72: Total Hours | I72: Labor Total | J72: Contractor Total | K72: TOTAL
A73: $ / Sq.Ft | B73: TOTAL DIVISION 10
A74: =K75/E6 -> 0 | F74: =SUM(F66:F70,F60:F62,F54:F56,F47:F50,F41:F43,F28:F37,F20:F24,F11:F16) -> 13329.39 | G74: =SUM(G66:G70,G60:G62,G54:G56,G47:G50,G41:G43,G28:G37,G20:G24,G11:G16) -> 5 | I74: =SUM(I66:I70,I60:I62,I54:I56,I47:I50,I41:I43,I28:I37,I20:I24,I11:I16) -> 300 | J74: =SUM(J66:J70,J60:J62,J54:J56,J47:J50,J41:J43,J28:J37,J20:J24,J11:J16) -> 74544.37 | K74: =K71+K63+K57+K51+K44+K38+K25+K17 -> 88173.76

Sheet 11
C1: ='Estimate Summary'!C1:H1 -> 0
G5: Equipment | J5: Schedule
D6: ='Estimate Summary'!C11 -> Area: | E6: ='Estimate Summary'!D11 -> 65592 | F6: ='Estimate Summary'!E11 -> Sq. Ft. | J6: ='1'!J6 -> 60 | K6: Weeks
A9: CODE | B9: DESCRIPTION | C9: Materials & Equipment | G9: Labor | L9: Sub Contractor | M9: Quote Total | N9: Additional Quote Info
A10: 11 11 00 | B10: Vehicle Service Equipment | C10: Qty | D10: Unit | E10: U. Price | F10: Sub Total | G10: MHrs | H10: U. Price | I10: Sub Total | J10: Quote | K10: Total
D11: LS | E11: 0 | F11: =C11*E11 -> 0 | H11: 0 | I11: =G11*H11 -> 0 | K11: =F11+I11+J11 -> 0
D12: LS | E12: 0 | F12: =C12*E12 -> 0 | H12: 0 | I12: =G12*H12 -> 0 | K12: =F12+I12+J12 -> 0
D13: LS | E13: 0 | F13: =C13*E13 -> 0 | H13: 0 | I13: =G13*H13 -> 0 | K13: =F13+I13+J13 -> 0
D14: LS | E14: 0 | F14: =C14*E14 -> 0 | H14: 0 | I14: =G14*H14 -> 0 | K14: =F14+I14+J14 -> 0
D15: LS | E15: 0 | F15: =C15*E15 -> 0 | H15: 0 | I15: =G15*H15 -> 0 | K15: =F15+I15+J15 -> 0
D16: LS | E16: 0 | F16: =C16*E16 -> 0 | H16: 0 | I16: =G16*H16 -> 0 | K16: =F16+I16+J16 -> 0
D17: LS | E17: 0 | F17: =C17*E17 -> 0 | H17: 0 | I17: =G17*H17 -> 0 | K17: =F17+I17+J17 -> 0
D18: LS | E18: 0 | F18: =C18*E18 -> 0 | H18: 0 | I18: =G18*H18 -> 0 | K18: =F18+I18+J18 -> 0
D19: LS | E19: 0 | F19: =C19*E19 -> 0 | H19: 0 | I19: =G19*H19 -> 0 | K19: =F19+I19+J19 -> 0
D20: LS | E20: 0 | F20: =C20*E20 -> 0 | H20: 0 | I20: =G20*H20 -> 0 | K20: =F20+I20+J20 -> 0
D21: LS | E21: 0 | F21: =C21*E21 -> 0 | H21: 0 | I21: =G21*H21 -> 0 | K21: =F21+I21+J21 -> 0
D22: LS | E22: 0 | F22: =C22*E22 -> 0 | H22: 0 | I22: =G22*H22 -> 0 | K22: =F22+I22+J22 -> 0
J24: Sub Total | K24: =SUM(K11:K23) -> 0
A25: CODE | B25: DESCRIPTION | C25: Materials & Equipment | G25: Labor
A26: 11 13 00 | B26: Loading Dock Equipment | C26: Qty | D26: Unit | E26: U. Price | F26: Sub Total | G26: MHrs | H26: U. Price | I26: Sub Total | J26: Quote | K26: Total
D27: LS | E27: 0 | F27: =C27*E27 -> 0 | H27: 0 | I27: =G27*H27 -> 0 | K27: =F27+I27+J27 -> 0
D28: LS | E28: 0 | F28: =C28*E28 -> 0 | H28: 0 | I28: =G28*H28 -> 0 | K28: =F28+I28+J28 -> 0
D29: LS | E29: 0 | F29: =C29*E29 -> 0 | H29: 0 | I29: =G29*H29 -> 0 | K29: =F29+I29+J29 -> 0
D30: LS | E30: 0 | F30: =C30*E30 -> 0 | H30: 0 | I30: =G30*H30 -> 0 | K30: =F30+I30+J30 -> 0
D31: LS | E31: 0 | F31: =C31*E31 -> 0 | H31: 0 | I31: =G31*H31 -> 0 | K31: =F31+I31+J31 -> 0
D32: LS | E32: 0 | F32: =C32*E32 -> 0 | H32: 0 | I32: =G32*H32 -> 0 | K32: =F32+I32+J32 -> 0
D33: LS | E33: 0 | F33: =C33*E33 -> 0 | H33: 0 | I33: =G33*H33 -> 0 | K33: =F33+I33+J33 -> 0
J35: Sub Total | K35: =SUM(K27:K34) -> 0
A36: CODE | B36: DESCRIPTION | C36: Materials & Equipment | G36: Labor
A37: 11 30 00 | B37: Residential Equipment | C37: Qty | D37: Unit | E37: U. Price | F37: Sub Total | G37: MHrs | H37: U. Price | I37: Sub Total | J37: Quote | K37: Total | O37: Previous Quote
A38: 11 30 13 | B38: Residential Appliances | C38: 59 | D38: Unit | E38: 3400 | F38: =C38*E38 -> 200600 | H38: 0 | I38: =G38*H38 -> 0 | K38: =F38+I38+J38 -> 200600 | L38: Does not follow ID schedule | O38: Greenfoot | P38: 227543
D39: LS | E39: 0 | F39: =C39*E39 -> 0 | H39: 0 | I39: =G39*H39 -> 0 | K39: =F39+I39+J39 -> 0
D40: LS | E40: 0 | F40: =C40*E40 -> 0 | H40: 0 | I40: =G40*H40 -> 0 | K40: =F40+I40+J40 -> 0
J43: Sub Total | K43: =SUM(K38:K42) -> 200600
A44: CODE | B44: DESCRIPTION | C44: Materials & Equipment | G44: Labor
A45: 11 41 00 | B45: Food Storage Equipment | C45: Qty | D45: Unit | E45: U. Price | F45: Sub Total | G45: MHrs | H45: U. Price | I45: Sub Total | J45: Quote | K45: Total
A46: 11 41 23 | B46: Walk-In Coolers | D46: LS | E46: 0 | F46: =C46*E46 -> 0 | H46: 0 | I46: =G46*H46 -> 0 | K46: =F46+I46+J46 -> 0
D47: LS | E47: 0 | F47: =C47*E47 -> 0 | H47: 0 | I47: =G47*H47 -> 0 | K47: =F47+I47+J47 -> 0
D48: LS | E48: 0 | F48: =C48*E48 -> 0 | H48: 0 | I48: =G48*H48 -> 0 | K48: =F48+I48+J48 -> 0
D49: LS | E49: 0 | F49: =C49*E49 -> 0 | H49: 0 | I49: =G49*H49 -> 0 | K49: =F49+I49+J49 -> 0
D50: LS | E50: 0 | F50: =C50*E50 -> 0 | H50: 0 | I50: =G50*H50 -> 0 | K50: =F50+I50+J50 -> 0
J52: Sub Total | K52: =SUM(K46:K51) -> 0
A53: CODE | B53: DESCRIPTION | C53: Materials & Equipment | G53: Labor
A54: 11 48 00 | B54: Food service Cleaning and Disposal Equipment | C54: Qty | D54: Unit | E54: U. Price | F54: Sub Total | G54: MHrs | H54: U. Price | I54: Sub Total | J54: Quote | K54: Total
A55: 11 48 13 | B55: Commercial Dishwasher | D55: LS | E55: 0 | F55: =C55*E55 -> 0 | H55: 0 | I55: =G55*H55 -> 0 | K55: =F55+I55+J55 -> 0
D56: LS | E56: 0 | F56: =C56*E56 -> 0 | H56: 0 | I56: =G56*H56 -> 0 | K56: =F56+I56+J56 -> 0
D57: LS | E57: 0 | F57: =C57*E57 -> 0 | H57: 0 | I57: =G57*H57 -> 0 | K57: =F57+I57+J57 -> 0
D58: LS | E58: 0 | F58: =C58*E58 -> 0 | H58: 0 | I58: =G58*H58 -> 0 | K58: =F58+I58+J58 -> 0
D59: LS | E59: 0 | F59: =C59*E59 -> 0 | H59: 0 | I59: =G59*H59 -> 0 | K59: =F59+I59+J59 -> 0
D60: LS | E60: 0 | F60: =C60*E60 -> 0 | H60: 0 | I60: =G60*H60 -> 0 | K60: =F60+I60+J60 -> 0
D61: LS | E61: 0 | F61: =C61*E61 -> 0 | H61: 0 | I61: =G61*H61 -> 0 | K61: =F61+I61+J61 -> 0
J63: Sub Total | K63: =SUM(K55:K62) -> 0
A64: CODE | B64: DESCRIPTION | C64: Materials & Equipment | G64: Labor
A65: 11 52 00 | B65: Audio-Visual Equipment | C65: Qty | D65: Unit | E65: U. Price | F65: Sub Total | G65: MHrs | H65: U. Price | I65: Sub Total | J65: Quote | K65: Total
D66: LS | E66: 0 | F66: =C66*E66 -> 0 | H66: 0 | I66: =G66*H66 -> 0 | K66: =F66+I66+J66 -> 0
D67: LS | E67: 0 | F67: =C67*E67 -> 0 | H67: 0 | I67: =G67*H67 -> 0 | K67: =F67+I67+J67 -> 0
D68: LS | E68: 0 | F68: =C68*E68 -> 0 | H68: 0 | I68: =G68*H68 -> 0 | K68: =F68+I68+J68 -> 0
D69: LS | E69: 0 | F69: =C69*E69 -> 0 | H69: 0 | I69: =G69*H69 -> 0 | K69: =F69+I69+J69 -> 0
D70: LS | E70: 0 | F70: =C70*E70 -> 0 | H70: 0 | I70: =G70*H70 -> 0 | K70: =F70+I70+J70 -> 0
J72: Sub Total | K72: =SUM(K66:K71) -> 0
A73: CODE | B73: DESCRIPTION | C73: Materials & Equipment | G73: Labor
A74: 11 53 00 | B74: Laboratory Equipment | C74: Qty | D74: Unit | E74: U. Price | F74: Sub Total | G74: MHrs | H74: U. Price | I74: Sub Total | J74: Quote | K74: Total
D75: LS | E75: 0 | F75: =C75*E75 -> 0 | H75: 0 | I75: =G75*H75 -> 0 | K75: =F75+I75+J75 -> 0
D76: LS | E76: 0 | F76: =C76*E76 -> 0 | H76: 0 | I76: =G76*H76 -> 0 | K76: =F76+I76+J76 -> 0
D77: LS | E77: 0 | F77: =C77*E77 -> 0 | H77: 0 | I77: =G77*H77 -> 0 | K77: =F77+I77+J77 -> 0
J79: Sub Total | K79: =SUM(K75:K78) -> 0
A80: CODE | B80: DESCRIPTION | C80: Materials & Equipment | G80: Labor
C81: Qty | D81: Unit | E81: U. Price | F81: Sub Total | G81: MHrs | H81: U. Price | I81: Sub Total | J81: Quote | K81: Total
D82: LS | E82: 0 | F82: =C82*E82 -> 0 | H82: 0 | I82: =G82*H82 -> 0 | K82: =F82+I82+J82 -> 0
D83: LS | E83: 0 | F83: =C83*E83 -> 0 | H83: 0 | I83: =G83*H83 -> 0 | K83: =F83+I83+J83 -> 0
D84: LS | E84: 0 | F84: =C84*E84 -> 0 | H84: 0 | I84: =G84*H84 -> 0 | K84: =F84+I84+J84 -> 0
D85: LS | E85: 0 | F85: =C85*E85 -> 0 | H85: 0 | I85: =G85*H85 -> 0 | K85: =F85+I85+J85 -> 0
D86: LS | E86: 0 | F86: =C86*E86 -> 0 | H86: 0 | I86: =G86*H86 -> 0 | K86: =F86+I86+J86 -> 0
J88: Sub Total | K88: =SUM(K82:K87) -> 0
A89: CODE | B89: DESCRIPTION | C89: Materials & Equipment | G89: Labor
C90: Qty | D90: Unit | E90: U. Price | F90: Sub Total | G90: MHrs | H90: U. Price | I90: Sub Total | J90: Quote | K90: Total
D91: LS | E91: 0 | F91: =C91*E91 -> 0 | H91: 0 | I91: =G91*H91 -> 0 | K91: =F91+I91+J91 -> 0
D92: LS | E92: 0 | F92: =C92*E92 -> 0 | H92: 0 | I92: =G92*H92 -> 0 | K92: =F92+I92+J92 -> 0
D93: LS | E93: 0 | F93: =C93*E93 -> 0 | H93: 0 | I93: =G93*H93 -> 0 | K93: =F93+I93+J93 -> 0
D94: LS | E94: 0 | F94: =C94*E94 -> 0 | H94: 0 | I94: =G94*H94 -> 0 | K94: =F94+I94+J94 -> 0
J96: Sub Total | K96: =SUM(K91:K95) -> 0
F97: Material Total | G97: Total Hours | I97: Labor Total | J97: Contractor Total | K97: TOTAL
A98: $ / Sq.Ft | B98: TOTAL DIVISION 11
A99: =K99/E6 -> 3.0582998 | F99: =SUM(F91:F95,F82:F87,F75:F78,F66:F71,F55:F61,F46:F51,F38:F42,F27:F34,F11:F23) -> 200600 | G99: =SUM(G91:G95,G82:G87,G75:G78,G66:G71,G55:G61,G46:G51,G38:G42,G27:G34,G11:G23) -> 0 | I99: =SUM(I91:I95,I82:I87,I75:I78,I66:I71,I55:I61,I46:I51,I38:I42,I27:I34,I11:I23) -> 0 | J99: =SUM(J91:J95,J82:J87,J75:J78,J66:J71,J55:J61,J46:J51,J38:J42,J27:J34,J11:J23) -> 0 | K99: =SUM(K96,K88,K79,K72,K63,K52,K43,K35,K24) -> 200600

Sheet 12
C1: ='Estimate Summary'!C1:H1 -> 0
G5: Furnishing | J5: Schedule
D6: ='Estimate Summary'!C11 -> Area: | E6: ='Estimate Summary'!D11 -> 65592 | F6: ='Estimate Summary'!E11 -> Sq. Ft. | J6: ='1'!J6 -> 60 | K6: Weeks
A9: CODE | B9: DESCRIPTION | C9: Materials & Equipment | G9: Labor | L9: Sub Contractor | M9: Quote Total | N9: Additional Quote Info
A10: 12 20 00 | B10: Window Treatments | C10: Qty | D10: Unit | E10: U. Price | F10: Sub Total | G10: MHrs | H10: U. Price | I10: Sub Total | J10: Quote | K10: Total
D11: LS | E11: 0 | F11: =C11*E11 -> 0 | H11: 0 | I11: =G11*H11 -> 0 | K11: =F11+I11+J11 -> 0
D12: LS | E12: 0 | F12: =C12*E12 -> 0 | H12: 0 | I12: =G12*H12 -> 0 | K12: =F12+I12+J12 -> 0
D13: LS | E13: 0 | F13: =C13*E13 -> 0 | H13: 0 | I13: =G13*H13 -> 0 | K13: =F13+I13+J13 -> 0
D14: LS | E14: 0 | F14: =C14*E14 -> 0 | H14: 0 | I14: =G14*H14 -> 0 | K14: =F14+I14+J14 -> 0
D15: LS | E15: 0 | F15: =C15*E15 -> 0 | H15: 0 | I15: =G15*H15 -> 0 | K15: =F15+I15+J15 -> 0
D16: LS | E16: 0 | F16: =C16*E16 -> 0 | H16: 0 | I16: =G16*H16 -> 0 | K16: =F16+I16+J16 -> 0
D17: LS | E17: 0 | F17: =C17*E17 -> 0 | H17: 0 | I17: =G17*H17 -> 0 | K17: =F17+I17+J17 -> 0
D18: LS | E18: 0 | F18: =C18*E18 -> 0 | H18: 0 | I18: =G18*H18 -> 0 | K18: =F18+I18+J18 -> 0
D19: LS | E19: 0 | F19: =C19*E19 -> 0 | H19: 0 | I19: =G19*H19 -> 0 | K19: =F19+I19+J19 -> 0
D20: LS | E20: 0 | F20: =C20*E20 -> 0 | H20: 0 | I20: =G20*H20 -> 0 | K20: =F20+I20+J20 -> 0
D21: LS | E21: 0 | F21: =C21*E21 -> 0 | H21: 0 | I21: =G21*H21 -> 0 | K21: =F21+I21+J21 -> 0
D22: LS | E22: 0 | F22: =C22*E22 -> 0 | H22: 0 | I22: =G22*H22 -> 0 | K22: =F22+I22+J22 -> 0
J24: Sub Total | K24: =SUM(K11:K23) -> 0
A25: CODE | B25: DESCRIPTION | C25: Materials & Equipment | G25: Labor
A26: 12 21 00 | B26: Window Blinds | C26: Qty | D26: Unit | E26: U. Price | F26: Sub Total | G26: MHrs | H26: U. Price | I26: Sub Total | J26: Quote | K26: Total
C27: 59 | D27: Unit | E27: 700 | F27: =C27*E27 -> 41300 | H27: 0 | I27: =G27*H27 -> 0 | K27: =F27+I27+J27 -> 41300 | L27: Interior Visions
D28: LS | E28: 0 | F28: =C28*E28 -> 0 | H28: 0 | I28: =G28*H28 -> 0 | K28: =F28+I28+J28 -> 0
D29: LS | E29: 0 | F29: =C29*E29 -> 0 | H29: 0 | I29: =G29*H29 -> 0 | K29: =F29+I29+J29 -> 0
D30: LS | E30: 0 | F30: =C30*E30 -> 0 | H30: 0 | I30: =G30*H30 -> 0 | K30: =F30+I30+J30 -> 0
D31: LS | E31: 0 | F31: =C31*E31 -> 0 | H31: 0 | I31: =G31*H31 -> 0 | K31: =F31+I31+J31 -> 0
D32: LS | E32: 0 | F32: =C32*E32 -> 0 | H32: 0 | I32: =G32*H32 -> 0 | K32: =F32+I32+J32 -> 0
D33: LS | E33: 0 | F33: =C33*E33 -> 0 | H33: 0 | I33: =G33*H33 -> 0 | K33: =F33+I33+J33 -> 0
J35: Sub Total | K35: =SUM(K27:K34) -> 41300
A36: CODE | B36: DESCRIPTION | C36: Materials & Equipment | G36: Labor
A37: 12 30 00 | B37: Casework | C37: Qty | D37: Unit | E37: U. Price | F37: Sub Total | G37: MHrs | H37: U. Price | I37: Sub Total | J37: Quote | K37: Total
D38: LS | E38: 0 | F38: =C38*E38 -> 0 | H38: 0 | I38: =G38*H38 -> 0 | K38: =F38+I38+J38 -> 0
D39: LS | E39: 0 | F39: =C39*E39 -> 0 | H39: 0 | I39: =G39*H39 -> 0 | K39: =F39+I39+J39 -> 0
D40: LS | E40: 0 | F40: =C40*E40 -> 0 | H40: 0 | I40: =G40*H40 -> 0 | K40: =F40+I40+J40 -> 0
J43: Sub Total | K43: =SUM(K38:K42) -> 0
A44: CODE | B44: DESCRIPTION | C44: Materials & Equipment | G44: Labor
A45: 12 32 00 | B45: Manufactured Wood Casework | C45: Qty | D45: Unit | E45: U. Price | F45: Sub Total | G45: MHrs | H45: U. Price | I45: Sub Total | J45: Quote | K45: Total
D46: LS | E46: 0 | F46: =C46*E46 -> 0 | H46: 0 | I46: =G46*H46 -> 0 | K46: =F46+I46+J46 -> 0
D47: LS | E47: 0 | F47: =C47*E47 -> 0 | H47: 0 | I47: =G47*H47 -> 0 | K47: =F47+I47+J47 -> 0
D48: LS | E48: 0 | F48: =C48*E48 -> 0 | H48: 0 | I48: =G48*H48 -> 0 | K48: =F48+I48+J48 -> 0
D49: LS | E49: 0 | F49: =C49*E49 -> 0 | H49: 0 | I49: =G49*H49 -> 0 | K49: =F49+I49+J49 -> 0
D50: LS | E50: 0 | F50: =C50*E50 -> 0 | H50: 0 | I50: =G50*H50 -> 0 | K50: =F50+I50+J50 -> 0
J52: Sub Total | K52: =SUM(K46:K51) -> 0
A53: CODE | B53: DESCRIPTION | C53: Materials & Equipment | G53: Labor
A54: 12 35 00 | B54: Specialty Casework | C54: Qty | D54: Unit | E54: U. Price | F54: Sub Total | G54: MHrs | H54: U. Price | I54: Sub Total | J54: Quote | K54: Total
D55: LS | E55: 0 | F55: =C55*E55 -> 0 | H55: 0 | I55: =G55*H55 -> 0 | K55: =F55+I55+J55 -> 0
D56: LS | E56: 0 | F56: =C56*E56 -> 0 | H56: 0 | I56: =G56*H56 -> 0 | K56: =F56+I56+J56 -> 0
D57: LS | E57: 0 | F57: =C57*E57 -> 0 | H57: 0 | I57: =G57*H57 -> 0 | K57: =F57+I57+J57 -> 0
D58: LS | E58: 0 | F58: =C58*E58 -> 0 | H58: 0 | I58: =G58*H58 -> 0 | K58: =F58+I58+J58 -> 0
D59: LS | E59: 0 | F59: =C59*E59 -> 0 | H59: 0 | I59: =G59*H59 -> 0 | K59: =F59+I59+J59 -> 0
D60: LS | E60: 0 | F60: =C60*E60 -> 0 | H60: 0 | I60: =G60*H60 -> 0 | K60: =F60+I60+J60 -> 0
D61: LS | E61: 0 | F61: =C61*E61 -> 0 | H61: 0 | I61: =G61*H61 -> 0 | K61: =F61+I61+J61 -> 0
J63: Sub Total | K63: =SUM(K55:K62) -> 0
A64: CODE | B64: DESCRIPTION | C64: Materials & Equipment | G64: Labor
A65: 12 36 00 | B65: Countertops | C65: Qty | D65: Unit | E65: U. Price | F65: Sub Total | G65: MHrs | H65: U. Price | I65: Sub Total | J65: Quote | K65: Total
D66: LS | E66: 0 | F66: =C66*E66 -> 0 | H66: 0 | I66: =G66*H66 -> 0 | K66: =F66+I66+J66 -> 0
D67: LS | E67: 0 | F67: =C67*E67 -> 0 | H67: 0 | I67: =G67*H67 -> 0 | K67: =F67+I67+J67 -> 0
D68: LS | E68: 0 | F68: =C68*E68 -> 0 | H68: 0 | I68: =G68*H68 -> 0 | K68: =F68+I68+J68 -> 0
D69: LS | E69: 0 | F69: =C69*E69 -> 0 | H69: 0 | I69: =G69*H69 -> 0 | K69: =F69+I69+J69 -> 0
D70: LS | E70: 0 | F70: =C70*E70 -> 0 | H70: 0 | I70: =G70*H70 -> 0 | K70: =F70+I70+J70 -> 0
J72: Sub Total | K72: =SUM(K66:K71) -> 0
A73: CODE | B73: DESCRIPTION | C73: Materials & Equipment | G73: Labor
C74: Qty | D74: Unit | E74: U. Price | F74: Sub Total | G74: MHrs | H74: U. Price | I74: Sub Total | J74: Quote | K74: Total
D75: LS | E75: 0 | F75: =C75*E75 -> 0 | H75: 0 | I75: =G75*H75 -> 0 | K75: =F75+I75+J75 -> 0
D76: LS | E76: 0 | F76: =C76*E76 -> 0 | H76: 0 | I76: =G76*H76 -> 0 | K76: =F76+I76+J76 -> 0
D77: LS | E77: 0 | F77: =C77*E77 -> 0 | H77: 0 | I77: =G77*H77 -> 0 | K77: =F77+I77+J77 -> 0
J79: Sub Total | K79: =SUM(K75:K78) -> 0
A80: CODE | B80: DESCRIPTION | C80: Materials & Equipment | G80: Labor
C81: Qty | D81: Unit | E81: U. Price | F81: Sub Total | G81: MHrs | H81: U. Price | I81: Sub Total | J81: Quote | K81: Total
D82: LS | E82: 0 | F82: =C82*E82 -> 0 | H82: 0 | I82: =G82*H82 -> 0 | K82: =F82+I82+J82 -> 0
D83: LS | E83: 0 | F83: =C83*E83 -> 0 | H83: 0 | I83: =G83*H83 -> 0 | K83: =F83+I83+J83 -> 0
D84: LS | E84: 0 | F84: =C84*E84 -> 0 | H84: 0 | I84: =G84*H84 -> 0 | K84: =F84+I84+J84 -> 0
D85: LS | E85: 0 | F85: =C85*E85 -> 0 | H85: 0 | I85: =G85*H85 -> 0 | K85: =F85+I85+J85 -> 0
D86: LS | E86: 0 | F86: =C86*E86 -> 0 | H86: 0 | I86: =G86*H86 -> 0 | K86: =F86+I86+J86 -> 0
J88: Sub Total | K88: =SUM(K82:K87) -> 0
A89: CODE | B89: DESCRIPTION | C89: Materials & Equipment | G89: Labor
C90: Qty | D90: Unit | E90: U. Price | F90: Sub Total | G90: MHrs | H90: U. Price | I90: Sub Total | J90: Quote | K90: Total
D91: LS | E91: 0 | F91: =C91*E91 -> 0 | H91: 0 | I91: =G91*H91 -> 0 | K91: =F91+I91+J91 -> 0
D92: LS | E92: 0 | F92: =C92*E92 -> 0 | H92: 0 | I92: =G92*H92 -> 0 | K92: =F92+I92+J92 -> 0
D93: LS | E93: 0 | F93: =C93*E93 -> 0 | H93: 0 | I93: =G93*H93 -> 0 | K93: =F93+I93+J93 -> 0
D94: LS | E94: 0 | F94: =C94*E94 -> 0 | H94: 0 | I94: =G94*H94 -> 0 | K94: =F94+I94+J94 -> 0
J96: Sub Total | K96: =SUM(K91:K95) -> 0
F97: Material Total | G97: Total Hours | I97: Labor Total | J97: Contractor Total | K97: TOTAL
A98: $ / Sq.Ft | B98: TOTAL DIVISION 12
A99: =K99/E6 -> 0.62964996 | F99: =SUM(F91:F95,F82:F87,F75:F78,F66:F71,F55:F61,F46:F51,F38:F42,F27:F34,F11:F23) -> 41300 | G99: =SUM(G91:G95,G82:G87,G75:G78,G66:G71,G55:G61,G46:G51,G38:G42,G27:G34,G11:G23) -> 0 | I99: =SUM(I91:I95,I82:I87,I75:I78,I66:I71,I55:I61,I46:I51,I38:I42,I27:I34,I11:I23) -> 0 | J99: =SUM(J91:J95,J82:J87,J75:J78,J66:J71,J55:J61,J46:J51,J38:J42,J27:J34,J11:J23) -> 0 | K99: =SUM(K96,K88,K79,K72,K63,K52,K43,K35,K24) -> 41300

Sheet 13
C1: ='Estimate Summary'!C1:H1 -> 0
G5: Special Construction | J5: Schedule
D6: ='Estimate Summary'!C11 -> Area: | E6: ='Estimate Summary'!D11 -> 65592 | F6: ='Estimate Summary'!E11 -> Sq. Ft. | J6: ='1'!J6 -> 60 | K6: Weeks
A9: CODE | B9: DESCRIPTION | C9: Materials & Equipment | G9: Labor | L9: Sub Contractor | M9: Quote Total | N9: Additional Quote Info
C10: Qty | D10: Unit | E10: U. Price | F10: Sub Total | G10: MHrs | H10: U. Price | I10: Sub Total | J10: Quote | K10: Total
B11: Solar | D11: LS | E11: 0 | F11: =C11*E11 -> 0 | H11: 0 | I11: =G11*H11 -> 0 | J11: =M15 -> 86400 | K11: =F11+I11+J11 -> 86400 | L11: Trusun | N11: Confirmed verbally with Alex Lissandro 19-Aug
B12: Framing | D12: LS | E12: 0 | F12: =C12*E12 -> 0 | H12: 0 | I12: =G12*H12 -> 0 | J12: =4500+1000+19500 -> 25000 | K12: =F12+I12+J12 -> 25000 | L12: Atlas, CMS, Materials
B13: Electrical | D13: LS | E13: 0 | F13: =C13*E13 -> 0 | H13: 0 | I13: =G13*H13 -> 0 | K13: =F13+I13+J13 -> 0 | L13: Total
D14: LS | E14: 0 | F14: =C14*E14 -> 0 | H14: 0 | I14: =G14*H14 -> 0 | K14: =F14+I14+J14 -> 0
D15: LS | E15: 0 | F15: =C15*E15 -> 0 | H15: 0 | I15: =G15*H15 -> 0 | K15: =F15+I15+J15 -> 0 | L15: Greenfoot | M15: 86400 | N15: Includes electrical portion of the work. Their estimated kw/h is 100 short.
B16: Contingency for Greenfoot | C16: 1 | D16: LS | E16: 10000 | F16: =C16*E16 -> 10000 | H16: 0 | I16: =G16*H16 -> 0 | K16: =F16+I16+J16 -> 10000
D17: LS | E17: 0 | F17: =C17*E17 -> 0 | H17: 0 | I17: =G17*H17 -> 0 | K17: =F17+I17+J17 -> 0
D18: LS | E18: 0 | F18: =C18*E18 -> 0 | H18: 0 | I18: =G18*H18 -> 0 | K18: =F18+I18+J18 -> 0
D19: LS | E19: 0 | F19: =C19*E19 -> 0 | H19: 0 | I19: =G19*H19 -> 0 | K19: =F19+I19+J19 -> 0
D20: LS | E20: 0 | F20: =C20*E20 -> 0 | H20: 0 | I20: =G20*H20 -> 0 | K20: =F20+I20+J20 -> 0
D21: LS | E21: 0 | F21: =C21*E21 -> 0 | H21: 0 | I21: =G21*H21 -> 0 | K21: =F21+I21+J21 -> 0
D22: LS | E22: 0 | F22: =C22*E22 -> 0 | H22: 0 | I22: =G22*H22 -> 0 | K22: =F22+I22+J22 -> 0
J24: Sub Total | K24: =SUM(K11:K23) -> 121400
A25: CODE | B25: DESCRIPTION | C25: Materials & Equipment | G25: Labor
C26: Qty | D26: Unit | E26: U. Price | F26: Sub Total | G26: MHrs | H26: U. Price | I26: Sub Total | J26: Quote | K26: Total
D27: LS | E27: 0 | F27: =C27*E27 -> 0 | H27: 0 | I27: =G27*H27 -> 0 | K27: =F27+I27+J27 -> 0
D28: LS | E28: 0 | F28: =C28*E28 -> 0 | H28: 0 | I28: =G28*H28 -> 0 | K28: =F28+I28+J28 -> 0
D29: LS | E29: 0 | F29: =C29*E29 -> 0 | H29: 0 | I29: =G29*H29 -> 0 | K29: =F29+I29+J29 -> 0
D30: LS | E30: 0 | F30: =C30*E30 -> 0 | H30: 0 | I30: =G30*H30 -> 0 | K30: =F30+I30+J30 -> 0
D31: LS | E31: 0 | F31: =C31*E31 -> 0 | H31: 0 | I31: =G31*H31 -> 0 | K31: =F31+I31+J31 -> 0
D32: LS | E32: 0 | F32: =C32*E32 -> 0 | H32: 0 | I32: =G32*H32 -> 0 | K32: =F32+I32+J32 -> 0
D33: LS | E33: 0 | F33: =C33*E33 -> 0 | H33: 0 | I33: =G33*H33 -> 0 | K33: =F33+I33+J33 -> 0
J35: Sub Total | K35: =SUM(K27:K34) -> 0
A36: CODE | B36: DESCRIPTION | C36: Materials & Equipment | G36: Labor
C37: Qty | D37: Unit | E37: U. Price | F37: Sub Total | G37: MHrs | H37: U. Price | I37: Sub Total | J37: Quote | K37: Total
D38: LS | E38: 0 | F38: =C38*E38 -> 0 | H38: 0 | I38: =G38*H38 -> 0 | K38: =F38+I38+J38 -> 0
D39: LS | E39: 0 | F39: =C39*E39 -> 0 | H39: 0 | I39: =G39*H39 -> 0 | K39: =F39+I39+J39 -> 0
D40: LS | E40: 0 | F40: =C40*E40 -> 0 | H40: 0 | I40: =G40*H40 -> 0 | K40: =F40+I40+J40 -> 0
J43: Sub Total | K43: =SUM(K38:K42) -> 0
A44: CODE | B44: DESCRIPTION | C44: Materials & Equipment | G44: Labor
C45: Qty | D45: Unit | E45: U. Price | F45: Sub Total | G45: MHrs | H45: U. Price | I45: Sub Total | J45: Quote | K45: Total
D46: LS | E46: 0 | F46: =C46*E46 -> 0 | H46: 0 | I46: =G46*H46 -> 0 | K46: =F46+I46+J46 -> 0
D47: LS | E47: 0 | F47: =C47*E47 -> 0 | H47: 0 | I47: =G47*H47 -> 0 | K47: =F47+I47+J47 -> 0
D48: LS | E48: 0 | F48: =C48*E48 -> 0 | H48: 0 | I48: =G48*H48 -> 0 | K48: =F48+I48+J48 -> 0
D49: LS | E49: 0 | F49: =C49*E49 -> 0 | H49: 0 | I49: =G49*H49 -> 0 | K49: =F49+I49+J49 -> 0
D50: LS | E50: 0 | F50: =C50*E50 -> 0 | H50: 0 | I50: =G50*H50 -> 0 | K50: =F50+I50+J50 -> 0
J52: Sub Total | K52: =SUM(K46:K51) -> 0
A53: CODE | B53: DESCRIPTION | C53: Materials & Equipment | G53: Labor
C54: Qty | D54: Unit | E54: U. Price | F54: Sub Total | G54: MHrs | H54: U. Price | I54: Sub Total | J54: Quote | K54: Total
D55: LS | E55: 0 | F55: =C55*E55 -> 0 | H55: 0 | I55: =G55*H55 -> 0 | K55: =F55+I55+J55 -> 0
D56: LS | E56: 0 | F56: =C56*E56 -> 0 | H56: 0 | I56: =G56*H56 -> 0 | K56: =F56+I56+J56 -> 0
D57: LS | E57: 0 | F57: =C57*E57 -> 0 | H57: 0 | I57: =G57*H57 -> 0 | K57: =F57+I57+J57 -> 0
D58: LS | E58: 0 | F58: =C58*E58 -> 0 | H58: 0 | I58: =G58*H58 -> 0 | K58: =F58+I58+J58 -> 0
D59: LS | E59: 0 | F59: =C59*E59 -> 0 | H59: 0 | I59: =G59*H59 -> 0 | K59: =F59+I59+J59 -> 0
D60: LS | E60: 0 | F60: =C60*E60 -> 0 | H60: 0 | I60: =G60*H60 -> 0 | K60: =F60+I60+J60 -> 0
D61: LS | E61: 0 | F61: =C61*E61 -> 0 | H61: 0 | I61: =G61*H61 -> 0 | K61: =F61+I61+J61 -> 0
J63: Sub Total | K63: =SUM(K55:K62) -> 0
A64: CODE | B64: DESCRIPTION | C64: Materials & Equipment | G64: Labor
C65: Qty | D65: Unit | E65: U. Price | F65: Sub Total | G65: MHrs | H65: U. Price | I65: Sub Total | J65: Quote | K65: Total
D66: LS | E66: 0 | F66: =C66*E66 -> 0 | H66: 0 | I66: =G66*H66 -> 0 | K66: =F66+I66+J66 -> 0
D67: LS | E67: 0 | F67: =C67*E67 -> 0 | H67: 0 | I67: =G67*H67 -> 0 | K67: =F67+I67+J67 -> 0
D68: LS | E68: 0 | F68: =C68*E68 -> 0 | H68: 0 | I68: =G68*H68 -> 0 | K68: =F68+I68+J68 -> 0
D69: LS | E69: 0 | F69: =C69*E69 -> 0 | H69: 0 | I69: =G69*H69 -> 0 | K69: =F69+I69+J69 -> 0
D70: LS | E70: 0 | F70: =C70*E70 -> 0 | H70: 0 | I70: =G70*H70 -> 0 | K70: =F70+I70+J70 -> 0
J72: Sub Total | K72: =SUM(K66:K71) -> 0
A73: CODE | B73: DESCRIPTION | C73: Materials & Equipment | G73: Labor
C74: Qty | D74: Unit | E74: U. Price | F74: Sub Total | G74: MHrs | H74: U. Price | I74: Sub Total | J74: Quote | K74: Total
D75: LS | E75: 0 | F75: =C75*E75 -> 0 | H75: 0 | I75: =G75*H75 -> 0 | K75: =F75+I75+J75 -> 0
D76: LS | E76: 0 | F76: =C76*E76 -> 0 | H76: 0 | I76: =G76*H76 -> 0 | K76: =F76+I76+J76 -> 0
D77: LS | E77: 0 | F77: =C77*E77 -> 0 | H77: 0 | I77: =G77*H77 -> 0 | K77: =F77+I77+J77 -> 0
J79: Sub Total | K79: =SUM(K75:K78) -> 0
A80: CODE | B80: DESCRIPTION | C80: Materials & Equipment | G80: Labor
C81: Qty | D81: Unit | E81: U. Price | F81: Sub Total | G81: MHrs | H81: U. Price | I81: Sub Total | J81: Quote | K81: Total
D82: LS | E82: 0 | F82: =C82*E82 -> 0 | H82: 0 | I82: =G82*H82 -> 0 | K82: =F82+I82+J82 -> 0
D83: LS | E83: 0 | F83: =C83*E83 -> 0 | H83: 0 | I83: =G83*H83 -> 0 | K83: =F83+I83+J83 -> 0
D84: LS | E84: 0 | F84: =C84*E84 -> 0 | H84: 0 | I84: =G84*H84 -> 0 | K84: =F84+I84+J84 -> 0
D85: LS | E85: 0 | F85: =C85*E85 -> 0 | H85: 0 | I85: =G85*H85 -> 0 | K85: =F85+I85+J85 -> 0
D86: LS | E86: 0 | F86: =C86*E86 -> 0 | H86: 0 | I86: =G86*H86 -> 0 | K86: =F86+I86+J86 -> 0
J88: Sub Total | K88: =SUM(K82:K87) -> 0
A89: CODE | B89: DESCRIPTION | C89: Materials & Equipment | G89: Labor
C90: Qty | D90: Unit | E90: U. Price | F90: Sub Total | G90: MHrs | H90: U. Price | I90: Sub Total | J90: Quote | K90: Total
D91: LS | E91: 0 | F91: =C91*E91 -> 0 | H91: 0 | I91: =G91*H91 -> 0 | K91: =F91+I91+J91 -> 0
D92: LS | E92: 0 | F92: =C92*E92 -> 0 | H92: 0 | I92: =G92*H92 -> 0 | K92: =F92+I92+J92 -> 0
D93: LS | E93: 0 | F93: =C93*E93 -> 0 | H93: 0 | I93: =G93*H93 -> 0 | K93: =F93+I93+J93 -> 0
D94: LS | E94: 0 | F94: =C94*E94 -> 0 | H94: 0 | I94: =G94*H94 -> 0 | K94: =F94+I94+J94 -> 0
J96: Sub Total | K96: =SUM(K91:K95) -> 0
F97: Material Total | G97: Total Hours | I97: Labor Total | J97: Contractor Total | K97: TOTAL
A98: $ / Sq.Ft | B98: TOTAL DIVISION 13
A99: =K99/E6 -> 1.8508355 | F99: =SUM(F91:F95,F82:F87,F75:F78,F66:F71,F55:F61,F46:F51,F38:F42,F27:F34,F11:F23) -> 10000 | G99: =SUM(G91:G95,G82:G87,G75:G78,G66:G71,G55:G61,G46:G51,G38:G42,G27:G34,G11:G23) -> 0 | I99: =SUM(I91:I95,I82:I87,I75:I78,I66:I71,I55:I61,I46:I51,I38:I42,I27:I34,I11:I23) -> 0 | J99: =SUM(J91:J95,J82:J87,J75:J78,J66:J71,J55:J61,J46:J51,J38:J42,J27:J34,J11:J23) -> 111400 | K99: =SUM(K96,K88,K79,K72,K63,K52,K43,K35,K24) -> 121400

Sheet 14
C1: ='Estimate Summary'!C1:H1 -> 0
G5: Conveying Equipment | J5: Schedule
D6: ='Estimate Summary'!C11 -> Area: | E6: ='Estimate Summary'!D11 -> 65592 | F6: ='Estimate Summary'!E11 -> Sq. Ft. | J6: ='1'!J6 -> 60 | K6: Weeks
A9: CODE | B9: DESCRIPTION | C9: Materials & Equipment | G9: Labor | L9: Sub Contractor | M9: Quote Total | N9: Additional Quote Info | O9: Previous Quotes
A10: 14 20 00 | B10: Elevators | C10: Qty | D10: Unit | E10: U. Price | F10: Sub Total | G10: MHrs | H10: U. Price | I10: Sub Total | J10: Quote | K10: Total
D11: LS | E11: 0 | F11: =C11*E11 -> 0 | H11: 0 | I11: =G11*H11 -> 0 | K11: =F11+I11+J11 -> 0 | O11: Kone | P11: 189000
D12: LS | E12: 0 | F12: =C12*E12 -> 0 | H12: 0 | I12: =G12*H12 -> 0 | J12: =M14 -> 155285 | K12: =F12+I12+J12 -> 155285 | L12: Kone | M12: 192000
D13: LS | E13: 0 | F13: =C13*E13 -> 0 | H13: 0 | I13: =G13*H13 -> 0 | K13: =F13+I13+J13 -> 0 | L13: Otis | M13: 193980
D14: LS | E14: 0 | F14: =C14*E14 -> 0 | H14: 0 | I14: =G14*H14 -> 0 | K14: =F14+I14+J14 -> 0 | L14: TK | M14: 155285 | N14: Potential mods to pit required
D15: LS | E15: 0 | F15: =C15*E15 -> 0 | H15: 0 | I15: =G15*H15 -> 0 | K15: =F15+I15+J15 -> 0
D16: LS | E16: 0 | F16: =C16*E16 -> 0 | H16: 0 | I16: =G16*H16 -> 0 | K16: =F16+I16+J16 -> 0
D17: LS | E17: 0 | F17: =C17*E17 -> 0 | H17: 0 | I17: =G17*H17 -> 0 | K17: =F17+I17+J17 -> 0
D18: LS | E18: 0 | F18: =C18*E18 -> 0 | H18: 0 | I18: =G18*H18 -> 0 | K18: =F18+I18+J18 -> 0
D19: LS | E19: 0 | F19: =C19*E19 -> 0 | H19: 0 | I19: =G19*H19 -> 0 | K19: =F19+I19+J19 -> 0
D20: LS | E20: 0 | F20: =C20*E20 -> 0 | H20: 0 | I20: =G20*H20 -> 0 | K20: =F20+I20+J20 -> 0
D21: LS | E21: 0 | F21: =C21*E21 -> 0 | H21: 0 | I21: =G21*H21 -> 0 | K21: =F21+I21+J21 -> 0
D22: LS | E22: 0 | F22: =C22*E22 -> 0 | H22: 0 | I22: =G22*H22 -> 0 | K22: =F22+I22+J22 -> 0
J24: Sub Total | K24: =SUM(K15:K23) -> 0
A25: CODE | B25: DESCRIPTION | C25: Materials & Equipment | G25: Labor
A26: 14 40 00 | B26: Lifts | C26: Qty | D26: Unit | E26: U. Price | F26: Sub Total | G26: MHrs | H26: U. Price | I26: Sub Total | J26: Quote | K26: Total
D27: LS | E27: 0 | F27: =C27*E27 -> 0 | H27: 0 | I27: =G27*H27 -> 0 | K27: =F27+I27+J27 -> 0
D28: LS | E28: 0 | F28: =C28*E28 -> 0 | H28: 0 | I28: =G28*H28 -> 0 | K28: =F28+I28+J28 -> 0
D29: LS | E29: 0 | F29: =C29*E29 -> 0 | H29: 0 | I29: =G29*H29 -> 0 | K29: =F29+I29+J29 -> 0
D30: LS | E30: 0 | F30: =C30*E30 -> 0 | H30: 0 | I30: =G30*H30 -> 0 | K30: =F30+I30+J30 -> 0
D31: LS | E31: 0 | F31: =C31*E31 -> 0 | H31: 0 | I31: =G31*H31 -> 0 | K31: =F31+I31+J31 -> 0
D32: LS | E32: 0 | F32: =C32*E32 -> 0 | H32: 0 | I32: =G32*H32 -> 0 | K32: =F32+I32+J32 -> 0
D33: LS | E33: 0 | F33: =C33*E33 -> 0 | H33: 0 | I33: =G33*H33 -> 0 | K33: =F33+I33+J33 -> 0
J35: Sub Total | K35: =SUM(K27:K34) -> 0
A36: CODE | B36: DESCRIPTION | C36: Materials & Equipment | G36: Labor
A37: 14 42 00 | B37: Wheelchair Lifts | C37: Qty | D37: Unit | E37: U. Price | F37: Sub Total | G37: MHrs | H37: U. Price | I37: Sub Total | J37: Quote | K37: Total
D38: LS | E38: 0 | F38: =C38*E38 -> 0 | H38: 0 | I38: =G38*H38 -> 0 | K38: =F38+I38+J38 -> 0
D39: LS | E39: 0 | F39: =C39*E39 -> 0 | H39: 0 | I39: =G39*H39 -> 0 | K39: =F39+I39+J39 -> 0
D40: LS | E40: 0 | F40: =C40*E40 -> 0 | H40: 0 | I40: =G40*H40 -> 0 | K40: =F40+I40+J40 -> 0
J43: Sub Total | K43: =SUM(K38:K42) -> 0
A44: CODE | B44: DESCRIPTION | C44: Materials & Equipment | G44: Labor
C45: Qty | D45: Unit | E45: U. Price | F45: Sub Total | G45: MHrs | H45: U. Price | I45: Sub Total | J45: Quote | K45: Total
D46: LS | E46: 0 | F46: =C46*E46 -> 0 | H46: 0 | I46: =G46*H46 -> 0 | K46: =F46+I46+J46 -> 0
D47: LS | E47: 0 | F47: =C47*E47 -> 0 | H47: 0 | I47: =G47*H47 -> 0 | K47: =F47+I47+J47 -> 0
D48: LS | E48: 0 | F48: =C48*E48 -> 0 | H48: 0 | I48: =G48*H48 -> 0 | K48: =F48+I48+J48 -> 0
D49: LS | E49: 0 | F49: =C49*E49 -> 0 | H49: 0 | I49: =G49*H49 -> 0 | K49: =F49+I49+J49 -> 0
D50: LS | E50: 0 | F50: =C50*E50 -> 0 | H50: 0 | I50: =G50*H50 -> 0 | K50: =F50+I50+J50 -> 0
J52: Sub Total | K52: =SUM(K46:K51) -> 0
A53: CODE | B53: DESCRIPTION | C53: Materials & Equipment | G53: Labor
C54: Qty | D54: Unit | E54: U. Price | F54: Sub Total | G54: MHrs | H54: U. Price | I54: Sub Total | J54: Quote | K54: Total
D55: LS | E55: 0 | F55: =C55*E55 -> 0 | H55: 0 | I55: =G55*H55 -> 0 | K55: =F55+I55+J55 -> 0
D56: LS | E56: 0 | F56: =C56*E56 -> 0 | H56: 0 | I56: =G56*H56 -> 0 | K56: =F56+I56+J56 -> 0
D57: LS | E57: 0 | F57: =C57*E57 -> 0 | H57: 0 | I57: =G57*H57 -> 0 | K57: =F57+I57+J57 -> 0
D58: LS | E58: 0 | F58: =C58*E58 -> 0 | H58: 0 | I58: =G58*H58 -> 0 | K58: =F58+I58+J58 -> 0
D59: LS | E59: 0 | F59: =C59*E59 -> 0 | H59: 0 | I59: =G59*H59 -> 0 | K59: =F59+I59+J59 -> 0
D60: LS | E60: 0 | F60: =C60*E60 -> 0 | H60: 0 | I60: =G60*H60 -> 0 | K60: =F60+I60+J60 -> 0
D61: LS | E61: 0 | F61: =C61*E61 -> 0 | H61: 0 | I61: =G61*H61 -> 0 | K61: =F61+I61+J61 -> 0
J63: Sub Total | K63: =SUM(K55:K62) -> 0
A64: CODE | B64: DESCRIPTION | C64: Materials & Equipment | G64: Labor
C65: Qty | D65: Unit | E65: U. Price | F65: Sub Total | G65: MHrs | H65: U. Price | I65: Sub Total | J65: Quote | K65: Total
D66: LS | E66: 0 | F66: =C66*E66 -> 0 | H66: 0 | I66: =G66*H66 -> 0 | K66: =F66+I66+J66 -> 0
D67: LS | E67: 0 | F67: =C67*E67 -> 0 | H67: 0 | I67: =G67*H67 -> 0 | K67: =F67+I67+J67 -> 0
D68: LS | E68: 0 | F68: =C68*E68 -> 0 | H68: 0 | I68: =G68*H68 -> 0 | K68: =F68+I68+J68 -> 0
D69: LS | E69: 0 | F69: =C69*E69 -> 0 | H69: 0 | I69: =G69*H69 -> 0 | K69: =F69+I69+J69 -> 0
D70: LS | E70: 0 | F70: =C70*E70 -> 0 | H70: 0 | I70: =G70*H70 -> 0 | K70: =F70+I70+J70 -> 0
J72: Sub Total | K72: =SUM(K66:K71) -> 0
A73: CODE | B73: DESCRIPTION | C73: Materials & Equipment | G73: Labor
C74: Qty | D74: Unit | E74: U. Price | F74: Sub Total | G74: MHrs | H74: U. Price | I74: Sub Total | J74: Quote | K74: Total
D75: LS | E75: 0 | F75: =C75*E75 -> 0 | H75: 0 | I75: =G75*H75 -> 0 | K75: =F75+I75+J75 -> 0
D76: LS | E76: 0 | F76: =C76*E76 -> 0 | H76: 0 | I76: =G76*H76 -> 0 | K76: =F76+I76+J76 -> 0
D77: LS | E77: 0 | F77: =C77*E77 -> 0 | H77: 0 | I77: =G77*H77 -> 0 | K77: =F77+I77+J77 -> 0
J79: Sub Total | K79: =SUM(K75:K78) -> 0
A80: CODE | B80: DESCRIPTION | C80: Materials & Equipment | G80: Labor
C81: Qty | D81: Unit | E81: U. Price | F81: Sub Total | G81: MHrs | H81: U. Price | I81: Sub Total | J81: Quote | K81: Total
D82: LS | E82: 0 | F82: =C82*E82 -> 0 | H82: 0 | I82: =G82*H82 -> 0 | K82: =F82+I82+J82 -> 0
D83: LS | E83: 0 | F83: =C83*E83 -> 0 | H83: 0 | I83: =G83*H83 -> 0 | K83: =F83+I83+J83 -> 0
D84: LS | E84: 0 | F84: =C84*E84 -> 0 | H84: 0 | I84: =G84*H84 -> 0 | K84: =F84+I84+J84 -> 0
D85: LS | E85: 0 | F85: =C85*E85 -> 0 | H85: 0 | I85: =G85*H85 -> 0 | K85: =F85+I85+J85 -> 0
D86: LS | E86: 0 | F86: =C86*E86 -> 0 | H86: 0 | I86: =G86*H86 -> 0 | K86: =F86+I86+J86 -> 0
J88: Sub Total | K88: =SUM(K82:K87) -> 0
A89: CODE | B89: DESCRIPTION | C89: Materials & Equipment | G89: Labor
C90: Qty | D90: Unit | E90: U. Price | F90: Sub Total | G90: MHrs | H90: U. Price | I90: Sub Total | J90: Quote | K90: Total
D91: LS | E91: 0 | F91: =C91*E91 -> 0 | H91: 0 | I91: =G91*H91 -> 0 | K91: =F91+I91+J91 -> 0
D92: LS | E92: 0 | F92: =C92*E92 -> 0 | H92: 0 | I92: =G92*H92 -> 0 | K92: =F92+I92+J92 -> 0
D93: LS | E93: 0 | F93: =C93*E93 -> 0 | H93: 0 | I93: =G93*H93 -> 0 | K93: =F93+I93+J93 -> 0
D94: LS | E94: 0 | F94: =C94*E94 -> 0 | H94: 0 | I94: =G94*H94 -> 0 | K94: =F94+I94+J94 -> 0
J96: Sub Total | K96: =SUM(K91:K95) -> 0
F97: Material Total | G97: Total Hours | I97: Labor Total | J97: Contractor Total | K97: TOTAL
A98: $ / Sq.Ft | B98: TOTAL DIVISION 14
A99: =K99/E6 -> 0 | F99: =SUM(F91:F95,F82:F87,F75:F78,F66:F71,F55:F61,F46:F51,F38:F42,F27:F34,F11:F23) -> 0 | G99: =SUM(G91:G95,G82:G87,G75:G78,G66:G71,G55:G61,G46:G51,G38:G42,G27:G34,G11:G23) -> 0 | I99: =SUM(I91:I95,I82:I87,I75:I78,I66:I71,I55:I61,I46:I51,I38:I42,I27:I34,I11:I23) -> 0 | J99: =SUM(J91:J95,J82:J87,J75:J78,J66:J71,J55:J61,J46:J51,J38:J42,J27:J34,J11:J23) -> 155285 | K99: =SUM(K96,K88,K79,K72,K63,K52,K43,K35,K24) -> 0

Sheet 21
C1: ='Estimate Summary'!C1:H1 -> 0
G5: Fire Suppression | J5: Schedule
D6: ='Estimate Summary'!C11 -> Area: | E6: ='Estimate Summary'!D11 -> 65592 | F6: ='Estimate Summary'!E11 -> Sq. Ft. | J6: ='1'!J6 -> 60 | K6: Weeks
A9: CODE | B9: DESCRIPTION | C9: Materials & Equipment | G9: Labor | L9: Sub Contractor | M9: Quote Total | N9: Additional Quote Info | O9: Previous Quotes
A10: 21 10 00 | B10: Water-Based Fire-Suppression System | C10: Qty | D10: Unit | E10: U. Price | F10: Sub Total | G10: MHrs | H10: U. Price | I10: Sub Total | J10: Quote | K10: Total
D11: LS | E11: 0 | F11: =C11*E11 -> 0 | H11: 0 | I11: =G11*H11 -> 0 | K11: =F11+I11+J11 -> 0 | L11: B&G | M11: 248500 | N11: Wet system in parkade | O11: B&G | P11: 340700
D12: LS | E12: 0 | F12: =C12*E12 -> 0 | H12: 0 | I12: =G12*H12 -> 0 | J12: =M16 -> 212000 | K12: =F12+I12+J12 -> 212000 | L12: Deploy | M12: 252546.1 | O12: Vipond | P12: =229800+6900 -> 236700
D13: LS | E13: 0 | F13: =C13*E13 -> 0 | H13: 0 | I13: =G13*H13 -> 0 | K13: =F13+I13+J13 -> 0 | L13: Troy | M13: 279000
D14: LS | E14: 0 | F14: =C14*E14 -> 0 | H14: 0 | I14: =G14*H14 -> 0 | K14: =F14+I14+J14 -> 0 | L14: Viking | M14: 209800 | N14: Mix of iron and CPVC piping. 4 Stories does not require dry system in attict
D15: LS | E15: 0 | F15: =C15*E15 -> 0 | H15: 0 | I15: =G15*H15 -> 0 | K15: =F15+I15+J15 -> 0 | L15: Vipond | M15: 221900 | N15: All iron piping.
D16: LS | E16: 0 | F16: =C16*E16 -> 0 | H16: 0 | I16: =G16*H16 -> 0 | K16: =F16+I16+J16 -> 0 | L16: Leblanc | M16: 212000 | N16: All iron piping.
D17: LS | E17: 0 | F17: =C17*E17 -> 0 | H17: 0 | I17: =G17*H17 -> 0 | K17: =F17+I17+J17 -> 0
D18: LS | E18: 0 | F18: =C18*E18 -> 0 | H18: 0 | I18: =G18*H18 -> 0 | K18: =F18+I18+J18 -> 0
D19: LS | E19: 0 | F19: =C19*E19 -> 0 | H19: 0 | I19: =G19*H19 -> 0 | K19: =F19+I19+J19 -> 0
D20: LS | E20: 0 | F20: =C20*E20 -> 0 | H20: 0 | I20: =G20*H20 -> 0 | K20: =F20+I20+J20 -> 0
D21: LS | E21: 0 | F21: =C21*E21 -> 0 | H21: 0 | I21: =G21*H21 -> 0 | K21: =F21+I21+J21 -> 0
D22: LS | E22: 0 | F22: =C22*E22 -> 0 | H22: 0 | I22: =G22*H22 -> 0 | K22: =F22+I22+J22 -> 0
J24: Sub Total | K24: =SUM(K11:K23) -> 212000
A25: CODE | B25: DESCRIPTION | C25: Materials & Equipment | G25: Labor
C26: Qty | D26: Unit | E26: U. Price | F26: Sub Total | G26: MHrs | H26: U. Price | I26: Sub Total | J26: Quote | K26: Total
D27: LS | E27: 0 | F27: =C27*E27 -> 0 | H27: 0 | I27: =G27*H27 -> 0 | K27: =F27+I27+J27 -> 0
D28: LS | E28: 0 | F28: =C28*E28 -> 0 | H28: 0 | I28: =G28*H28 -> 0 | K28: =F28+I28+J28 -> 0
D29: LS | E29: 0 | F29: =C29*E29 -> 0 | H29: 0 | I29: =G29*H29 -> 0 | K29: =F29+I29+J29 -> 0
D30: LS | E30: 0 | F30: =C30*E30 -> 0 | H30: 0 | I30: =G30*H30 -> 0 | K30: =F30+I30+J30 -> 0
D31: LS | E31: 0 | F31: =C31*E31 -> 0 | H31: 0 | I31: =G31*H31 -> 0 | K31: =F31+I31+J31 -> 0
D32: LS | E32: 0 | F32: =C32*E32 -> 0 | H32: 0 | I32: =G32*H32 -> 0 | K32: =F32+I32+J32 -> 0
D33: LS | E33: 0 | F33: =C33*E33 -> 0 | H33: 0 | I33: =G33*H33 -> 0 | K33: =F33+I33+J33 -> 0
J35: Sub Total | K35: =SUM(K27:K34) -> 0
A36: CODE | B36: DESCRIPTION | C36: Materials & Equipment | G36: Labor
C37: Qty | D37: Unit | E37: U. Price | F37: Sub Total | G37: MHrs | H37: U. Price | I37: Sub Total | J37: Quote | K37: Total
D38: LS | E38: 0 | F38: =C38*E38 -> 0 | H38: 0 | I38: =G38*H38 -> 0 | K38: =F38+I38+J38 -> 0
D39: LS | E39: 0 | F39: =C39*E39 -> 0 | H39: 0 | I39: =G39*H39 -> 0 | K39: =F39+I39+J39 -> 0
D40: LS | E40: 0 | F40: =C40*E40 -> 0 | H40: 0 | I40: =G40*H40 -> 0 | K40: =F40+I40+J40 -> 0
J43: Sub Total | K43: =SUM(K38:K42) -> 0
A44: CODE | B44: DESCRIPTION | C44: Materials & Equipment | G44: Labor
C45: Qty | D45: Unit | E45: U. Price | F45: Sub Total | G45: MHrs | H45: U. Price | I45: Sub Total | J45: Quote | K45: Total
D46: LS | E46: 0 | F46: =C46*E46 -> 0 | H46: 0 | I46: =G46*H46 -> 0 | K46: =F46+I46+J46 -> 0
D47: LS | E47: 0 | F47: =C47*E47 -> 0 | H47: 0 | I47: =G47*H47 -> 0 | K47: =F47+I47+J47 -> 0
D48: LS | E48: 0 | F48: =C48*E48 -> 0 | H48: 0 | I48: =G48*H48 -> 0 | K48: =F48+I48+J48 -> 0
D49: LS | E49: 0 | F49: =C49*E49 -> 0 | H49: 0 | I49: =G49*H49 -> 0 | K49: =F49+I49+J49 -> 0
D50: LS | E50: 0 | F50: =C50*E50 -> 0 | H50: 0 | I50: =G50*H50 -> 0 | K50: =F50+I50+J50 -> 0
J52: Sub Total | K52: =SUM(K46:K51) -> 0
A53: CODE | B53: DESCRIPTION | C53: Materials & Equipment | G53: Labor
C54: Qty | D54: Unit | E54: U. Price | F54: Sub Total | G54: MHrs | H54: U. Price | I54: Sub Total | J54: Quote | K54: Total
D55: LS | E55: 0 | F55: =C55*E55 -> 0 | H55: 0 | I55: =G55*H55 -> 0 | K55: =F55+I55+J55 -> 0
D56: LS | E56: 0 | F56: =C56*E56 -> 0 | H56: 0 | I56: =G56*H56 -> 0 | K56: =F56+I56+J56 -> 0
D57: LS | E57: 0 | F57: =C57*E57 -> 0 | H57: 0 | I57: =G57*H57 -> 0 | K57: =F57+I57+J57 -> 0
D58: LS | E58: 0 | F58: =C58*E58 -> 0 | H58: 0 | I58: =G58*H58 -> 0 | K58: =F58+I58+J58 -> 0
D59: LS | E59: 0 | F59: =C59*E59 -> 0 | H59: 0 | I59: =G59*H59 -> 0 | K59: =F59+I59+J59 -> 0
D60: LS | E60: 0 | F60: =C60*E60 -> 0 | H60: 0 | I60: =G60*H60 -> 0 | K60: =F60+I60+J60 -> 0
D61: LS | E61: 0 | F61: =C61*E61 -> 0 | H61: 0 | I61: =G61*H61 -> 0 | K61: =F61+I61+J61 -> 0
J63: Sub Total | K63: =SUM(K55:K62) -> 0
A64: CODE | B64: DESCRIPTION | C64: Materials & Equipment | G64: Labor
C65: Qty | D65: Unit | E65: U. Price | F65: Sub Total | G65: MHrs | H65: U. Price | I65: Sub Total | J65: Quote | K65: Total
D66: LS | E66: 0 | F66: =C66*E66 -> 0 | H66: 0 | I66: =G66*H66 -> 0 | K66: =F66+I66+J66 -> 0
D67: LS | E67: 0 | F67: =C67*E67 -> 0 | H67: 0 | I67: =G67*H67 -> 0 | K67: =F67+I67+J67 -> 0
D68: LS | E68: 0 | F68: =C68*E68 -> 0 | H68: 0 | I68: =G68*H68 -> 0 | K68: =F68+I68+J68 -> 0
D69: LS | E69: 0 | F69: =C69*E69 -> 0 | H69: 0 | I69: =G69*H69 -> 0 | K69: =F69+I69+J69 -> 0
D70: LS | E70: 0 | F70: =C70*E70 -> 0 | H70: 0 | I70: =G70*H70 -> 0 | K70: =F70+I70+J70 -> 0
J72: Sub Total | K72: =SUM(K66:K71) -> 0
A73: CODE | B73: DESCRIPTION | C73: Materials & Equipment | G73: Labor
C74: Qty | D74: Unit | E74: U. Price | F74: Sub Total | G74: MHrs | H74: U. Price | I74: Sub Total | J74: Quote | K74: Total
D75: LS | E75: 0 | F75: =C75*E75 -> 0 | H75: 0 | I75: =G75*H75 -> 0 | K75: =F75+I75+J75 -> 0
D76: LS | E76: 0 | F76: =C76*E76 -> 0 | H76: 0 | I76: =G76*H76 -> 0 | K76: =F76+I76+J76 -> 0
D77: LS | E77: 0 | F77: =C77*E77 -> 0 | H77: 0 | I77: =G77*H77 -> 0 | K77: =F77+I77+J77 -> 0
J79: Sub Total | K79: =SUM(K75:K78) -> 0
A80: CODE | B80: DESCRIPTION | C80: Materials & Equipment | G80: Labor
C81: Qty | D81: Unit | E81: U. Price | F81: Sub Total | G81: MHrs | H81: U. Price | I81: Sub Total | J81: Quote | K81: Total
D82: LS | E82: 0 | F82: =C82*E82 -> 0 | H82: 0 | I82: =G82*H82 -> 0 | K82: =F82+I82+J82 -> 0
D83: LS | E83: 0 | F83: =C83*E83 -> 0 | H83: 0 | I83: =G83*H83 -> 0 | K83: =F83+I83+J83 -> 0
D84: LS | E84: 0 | F84: =C84*E84 -> 0 | H84: 0 | I84: =G84*H84 -> 0 | K84: =F84+I84+J84 -> 0
D85: LS | E85: 0 | F85: =C85*E85 -> 0 | H85: 0 | I85: =G85*H85 -> 0 | K85: =F85+I85+J85 -> 0
D86: LS | E86: 0 | F86: =C86*E86 -> 0 | H86: 0 | I86: =G86*H86 -> 0 | K86: =F86+I86+J86 -> 0
J88: Sub Total | K88: =SUM(K82:K87) -> 0
A89: CODE | B89: DESCRIPTION | C89: Materials & Equipment | G89: Labor
C90: Qty | D90: Unit | E90: U. Price | F90: Sub Total | G90: MHrs | H90: U. Price | I90: Sub Total | J90: Quote | K90: Total
D91: LS | E91: 0 | F91: =C91*E91 -> 0 | H91: 0 | I91: =G91*H91 -> 0 | K91: =F91+I91+J91 -> 0
D92: LS | E92: 0 | F92: =C92*E92 -> 0 | H92: 0 | I92: =G92*H92 -> 0 | K92: =F92+I92+J92 -> 0
D93: LS | E93: 0 | F93: =C93*E93 -> 0 | H93: 0 | I93: =G93*H93 -> 0 | K93: =F93+I93+J93 -> 0
D94: LS | E94: 0 | F94: =C94*E94 -> 0 | H94: 0 | I94: =G94*H94 -> 0 | K94: =F94+I94+J94 -> 0
J96: Sub Total | K96: =SUM(K91:K95) -> 0
F97: Material Total | G97: Total Hours | I97: Labor Total | J97: Contractor Total | K97: TOTAL
A98: $ / Sq.Ft | B98: TOTAL DIVISION 21
A99: =K99/E6 -> 3.2321015 | F99: =SUM(F91:F95,F82:F87,F75:F78,F66:F71,F55:F61,F46:F51,F38:F42,F27:F34,F11:F23) -> 0 | G99: =SUM(G91:G95,G82:G87,G75:G78,G66:G71,G55:G61,G46:G51,G38:G42,G27:G34,G11:G23) -> 0 | I99: =SUM(I91:I95,I82:I87,I75:I78,I66:I71,I55:I61,I46:I51,I38:I42,I27:I34,I11:I23) -> 0 | J99: =SUM(J91:J95,J82:J87,J75:J78,J66:J71,J55:J61,J46:J51,J38:J42,J27:J34,J11:J23) -> 212000 | K99: =SUM(K96,K88,K79,K72,K63,K52,K43,K35,K24) -> 212000

Sheet 22
C1: ='Estimate Summary'!C1:H1 -> 0
G5: Plumbing | J5: Schedule
D6: ='Estimate Summary'!C11 -> Area: | E6: ='Estimate Summary'!D11 -> 65592 | F6: ='Estimate Summary'!E11 -> Sq. Ft. | J6: ='1'!J6 -> 60 | K6: Weeks
A9: CODE | B9: DESCRIPTION | C9: Materials & Equipment | G9: Labor | L9: Sub Contractor | M9: Quote Total | N9: Additional Quote Info
A10: 22 10 00 | B10: Plumbing Piping | C10: Qty | D10: Unit | E10: U. Price | F10: Sub Total | G10: MHrs | H10: U. Price | I10: Sub Total | J10: Quote | K10: Total
D11: LS | E11: 0 | F11: =C11*E11 -> 0 | H11: 0 | I11: =G11*H11 -> 0 | K11: =F11+I11+J11 -> 0
C12: 59 | D12: Unit | E12: =M20 -> 10779.661 | H12: 0 | I12: =G12*H12 -> 0 | K12: =F12+I12+J12 -> 0 | L12: Spent | M12: 17707
D13: LS | E13: 0 | F13: =C13*E13 -> 0 | H13: 0 | I13: =G13*H13 -> 0 | K13: =F13+I13+J13 -> 0 | N13: Fixtures
D14: LS | E14: 0 | F14: =C14*E14 -> 0 | H14: 0 | I14: =G14*H14 -> 0 | J14: =M15 -> 674850 | K14: =F14+I14+J14 -> 674850 | L14: JR Snowdon | M14: 632530.34 | N14: 195093.54
D15: LS | E15: 0 | F15: =C15*E15 -> 0 | H15: 0 | I15: =G15*H15 -> 0 | K15: =F15+I15+J15 -> 0 | L15: Premiere | M15: 674850 | N15: Cannot start rough ins until March
D16: LS | E16: 0 | F16: =C16*E16 -> 0 | H16: 0 | I16: =G16*H16 -> 0 | K16: =F16+I16+J16 -> 0 | O16: Snowdon Comparison to Master
D17: LS | E17: 0 | F17: =C17*E17 -> 0 | H17: 0 | I17: =G17*H17 -> 0 | K17: =F17+I17+J17 -> 0 | L17: Master Interior Fixtures Black | M17: =10502+4779+5904+10981+138+2952 -> 35256 | O17: =17023+10056.48+2865.9+11166.34+7632.24 -> 48743.96
D18: LS | E18: 0 | F18: =C18*E18 -> 0 | H18: 0 | I18: =G18*H18 -> 0 | K18: =F18+I18+J18 -> 0 | L18: Master Interior Fixtures Partial Chrome | M18: =10502+2952+3599+4264+10981+138 -> 32436
D19: LS | E19: 0 | F19: =C19*E19 -> 0 | H19: 0 | I19: =G19*H19 -> 0 | K19: =F19+I19+J19 -> 0
D20: LS | E20: 0 | F20: =C20*E20 -> 0 | H20: 0 | I20: =G20*H20 -> 0 | K20: =F20+I20+J20 -> 0 | L20: Joyce | M20: =636000/59 -> 10779.661
D21: LS | E21: 0 | F21: =C21*E21 -> 0 | H21: 0 | I21: =G21*H21 -> 0 | K21: =F21+I21+J21 -> 0
D22: LS | E22: 0 | F22: =C22*E22 -> 0 | H22: 0 | I22: =G22*H22 -> 0 | K22: =F22+I22+J22 -> 0
J24: Sub Total | K24: =SUM(K11:K23) -> 674850
A25: CODE | B25: DESCRIPTION | C25: Materials & Equipment | G25: Labor
A26: 22 30 00 | B26: Plumbing Equipment | C26: Qty | D26: Unit | E26: U. Price | F26: Sub Total | G26: MHrs | H26: U. Price | I26: Sub Total | J26: Quote | K26: Total
A27: 22 33 00 | B27: Electric Domestic Water Heaters | D27: LS | E27: 0 | F27: =C27*E27 -> 0 | H27: 0 | I27: =G27*H27 -> 0 | K27: =F27+I27+J27 -> 0
A28: 22 34 00 | B28: Fuel-Fired Domestic Water Heaters | D28: LS | E28: 0 | F28: =C28*E28 -> 0 | H28: 0 | I28: =G28*H28 -> 0 | K28: =F28+I28+J28 -> 0
D29: LS | E29: 0 | F29: =C29*E29 -> 0 | H29: 0 | I29: =G29*H29 -> 0 | K29: =F29+I29+J29 -> 0
D30: LS | E30: 0 | F30: =C30*E30 -> 0 | H30: 0 | I30: =G30*H30 -> 0 | K30: =F30+I30+J30 -> 0
D31: LS | E31: 0 | F31: =C31*E31 -> 0 | H31: 0 | I31: =G31*H31 -> 0 | K31: =F31+I31+J31 -> 0
D32: LS | E32: 0 | F32: =C32*E32 -> 0 | H32: 0 | I32: =G32*H32 -> 0 | K32: =F32+I32+J32 -> 0
D33: LS | E33: 0 | F33: =C33*E33 -> 0 | H33: 0 | I33: =G33*H33 -> 0 | K33: =F33+I33+J33 -> 0
J35: Sub Total | K35: =SUM(K27:K34) -> 0
A36: CODE | B36: DESCRIPTION | C36: Materials & Equipment | G36: Labor
A37: 22 40 00 | B37: Plumbing Fixtures | C37: Qty | D37: Unit | E37: U. Price | F37: Sub Total | G37: MHrs | H37: U. Price | I37: Sub Total | J37: Quote | K37: Total
D38: LS | E38: 0 | F38: =C38*E38 -> 0 | H38: 0 | I38: =G38*H38 -> 0 | K38: =F38+I38+J38 -> 0
D39: LS | E39: 0 | F39: =C39*E39 -> 0 | H39: 0 | I39: =G39*H39 -> 0 | K39: =F39+I39+J39 -> 0
D40: LS | E40: 0 | F40: =C40*E40 -> 0 | H40: 0 | I40: =G40*H40 -> 0 | K40: =F40+I40+J40 -> 0
D41: LS | E41: 0 | F41: =C41*E41 -> 0 | H41: 0 | I41: =G41*H41 -> 0 | K41: =F41+I41+J41 -> 0
D42: LS | E42: 0 | F42: =C42*E42 -> 0 | H42: 0 | I42: =G42*H42 -> 0 | K42: =F42+I42+J42 -> 0
D43: LS | E43: 0 | F43: =C43*E43 -> 0 | H43: 0 | I43: =G43*H43 -> 0 | K43: =F43+I43+J43 -> 0
D44: LS | E44: 0 | F44: =C44*E44 -> 0 | H44: 0 | I44: =G44*H44 -> 0 | K44: =F44+I44+J44 -> 0
J46: Sub Total | K46: =SUM(K38:K45) -> 0
A47: CODE | B47: DESCRIPTION | C47: Materials & Equipment | G47: Labor
A48: 22 42 00 | B48: Commercial Plumbing Fixtures | C48: Qty | D48: Unit | E48: U. Price | F48: Sub Total | G48: MHrs | H48: U. Price | I48: Sub Total | J48: Quote | K48: Total
A49: 22 42 13 | B49: Commercial Water Closets, Urinals, and Bidets | D49: LS | E49: 0 | F49: =C49*E49 -> 0 | H49: 0 | I49: =G49*H49 -> 0 | K49: =F49+I49+J49 -> 0
A50: 22 42 13.13 | B50: Commercial Water Closets | D50: LS | E50: 0 | F50: =C50*E50 -> 0 | H50: 0 | I50: =G50*H50 -> 0 | K50: =F50+I50+J50 -> 0
A51: 22 42 13.16 | B51: Commercial Urinals | D51: LS | E51: 0 | F51: =C51*E51 -> 0 | H51: 0 | I51: =G51*H51 -> 0 | K51: =F51+I51+J51 -> 0
A52: 22 42 16 | B52: Commercial Lavatories and Sinks | D52: LS | E52: 0 | F52: =C52*E52 -> 0 | H52: 0 | I52: =G52*H52 -> 0 | K52: =F52+I52+J52 -> 0
A53: 22 42 16.13 | B53: Commercial Lavatories | D53: LS | E53: 0 | F53: =C53*E53 -> 0 | H53: 0 | I53: =G53*H53 -> 0 | K53: =F53+I53+J53 -> 0
A54: 22 42 16.16 | B54: Commercial Sinks | D54: LS | E54: 0 | F54: =C54*E54 -> 0 | H54: 0 | I54: =G54*H54 -> 0 | K54: =F54+I54+J54 -> 0
A55: 22 42 19 | B55: Commercial Bathtubs | D55: LS | E55: 0 | F55: =C55*E55 -> 0 | H55: 0 | I55: =G55*H55 -> 0 | K55: =F55+I55+J55 -> 0
A56: 22 42 23 | B56: Commercial Showers | D56: LS | E56: 0 | F56: =C56*E56 -> 0 | H56: 0 | I56: =G56*H56 -> 0 | K56: =F56+I56+J56 -> 0
A57: 22 42 26 | B57: Commercial Disposers | D57: LS | E57: 0 | F57: =C57*E57 -> 0 | H57: 0 | I57: =G57*H57 -> 0 | K57: =F57+I57+J57 -> 0
A58: 22 42 29 | B58: Shampoo Bowls | D58: LS | E58: 0 | F58: =C58*E58 -> 0 | H58: 0 | I58: =G58*H58 -> 0 | K58: =F58+I58+J58 -> 0
A59: 22 42 33 | B59: Wash Fountains | D59: LS | E59: 0 | F59: =C59*E59 -> 0 | H59: 0 | I59: =G59*H59 -> 0 | K59: =F59+I59+J59 -> 0
A60: 22 42 36 | B60: Commercial Laundry Trays | D60: LS | E60: 0 | F60: =C60*E60 -> 0 | H60: 0 | I60: =G60*H60 -> 0 | K60: =F60+I60+J60 -> 0
... A62: 22 42 43 | B62: Flushometers | D62: LS | E62: 0 | F62: =C62*E62 -> 0 | H62: 0 | I62: =G62*H62 -> 0 | K62: =F62+I62+J62 -> 0
D63: LS | E63: 0 | F63: =C63*E63 -> 0 | H63: 0 | I63: =G63*H63 -> 0 | K63: =F63+I63+J63 -> 0
D64: LS | E64: 0 | F64: =C64*E64 -> 0 | H64: 0 | I64: =G64*H64 -> 0 | K64: =F64+I64+J64 -> 0
D65: LS | E65: 0 | F65: =C65*E65 -> 0 | H65: 0 | I65: =G65*H65 -> 0 | K65: =F65+I65+J65 -> 0
J67: Sub Total | K67: =SUM(K49:K66) -> 0
A68: CODE | B68: DESCRIPTION | C68: Materials & Equipment | G68: Labor
A69: 22 45 00 | B69: Emergency Plumbing Fixtures | C69: Qty | D69: Unit | E69: U. Price | F69: Sub Total | G69: MHrs | H69: U. Price | I69: Sub Total | J69: Quote | K69: Total
A70: 22 45 13 | B70: Emergency Showers | D70: LS | E70: 0 | F70: =C70*E70 -> 0 | H70: 0 | I70: =G70*H70 -> 0 | K70: =F70+I70+J70 -> 0
A71: 22 45 16 | B71: Eyewash Station | D71: LS | E71: 0 | F71: =C71*E71 -> 0 | H71: 0 | I71: =G71*H71 -> 0 | K71: =F71+I71+J71 -> 0
D72: LS | E72: 0 | F72: =C72*E72 -> 0 | H72: 0 | I72: =G72*H72 -> 0 | K72: =F72+I72+J72 -> 0
J74: Sub Total | K74: =SUM(K70:K73) -> 0
A75: CODE | B75: DESCRIPTION | C75: Materials & Equipment | G75: Labor
A76: 22 47 00 | B76: Drinking Fountains and Water Coolers | C76: Qty | D76: Unit | E76: U. Price | F76: Sub Total | G76: MHrs | H76: U. Price | I76: Sub Total | J76: Quote | K76: Total
D77: LS | E77: 0 | F77: =C77*E77 -> 0 | H77: 0 | I77: =G77*H77 -> 0 | K77: =F77+I77+J77 -> 0
D78: LS | E78: 0 | F78: =C78*E78 -> 0 | H78: 0 | I78: =G78*H78 -> 0 | K78: =F78+I78+J78 -> 0
D79: LS | E79: 0 | F79: =C79*E79 -> 0 | H79: 0 | I79: =G79*H79 -> 0 | K79: =F79+I79+J79 -> 0
D80: LS | E80: 0 | F80: =C80*E80 -> 0 | H80: 0 | I80: =G80*H80 -> 0 | K80: =F80+I80+J80 -> 0
D81: LS | E81: 0 | F81: =C81*E81 -> 0 | H81: 0 | I81: =G81*H81 -> 0 | K81: =F81+I81+J81 -> 0
J83: Sub Total | K83: =SUM(K77:K82) -> 0
A84: CODE | B84: DESCRIPTION | C84: Materials & Equipment | G84: Labor
C85: Qty | D85: Unit | E85: U. Price | F85: Sub Total | G85: MHrs | H85: U. Price | I85: Sub Total | J85: Quote | K85: Total
D86: LS | E86: 0 | F86: =C86*E86 -> 0 | H86: 0 | I86: =G86*H86 -> 0 | K86: =F86+I86+J86 -> 0
D87: LS | E87: 0 | F87: =C87*E87 -> 0 | H87: 0 | I87: =G87*H87 -> 0 | K87: =F87+I87+J87 -> 0
D88: LS | E88: 0 | F88: =C88*E88 -> 0 | H88: 0 | I88: =G88*H88 -> 0 | K88: =F88+I88+J88 -> 0
D89: LS | E89: 0 | F89: =C89*E89 -> 0 | H89: 0 | I89: =G89*H89 -> 0 | K89: =F89+I89+J89 -> 0
J91: Sub Total | K91: =SUM(K86:K90) -> 0
F92: Material Total | G92: Total Hours | I92: Labor Total | J92: Contractor Total | K92: TOTAL
A93: $ / Sq.Ft | B93: TOTAL DIVISION 22
A94: =K94/E6 -> 10.288602 | F94: =SUM(F77:F82,F70:F73,F49:F66,F38:F45,F27:F34,F11:F23) -> 0 | G94: =SUM(G77:G82,G70:G73,G49:G66,G38:G45,G27:G34,G11:G23) -> 0 | I94: =SUM(I77:I82,I70:I73,I49:I66,I38:I45,I27:I34,I11:I23) -> 0 | J94: =SUM(J77:J82,J70:J73,J49:J66,J38:J45,J27:J34,J11:J23) -> 674850 | K94: =K91+K83+K74+K67+K46+K35+K24 -> 674850

Sheet 23
C1: ='Estimate Summary'!C1:H1 -> 0
G5: HVAC | J5: Schedule
D6: ='Estimate Summary'!C11 -> Area: | E6: ='Estimate Summary'!D11 -> 65592 | F6: ='Estimate Summary'!E11 -> Sq. Ft. | J6: ='1'!J6 -> 60 | K6: Weeks
A9: CODE | B9: DESCRIPTION | C9: Materials & Equipment | G9: Labor | L9: Sub Contractor | M9: Quote Total | N9: Additional Quote Info | O9: Previous Quotes
A10: 23 07 00 | B10: HVAC Insulation | C10: Qty | D10: Unit | E10: U. Price | F10: Sub Total | G10: MHrs | H10: U. Price | I10: Sub Total | J10: Quote | K10: Total
D11: LS | E11: 0 | F11: =C11*E11 -> 0 | H11: 0 | I11: =G11*H11 -> 0 | K11: =F11+I11+J11 -> 0 | L11: Conair | M11: 509800 | N11: Alternative heat pumps | O11: GreenFoot | P11: 471000
C12: 59 | D12: Unit | E12: =M17 -> 7580.5085 | H12: 0 | I12: =G12*H12 -> 0 | J12: =M12 -> 467650 | K12: =F12+I12+J12 -> 467650 | L12: Greenfoot | M12: =472650-5000 -> 467650 | N12: Alternative heat pumps Equivalet to Hisense. Removed in-unit professional balancing. | O12: Ray Mutch | P12: 337362 | Q12: HP and HRV Only. No Common Areas
D13: LS | E13: 0 | F13: =C13*E13 -> 0 | H13: 0 | I13: =G13*H13 -> 0 | K13: =F13+I13+J13 -> 0 | L13: Sica | M13: 539275
D14: LS | E14: 0 | F14: =C14*E14 -> 0 | H14: 0 | I14: =G14*H14 -> 0 | K14: =F14+I14+J14 -> 0 | L14: ECR | M14: 686000
D15: LS | E15: 0 | F15: =C15*E15 -> 0 | H15: 0 | I15: =G15*H15 -> 0 | K15: =F15+I15+J15 -> 0 | L15: Coldtech | M15: 545250
D16: LS | E16: 0 | F16: =C16*E16 -> 0 | H16: 0 | I16: =G16*H16 -> 0 | K16: =F16+I16+J16 -> 0
L17: Joyce | M17: =447250/59 -> 7580.5085
J18: Sub Total | K18: =SUM(K11:K17) -> 467650
A19: CODE | B19: DESCRIPTION | C19: Materials & Equipment | G19: Labor
A20: 23 08 00 | B20: Commissioning of HVAC | C20: Qty | D20: Unit | E20: U. Price | F20: Sub Total | G20: MHrs | H20: U. Price | I20: Sub Total | J20: Quote | K20: Total
D21: LS | E21: 0 | F21: =C21*E21 -> 0 | H21: 0 | I21: =G21*H21 -> 0 | K21: =F21+I21+J21 -> 0
D22: LS | E22: 0 | F22: =C22*E22 -> 0 | H22: 0 | I22: =G22*H22 -> 0 | K22: =F22+I22+J22 -> 0
D23: LS | E23: 0 | F23: =C23*E23 -> 0 | H23: 0 | I23: =G23*H23 -> 0 | K23: =F23+I23+J23 -> 0
J25: Sub Total | K25: =SUM(K21:K24) -> 0
A26: CODE | B26: DESCRIPTION | C26: Materials & Equipment | G26: Labor
A27: 23 09 00 | B27: Instrumentation and Control for HVAC | C27: Qty | D27: Unit | E27: U. Price | F27: Sub Total | G27: MHrs | H27: U. Price | I27: Sub Total | J27: Quote | K27: Total
D28: LS | E28: 0 | F28: =C28*E28 -> 0 | H28: 0 | I28: =G28*H28 -> 0 | K28: =F28+I28+J28 -> 0
D29: LS | E29: 0 | F29: =C29*E29 -> 0 | H29: 0 | I29: =G29*H29 -> 0 | K29: =F29+I29+J29 -> 0
J31: Sub Total | K31: =SUM(K28:K30) -> 0
A32: CODE | B32: DESCRIPTION | C32: Materials & Equipment | G32: Labor
A33: 23 11 00 | B33: Facility Fuel piping | C33: Qty | D33: Unit | E33: U. Price | F33: Sub Total | G33: MHrs | H33: U. Price | I33: Sub Total | J33: Quote | K33: Total
A34: 23 11 23 | B34: Facility Natural Gas Piping | D34: LS | E34: 0 | F34: =C34*E34 -> 0 | H34: 0 | I34: =G34*H34 -> 0 | K34: =F34+I34+J34 -> 0
D35: LS | E35: 0 | F35: =C35*E35 -> 0 | H35: 0 | I35: =G35*H35 -> 0 | K35: =F35+I35+J35 -> 0
D36: LS | E36: 0 | F36: =C36*E36 -> 0 | H36: 0 | I36: =G36*H36 -> 0 | K36: =F36+I36+J36 -> 0
J38: Sub Total | K38: =SUM(K34:K37) -> 0
A39: CODE | B39: DESCRIPTION | C39: Materials & Equipment | G39: Labor
A40: 23 13 00 | B40: Facility Fuel Storage | C40: Qty | D40: Unit | E40: U. Price | F40: Sub Total | G40: MHrs | H40: U. Price | I40: Sub Total | J40: Quote | K40: Total
D41: LS | E41: 0 | F41: =C41*E41 -> 0 | H41: 0 | I41: =G41*H41 -> 0 | K41: =F41+I41+J41 -> 0
D42: LS | E42: 0 | F42: =C42*E42 -> 0 | H42: 0 | I42: =G42*H42 -> 0 | K42: =F42+I42+J42 -> 0
D43: LS | E43: 0 | F43: =C43*E43 -> 0 | H43: 0 | I43: =G43*H43 -> 0 | K43: =F43+I43+J43 -> 0
D44: LS | E44: 0 | F44: =C44*E44 -> 0 | H44: 0 | I44: =G44*H44 -> 0 | K44: =F44+I44+J44 -> 0
J46: Sub Total | K46: =SUM(K41:K45) -> 0
A47: CODE | B47: DESCRIPTION | C47: Materials & Equipment | G47: Labor
A48: 23 20 00 | B48: HVAC Piping and Pumps | C48: Qty | D48: Unit | E48: U. Price | F48: Sub Total | G48: MHrs | H48: U. Price | I48: Sub Total | J48: Quote | K48: Total
D49: LS | E49: 0 | F49: =C49*E49 -> 0 | H49: 0 | I49: =G49*H49 -> 0 | K49: =F49+I49+J49 -> 0
D50: LS | E50: 0 | F50: =C50*E50 -> 0 | H50: 0 | I50: =G50*H50 -> 0 | K50: =F50+I50+J50 -> 0
D51: LS | E51: 0 | F51: =C51*E51 -> 0 | H51: 0 | I51: =G51*H51 -> 0 | K51: =F51+I51+J51 -> 0
J53: Sub Total | K53: =SUM(K49:K52) -> 0
A54: CODE | B54: DESCRIPTION | C54: Materials & Equipment | G54: Labor
A55: 23 23 00 | B55: Refrigerant Piping | C55: Qty | D55: Unit | E55: U. Price | F55: Sub Total | G55: MHrs | H55: U. Price | I55: Sub Total | J55: Quote | K55: Total
D56: LS | E56: 0 | F56: =C56*E56 -> 0 | H56: 0 | I56: =G56*H56 -> 0 | K56: =F56+I56+J56 -> 0
J58: Sub Total | K58: =SUM(K56:K57) -> 0
A59: CODE | B59: DESCRIPTION | C59: Materials & Equipment | G59: Labor
A60: 23 30 00 | B60: HVAC Air Distribution | C60: Qty | D60: Unit | E60: U. Price | F60: Sub Total | G60: MHrs | H60: U. Price | I60: Sub Total | J60: Quote | K60: Total
A61: 23 31 00 | B61: HVAC Ducts and Casings | D61: LS | E61: 0 | F61: =C61*E61 -> 0 | H61: 0 | I61: =G61*H61 -> 0 | K61: =F61+I61+J61 -> 0
A62: 23 31 12 | B62: Metal Ducts | D62: LS | E62: 0 | F62: =C62*E62 -> 0 | H62: 0 | I62: =G62*H62 -> 0 | K62: =F62+I62+J62 -> 0
A63: 23 31 12.13 | B63: Rectangular Metal Ducts | D63: LS | E63: 0 | F63: =C63*E63 -> 0 | H63: 0 | I63: =G63*H63 -> 0 | K63: =F63+I63+J63 -> 0
A64: 23 31 12.16 | B64: Round and Flat-Oval Spiral Ducts | D64: LS | E64: 0 | F64: =C64*E64 -> 0 | H64: 0 | I64: =G64*H64 -> 0 | K64: =F64+I64+J64 -> 0
A65: 23 33 00 | B65: Air Duct Accessories | D65: LS | E65: 0 | F65: =C65*E65 -> 0 | H65: 0 | I65: =G65*H65 -> 0 | K65: =F65+I65+J65 -> 0
A66: 23 33 46 | B66: Flexible Ducts | D66: LS | E66: 0 | F66: =C66*E66 -> 0 | H66: 0 | I66: =G66*H66 -> 0 | K66: =F66+I66+J66 -> 0
A67: 23 34 00 | B67: HVAC Fans | D67: LS | E67: 0 | F67: =C67*E67 -> 0 | H67: 0 | I67: =G67*H67 -> 0 | K67: =F67+I67+J67 -> 0
A68: 23 38 00 | B68: Ventilation Hoods | D68: LS | E68: 0 | F68: =C68*E68 -> 0 | H68: 0 | I68: =G68*H68 -> 0 | K68: =F68+I68+J68 -> 0
D69: LS | E69: 0 | F69: =C69*E69 -> 0 | H69: 0 | I69: =G69*H69 -> 0 | K69: =F69+I69+J69 -> 0
D70: LS | E70: 0 | F70: =C70*E70 -> 0 | H70: 0 | I70: =G70*H70 -> 0 | K70: =F70+I70+J70 -> 0
D71: LS | E71: 0 | F71: =C71*E71 -> 0 | H71: 0 | I71: =G71*H71 -> 0 | K71: =F71+I71+J71 -> 0
J73: Sub Total | K73: =SUM(K61:K72) -> 0
A74: CODE | B74: DESCRIPTION | C74: Materials & Equipment | G74: Labor
A75: 23 70 00 | B75: Central HVAC Equipment | C75: Qty | D75: Unit | E75: U. Price | F75: Sub Total | G75: MHrs | H75: U. Price | I75: Sub Total | J75: Quote | K75: Total
A76: 23 74 00 | B76: Packaged Outdoor HVAC Equipment | D76: LS | E76: 0 | F76: =C76*E76 -> 0 | H76: 0 | I76: =G76*H76 -> 0 | K76: =F76+I76+J76 -> 0
D77: LS | E77: 0 | F77: =C77*E77 -> 0 | H77: 0 | I77: =G77*H77 -> 0 | K77: =F77+I77+J77 -> 0
J79: Sub Total | K79: =SUM(K76:K78) -> 0
A80: CODE | B80: DESCRIPTION | C80: Materials & Equipment | G80: Labor
A81: 23 83 00 | B81: Radiant Heating Units | C81: Qty | D81: Unit | E81: U. Price | F81: Sub Total | G81: MHrs | H81: U. Price | I81: Sub Total | J81: Quote | K81: Total
D82: LS | E82: 0 | F82: =C82*E82 -> 0 | H82: 0 | I82: =G82*H82 -> 0 | K82: =F82+I82+J82 -> 0
D83: LS | E83: 0 | F83: =C83*E83 -> 0 | H83: 0 | I83: =G83*H83 -> 0 | K83: =F83+I83+J83 -> 0
J85: Sub Total | K85: =SUM(K82:K84) -> 0
A86: CODE | B86: DESCRIPTION | C86: Materials & Equipment | G86: Labor
A87: 23 84 00 | B87: Humidity Control Equipment | C87: Qty | D87: Unit | E87: U. Price | F87: Sub Total | G87: MHrs | H87: U. Price | I87: Sub Total | J87: Quote | K87: Total
D88: LS | E88: 0 | F88: =C88*E88 -> 0 | H88: 0 | I88: =G88*H88 -> 0 | K88: =F88+I88+J88 -> 0
D89: LS | E89: 0 | F89: =C89*E89 -> 0 | H89: 0 | I89: =G89*H89 -> 0 | K89: =F89+I89+J89 -> 0
J91: Sub Total | K91: =SUM(K88:K90) -> 0
A92: CODE | B92: DESCRIPTION | C92: Materials & Equipment | G92: Labor
C93: Qty | D93: Unit | E93: U. Price | F93: Sub Total | G93: MHrs | H93: U. Price | I93: Sub Total | J93: Quote | K93: Total
D94: LS | E94: 0 | F94: =C94*E94 -> 0 | H94: 0 | I94: =G94*H94 -> 0 | K94: =F94+I94+J94 -> 0
D95: LS | E95: 0 | F95: =C95*E95 -> 0 | H95: 0 | I95: =G95*H95 -> 0 | K95: =F95+I95+J95 -> 0
D96: LS | E96: 0 | F96: =C96*E96 -> 0 | H96: 0 | I96: =G96*H96 -> 0 | K96: =F96+I96+J96 -> 0
D97: LS | E97: 0 | F97: =C97*E97 -> 0 | H97: 0 | I97: =G97*H97 -> 0 | K97: =F97+I97+J97 -> 0
J99: Sub Total | K99: =SUM(K94:K98) -> 0
F100: Material Total | G100: Total Hours | I100: Labor Total | J100: Contractor Total | K100: TOTAL
A101: $ / Sq.Ft | B101: TOTAL DIVISION 23
A102: =K102/E6 -> 7.1296804 | F102: =SUM(F94:F98,F88:F90,F82:F84,F76:F78,F61:F72,F56:F57,F49:F52,F41:F45,F34:F37,F28:F30,F21:F24,F11:F17) -> 0 | G102: =SUM(G94:G98,G88:G90,G82:G84,G76:G78,G61:G72,G56:G57,G49:G52,G41:G45,G34:G37,G28:G30,G21:G24,G11:G17) -> 0 | I102: =SUM(I94:I98,I88:I90,I82:I84,I76:I78,I61:I72,I56:I57,I49:I52,I41:I45,I34:I37,I28:I30,I21:I24,I11:I17) -> 0 | J102: =SUM(J94:J98,J88:J90,J82:J84,J76:J78,J61:J72,J56:J57,J49:J52,J41:J45,J34:J37,J28:J30,J21:J24,J11:J17) -> 467650 | K102: =K99+K91+K85+K79+K73+K58+K53+K46+K38+K31+K25+K18 -> 467650

Sheet 25
C1: ='Estimate Summary'!C1:H1 -> 0
G5: Controls | J5: Schedule
D6: ='Estimate Summary'!C11 -> Area: | E6: ='Estimate Summary'!D11 -> 65592 | F6: ='Estimate Summary'!E11 -> Sq. Ft. | J6: ='1'!J6 -> 60 | K6: Weeks
A9: CODE | B9: DESCRIPTION | C9: Materials & Equipment | G9: Labor | L9: Sub Contractor | M9: Quote Total | N9: Additional Quote Info
A10: 25 00 00 | B10: Integrated Automation | C10: Qty | D10: Unit | E10: U. Price | F10: Sub Total | G10: MHrs | H10: U. Price | I10: Sub Total | J10: Quote | K10: Total
D11: LS | E11: 0 | F11: =C11*E11 -> 0 | H11: 0 | I11: =G11*H11 -> 0 | K11: =F11+I11+J11 -> 0
D12: LS | E12: 0 | F12: =C12*E12 -> 0 | H12: 0 | I12: =G12*H12 -> 0 | K12: =F12+I12+J12 -> 0
D13: LS | E13: 0 | F13: =C13*E13 -> 0 | H13: 0 | I13: =G13*H13 -> 0 | K13: =F13+I13+J13 -> 0
D14: LS | E14: 0 | F14: =C14*E14 -> 0 | H14: 0 | I14: =G14*H14 -> 0 | K14: =F14+I14+J14 -> 0
D15: LS | E15: 0 | F15: =C15*E15 -> 0 | H15: 0 | I15: =G15*H15 -> 0 | K15: =F15+I15+J15 -> 0
D16: LS | E16: 0 | F16: =C16*E16 -> 0 | H16: 0 | I16: =G16*H16 -> 0 | K16: =F16+I16+J16 -> 0
D17: LS | E17: 0 | F17: =C17*E17 -> 0 | H17: 0 | I17: =G17*H17 -> 0 | K17: =F17+I17+J17 -> 0
D18: LS | E18: 0 | F18: =C18*E18 -> 0 | H18: 0 | I18: =G18*H18 -> 0 | K18: =F18+I18+J18 -> 0
D19: LS | E19: 0 | F19: =C19*E19 -> 0 | H19: 0 | I19: =G19*H19 -> 0 | K19: =F19+I19+J19 -> 0
D20: LS | E20: 0 | F20: =C20*E20 -> 0 | H20: 0 | I20: =G20*H20 -> 0 | K20: =F20+I20+J20 -> 0
D21: LS | E21: 0 | F21: =C21*E21 -> 0 | H21: 0 | I21: =G21*H21 -> 0 | K21: =F21+I21+J21 -> 0
D22: LS | E22: 0 | F22: =C22*E22 -> 0 | H22: 0 | I22: =G22*H22 -> 0 | K22: =F22+I22+J22 -> 0
J24: Sub Total | K24: =SUM(K11:K23) -> 0
A25: CODE | B25: DESCRIPTION | C25: Materials & Equipment | G25: Labor
C26: Qty | D26: Unit | E26: U. Price | F26: Sub Total | G26: MHrs | H26: U. Price | I26: Sub Total | J26: Quote | K26: Total
D27: LS | E27: 0 | F27: =C27*E27 -> 0 | H27: 0 | I27: =G27*H27 -> 0 | K27: =F27+I27+J27 -> 0
D28: LS | E28: 0 | F28: =C28*E28 -> 0 | H28: 0 | I28: =G28*H28 -> 0 | K28: =F28+I28+J28 -> 0
D29: LS | E29: 0 | F29: =C29*E29 -> 0 | H29: 0 | I29: =G29*H29 -> 0 | K29: =F29+I29+J29 -> 0
D30: LS | E30: 0 | F30: =C30*E30 -> 0 | H30: 0 | I30: =G30*H30 -> 0 | K30: =F30+I30+J30 -> 0
D31: LS | E31: 0 | F31: =C31*E31 -> 0 | H31: 0 | I31: =G31*H31 -> 0 | K31: =F31+I31+J31 -> 0
D32: LS | E32: 0 | F32: =C32*E32 -> 0 | H32: 0 | I32: =G32*H32 -> 0 | K32: =F32+I32+J32 -> 0
D33: LS | E33: 0 | F33: =C33*E33 -> 0 | H33: 0 | I33: =G33*H33 -> 0 | K33: =F33+I33+J33 -> 0
J35: Sub Total | K35: =SUM(K27:K34) -> 0
A36: CODE | B36: DESCRIPTION | C36: Materials & Equipment | G36: Labor
C37: Qty | D37: Unit | E37: U. Price | F37: Sub Total | G37: MHrs | H37: U. Price | I37: Sub Total | J37: Quote | K37: Total
D38: LS | E38: 0 | F38: =C38*E38 -> 0 | H38: 0 | I38: =G38*H38 -> 0 | K38: =F38+I38+J38 -> 0
D39: LS | E39: 0 | F39: =C39*E39 -> 0 | H39: 0 | I39: =G39*H39 -> 0 | K39: =F39+I39+J39 -> 0
D40: LS | E40: 0 | F40: =C40*E40 -> 0 | H40: 0 | I40: =G40*H40 -> 0 | K40: =F40+I40+J40 -> 0
J43: Sub Total | K43: =SUM(K38:K42) -> 0
A44: CODE | B44: DESCRIPTION | C44: Materials & Equipment | G44: Labor
C45: Qty | D45: Unit | E45: U. Price | F45: Sub Total | G45: MHrs | H45: U. Price | I45: Sub Total | J45: Quote | K45: Total
D46: LS | E46: 0 | F46: =C46*E46 -> 0 | H46: 0 | I46: =G46*H46 -> 0 | K46: =F46+I46+J46 -> 0
D47: LS | E47: 0 | F47: =C47*E47 -> 0 | H47: 0 | I47: =G47*H47 -> 0 | K47: =F47+I47+J47 -> 0
D48: LS | E48: 0 | F48: =C48*E48 -> 0 | H48: 0 | I48: =G48*H48 -> 0 | K48: =F48+I48+J48 -> 0
D49: LS | E49: 0 | F49: =C49*E49 -> 0 | H49: 0 | I49: =G49*H49 -> 0 | K49: =F49+I49+J49 -> 0
J51: Sub Total | K51: =SUM(K46:K50) -> 0
F52: Material Total | G52: Total Hours | I52: Labor Total | J52: Contractor Total | K52: TOTAL
A53: $ / Sq.Ft | B53: TOTAL DIVISION 25
A54: =K54/E6 -> 0 | F54: =SUM(F46:F50,F38:F42,F27:F34,F11:F23) -> 0 | G54: =SUM(G46:G50,G38:G42,G27:G34,G11:G23) -> 0 | I54: =SUM(I46:I50,I38:I42,I27:I34,I11:I23) -> 0 | J54: =SUM(J46:J50,J38:J42,J27:J34,J11:J23) -> 0 | K54: =K51+K43+K35+K24 -> 0

Sheet 26
C1: ='Estimate Summary'!C1:H1 -> 0
G5: Electrical | J5: Schedule
D6: ='Estimate Summary'!C11 -> Area: | E6: ='Estimate Summary'!D11 -> 65592 | F6: ='Estimate Summary'!E11 -> Sq. Ft. | J6: ='1'!J6 -> 60 | K6: Weeks
L8: sub | M8: qty | N8: units | O8: unit $ | P8: ext
A11: CODE | B11: DESCRIPTION | C11: Materials & Equipment | G11: Labor | L11: Sub Contractor | M11: Quote Total | N11: Additional Quote Info
A12: 26 09 00 | B12: Instrumentation and Controls for Electrical Systems | C12: Qty | D12: Unit | E12: U. Price | F12: Sub Total | G12: MHrs | H12: U. Price | I12: Sub Total | J12: Quote | K12: Total
A13: 26 09 13 | B13: Electrical Contractor | D13: LS | E13: 0 | F13: =C13*E13 -> 0 | H13: 0 | I13: =G13*H13 -> 0 | K13: =F13+I13+J13 -> 0 | L13: Amplify | M13: 889500 | N13: Solar Mods Included
D14: LS | E14: 0 | F14: =C14*E14 -> 0 | H14: 0 | I14: =G14*H14 -> 0 | K14: =F14+I14+J14 -> 0 | L14: Lakeview | M14: 1091500
D15: LS | E15: 0 | F15: =C15*E15 -> 0 | H15: 0 | I15: =G15*H15 -> 0 | K15: =F15+I15+J15 -> 0 | L15: Lumar | M15: 886000 | N15: Solar Mods Included
C16: 59 | D16: Unit | E16: =M25 -> 13289.407 | H16: 0 | I16: =G16*H16 -> 0 | J16: =M16 -> 770000 | K16: =F16+I16+J16 -> 770000 | L16: Melco | M16: 770000 | N16: $9,750 additional for Solar
D17: LS | E17: 0 | F17: =C17*E17 -> 0 | H17: 0 | I17: =G17*H17 -> 0 | K17: =F17+I17+J17 -> 0 | L17: Total | M17: 733500
D18: LS | E18: 0 | F18: =C18*E18 -> 0 | H18: 0 | I18: =G18*H18 -> 0 | K18: =F18+I18+J18 -> 0
D19: LS | E19: 0 | F19: =C19*E19 -> 0 | H19: 0 | I19: =G19*H19 -> 0 | K19: =F19+I19+J19 -> 0
D20: LS | E20: 0 | F20: =C20*E20 -> 0 | H20: 0 | I20: =G20*H20 -> 0 | K20: =F20+I20+J20 -> 0
D21: LS | E21: 0 | F21: =C21*E21 -> 0 | H21: 0 | I21: =G21*H21 -> 0 | K21: =F21+I21+J21 -> 0
D22: LS | E22: 0 | F22: =C22*E22 -> 0 | H22: 0 | I22: =G22*H22 -> 0 | K22: =F22+I22+J22 -> 0
D23: LS | E23: 0 | F23: =C23*E23 -> 0 | H23: 0 | I23: =G23*H23 -> 0 | K23: =F23+I23+J23 -> 0 | U23: Exterior | W23: Large | Y23: Pendant | AA23: Small | AC23: Vanity
D24: LS | E24: 0 | F24: =C24*E24 -> 0 | H24: 0 | I24: =G24*H24 -> 0 | K24: =F24+I24+J24 -> 0 | S24: A | T24: 1 | U24: 1 | V24: =$T24*U24 -> 1 | W24: 1 | X24: =$T24*W24 -> 1 | Y24: 3 | Z24: =$T24*Y24 -> 3 | AA24: 17 | AB24: =$T24*AA24 -> 17 | AC24: 1 | AD24: =$T24*AC24 -> 1
L25: Joyce | M25: =784075/59 -> 13289.407 | S25: B | T25: 7 | U25: 1 | V25: =$T25*U25 -> 7 | W25: 1 | X25: =$T25*W25 -> 7 | Y25: 3 | Z25: =$T25*Y25 -> 21 | AA25: 13 | AB25: =$T25*AA25 -> 91 | AC25: 1 | AD25: =$T25*AC25 -> 7
J26: Sub Total | K26: =SUM(K13:K25) -> 770000 | S26: C | T26: 4 | U26: 1 | V26: =$T26*U26 -> 4 | W26: 1 | X26: =$T26*W26 -> 4 | Y26: 3 | Z26: =$T26*Y26 -> 12 | AA26: 14 | AB26: =$T26*AA26 -> 56 | AC26: 1 | AD26: =$T26*AC26 -> 4
A27: CODE | B27: DESCRIPTION | C27: Materials & Equipment | G27: Labor | S27: D | T27: 16 | U27: 1 | V27: =$T27*U27 -> 16 | W27: 2 | X27: =$T27*W27 -> 32 | Y27: 3 | Z27: =$T27*Y27 -> 48 | AA27: 14 | AB27: =$T27*AA27 -> 224 | AC27: 1 | AD27: =$T27*AC27 -> 16
A28: 26 10 00 | B28: Medium-Voltage Electrical Distribution | C28: Qty | D28: Unit | E28: U. Price | F28: Sub Total | G28: MHrs | H28: U. Price | I28: Sub Total | J28: Quote | K28: Total | S28: E | T28: 4 | U28: 1 | V28: =$T28*U28 -> 4 | W28: 3 | X28: =$T28*W28 -> 12 | Y28: 3 | Z28: =$T28*Y28 -> 12 | AA28: 20 | AB28: =$T28*AA28 -> 80 | AC28: 2 | AD28: =$T28*AC28 -> 8
A29: 26 11 00 | B29: Solar Panels | D29: LS | E29: 0 | F29: =C29*E29 -> 0 | H29: 0 | I29: =G29*H29 -> 0 | K29: =F29+I29+J29 -> 0 | L29: Trusun | M29: 124241 | N29: *** In Div 13 | S29: F | T29: 12 | U29: 1 | V29: =$T29*U29 -> 12 | W29: 2 | X29: =$T29*W29 -> 24 | Y29: 3 | Z29: =$T29*Y29 -> 36 | AA29: 20 | AB29: =$T29*AA29 -> 240 | AC29: 2 | AD29: =$T29*AC29 -> 24
A30: 26 12 00 | B30: Electrical Change | D30: LS | E30: 0 | F30: =C30*E30 -> 0 | H30: 0 | I30: =G30*H30 -> 0 | K30: =F30+I30+J30 -> 0 | S30: G | T30: 1 | U30: 1 | V30: =$T30*U30 -> 1 | W30: 1 | X30: =$T30*W30 -> 1 | Y30: 3 | Z30: =$T30*Y30 -> 3 | AA30: 13 | AB30: =$T30*AA30 -> 13 | AC30: 1 | AD30: =$T30*AC30 -> 1
A31: 26 13 00 | B31: Structural Change | D31: LS | E31: 0 | F31: =C31*E31 -> 0 | H31: 0 | I31: =G31*H31 -> 0 | K31: =F31+I31+J31 -> 0 | S31: H | T31: 7 | U31: 1 | V31: =$T31*U31 -> 7 | W31: 2 | X31: =$T31*W31 -> 14 | Y31: 3 | Z31: =$T31*Y31 -> 21 | AA31: 19 | AB31: =$T31*AA31 -> 133 | AC31: 2 | AD31: =$T31*AC31 -> 14
A32: 26 16 00 | B32: Medium-Voltage Metering | D32: LS | E32: 0 | F32: =C32*E32 -> 0 | H32: 0 | I32: =G32*H32 -> 0 | K32: =F32+I32+J32 -> 0 | S32: I | T32: 4 | U32: 1 | V32: =$T32*U32 -> 4 | W32: 1 | X32: =$T32*W32 -> 4 | Y32: 1 | Z32: =$T32*Y32 -> 4 | AA32: 15 | AB32: =$T32*AA32 -> 60 | AC32: 1 | AD32: =$T32*AC32 -> 4
A33: 26 18 00 | B33: Medium-Voltage Circuit Protection Devices | D33: LS | E33: 0 | F33: =C33*E33 -> 0 | H33: 0 | I33: =G33*H33 -> 0 | K33: =F33+I33+J33 -> 0 | S33: BF | T33: 3 | U33: 1 | V33: =$T33*U33 -> 3 | W33: 1 | X33: =$T33*W33 -> 3 | Y33: 1 | Z33: =$T33*Y33 -> 3 | AA33: 16 | AB33: =$T33*AA33 -> 48 | AC33: 1 | AD33: =$T33*AC33 -> 3
D34: LS | E34: 0 | F34: =C34*E34 -> 0 | H34: 0 | I34: =G34*H34 -> 0 | K34: =F34+I34+J34 -> 0 | S34: Total | V34: =SUM(V24:V33) -> 59 | X34: =SUM(X24:X33) -> 102 | Z34: =SUM(Z24:Z33) -> 163 | AB34: =SUM(AB24:AB33) -> 962 | AD34: =SUM(AD24:AD33) -> 82
D35: LS | E35: 0 | F35: =C35*E35 -> 0 | H35: 0 | I35: =G35*H35 -> 0 | K35: =F35+I35+J35 -> 0
J37: Sub Total | K37: =SUM(K29:K36) -> 0
A38: CODE | B38: DESCRIPTION | C38: Materials & Equipment | G38: Labor
A39: 26 50 00 | B39: Lighting | C39: Qty | D39: Unit | E39: U. Price | F39: Sub Total | G39: MHrs | H39: U. Price | I39: Sub Total | J39: Quote | K39: Total
A40: 26 51 00 | B40: Exterior Light | C40: 59 | D40: LS | E40: 80 | F40: =C40*E40 -> 4720 | H40: 0 | I40: =G40*H40 -> 0 | K40: =F40+I40+J40 -> 4720 | L40: Master Interior
A41: 26 52 00 | B41: Large Flush | C41: 102 | D41: LS | E41: 42 | F41: =C41*E41 -> 4284 | H41: 0 | I41: =G41*H41 -> 0 | K41: =F41+I41+J41 -> 4284 | L41: Master Interior
A42: 26 56 00 | B42: Pendant | C42: 163 | D42: LS | E42: 89 | F42: =C42*E42 -> 14507 | H42: 0 | I42: =G42*H42 -> 0 | K42: =F42+I42+J42 -> 14507 | L42: Master Interior
B43: Small Flush | C43: 962 | D43: LS | E43: 21 | F43: =C43*E43 -> 20202 | H43: 0 | I43: =G43*H43 -> 0 | K43: =F43+I43+J43 -> 20202 | L43: Master Interior
B44: Vanity | C44: 82 | D44: LS | E44: 112 | F44: =C44*E44 -> 9184 | H44: 0 | I44: =G44*H44 -> 0 | K44: =F44+I44+J44 -> 9184 | L44: Master Interior
J46: Sub Total | K46: =SUM(K40:K45) -> 52897
A47: CODE | B47: DESCRIPTION | C47: Materials & Equipment | G47: Labor
C48: Qty | D48: Unit | E48: U. Price | F48: Sub Total | G48: MHrs | H48: U. Price | I48: Sub Total | J48: Quote | K48: Total
D49: LS | E49: 0 | F49: =C49*E49 -> 0 | H49: 0 | I49: =G49*H49 -> 0 | K49: =F49+I49+J49 -> 0
D50: LS | E50: 0 | F50: =C50*E50 -> 0 | H50: 0 | I50: =G50*H50 -> 0 | K50: =F50+I50+J50 -> 0
D51: LS | E51: 0 | F51: =C51*E51 -> 0 | H51: 0 | I51: =G51*H51 -> 0 | K51: =F51+I51+J51 -> 0
D52: LS | E52: 0 | F52: =C52*E52 -> 0 | H52: 0 | I52: =G52*H52 -> 0 | K52: =F52+I52+J52 -> 0
D53: LS | E53: 0 | F53: =C53*E53 -> 0 | H53: 0 | I53: =G53*H53 -> 0 | K53: =F53+I53+J53 -> 0
J55: Sub Total | K55: =SUM(K49:K54) -> 0
F56: Material Total | G56: Total Hours | I56: Labor Total | J56: Contractor Total | K56: TOTAL
A57: $ / Sq.Ft | B57: TOTAL DIVISION 26
A58: =K58/E6 -> 12.545692 | F58: =SUM(F49:F54,F40:F45,F29:F36,F13:F25) -> 52897 | G58: =SUM(G49:G54,G40:G45,G29:G36,G13:G25) -> 0 | I58: =SUM(I49:I54,I40:I45,I29:I36,I13:I25) -> 0 | J58: =SUM(J49:J54,J40:J45,J29:J36,J13:J25) -> 770000 | K58: =SUM(K55,K46,K37,K26) -> 822897

Sheet 27
C1: ='Estimate Summary'!C1:H1 -> 0
G5: Communications | J5: Schedule
D6: ='Estimate Summary'!C11 -> Area: | E6: ='Estimate Summary'!D11 -> 65592 | F6: ='Estimate Summary'!E11 -> Sq. Ft. | J6: ='1'!J6 -> 60 | K6: Weeks
A9: CODE | B9: DESCRIPTION | C9: Materials & Equipment | G9: Labor | L9: Sub Contractor | M9: Quote Total | N9: Additional Quote Info
A10: 27 10 00 | B10: Structured Cabling | C10: Qty | D10: Unit | E10: U. Price | F10: Sub Total | G10: MHrs | H10: U. Price | I10: Sub Total | J10: Quote | K10: Total
D11: LS | E11: 0 | F11: =C11*E11 -> 0 | H11: 0 | I11: =G11*H11 -> 0 | K11: =F11+I11+J11 -> 0
D12: LS | E12: 0 | F12: =C12*E12 -> 0 | H12: 0 | I12: =G12*H12 -> 0 | K12: =F12+I12+J12 -> 0
D13: LS | E13: 0 | F13: =C13*E13 -> 0 | H13: 0 | I13: =G13*H13 -> 0 | K13: =F13+I13+J13 -> 0
D14: LS | E14: 0 | F14: =C14*E14 -> 0 | H14: 0 | I14: =G14*H14 -> 0 | K14: =F14+I14+J14 -> 0
D15: LS | E15: 0 | F15: =C15*E15 -> 0 | H15: 0 | I15: =G15*H15 -> 0 | K15: =F15+I15+J15 -> 0
D16: LS | E16: 0 | F16: =C16*E16 -> 0 | H16: 0 | I16: =G16*H16 -> 0 | K16: =F16+I16+J16 -> 0
D17: LS | E17: 0 | F17: =C17*E17 -> 0 | H17: 0 | I17: =G17*H17 -> 0 | K17: =F17+I17+J17 -> 0
D18: LS | E18: 0 | F18: =C18*E18 -> 0 | H18: 0 | I18: =G18*H18 -> 0 | K18: =F18+I18+J18 -> 0
D19: LS | E19: 0 | F19: =C19*E19 -> 0 | H19: 0 | I19: =G19*H19 -> 0 | K19: =F19+I19+J19 -> 0
D20: LS | E20: 0 | F20: =C20*E20 -> 0 | H20: 0 | I20: =G20*H20 -> 0 | K20: =F20+I20+J20 -> 0
D21: LS | E21: 0 | F21: =C21*E21 -> 0 | H21: 0 | I21: =G21*H21 -> 0 | K21: =F21+I21+J21 -> 0
D22: LS | E22: 0 | F22: =C22*E22 -> 0 | H22: 0 | I22: =G22*H22 -> 0 | K22: =F22+I22+J22 -> 0
J24: Sub Total | K24: =SUM(K11:K23) -> 0
A25: CODE | B25: DESCRIPTION | C25: Materials & Equipment | G25: Labor
A26: 27 20 00 | B26: Data Communications | C26: Qty | D26: Unit | E26: U. Price | F26: Sub Total | G26: MHrs | H26: U. Price | I26: Sub Total | J26: Quote | K26: Total
A27: 27 21 00 | B27: Data Communications Network Equipment | D27: LS | E27: 0 | F27: =C27*E27 -> 0 | H27: 0 | I27: =G27*H27 -> 0 | K27: =F27+I27+J27 -> 0
A28: 27 22 00 | B28: Data Communications Hardware | D28: LS | E28: 0 | F28: =C28*E28 -> 0 | H28: 0 | I28: =G28*H28 -> 0 | K28: =F28+I28+J28 -> 0
D29: LS | E29: 0 | F29: =C29*E29 -> 0 | H29: 0 | I29: =G29*H29 -> 0 | K29: =F29+I29+J29 -> 0
D30: LS | E30: 0 | F30: =C30*E30 -> 0 | H30: 0 | I30: =G30*H30 -> 0 | K30: =F30+I30+J30 -> 0
D31: LS | E31: 0 | F31: =C31*E31 -> 0 | H31: 0 | I31: =G31*H31 -> 0 | K31: =F31+I31+J31 -> 0
D32: LS | E32: 0 | F32: =C32*E32 -> 0 | H32: 0 | I32: =G32*H32 -> 0 | K32: =F32+I32+J32 -> 0
D33: LS | E33: 0 | F33: =C33*E33 -> 0 | H33: 0 | I33: =G33*H33 -> 0 | K33: =F33+I33+J33 -> 0
J35: Sub Total | K35: =SUM(K27:K34) -> 0
A36: CODE | B36: DESCRIPTION | C36: Materials & Equipment | G36: Labor
A37: 27 30 00 | B37: Voice Communications | C37: Qty | D37: Unit | E37: U. Price | F37: Sub Total | G37: MHrs | H37: U. Price | I37: Sub Total | J37: Quote | K37: Total
D38: LS | E38: 0 | F38: =C38*E38 -> 0 | H38: 0 | I38: =G38*H38 -> 0 | K38: =F38+I38+J38 -> 0
D39: LS | E39: 0 | F39: =C39*E39 -> 0 | H39: 0 | I39: =G39*H39 -> 0 | K39: =F39+I39+J39 -> 0
D40: LS | E40: 0 | F40: =C40*E40 -> 0 | H40: 0 | I40: =G40*H40 -> 0 | K40: =F40+I40+J40 -> 0
J43: Sub Total | K43: =SUM(K38:K42) -> 0
A44: CODE | B44: DESCRIPTION | C44: Materials & Equipment | G44: Labor
A45: 27 40 00 | B45: Audio-Voice Communications | C45: Qty | D45: Unit | E45: U. Price | F45: Sub Total | G45: MHrs | H45: U. Price | I45: Sub Total | J45: Quote | K45: Total
D46: LS | E46: 0 | F46: =C46*E46 -> 0 | H46: 0 | I46: =G46*H46 -> 0 | K46: =F46+I46+J46 -> 0
D47: LS | E47: 0 | F47: =C47*E47 -> 0 | H47: 0 | I47: =G47*H47 -> 0 | K47: =F47+I47+J47 -> 0
D48: LS | E48: 0 | F48: =C48*E48 -> 0 | H48: 0 | I48: =G48*H48 -> 0 | K48: =F48+I48+J48 -> 0
D49: LS | E49: 0 | F49: =C49*E49 -> 0 | H49: 0 | I49: =G49*H49 -> 0 | K49: =F49+I49+J49 -> 0
D50: LS | E50: 0 | F50: =C50*E50 -> 0 | H50: 0 | I50: =G50*H50 -> 0 | K50: =F50+I50+J50 -> 0
J52: Sub Total | K52: =SUM(K46:K51) -> 0
A53: CODE | B53: DESCRIPTION | C53: Materials & Equipment | G53: Labor
A54: 27 50 00 | B54: Distributed Communications and Monitoring Systems | C54: Qty | D54: Unit | E54: U. Price | F54: Sub Total | G54: MHrs | H54: U. Price | I54: Sub Total | J54: Quote | K54: Total
D55: LS | E55: 0 | F55: =C55*E55 -> 0 | H55: 0 | I55: =G55*H55 -> 0 | K55: =F55+I55+J55 -> 0
D56: LS | E56: 0 | F56: =C56*E56 -> 0 | H56: 0 | I56: =G56*H56 -> 0 | K56: =F56+I56+J56 -> 0
D57: LS | E57: 0 | F57: =C57*E57 -> 0 | H57: 0 | I57: =G57*H57 -> 0 | K57: =F57+I57+J57 -> 0
D58: LS | E58: 0 | F58: =C58*E58 -> 0 | H58: 0 | I58: =G58*H58 -> 0 | K58: =F58+I58+J58 -> 0
D59: LS | E59: 0 | F59: =C59*E59 -> 0 | H59: 0 | I59: =G59*H59 -> 0 | K59: =F59+I59+J59 -> 0
D60: LS | E60: 0 | F60: =C60*E60 -> 0 | H60: 0 | I60: =G60*H60 -> 0 | K60: =F60+I60+J60 -> 0
D61: LS | E61: 0 | F61: =C61*E61 -> 0 | H61: 0 | I61: =G61*H61 -> 0 | K61: =F61+I61+J61 -> 0
J63: Sub Total | K63: =SUM(K55:K62) -> 0
A64: CODE | B64: DESCRIPTION | C64: Materials & Equipment | G64: Labor
C65: Qty | D65: Unit | E65: U. Price | F65: Sub Total | G65: MHrs | H65: U. Price | I65: Sub Total | J65: Quote | K65: Total
D66: LS | E66: 0 | F66: =C66*E66 -> 0 | H66: 0 | I66: =G66*H66 -> 0 | K66: =F66+I66+J66 -> 0
D67: LS | E67: 0 | F67: =C67*E67 -> 0 | H67: 0 | I67: =G67*H67 -> 0 | K67: =F67+I67+J67 -> 0
D68: LS | E68: 0 | F68: =C68*E68 -> 0 | H68: 0 | I68: =G68*H68 -> 0 | K68: =F68+I68+J68 -> 0
D69: LS | E69: 0 | F69: =C69*E69 -> 0 | H69: 0 | I69: =G69*H69 -> 0 | K69: =F69+I69+J69 -> 0
D70: LS | E70: 0 | F70: =C70*E70 -> 0 | H70: 0 | I70: =G70*H70 -> 0 | K70: =F70+I70+J70 -> 0
J72: Sub Total | K72: =SUM(K66:K71) -> 0
A73: CODE | B73: DESCRIPTION | C73: Materials & Equipment | G73: Labor
C74: Qty | D74: Unit | E74: U. Price | F74: Sub Total | G74: MHrs | H74: U. Price | I74: Sub Total | J74: Quote | K74: Total
D75: LS | E75: 0 | F75: =C75*E75 -> 0 | H75: 0 | I75: =G75*H75 -> 0 | K75: =F75+I75+J75 -> 0
D76: LS | E76: 0 | F76: =C76*E76 -> 0 | H76: 0 | I76: =G76*H76 -> 0 | K76: =F76+I76+J76 -> 0
