Workbook
Name Discount: #REF!
Name Discount: #REF!
Name Discount: #REF!
Name Discount: #REF!
Name Discount: #REF!
Name Discount: #REF!
Name Discount: #REF!
Name Discount: #REF!
Name Discount: #REF!
Name Discount: #REF!
Name Discount: #REF!
Name Discount: #REF!
Name Discount: #REF!
Name Discount: #REF!
Name Discount: #REF!

Sheet Cost Data
A1: Division | B1: 2
B2: 01 00 00 | C2: General Requirements
B3: 01 11 00 | C3: Preconstruction Costs | D3: ='1'!K24 -> 52700
B4: 01 31 00 | C4: Project Management and Coordination | D4: ='1'!K35 -> 57200
B5: 01 41 00 | C5: Permits | D5: ='1'!K67 -> 2816.89
B6: 01 45 00 | C6: Quality Control | D6: ='1'!K76 -> 0
B7: 01 51 00 | C7: Temporary Utilities | D7: ='1'!K87 -> 0
B8: 01 52 00 | C8: Construction Facilities | D8: ='1'!K97 -> 2154.4402
B9: 01 54 00 | C9: Construction Aids | D9: ='1'!K105 -> 1395.6286
B10: 01 56 00 | C10: Temporary Barriers & Enclosures | D10: ='1'!K128 -> 3000
B11: 01 74 00 | C11: Cleaning & Waste Management | D11: ='1'!K136 -> 5347
A13: Division | B13: 2
B15: 02 00 00 | C15: Existing Conditions
B16: 02 41 00 | C16: Demolition | D16: ='2'!K26 -> 15786
B17: 02 82 00 | C17: Asbestos Remediation | D17: ='2'!K37 -> 0
B18: 02 83 00 | C18: Trenching | D18: ='2'!K48 -> 1500
A21: Division | B21: 3
B22: 03 00 00 | C22: Concrete
B23: 03 11 00 | C23: Concrete Forming | D23: ='3'!K26 -> 0
B24: 03 20 00 | C24: Concrete Reinforcing | D24: ='3'!K37 -> 0
B25: 03 30 00 | C25: Cast-in-Place Concrete | D25: ='3'!K46 -> 0
B26: 03 35 00 | C26: Concrete Finishing | D26: ='3'!K55 -> 0
B27: 03 40 00 | C27: Precast Concrete | D27: ='3'!K66 -> 0
B28: 03 60 00 | C28: Grouting | D28: ='3'!K75 -> 0
A31: Division | B31: 4
B32: 04 00 00 | C32: Masonry
B33: 04 20 00 | C33: Unit Masonry | D33: ='4'!K26 -> 0
B34: 04 43 00 | C34: Stone Masonry | D34: ='4'!K37 -> 0
A36: Division | B36: 5
B37: 05 00 00 | C37: Metals
B38: 05 12 00 | C38: Structural Steel Framing | D38: ='5'!K26 -> 0
B39: 05 20 00 | C39: Metal Joists | D39: ='5'!K37 -> 0
B40: 05 30 00 | C40: Metal Decking | D40: ='5'!K45 -> 0
B41: 05 51 00 | C41: Metal Stairs | D41: ='5'!K54 -> 0
B42: 05 52 00 | C42: Metal Railings | D42: ='5'!K65 -> 0
B43: 05 59 00 | C43: Metal Specialties | D43: ='5'!K74 -> 0
A46: Division | B46: 6
B47: 06 00 00 | C47: Wood, Plastics, and Composites
B48: 06 11 00 | C48: Framing | D48: ='6'!K19 -> 1300
B49: 06 20 00 | C49: Finish Carpentry | D49: ='6'!K36 -> 1995.8
B50: 06 22 00 | C50: Millwork | D50: ='6'!K51 -> 180875
B51: 06 41 00 | C51: Architechtural Wood Casework | D51: ='6'!K59 -> 0
B52: 06 42 00 | C52: Wood Paneling | D52: ='6'!K68 -> 0
B53: 06 43 00 | C53: Wood Stairs and Railings | D53: ='6'!K79 -> 0
B54: 06 46 00 | C54: Wood Trim | D54: ='6'!K88 -> 0
B55: 06 48 00 | C55: Wood Frames | D55: ='6'!K95 -> 0
A58: Division | B58: 7
B59: 07 00 00 | C59: Thermal and Moisture Protection
B60: 07 21 00 | C60: Thermal Insulation | D60: ='7'!K16 -> 0
B61: 07 24 00 | C61: EIFS | D61: ='7'!K22 -> 0
B62: 07 31 00 | C62: Shingles | D62: ='7'!K27 -> 0
B63: 07 42 00 | C63: Wall Panels | D63: ='7'!K33 -> 0
B64: 07 46 00 | C64: Siding | D64: ='7'!K39 -> 0
B65: 07 52 00 | C65: Modified Bituminous Membrane Roofing | D65: ='7'!K45 -> 0
B66: 07 53 00 | C66: Elastomeric Membrane Roofing | D66: ='7'!K50 -> 0
B67: 07 62 00 | C67: Sheet Metal Flashing and Trim | D67: ='7'!K55 -> 0
B68: 07 63 00 | C68: Sheet Metal Roofing Specialties | D68: ='7'!K60 -> 0
B69: 07 64 00 | C69: Sheet Metal Wall Cladding | D69: ='7'!K66 -> 0
B70: 07 72 00 | C70: Roof Accessories | D70: ='7'!K72 -> 0
B71: 07 81 00 | C71: Applied Fireproofing | D71: ='7'!K78 -> 8446
B72: 07 90 00 | C72: Joint Protection | D72: ='7'!K84 -> 0
A74: Division | B74: 8
B75: 08 00 00 | C75: Openings
B76: 08 11 00 | C76: Metal Doors and Frames | D76: ='8'!K18 -> 20485
B77: 08 14 00 | C77: Wood Doors | D77: ='8'!K24 -> 0
B78: 08 31 00 | C78: Access Doors and Panels | D78: ='8'!K29 -> 0
B79: 08 32 00 | C79: Sliding Gates | D79: ='8'!K35 -> 0
B80: 08 33 00 | C80: Coiling Doors and Drilles | D80: ='8'!K41 -> 0
B81: 08 34 00 | C81: Special Function Doors | D81: ='8'!K47 -> 0
B82: 08 38 00 | C82: Traffic Doors | D82: ='8'!K52 -> 0
B83: 08 41 00 | C83: Entrances and Storefronts | D83: ='8'!K57 -> 0
B84: 08 44 00 | C84: Curtain Wall and Glazed Assemblies | D84: ='8'!K62 -> 0
B85: 08 50 00 | C85: Windows | D85: ='8'!K69 -> 0
B86: 08 70 00 | C86: Hardware | D86: ='8'!K75 -> 0
B87: 08 81 00 | C87: Glass Glazing | D87: ='8'!K81 -> 2225
B88: 08 83 00 | C88: Mirrors | D88: ='8'!K87 -> 0
B89: 08 87 00 | C89: Glazing Surface Films | D89: ='8'!K93 -> 0
B90: 08 91 00 | C90: Louvers | D90: ='8'!K99 -> 0
A92: Division | B92: 9
B93: 09 00 00 | C93: Finishes
B94: 09 20 00 | C94: Plaster and Gypsum Board | D94: ='9'!K18 -> 61750
B95: 09 30 00 | C95: Tiling | D95: ='9'!K26 -> 0
B96: 09 50 00 | C96: Ceiling | D96: ='9'!K32 -> 0
B97: 09 60 00 | C97: Flooring | D97: ='9'!K47 -> 26169
B98: 09 72 00 | C98: Wall Coverings | D98: ='9'!K53 -> 0
B99: 09 91 00 | C99: Painting | D99: ='9'!K62 -> 12192.44
A102: Division | B102: 10
B103: 10 00 00 | C103: Specialties
B104: 10 11 00 | C104: Visual Display Units | D104: ='10'!K17 -> 0
B105: 10 14 00 | C105: Signage | D105: ='10'!K25 -> 0
B106: 10 20 00 | C106: Interior Specialties | D106: ='10'!K38 -> 11690
B107: 10 44 00 | C107: Fire Protection Specialties | D107: ='10'!K44 -> 0
B108: 10 51 00 | C108: Lockers | D108: ='10'!K51 -> 0
B109: 10 57 00 | C109: Wardrobe and Closet Specialties | D109: ='10'!K57 -> 0
B110: 10 70 00 | C110: Exterior Specialties | D110: ='10'!K63 -> 0
A112: Division | B112: 11
B113: 11 00 00 | C113: Equipment
B114: 11 11 00 | C114: Vehicle Service Equipment | D114: ='11'!K24 -> 0
B115: 11 13 00 | C115: Loading Dock Equipment | D115: ='11'!K35 -> 0
B116: 11 30 00 | C116: Residential Equipment | D116: ='11'!K43 -> 0
...

Sheet Cost Report
B1: Division | C1: Sub - Division | D1: Discription | E1: Cost
B2: 01 00 00 | D2: General Requirements | E2: ='Estimate Summary'!H15 -> 125764
B3: 01 11 00 | D3: Preconstruction Costs | E3: ='1'!K24 -> 52700
B4: 01 31 00 | D4: Project Management and Coordination | E4: ='1'!K35 -> 57200
B5: 01 31 00 | C5: 01 31 01 | D5: Senior Construction Manager | E5: ='1'!K27 -> 0
B6: 01 31 00 | C6: 01 31 02 | D6: Senior Estimator | E6: ='1'!K28 -> 0
B7: 01 31 00 | C7: 01 31 03 | D7: Senior Project Manager | E7: ='1'!K29 -> 13000
B8: 01 31 00 | C8: 01 31 04 | D8: Project Coordinator | E8: ='1'!K30 -> 0
B9: 01 31 00 | C9: 01 31 05 | D9: Project Superintendent | E9: ='1'!K31 -> 44200
B10: 01 31 00 | C10: 01 31 06 | D10: Project Foreman | E10: ='1'!K32 -> 0
B11: 01 32 00 | C11: 01 32 00 | D11: Travel
B12: 01 41 00 | D12: Permits | E12: ='1'!K67 -> 2816.89
B13: 01 45 00 | D13: Quality Control | E13: ='1'!K76 -> 0
B14: 01 51 00 | D14: Temporary Utilities | E14: ='1'!K87 -> 0
B15: 01 52 00 | D15: Construction Facilities | E15: ='1'!K97 -> 2154.4402
B16: 01 52 00 | C16: 01 52 01 | D16: Construction Field Office | E16: ='1'!K90 -> 0
B17: 01 52 00 | C17: 01 52 02 | D17: Sanitary Facilities | E17: ='1'!K92 -> 0
B18: 01 52 00 | C18: 01 52 03 | D18: Drawing Reprographics | E18: ='1'!K93 -> 329.44023
B19: 01 52 00 | C19: 01 52 04 | D19: First-Aid / Safety | E19: ='1'!K94 -> 1625
B20: 01 52 00 | C20: 01 52 05 | D20: Job Sign | E20: ='1'!K95 -> 200
B21: 01 54 00 | D21: Construction Aids | E21: ='1'!K105 -> 1395.6286
B22: 01 55 00 | C22: 01 55 00 | D22: Winter Conditions
B23: 01 56 00 | D23: Temporary Barriers & Enclosures | E23: ='1'!K128 -> 3000
B24: 01 74 00 | D24: Cleaning & Waste Management | E24: ='1'!K136 -> 5347
B25: 01 74 00 | C25: 01 74 01 | D25: Progress Cleaning | E25: ='1'!K131 -> 0
B26: 01 74 00 | C26: 01 74 02 | D26: Site Maintenance | E26: ='1'!K132 -> 0
B27: 01 74 00 | C27: 01 74 03 | D27: Construction Waste Mgmt & Disposal | E27: ='1'!K133 -> 3600
B28: 01 74 00 | C28: 01 74 04 | D28: Final Cleaning | E28: ='1'!K134 -> 1747
B29: 02 00 00 | D29: Existing Conditions | E29: ='Estimate Summary'!H17 -> 17286
B30: 02 41 00 | D30: Demolition | E30: ='2'!K26 -> 15786
B31: 02 82 00 | D31: Asbestos Remediation | E31: ='2'!K37 -> 0
B32: 02 83 00 | D32: Trenching | E32: ='2'!K48 -> 1500
B33: 03 00 00 | D33: Concrete | E33: ='Estimate Summary'!H19 -> 0
B34: 03 11 00 | D34: Concrete Forming | E34: ='3'!K26 -> 0
B35: 03 20 00 | D35: Concrete Reinforcing | E35: ='3'!K37 -> 0
B36: 03 30 00 | D36: Cast-in-Place Concrete | E36: ='3'!K46 -> 0
B37: 03 35 00 | D37: Concrete Finishing | E37: ='3'!K55 -> 0
B38: 03 40 00 | D38: Precast Concrete | E38: ='3'!K66 -> 0
B39: 03 60 00 | D39: Foundation Materials | E39: ='3'!K75 -> 0
B40: 03 60 00 | C40: 03 60 01 | D40: Insulation | E40: ='3'!K69 -> 0
B41: 03 60 00 | C41: 03 60 02 | D41: Vapour Barrier | E41: ='3'!K70 -> 0
B42: 04 00 00 | D42: Masonry | E42: ='Estimate Summary'!H21 -> 0
B43: 04 20 00 | D43: Unit Masonry | E43: ='4'!K26 -> 0
B44: 04 43 00 | D44: Stone Masonry | E44: ='4'!K37 -> 0
B45: 05 00 00 | D45: Metals | E45: ='Estimate Summary'!H23 -> 0
B46: 05 12 00 | D46: Structural Steel Framing | E46: ='5'!K26 -> 0
B47: 05 20 00 | D47: Metal Joists | E47: ='5'!K37 -> 0
B48: 05 30 00 | D48: Metal Decking | E48: ='5'!K45 -> 0
B49: 05 51 00 | D49: Metal Stairs | E49: ='5'!K54 -> 0
B50: 05 52 00 | D50: Metal Railings | E50: ='5'!K65 -> 0
B51: 05 59 00 | D51: Metal Specialties | E51: ='5'!K74 -> 0
B52: 06 00 00 | D52: Wood, Plastics, and Composites | E52: ='Estimate Summary'!H25 -> 184170.8
B53: 06 11 00 | D53: Framing Labour | E53: ='6'!K19 -> 1300
B54: 06 20 00 | D54: Framing Material | E54: ='6'!K36 -> 1995.8
B55: 06 22 00 | D55: Millwork | E55: ='6'!K51 -> 180875
B56: 06 41 00 | D56: Architechtural Wood Casework | E56: ='6'!K59 -> 0
B57: 06 42 00 | D57: Wood Paneling | E57: ='6'!K68 -> 0
B58: 06 43 00 | D58: Wood Stairs and Railings | E58: ='6'!K79 -> 0
B59: 06 46 00 | D59: Wood Trim | E59: ='6'!K88 -> 0
B60: 06 48 00 | D60: Wood Frames | E60: ='6'!K95 -> 0
B61: 07 00 00 | D61: Thermal and Moisture Protection | E61: ='Estimate Summary'!H27 -> 8446
B62: 07 21 00 | D62: Thermal Insulation | E62: ='7'!K16 -> 0
B63: 07 24 00 | D63: EIFS | E63: ='7'!K22 -> 0
B64: 07 31 00 | D64: Shingles | E64: ='7'!K27 -> 0
B65: 07 42 00 | D65: Wall Panels | E65: ='7'!K33 -> 0
B66: 07 46 00 | D66: Siding | E66: ='7'!K39 -> 0
B67: 07 52 00 | D67: Modified Bituminous Membrane Roofing | E67: ='7'!K45 -> 0
B68: 07 53 00 | D68: Elastomeric Membrane Roofing | E68: ='7'!K50 -> 0
B69: 07 62 00 | D69: Sheet Metal Flashing and Trim | E69: ='7'!K55 -> 0
B70: 07 63 00 | D70: Sheet Metal Roofing Specialties | E70: ='7'!K60 -> 0
B71: 07 64 00 | D71: Sheet Metal Wall Cladding | E71: ='7'!K66 -> 0
B72: 07 72 00 | D72: Roof Accessories | E72: ='7'!K72 -> 0
B73: 07 81 00 | D73: Applied Fireproofing | E73: ='7'!K78 -> 8446
B74: 07 90 00 | D74: Joint Protection | E74: ='7'!K84 -> 0
B75: 08 00 00 | D75: Openings | E75: ='Estimate Summary'!H29 -> 22710
B76: 08 11 00 | D76: Metal Doors and Frames | E76: ='8'!K18 -> 20485
B77: 08 14 00 | D77: Wood Doors | E77: ='8'!K24 -> 0
B78: 08 31 00 | D78: Access Doors and Panels | E78: ='8'!K29 -> 0
B79: 08 32 00 | D79: Sliding Gates | E79: ='8'!K35 -> 0
B80: 08 33 00 | D80: Coiling Doors and Drilles | E80: ='8'!K41 -> 0
B81: 08 34 00 | D81: Special Function Doors | E81: ='8'!K47 -> 0
B82: 08 38 00 | D82: Traffic Doors | E82: ='8'!K52 -> 0
B83: 08 41 00 | D83: Entrances and Storefronts | E83: ='8'!K57 -> 0
B84: 08 44 00 | D84: Curtain Wall and Glazed Assemblies | E84: ='8'!K62 -> 0
B85: 08 50 00 | D85: Windows | E85: ='8'!K69 -> 0
B86: 08 70 00 | D86: Hardware | E86: ='8'!K75 -> 0
B87: 08 81 00 | D87: Glass Glazing | E87: ='8'!K81 -> 2225
B88: 08 83 00 | D88: Mirrors | E88: ='8'!K87 -> 0
B89: 08 87 00 | D89: Glazing Surface Films | E89: ='8'!K93 -> 0
B90: 08 91 00 | D90: Louvers | E90: ='8'!K99 -> 0
B91: 09 00 00 | D91: Finishes | E91: ='Estimate Summary'!H31 -> 100111.44
B92: 09 20 00 | D92: Plaster and Gypsum Board | E92: ='9'!K18 -> 61750
B93: 09 30 00 | D93: Tiling | E93: ='9'!K26 -> 0
B94: 09 50 00 | D94: Ceiling | E94: ='9'!K32 -> 0
B95: 09 60 00 | D95: Flooring | E95: ='9'!K47 -> 26169
B96: 09 60 00 | C96: 09 61 00 | D96: Concrete Floor Polishing | E96: ='9'!K35 -> 0
B97: 09 60 00 | C97: 09 62 00 | D97: Specialty Flooring | E97: ='9'!K37 -> 0
B98: 09 60 00 | C98: 09 64 00 | D98: Wood Flooring | E98: ='9'!K38 -> 0
B99: 09 60 00 | C99: 09 65 00 | D99: VCT | E99: ='9'!K39 -> 22675
B100: 09 60 00 | C100: 09 67 00 | D100: LVT | E100: ='9'!K40 -> 3494
...

Sheet DATA
B2: Quarter | C2: Column1 | D2: Province | H2: Project Definition | J2: Contract Type | K2: Payment Method | M2: A | N2: >5M
B3: Q1 | D3: NB | H3: Multi Residential | J3: CCDC 2 | K3: Stipulated Price | M3: B | N3: 2-5M
B4: Q2 | D4: PEI | H4: Office | J4: CCDC 5B | K4: Fixed Fee | M4: C | N4: 500K - 2M | R4: Status | T4: Result
B5: Q3 | D5: NS | H5: Retail | J5: CCDC 5A | M5: D | N5: 100K - 500K | R5: Awarded | T5: Successful
B6: Q4 | D6: Other | H6: Food | J6: Design Build | M6: E | N6: less than 100K | R6: Not Awarded | T6: Unsuccessful
R7: Pending
A10: Closing Date | B10: Budget Year | C10: Quarter | D10: Province | E10: City/Town | F10: Estimate Number | G10: Estimate Name | H10: Type of Construction | I10: Area | J10: Contract Type | K10: Payment Method | L10: Estimate Price | M10: Price Category | N10: Schedule | O10: Soft Cost | P10: Cost per Week | Q10: Margin | R10: Status | S10: Bid Docs | T10: Successful / Unsuccessful
A11: =+'Estimate Summary'!B3 -> 46030 | B11: =+'Estimate Summary'!B7 -> 2026 | C11: =+'Estimate Summary'!B8 -> Q1 | D11: =+'Estimate Summary'!B5 -> NB | E11: ='Estimate Summary'!B6 -> Moncton | F11: ='Estimate Summary'!B4 -> 3041 | G11: ='Estimate Summary'!D5 -> Dr. Goel Dental Office | H11: =+'Estimate Summary'!F8 -> 0 | I11: =+'Estimate Summary'!D11 -> 1747 | J11: ='Estimate Summary'!D7 -> CCDC 5B | K11: =+'Estimate Summary'!D8 -> Fixed Fee | L11: =+'Estimate Summary'!D75 -> 760983.56 | M11: =IF(L11<100000,"E",IF(L11<500000,"D",IF(L11<2000000,"C",IF(L11<5000000,"B",IF(L11>=5000000,"A"))))) -> C | N11: ='Estimate Summary'!D81 -> 13 | O11: ='Estimate Summary'!D82 -> 95539.74 | P11: ='Estimate Summary'!E82 -> 7349.2108 | Q11: ='Estimate Summary'!D84 -> 0.12554771 | R11: ='Estimate Summary'!F6 -> 0 | S11: ='Estimate Summary'!F5 -> 0 | T11: ='Estimate Summary'!F7 -> 0

Sheet Estimate Version Comparison
B2: ='Estimate Summary'!D5 -> Dr. Goel Dental Office | I2: CLIENT SUMMARY
B3: ='Estimate Summary'!D6 -> Dr. Goel
B4: Date: | C4: ='Estimate Summary'!B3 -> 46030
D7: 45839 | G7: 46023 | H7: ='Estimate Summary'!G8 -> 0
B8: 01 00 00 | C8: General Requirements | E8: =SUM(D9:D17) -> 126486.21 | H8: =SUM(G9:G17) -> 125764 | J8: =IF(H8>E8,"Increase","Decrease or No Change") -> Decrease or No Change | K8: =H8-E8 -> -722.20365
B9: 01 11 00 | C9: Preconstruction Costs | D9: 56200 | G9: ='1'!K24 -> 52700
B10: 01 31 00 | C10: Project Management and Coordination | D10: 57200 | G10: ='1'!K35 -> 57200
B11: 01 41 00 | C11: Permits | D11: 2914.7553 | G11: ='1'!K67 -> 2816.89
B12: 01 45 00 | C12: Insurance | D12: 699.54126 | G12: ='1'!K45 -> 1150.0459
B13: 01 51 00 | C13: Temporary Utilities | D13: 0 | G13: ='1'!K87 -> 0
B14: 01 52 00 | C14: Construction Facilities | D14: 2025.3894 | G14: ='1'!K97 -> 2154.4402
B15: 01 54 00 | C15: Construction Aids | D15: 848.92247 | G15: ='1'!K105 -> 1395.6286
B16: 01 56 00 | C16: Temporary Barriers & Enclosures | D16: 3000 | G16: ='1'!K128 -> 3000
B17: 01 74 00 | C17: Cleaning & Waste Management | D17: 3597.6 | G17: ='1'!K136 -> 5347
B19: 02 00 00 | C19: Existing Conditions | E19: =SUM(D20:D22) -> 16615 | H19: =SUM(G20:G22) -> 11586 | J19: =IF(H19>E19,"Increase","Decrease or No Change") -> Decrease or No Change | K19: =H19-E19 -> -5029
B20: 02 41 00 | C20: Demolition | D20: 8735 | G20: ='2'!K13 -> 10086
B21: 02 82 00 | C21: Asbestos Remediation | D21: 0 | G21: ='2'!K37 -> 0
B22: 02 83 00 | C22: Trenching | D22: 7880 | G22: ='2'!K48 -> 1500
B24: 03 00 00 | C24: Concrete | E24: =SUM(D25:D29) -> 0 | H24: =SUM(G25:G29) -> 0 | J24: =IF(H24>E24,"Increase","Decrease or No Change") -> Decrease or No Change | K24: =H24-E24 -> 0
B25: 03 11 00 | C25: Concrete Forming | D25: 0 | G25: ='3'!K26 -> 0
B26: 03 20 00 | C26: Concrete Reinforcing | D26: 0 | G26: ='3'!K37 -> 0
B27: 03 30 00 | C27: Cast-in-Place Concrete | D27: 0 | G27: ='3'!K46+'3'!K55 -> 0
B28: 03 40 00 | C28: Precast Concrete | D28: 0 | G28: ='3'!K66 -> 0
B29: 03 60 00 | C29: Grouting | D29: 0 | G29: ='3'!K75 -> 0
B31: 04 00 00 | C31: Masonry | E31: =SUM(D32:D33) -> 0 | H31: =SUM(G32:G33) -> 0 | J31: =IF(H31>E31,"Increase","Decrease or No Change") -> Decrease or No Change | K31: =H31-E31 -> 0
B32: 04 20 00 | C32: Unit Masonry | D32: 0 | G32: ='4'!K26 -> 0
B33: 04 40 00 | C33: Stone Assemblies | D33: 0 | G33: ='4'!K37 -> 0
B35: 05 00 00 | C35: Metals | E35: =SUM(D36:D39) -> 0 | H35: =SUM(G36:G39) -> 0 | J35: =IF(H35>E35,"Increase","Decrease or No Change") -> Decrease or No Change | K35: =H35-E35 -> 0
B36: 05 12 00 | C36: Structural Steel Framing | D36: 0 | G36: ='5'!K26 -> 0
B37: 05 20 00 | C37: Metal Joists | D37: 0 | G37: ='5'!K37 -> 0
B38: 05 30 00 | C38: Metal Decking | D38: 0 | G38: ='5'!K45 -> 0
B39: 05 50 00 | C39: Metal Fabrications | D39: 0 | G39: ='5'!K54+'5'!K65+'5'!K74 -> 0
B41: 06 00 00 | C41: Wood, Plastics, and Composites | E41: =SUM(D42:D45) -> 57936.36 | H41: =SUM(G42:G45) -> 184170.8 | J41: =IF(H41>E41,"Increase","Decrease or No Change") -> Increase | K41: =H41-E41 -> 126234.44
B42: 06 11 00 | C42: Framing Labour | D42: 0 | G42: ='6'!K19 -> 1300
B43: 06 11 00 | C43: Framing Material | D43: 2836.36 | G43: ='6'!K36 -> 1995.8
B44: 06 22 00 | C44: Millwork | D44: 55100 | G44: ='6'!K51 -> 180875 | J44: All Laminates
B45: 06 40 00 | C45: Architectural Woodwork | D45: 0 | G45: ='6'!K59+'6'!K68+'6'!K79+'6'!K88+'6'!K95 -> 0
B47: 07 00 00 | C47: Thermal and Moisture Protection | E47: =SUM(D48:D57) -> 0 | H47: =SUM(G48:G57) -> 8446 | J47: =IF(H47>E47,"Increase","Decrease or No Change") -> Increase | K47: =H47-E47 -> 8446
B48: 07 21 00 | C48: Thermal Insulation | D48: 0 | G48: ='7'!K16 -> 0
B49: 07 24 00 | C49: EIFS | D49: 0 | G49: ='7'!K22 -> 0
B50: 07 31 00 | C50: Shingles | D50: 0 | G50: ='7'!K27 -> 0
B51: 07 42 00 | C51: Wall Panels | D51: 0 | G51: ='7'!K33 -> 0
B52: 07 46 00 | C52: Siding | D52: 0 | G52: ='7'!K39 -> 0
B53: 07 50 00 | C53: Membrane Roofing | D53: 0 | G53: ='7'!K45+'7'!K50 -> 0
B54: 07 60 00 | C54: Flashing and Sheet Metal | D54: 0 | G54: ='7'!K55+'7'!K60+'7'!K66 -> 0
B55: 07 72 00 | C55: Roof Accessories | D55: 0 | G55: ='7'!K72 -> 0
B56: 07 80 00 | C56: Smoke and Fire Protection | D56: 0 | G56: ='7'!K78 -> 8446
B57: 07 90 00 | C57: Joint Protection | D57: 0 | G57: ='7'!K84 -> 0
B59: 08 00 00 | C59: Openings | E59: =SUM(D60:D66) -> 44720 | H59: =SUM(G60:G66) -> 22710 | J59: =IF(H59>E59,"Increase","Decrease or No Change") -> Decrease or No Change | K59: =H59-E59 -> -22010
B60: 08 10 00 | C60: Doors and Frames | D60: 11865 | G60: ='8'!K18+'8'!K24 -> 20485
B61: 08 30 00 | C61: Speciality Doors and Frames | D61: 900 | G61: ='8'!K29+'8'!K35+'8'!K41+'8'!K47+'8'!K52 -> 0
B62: 08 40 00 | C62: Store Fronts and Curtainwalls | D62: 0 | G62: ='8'!K57+'8'!K62 -> 0
B63: 08 50 00 | C63: Windows | D63: 0 | G63: ='8'!K69 -> 0
B64: 08 70 00 | C64: Hardeware | D64: 0 | G64: ='8'!K75 -> 0
B65: 08 80 00 | C65: Glazing | D65: 31955 | G65: ='8'!K81+'8'!K87+'8'!K93 -> 2225
B66: 08 90 00 | C66: Louvers | D66: 0 | G66: ='8'!K99 -> 0
B68: 09 00 00 | C68: Finishes | E68: =SUM(D69:D74) -> 97498.62 | H68: =SUM(G69:G74) -> 100111.44 | J68: =IF(H68>E68,"Increase","Decrease or No Change") -> Increase | K68: =H68-E68 -> 2612.82
B69: 09 20 00 | C69: Plaster and Gypsum Board | D69: 53159 | G69: ='9'!K18 -> 61750
B70: 09 30 00 | C70: Tiling | D70: 1608 | G70: ='9'!K26 -> 0
B71: 09 50 00 | C71: Ceiling | D71: 10482 | G71: ='9'!K32 -> 0
B72: 09 60 00 | C72: Flooring | D72: 20964 | G72: ='9'!K47 -> 26169
B73: 09 70 00 | C73: Wall Finishes | D73: 0 | G73: ='9'!K53 -> 0
B74: 09 90 00 | C74: Painting | D74: 11285.62 | G74: ='9'!K62 -> 12192.44
B76: 10 00 00 | C76: Specialties | E76: =SUM(D77:D82) -> 7674.6667 | H76: =SUM(G77:G82) -> 11690 | J76: =IF(H76>E76,"Increase","Decrease or No Change") -> Increase | K76: =H76-E76 -> 4015.3333
B77: 10 11 00 | C77: Visual Display Units | D77: 0 | G77: ='10'!K17 -> 0
B78: 10 14 00 | C78: Signage | D78: 0 | G78: ='10'!K25 -> 0
B79: 10 20 00 | C79: Interior Specialties | D79: 7674.6667 | G79: ='10'!K38 -> 11690
B80: 10 40 00 | C80: Safety Specialties | D80: 0 | G80: ='10'!K44 -> 0
B81: 10 50 00 | C81: Storage Specialties | D81: 0 | G81: ='10'!K51 -> 0
B82: 10 70 00 | C82: Exterior Specialties | D82: 0 | G82: ='10'!K63 -> 0
B86: 11 00 00 | C86: Equipment | E86: =SUM(D87:D90) -> 0 | H86: =SUM(G87:G90) -> 0
B87: 11 10 00 | C87: Vehicle Equipment | D87: 0 | G87: ='11'!K24+'11'!K35 -> 0
B88: 11 30 00 | C88: Residential Equipment | D88: 0 | G88: ='11'!K43 -> 0 | J88: =IF(H88>E88,"Increase","Decrease or No Change") -> Decrease or No Change | K88: =H88-E88 -> 0
B89: 11 40 00 | C89: Food Service Equipment | D89: 0 | G89: ='11'!K52+'11'!K63 -> 0
B90: 11 50 00 | C90: Educational & Lab Equipment | D90: 0 | G90: ='11'!K72+'11'!K79 -> 0
B92: 12 00 00 | C92: Furnishings | E92: =SUM(D93:D94) -> 0 | H92: =SUM(G93:G94) -> 0 | J92: =IF(H92>E92,"Increase","Decrease or No Change") -> Decrease or No Change | K92: =H92-E92 -> 0
B93: 12 20 00 | C93: Window Treatments | D93: 0 | G93: ='12'!K24+'12'!K35 -> 0
B94: 12 30 00 | C94: Casework | D94: 0 | G94: ='12'!K43+'12'!K52+'12'!K63+'12'!K72 -> 0
B96: 13 00 00 | C96: Special Construction | E96: ='Estimate Summary'!E39 -> 0 | H96: ='Estimate Summary'!H39 -> 0 | J96: =IF(H96>E96,"Increase","Decrease or No Change") -> Decrease or No Change | K96: =H96-E96 -> 0
B98: 14 00 00 | C98: Conveying Equipment | E98: =SUM(D99:D100) -> 0 | H98: =SUM(G99:G100) -> 0 | J98: =IF(H98>E98,"Increase","Decrease or No Change") -> Decrease or No Change | K98: =H98-E98 -> 0
B99: 14 20 00 | C99: Elevators | D99: 0 | G99: ='14'!K24 -> 0
B100: 14 40 00 | C100: Lifts | D100: 0 | G100: ='14'!K35+'14'!K43 -> 0
B102: 21 00 00 | C102: Fire Suppression | E102: =D103 -> 6114.5 | H102: =G103 -> 6938 | J102: =IF(H102>E102,"Increase","Decrease or No Change") -> Increase | K102: =H102-E102 -> 823.5
B103: 21 10 00 | C103: Water-Based Fire-Suppression System | D103: 6114.5 | G103: ='21'!K24 -> 6938
B105: 22 00 00 | C105: Plumbing | E105: =SUM(D106:D108) -> 51251.739 | H105: =SUM(G106:G108) -> 129800 | J105: =IF(H105>E105,"Increase","Decrease or No Change") -> Increase | K105: =H105-E105 -> 78548.261
B106: 22 10 00 | C106: Plumbing Piping and Fixtures | D106: 51251.739 | G106: ='22'!K24 -> 129800
B107: 22 30 00 | C107: Plumbing Equipment | D107: 0 | G107: ='22'!K35 -> 0
B108: 22 40 00 | C108: Plumbing Fixtures | D108: 0 | G108: ='22'!K46+'22'!K67+'22'!K74 -> 0
B110: 23 00 00 | C110: HVAC | E110: =SUM(D111:D118) -> 20964 | H110: =SUM(G111:G118) -> 37030 | J110: =IF(H110>E110,"Increase","Decrease or No Change") -> Increase | K110: =H110-E110 -> 16066
B111: 23 07 00 | C111: HVAC Installation | D111: 20964 | G111: ='23'!K18 -> 37030
B112: 23 08 00 | C112: Commissioning of HVAC | D112: 0 | G112: ='23'!K25 -> 0
B113: 23 09 00 | C113: Instrumentation and Control for HVAC | D113: 0 | G113: ='23'!K31 -> 0
B114: 23 10 00 | C114: Facility Fuel System | D114: 0 | G114: ='23'!K38+'23'!K46 -> 0
B115: 23 20 00 | C115: HVAC Piping and Pumps | D115: 0 | G115: ='23'!K53+'23'!K58 -> 0
B116: 23 30 00 | C116: HVAC Air Distribution | D116: 0 | G116: ='23'!K73 -> 0
B117: 23 70 00 | C117: Central HVAC Equipment | D117: 0 | G117: ='23'!K79 -> 0
B118: 23 80 00 | C118: Decentralized HVAC Equipment | D118: 0 | G118: ='23'!K85+'23'!K91 -> 0
B120: 25 00 00 | C120: Integrated Automation | E120: ='Estimate Summary'!E49 -> 0 | H120: ='Estimate Summary'!H49 -> 0 | J120: =IF(H120>E120,"Increase","Decrease or No Change") -> Decrease or No Change | K120: =H120-E120 -> 0
B122: 26 00 00 | C122: Electrical | E122: =SUM(D123:D125) -> 53096.571 | H122: =SUM(G123:G125) -> 80800 | J122: =IF(H122>E122,"Increase","Decrease or No Change") -> Increase | K122: =H122-E122 -> 27703.429
B123: 26 09 00 | C123: Electrical Distribution and Lighting | D123: 53096.571 | G123: ='26'!K26 -> 80800
...

Sheet Client  Detailed Summary 
B3: ='Estimate Summary'!D5 -> Dr. Goel Dental Office | F3: CLIENT SUMMARY
B4: 585 Mapleton Drive
B5: Date: | C5: ='Estimate Summary'!B3 -> 46030
B7: 01 00 00 | C7: General Requirements | H7: =SUM(G8:G17) -> 125764
B8: 01 11 00 | C8: Preconstruction Costs - Design | G8: ='1'!K24 -> 52700
B9: 01 31 00 | C9: Project Management and Coordination | G9: ='1'!K35 -> 57200
B10: 01 32 00 | C10: Insurance | G10: ='1'!K45+'1'!K56 -> 1150.0459
B11: 01 41 00 | C11: Permits | G11: ='1'!K67 -> 2816.89
B12: 01 45 00 | C12: Quality Control | G12: ='1'!K76 -> 0
B13: 01 51 00 | C13: Temporary Utilities | G13: ='1'!K87 -> 0
B14: 01 52 00 | C14: Construction Facilities | G14: ='1'!K97 -> 2154.4402
B15: 01 54 00 | C15: Construction Aids & Winter Conditions | G15: ='1'!K105+'1'!K120 -> 1395.6286
B16: 01 56 00 | C16: Temporary Barriers & Enclosures | G16: ='1'!K128 -> 3000
B17: 01 74 00 | C17: Cleaning & Waste Management | G17: ='1'!K136 -> 5347
B19: 02 00 00 | C19: Existing Conditions | H19: =SUM(G20:G22) -> 17286
B20: 02 41 00 | C20: Demolition and Core Drilling | G20: ='2'!K26 -> 15786
B21: 02 82 00 | C21: Asbestos Remediation | G21: ='2'!K37 -> 0
B22: 02 83 00 | C22: Core Drilling | G22: ='2'!K48 -> 1500
B24: 03 00 00 | C24: Concrete | H24: =SUM(G25:G29) -> 0
B25: 03 11 00 | C25: Concrete Forming | G25: ='3'!K26 -> 0
B26: 03 20 00 | C26: Concrete Reinforcing | G26: ='3'!K37 -> 0
B27: 03 30 00 | C27: Cast-in-Place Concrete | G27: ='3'!K46+'3'!K55 -> 0
B28: 03 40 00 | C28: Precast Concrete | G28: ='3'!K66 -> 0
B29: 03 60 00 | C29: Grouting | G29: ='3'!K75 -> 0
B31: 04 00 00 | C31: Masonry | H31: =SUM(G32:G33) -> 0
B32: 04 20 00 | C32: Unit Masonry | G32: ='4'!K26 -> 0
B33: 04 40 00 | C33: Stone Assemblies | G33: ='4'!K37 -> 0
B35: 05 00 00 | C35: Metals | H35: =SUM(G36:G39) -> 0
B36: 05 12 00 | C36: Structural Steel Framing | G36: ='5'!K26 -> 0
B37: 05 20 00 | C37: Metal Joists | G37: ='5'!K37 -> 0
B38: 05 30 00 | C38: Metal Decking | G38: ='5'!K45 -> 0
B39: 05 50 00 | C39: Metal Fabrications | G39: ='5'!K54+'5'!K65+'5'!K74 -> 0
B41: 06 00 00 | C41: Wood, Plastics, and Composites | H41: =SUM(G42:G45) -> 184170.8
B42: 06 11 00 | C42: Wood Labour | G42: ='6'!K19 -> 1300
B43: 06 11 00 | C43: Wood materials | G43: ='6'!K36 -> 1995.8
B44: 06 22 00 | C44: Millwork | G44: ='6'!K51 -> 180875
B45: 06 40 00 | C45: Architectural Woodwork | G45: ='6'!K59+'6'!K68+'6'!K79+'6'!K88+'6'!K95 -> 0
B47: 07 00 00 | C47: Thermal and Moisture Protection | H47: =SUM(G48:G57) -> 8446
B48: 07 21 00 | C48: Thermal Insulation | G48: ='7'!K16 -> 0
B49: 07 24 00 | C49: EIFS | G49: ='7'!K22 -> 0
B50: 07 31 00 | C50: Shingles | G50: ='7'!K27 -> 0
B51: 07 42 00 | C51: Wall Panels | G51: ='7'!K33 -> 0
B52: 07 46 00 | C52: Siding | G52: ='7'!K39 -> 0
B53: 07 50 00 | C53: Membrane Roofing | G53: ='7'!K45+'7'!K50 -> 0
B54: 07 60 00 | C54: Flashing and Sheet Metal | G54: ='7'!K55+'7'!K60+'7'!K66 -> 0
B55: 07 72 00 | C55: Roof Accessories | G55: ='7'!K72 -> 0
B56: 07 80 00 | C56: Smoke and Fire Protection | G56: ='7'!K78 -> 8446
B57: 07 90 00 | C57: Joint Protection | G57: ='7'!K84 -> 0
B59: 08 00 00 | C59: Openings | H59: =SUM(G60:G66) -> 22710
B60: 08 10 00 | C60: Doors and Frames | G60: ='8'!K18+'8'!K24 -> 20485
B61: 08 30 00 | C61: Speciality Doors and Frames | G61: ='8'!K29+'8'!K35+'8'!K41+'8'!K47+'8'!K52 -> 0
B62: 08 40 00 | C62: Store Fronts and Curtainwalls | G62: ='8'!K57+'8'!K62 -> 0
B63: 08 50 00 | C63: Windows | G63: ='8'!K69 -> 0
B64: 08 70 00 | C64: Hardeware | G64: ='8'!K75 -> 0
B65: 08 80 00 | C65: Glazing and Frosted Film | G65: ='8'!K81+'8'!K87+'8'!K93 -> 2225
B66: 08 90 00 | C66: Louvers | G66: ='8'!K99 -> 0
B68: 09 00 00 | C68: Finishes | H68: =SUM(G69:G74) -> 100111.44
B69: 09 20 00 | C69: Plaster and Gypsum Board and Ceilings | G69: ='9'!K18 -> 61750
B70: 09 30 00 | C70: Tiling | G70: ='9'!K26 -> 0
B71: 09 50 00 | C71: Ceiling | G71: ='9'!K32 -> 0
B72: 09 60 00 | C72: Flooring | G72: ='9'!K47 -> 26169
B73: 09 70 00 | C73: Wall Finishes | G73: ='9'!K53 -> 0
B74: 09 90 00 | C74: Painting | G74: ='9'!K62 -> 12192.44
B76: 10 00 00 | C76: Specialties | H76: =SUM(G77:G82) -> 11690
B77: 10 11 00 | C77: Visual Display Units | G77: ='10'!K17 -> 0
B78: 10 14 00 | C78: Signage | G78: ='10'!K25 -> 0
B79: 10 20 00 | C79: Interior Specialties | G79: ='10'!K38 -> 11690
B80: 10 40 00 | C80: Safety Specialties | G80: ='10'!K44 -> 0
B81: 10 50 00 | C81: Storage Specialties | G81: ='10'!K51 -> 0
B82: 10 70 00 | C82: Exterior Specialties | G82: ='10'!K63 -> 0
B84: 11 00 00 | C84: Equipment | H84: =SUM(G85:G88) -> 0
B85: 11 10 00 | C85: Vehicle Equipment | G85: ='11'!K24+'11'!K35 -> 0
B86: 11 30 00 | C86: Residential Equipment | G86: ='11'!K43 -> 0
B87: 11 40 00 | C87: Food Service Equipment | G87: ='11'!K52+'11'!K63 -> 0
B88: 11 50 00 | C88: Educational & Lab Equipment | G88: ='11'!K72+'11'!K79 -> 0
B90: 12 00 00 | C90: Furnishings | H90: =SUM(G91:G92) -> 0
B91: 12 20 00 | C91: Window Treatments | G91: ='12'!K24+'12'!K35 -> 0
B92: 12 30 00 | C92: Casework | G92: ='12'!K43+'12'!K52+'12'!K63+'12'!K72 -> 0
B94: 13 00 00 | C94: Special Construction | H94: ='Estimate Summary'!H39 -> 0
B96: 14 00 00 | C96: Conveying Equipment | H96: =SUM(G97:G98) -> 0
B97: 14 20 00 | C97: Elevators | G97: ='14'!K24 -> 0
B98: 14 40 00 | C98: Lifts | G98: ='14'!K35+'14'!K43 -> 0
B100: 21 00 00 | C100: Fire Suppression | H100: =G101 -> 6938
B101: 21 10 00 | C101: Water-Based Fire-Suppression System | G101: ='21'!K24 -> 6938
B103: 22 00 00 | C103: Plumbing | H103: =SUM(G104:G106) -> 129800
B104: 22 10 00 | C104: Plumbing Piping & Equipment | G104: ='22'!K24 -> 129800
B105: 22 30 00 | C105: Plumbing Equipment | G105: ='22'!K35 -> 0
B106: 22 40 00 | C106: Plumbing Fixtures | G106: ='22'!K46+'22'!K67+'22'!K74 -> 0
B108: 23 00 00 | C108: HVAC | H108: =SUM(G109:G116) -> 37030
B109: 23 07 00 | C109: HVAC Equipment & Air Distribution | G109: ='23'!K18 -> 37030
B110: 23 08 00 | C110: Commissioning of HVAC | G110: ='23'!K25 -> 0
B111: 23 09 00 | C111: Instrumentation and Control for HVAC | G111: ='23'!K31 -> 0
B112: 23 10 00 | C112: Facility Fuel System | G112: ='23'!K38+'23'!K46 -> 0
B113: 23 20 00 | C113: HVAC Piping and Pumps | G113: ='23'!K53+'23'!K58 -> 0
B114: 23 30 00 | C114: HVAC Air Distribution | G114: ='23'!K73 -> 0
B115: 23 70 00 | C115: Central HVAC Equipment | G115: ='23'!K79 -> 0
B116: 23 80 00 | C116: Decentralized HVAC Equipment | G116: ='23'!K85+'23'!K91 -> 0
B118: 25 00 00 | C118: Integrated Automation | H118: ='Estimate Summary'!H49 -> 0
B120: 26 00 00 | C120: Electrical | H120: =SUM(G121:G123) -> 80800
B121: 26 09 00 | C121: Distribution, Lighting, Fire Alarm | G121: ='26'!K26 -> 80800
...

Sheet Estimate Summary
A2: Project Information
A3: Closing Date : | B3: 46030
A4: Estimate # E- | B4: 3041 | C4: Area: | D4: 1747
A5: Province : | B5: NB | C5: Estimate Name : | D5: Dr. Goel Dental Office | E5: Bid Documents :
A6: City/Town : | B6: Moncton | C6: Client : | D6: Dr. Goel | E6: Status :
A7: Budget Year : | B7: 2026 | C7: Contract Type : | D7: CCDC 5B | E7: Result:
A8: Quarter: | B8: Q1 | C8: Payment Method : | D8: Fixed Fee
C11: Area: | D11: =D4 -> 1747 | E11: Sq. Ft.
A13: CODE | B13: DESCRIPTION | D13: M&E $$ | E13: M-HRS | F13: LAB $$ | G13: SUB CONT. | H13: Total | K13: Sackville Smiles | L13: Prisma Dental | M13: Mountain View Dental
C14: % | I14: $/SF
A15: 01 00 00 | B15: General Requirements | C15: =H15/D$66 -> 0.17352833 | D15: =SUM('1'!F139:F140) -> 17547.115 | E15: =SUM('1'!G139:G140) -> 50 | F15: =SUM('1'!I139:I140) -> 57200 | G15: =SUM('1'!J139:J140) -> 51016.89 | H15: =D15+F15+G15 -> 125764 | I15: =ROUNDUP(H15/D$11,1)&"$/SF" -> 72$/SF | K15: 75.6$/SF | L15: 22.8$/SF | M15: 53.3$/SF
A17: 02 00 00 | B17: Existing Conditions | C17: =H17/D$66 -> 0.023851107 | D17: =SUM('2'!F51:F52) -> 1500 | E17: =SUM('2'!G51:G52) -> 0 | F17: =SUM('2'!I51:I52) -> 0 | G17: =SUM('2'!J51:J52) -> 15786 | H17: =D17+F17+G17 -> 17286 | I17: =ROUNDUP(H17/D$11,1)&"$/SF" -> 9.9$/SF | K17: 0$/SF | L17: 0$/SF | M17: 8.7$/SF
A19: 03 00 00 | B19: Concrete | C19: =H19/D$66 -> 0 | D19: =SUM('3'!F78:F79) -> 0 | E19: =SUM('3'!G78:G79) -> 0 | F19: =SUM('3'!I78:I79) -> 0 | G19: =SUM('3'!J78:J79) -> 0 | H19: =D19+F19+G19 -> 0 | I19: =ROUNDUP(H19/D$11,1)&"$/SF" -> 0$/SF | K19: 21.7$/SF | L19: 25.9$/SF | M19: 0.6$/SF
A21: 04 00 00 | B21: Masonry | C21: =H21/D$66 -> 0 | D21: =SUM('4'!F68:F69) -> 0 | E21: =SUM('4'!G68:G69) -> 0 | F21: =SUM('4'!I68:I69) -> 0 | G21: =SUM('4'!J68:J69) -> 0 | H21: =D21+F21+G21 -> 0 | I21: =ROUNDUP(H21/D$11,1)&"$/SF" -> 0$/SF | K21: 9.5$/SF | L21: 0$/SF | M21: 0$/SF
A23: 05 00 00 | B23: Metals | C23: =H23/D$66 -> 0 | D23: =SUM('5'!F77:F78) -> 0 | E23: =SUM('5'!G77:G78) -> 0 | F23: =SUM('5'!I77:I78) -> 0 | G23: =SUM('5'!J77:J78) -> 0 | H23: =D23+F23+G23 -> 0 | I23: =ROUNDUP(H23/D$11,1)&"$/SF" -> 0$/SF | K23: 0$/SF | L23: 25.3$/SF | M23: 10.4$/SF
A25: 06 00 00 | B25: Wood, Plastics, and Composites | C25: =H25/D$66 -> 0.25411763 | D25: =SUM('6'!F98:F99) -> 1995.8 | E25: =SUM('6'!G98:G99) -> 20 | F25: =SUM('6'!I98:I99) -> 1300 | G25: =SUM('6'!J98:J99) -> 180875 | H25: =D25+F25+G25 -> 184170.8 | I25: =ROUNDUP(H25/D$11,1)&"$/SF" -> 105.5$/SF | K25: 40$/SF | L25: 41.2$/SF | M25: 57.5$/SF
A27: 07 00 00 | B27: Thermal and Moisture Protection | C27: =H27/D$66 -> 0.011653734 | D27: =SUM('7'!F93:F94) -> 0 | E27: =SUM('7'!G93:G94) -> 0 | F27: =SUM('7'!I93:I94) -> 0 | G27: =SUM('7'!J93:J94) -> 8446 | H27: =D27+F27+G27 -> 8446 | I27: =ROUNDUP(H27/D$11,1)&"$/SF" -> 4.9$/SF | K27: 29.1$/SF | L27: 48.1$/SF | M27: 0$/SF
A29: 08 00 00 | B29: Openings | C29: =H29/D$66 -> 0.031335105 | D29: =SUM('8'!F108:F109) -> 480 | E29: =SUM('8'!G108:G109) -> 28 | F29: =SUM('8'!I108:I109) -> 1820 | G29: =SUM('8'!J108:J109) -> 20410 | H29: =D29+F29+G29 -> 22710 | I29: =ROUNDUP(H29/D$11,1)&"$/SF" -> 13$/SF | K29: 22.4$/SF | L29: 22.2$/SF | M29: 6.6$/SF
A31: 09 00 00 | B31: Finishes | C31: =H31/D$66 -> 0.13813309 | D31: =SUM('9'!F65:F66) -> 3494 | E31: =SUM('9'!G65:G66) -> 0 | F31: =SUM('9'!I65:I66) -> 0 | G31: =SUM('9'!J65:J66) -> 96617.44 | H31: =D31+F31+G31 -> 100111.44 | I31: =ROUNDUP(H31/D$11,1)&"$/SF" -> 57.4$/SF | K31: 42.2$/SF | L31: 58.2$/SF | M31: 43.4$/SF
A33: 10 00 00 | B33: Specialties | C33: =H33/D$66 -> 0.016129783 | D33: =SUM('10'!F74:F75) -> 0 | E33: =SUM('10'!G74:G75) -> 46 | F33: =SUM('10'!I74:I75) -> 1690 | G33: =SUM('10'!J74:J75) -> 10000 | H33: =D33+F33+G33 -> 11690 | I33: =ROUNDUP(H33/D$11,1)&"$/SF" -> 6.7$/SF | K33: 2.3$/SF | L33: 0.9$/SF | M33: 0.7$/SF
A35: 11 00 00 | B35: Equipment | C35: =H35/D$66 -> 0 | D35: =SUM('11'!F99:F100) -> 0 | E35: =SUM('11'!G99:G100) -> 0 | F35: =SUM('11'!I99:I100) -> 0 | G35: =SUM('11'!J99:J100) -> 0 | H35: =D35+F35+G35 -> 0 | I35: =ROUNDUP(H35/D$11,1)&"$/SF" -> 0$/SF | K35: 0$/SF | L35: 0$/SF | M35: 0$/SF
A37: 12 00 00 | B37: Furnishings | C37: =H37/D$66 -> 0 | D37: =SUM('12'!F99:F100) -> 0 | E37: =SUM('12'!G99:G100) -> 0 | F37: =SUM('12'!I99:I100) -> 0 | G37: =SUM('12'!J99:J100) -> 0 | H37: =D37+F37+G37 -> 0 | I37: =ROUNDUP(H37/D$11,1)&"$/SF" -> 0$/SF | K37: 0.8$/SF | L37: 0$/SF | M37: 0$/SF
A39: 13 00 00 | B39: Special Construction | C39: =H39/D$66 -> 0 | D39: =+SUM('13'!F99:F100) -> 0 | E39: =SUM('13'!G99:G100) -> 0 | F39: =SUM('13'!I99:I100) -> 0 | G39: =SUM('13'!J99:J100) -> 0 | H39: =D39+F39+G39 -> 0 | I39: =ROUNDUP(H39/D$11,1)&"$/SF" -> 0$/SF | K39: 0$/SF | L39: 0$/SF | M39: 0$/SF
A41: 14 00 00 | B41: Conveying Equipment | C41: =H41/D$66 -> 0 | D41: =SUM('14'!F99:F100) -> 0 | E41: =SUM('14'!G99:G100) -> 0 | F41: =SUM('14'!I99:I100) -> 0 | G41: =SUM('14'!J99:J100) -> 0 | H41: =D41+F41+G41 -> 0 | I41: =ROUNDUP(H41/D$11,1)&"$/SF" -> 0$/SF | K41: 0$/SF | L41: 0$/SF | M41: 0$/SF
A43: 21 00 00 | B43: Fire Suppression | C43: =H43/D$66 -> 0.0095730058 | D43: =SUM('21'!F99:F100) -> 0 | E43: =SUM('21'!G99:G100) -> 0 | F43: =SUM('21'!I99:I100) -> 0 | G43: =SUM('21'!J99:J100) -> 6938 | H43: =D43+F43+G43 -> 6938 | I43: =ROUNDUP(H43/D$11,1)&"$/SF" -> 4$/SF | K43: 0$/SF | L43: 6.3$/SF | M43: 2.8$/SF
A45: 22 00 00 | B45: Plumbing | C45: =H45/D$66 -> 0.17909717 | D45: =SUM('22'!F94:F95) -> 0 | E45: =SUM('22'!G94:G95) -> 0 | F45: =SUM('22'!I94:I95) -> 0 | G45: =SUM('22'!J94:J95) -> 129800 | H45: =D45+F45+G45 -> 129800 | I45: =ROUNDUP(H45/D$11,1)&"$/SF" -> 74.3$/SF | K45: 33.3$/SF | L45: 27.3$/SF | M45: 16.1$/SF
A47: 23 00 00 | B47: HVAC | C47: =H47/D$66 -> 0.051093745 | D47: =SUM('23'!F102:F103) -> 0 | E47: =SUM('23'!G102:G103) -> 0 | F47: =SUM('23'!I102:I103) -> 0 | G47: =SUM('23'!J102:J103) -> 37030 | H47: =D47+F47+G47 -> 37030 | I47: =ROUNDUP(H47/D$11,1)&"$/SF" -> 21.2$/SF | K47: 43.7$/SF | L47: 30.9$/SF | M47: 14.7$/SF
A49: 25 00 00 | B49: Integrated Automation | C49: =H49/D$66 -> 0 | D49: =SUM('25'!F54:F55) -> 0 | E49: =SUM('25'!G54:G55) -> 0 | F49: =SUM('25'!I54:I55) -> 0 | G49: =SUM('25'!J54:J55) -> 0 | H49: =D49+F49+G49 -> 0 | I49: =ROUNDUP(H49/D$11,1)&"$/SF" -> 0$/SF | K49: 0$/SF | L49: 0$/SF | M49: 0$/SF
A51: 26 00 00 | B51: Electrical | C51: =H51/D$66 -> 0.1114873 | D51: =SUM('26'!F57:F58) -> 0 | E51: =SUM('26'!G57:G58) -> 0 | F51: =SUM('26'!I57:I58) -> 0 | G51: =SUM('26'!J57:J58) -> 80800 | H51: =D51+F51+G51 -> 80800 | I51: =ROUNDUP(H51/D$11,1)&"$/SF" -> 46.3$/SF | K51: 64.9$/SF | L51: 34.6$/SF | M51: 37.6$/SF
A53: 27 00 00 | B53: Communications | C53: =H53/D$66 -> 0 | D53: =SUM('27'!F99:F100) -> 0 | E53: =SUM('27'!G99:G100) -> 0 | F53: =SUM('27'!I99:I100) -> 0 | G53: =SUM('27'!J99:J100) -> 0 | H53: =D53+F53+G53 -> 0 | I53: =ROUNDUP(H53/D$11,1)&"$/SF" -> 0$/SF | K53: 0$/SF | L53: 0$/SF | M53: 4.9$/SF
A55: 28 00 00 | B55: Electronic Safety and Security | C55: =H55/D$66 -> 0 | D55: =SUM('28'!F55:F56) -> 0 | E55: =SUM('28'!G55:G56) -> 0 | F55: =SUM('28'!I55:I56) -> 0 | G55: =SUM('28'!J55:J56) -> 0 | H55: =D55+F55+G55 -> 0 | I55: =ROUNDUP(H55/D$11,1)&"$/SF" -> 0$/SF | K55: 0$/SF | L55: 0$/SF | M55: 0$/SF
A57: 31 00 00 | B57: Earthwork | C57: =H57/D$66 -> 0 | D57: =SUM('31'!F69:F70) -> 0 | E57: =SUM('31'!G69:G70) -> 0 | F57: =SUM('31'!I69:I70) -> 0 | G57: =SUM('31'!J69:J70) -> 0 | H57: =D57+F57+G57 -> 0 | I57: =ROUNDUP(H57/D$11,1)&"$/SF" -> 0$/SF | K57: 102.9$/SF | L57: 49.6$/SF | M57: 0$/SF
A59: 32 00 00 | B59: Exterior Improvements | C59: =H59/D$66 -> 0 | D59: =SUM('32'!F97:F98) -> 0 | E59: =SUM('32'!G97:G98) -> 0 | F59: =SUM('32'!I97:I98) -> 0 | G59: =SUM('32'!J97:J98) -> 0 | H59: =D59+F59+G59 -> 0 | I59: =ROUNDUP(H59/D$11,1)&"$/SF" -> 0$/SF | K59: 59.3$/SF | L59: 16.2$/SF | M59: 0$/SF
A61: 33 00 00 | B61: Utilities | C61: =H61/D$66 -> 0 | D61: =SUM('33'!F57:F58) -> 0 | E61: =SUM('33'!G57:G58) -> 0 | F61: =SUM('33'!I57:I58) -> 0 | G61: =SUM('33'!J57:J58) -> 0 | H61: =D61+F61+G61 -> 0 | I61: =ROUNDUP(H61/D$11,1)&"$/SF" -> 0$/SF | K61: 0$/SF | L61: 0$/SF | M61: 0$/SF
B64: Sub Totals>>>>>> | C64: =SUM(C15:C63) -> 1 | D64: =SUM(D15:D63) -> 25016.915 | E64: =SUM(E15:E63) -> 144 | F64: =SUM(F15:F63) -> 62010 | G64: =SUM(G15:G63) -> 637719.33 | H64: =SUM(H15:H63) -> 724746.24 | I64: =ROUNDUP(H64/D$11,1)&"$/SF" -> 414.9$/SF | K64: 546.9$/SF | L64: 408.7$/SF | M64: 256.7$/SF
B66: Total Construction Cost>>>>>> | D66: =D64+F64+G64 -> 724746.24
B68: OH&P>>>>>> | D68: =(D66*E68) -> 36237.312 | E68: 0.05
F69: HST | G69: TOTAL
F70: 0.15
B71: Estimated Price | D71: =D68+D66 -> 760983.56 | F71: =D71*F70 -> 114147.53 | G71: =D71+F71 -> 875131.09
B73: Contingency | C73: 0.1
F74: HST | G74: TOTAL
B75: Total (HST excluded) | D75: =D71+D73 -> 760983.56 | F75: =D75*F70 -> 114147.53 | G75: =D75+F75 -> 875131.09
D77: =D71/D11 -> 435.59448 | E77: /sq.ft.
I80: Area | K80: 2700sf | L80: 8415sf | M80: 2052sf
C81: Schedule | D81: 13 | E81: Weeks | G81: Job Type | H81: Target Margin | I81: Schedule | K81: 22 | L81: 26 | M81: 13
C82: Soft Cost | D82: =D68+'1'!K14+'1'!K93+'1'!K38+'1'!K103+'1'!K35+'1'!K11 -> 95539.74 | E82: =D82/D81 -> 7349.2108 | G82: A > 1,000,000 | H82: 0.1 | I82: Margin | K82: 0.1076 | L82: 0.0806 | M82: 0.1392
G83: B > 500,000 | H83: 0.15
C84: Margin | D84: =D82/D71 -> 0.12554771 | G84: C > 100,000 | H84: 0.2 | I84: OH&P | K84: 0.045 | L84: 0.05 | M84: 0.05
C85: Buyouts | D85: =D75*E85 -> 7609.8356 | E85: 0.01 | G85: D < 100,000 | H85: 0.25
C86: CO's | D86: =D75*E86 -> 38049.178 | E86: 0.05
A87: Competititors on Bid | B87: =COUNTIF(A88:A96,"*") -> 0

Sheet 1
C1: ='Estimate Summary'!C1:H1 -> 0
G5: General Requirements | J5: Schedule
D6: ='Estimate Summary'!C11 -> Area: | E6: ='Estimate Summary'!D11 -> 1747 | F6: ='Estimate Summary'!E11 -> Sq. Ft. | J6: ='Estimate Summary'!D81 -> 13 | K6: Weeks
A9: CODE | B9: DESCRIPTION | C9: Materials & Equipment | G9: Labor | L9: Sub Contractor | M9: Quote Total | N9: Additional Quote Info
A10: 01 11 00 | B10: Preconstruction Costs | C10: Qty | D10: Unit | E10: U. Price | F10: Sub Total | G10: MHrs | H10: U. Price | I10: Sub Total | J10: Quote | K10: Total
A11: 01 11 13 | B11: Senior Construction Manager | D11: LS | E11: 0 | F11: =C11*E11 -> 0 | H11: 0 | I11: =G11*H11 -> 0 | K11: =F11+I11+J11 -> 0
A12: 01 11 16 | B12: Senior Estimator | C12: 1 | D12: LS | E12: 4500 | F12: =C12*E12 -> 4500 | H12: 0 | I12: =G12*H12 -> 0 | K12: =F12+I12+J12 -> 4500
A13: 01 11 19 | B13: Junior Estimator | D13: LS | E13: 0 | F13: =C13*E13 -> 0 | H13: 0 | I13: =G13*H13 -> 0 | K13: =F13+I13+J13 -> 0
A14: 01 11 23 | B14: Reprographics | D14: LS | E14: 0 | F14: =C14*E14 -> 0 | H14: 0 | I14: =G14*H14 -> 0 | K14: =F14+I14+J14 -> 0
A15: 01 11 26 | B15: Design Costs | D15: LS | E15: 0 | F15: =C15*E15 -> 0 | H15: 0 | I15: =G15*H15 -> 0 | K15: =F15+I15+J15 -> 0
A16: 01 11 26.13 | B16: Architectural | D16: LS | E16: 0 | F16: =C16*E16 -> 0 | H16: 0 | I16: =G16*H16 -> 0 | J16: =M16 -> 35000 | K16: =F16+I16+J16 -> 35000 | L16: KUB | M16: 35000 | N16: KUB
A17: 01 11 26.16 | B17: Civil | D17: LS | E17: 0 | F17: =C17*E17 -> 0 | H17: 0 | I17: =G17*H17 -> 0 | K17: =F17+I17+J17 -> 0
A18: 01 11 26.19 | B18: Structural | D18: LS | E18: 0 | F18: =C18*E18 -> 0 | H18: 0 | I18: =G18*H18 -> 0 | K18: =F18+I18+J18 -> 0 | L18: Mountain View | M18: 3500 | N18: Giffin
A19: 01 11 26.23 | B19: HVAC | D19: LS | E19: 0 | F19: =C19*E19 -> 0 | H19: 0 | I19: =G19*H19 -> 0 | J19: =M19 -> 13200 | K19: =F19+I19+J19 -> 13200 | L19: MCW | M19: =12450+750 -> 13200
A20: 01 11 26.26 | B20: Plumbing | D20: LS | E20: 0 | F20: =C20*E20 -> 0 | H20: 0 | I20: =G20*H20 -> 0 | K20: =F20+I20+J20 -> 0
A21: 01 11 26.29 | B21: Electrical | D21: LS | E21: 0 | F21: =C21*E21 -> 0 | H21: 0 | I21: =G21*H21 -> 0 | K21: =F21+I21+J21 -> 0
A22: 01 11 26.33 | B22: Geotechnical | D22: LS | E22: 0 | F22: =C22*E22 -> 0 | H22: 0 | I22: =G22*H22 -> 0 | K22: =F22+I22+J22 -> 0
J24: Sub Total | K24: =SUM(K11:K23) -> 52700
A25: CODE | B25: DESCRIPTION | C25: Materials & Equipment | G25: Labor
A26: 01 31 00 | B26: Project Management and Coordination | C26: Qty | D26: Unit | E26: U. Price | F26: Sub Total | G26: MHrs | H26: U. Price | I26: Sub Total | J26: Quote | K26: Total
A27: 01 31 01 | B27: Senior Construction Manager | D27: LS | E27: 0 | F27: =C27*E27 -> 0 | H27: 0 | I27: =G27*H27 -> 0 | K27: =F27+I27+J27 -> 0
A28: 01 31 02 | B28: Senior Estimator | D28: LS | E28: 0 | F28: =C28*E28 -> 0 | H28: 0 | I28: =G28*H28 -> 0 | K28: =F28+I28+J28 -> 0
A29: 01 31 03 | B29: Senior Project Manager | C29: =J6 -> 13 | D29: LS | E29: 0 | F29: =C29*E29 -> 0 | G29: 10 | H29: 100 | I29: =H29*G29*C29 -> 13000 | K29: =F29+I29+J29 -> 13000
A30: 01 31 04 | B30: Project Coordinator | C30: =J6 -> 13 | D30: LS | E30: 0 | F30: =C30*E30 -> 0 | H30: 75 | I30: =H30*G30*C30 -> 0 | K30: =F30+I30+J30 -> 0
A31: 01 31 05 | B31: Project Superintendent | C31: =J6 -> 13 | D31: LS | E31: 0 | F31: =C31*E31 -> 0 | G31: 40 | H31: 85 | I31: =H31*G31*C31 -> 44200 | K31: =F31+I31+J31 -> 44200
A32: 01 31 06 | B32: Project Foreman | D32: LS | E32: 0 | F32: =C32*E32 -> 0 | H32: 0 | I32: =G32*H32 -> 0 | K32: =F32+I32+J32 -> 0
D33: LS | E33: 0 | F33: =C33*E33 -> 0 | H33: 0 | I33: =G33*H33 -> 0 | K33: =F33+I33+J33 -> 0
K34: =F34+I34+J34 -> 0
J35: Sub Total | K35: =SUM(K27:K34) -> 57200
A36: CODE | B36: DESCRIPTION
A37: 01 32 00 | B37: Insurance | D37: /$1000 | E37: Cost | F37: Rate | G37: Toll Cost | H37: Frequency | J37: Sub Total | K37: Total
A38: 01 32 01 | B38: General Liability & Contractor's Pollution Liability | C38: =SUM('Estimate Summary'!H17:H61)/1000 -> 598.98224 | D38: /$1000 | E38: 0.63 | F38: =C38*E38 -> 377.35881 | K38: =F38 -> 377.35881
B39: Contractor's Pollution Liability | C39: =SUM('Estimate Summary'!H17:H61)/1000 -> 598.98224 | D39: /$1000 | E39: 1.29 | F39: =C39*E39 -> 772.68709 | K39: =F39 -> 772.68709
B40: Builders Risk | C40: =+J6/4.5 -> 2.8888889 | D40: $1000/month | E40: 0.75 | K40: =F40 -> 0
B41: Wrap-up Liability | C41: =SUM('Estimate Summary'!H17:H61)/1000 -> 598.98224 | D41: /$1000 | E41: 1.88 | K41: =F41 -> 0
A45: 01 32 00 | J45: Sub Total | K45: =SUM(K38:K44) -> 1150.0459
A46: CODE | B46: DESCRIPTION | C46: Materials & Equipment | G46: Labor
A47: CODE | B47: DESCRIPTION
A48: 01 32 00 | B48: Travel | C48: Frequency | D48: Weeks | E48: Distance (Round Trip) | F48: Rate | G48: Toll Cost | H48: Frequency | J48: Sub Total | K48: Total
B49: PM KM | D49: =J6 -> 13 | E49: 0 | F49: 0.45 | H49: =C49*D49 -> 0 | J49: =C49*D49*E49*F49+G49*H49 -> 0 | K49: =J49+(G49*H49) -> 0
B50: Superintendent KM | D50: =J6 -> 13 | E50: 0 | F50: 0.45 | H50: =C50*D50 -> 0 | J50: =C50*D50*E50*F50+G50*H50 -> 0 | K50: =J50+(G50*H50) -> 0
B51: Hotel | D51: =J6 -> 13 | F51: 120 | J51: =C51*D51*F51 -> 0 | K51: =J51 -> 0
B52: Per Diem
B53: foreman - Mondays | D53: =J$6 -> 13 | F53: 40 | J53: =C53*D53*F53 -> 0 | K53: =J53 -> 0
B54: foreman: Tues to Thurs | D54: =J$6 -> 13 | F54: 47 | J54: =C54*D54*F54 -> 0 | K54: =J54 -> 0
B55: foreman: Fridays | D55: =J$6 -> 13 | F55: 22 | J55: =C55*D55*F55 -> 0 | K55: =J55 -> 0
A56: 01 32 00 | J56: Sub Total | K56: =SUM(K49:K55) -> 0
A57: CODE | B57: DESCRIPTION | C57: Materials & Equipment | G57: Labor
A58: 01 41 00 | B58: Permits | C58: Qty | D58: Unit | E58: U. Price | F58: Sub Total | G58: MHrs | H58: U. Price | I58: Sub Total | J58: Quote | K58: Total
A59: 01 41 00 | B59: Bldg Permit Fees | C59: =SUM('Estimate Summary'!H17:H61)/1000 -> 598.98224 | D59: /$1000 | E59: 0 | F59: =C59*E59 -> 0 | J59: =M59 -> 2816.89 | K59: =F59+I59+J59 -> 2816.89 | L59: Permit | M59: 2816.89
B60: Moncton | C60: 8 | D60: /$1000 | E60: "+ Development Fee | G60: $100 <$500k, $150 $500k to 1M, $300 1M - 5 M, $500 > 5M
B61: Dieppe | C61: 7.5 | D61: /$1000
B62: Saint John | C62: 8.9 | D62: /$1000 | E62: $120 Base Fee
B63: Fredericton | C63: 8 | D63: /$1000
B64: Halifax | C64: 5.5 | D64: /$1000
J67: Sub Total | K67: =SUM(K59:K66) -> 2816.89
A68: CODE | B68: DESCRIPTION | C68: Materials & Equipment | G68: Labor
A69: 01 45 00 | B69: Quality Control | C69: Qty | D69: Unit | E69: U. Price | F69: Sub Total | G69: MHrs | H69: U. Price | I69: Sub Total | J69: Quote | K69: Total
A70: 01 45 01 | B70: Soil Investigation and Testing | D70: LS | E70: 2500 | F70: =C70*E70 -> 0 | H70: 0 | I70: =G70*H70 -> 0 | K70: =F70+I70+J70 -> 0
A71: 01 45 02 | B71: Material Inspection and Testing | D71: LS | E71: 2500 | F71: =C71*E71 -> 0 | H71: 0 | I71: =G71*H71 -> 0 | K71: =F71+I71+J71 -> 0
A72: 01 45 03 | B72: Survey and Layout | D72: LS | E72: 3000 | F72: =C72*E72 -> 0 | H72: 0 | I72: =G72*H72 -> 0 | K72: =F72+I72+J72 -> 0
A73: 01 45 04 | B73: Hazardous Idendification Inspection | D73: LS | E73: 0 | F73: =C73*E73 -> 0 | H73: 0 | I73: =G73*H73 -> 0 | K73: =F73+I73+J73 -> 0
A74: 01 45 05 | B74: Sanitary Line Video | D74: LS | E74: 0 | F74: =C74*E74 -> 0 | H74: 0 | I74: =G74*H74 -> 0 | K74: =F74+I74+J74 -> 0
J76: Sub Total | K76: =SUM(K70:K75) -> 0
A77: CODE | B77: DESCRIPTION | C77: Materials & Equipment | G77: Labor
A78: 01 51 00 | B78: Temporary Utilities | C78: Qty | D78: Unit | E78: U. Price | F78: Sub Total | G78: MHrs | H78: U. Price | I78: Sub Total | J78: Quote | K78: Total
A79: 01 51 01 | B79: Temporary Fire Protection | D79: Week | E79: 0 | F79: =C79*E79 -> 0 | H79: 0 | I79: =G79*H79 -> 0 | K79: =F79+I79+J79 -> 0
A80: 01 51 02 | B80: Temporary Power | D80: Week | E80: 100 | F80: =C80*E80 -> 0 | H80: 0 | I80: =G80*H80 -> 0 | K80: =F80+I80+J80 -> 0
A81: 01 51 03 | B81: Temporary Lighting | D81: Week | E81: 0 | F81: =C81*E81 -> 0 | H81: 0 | I81: =G81*H81 -> 0 | K81: =F81+I81+J81 -> 0
A82: 01 51 04 | B82: Temporary Fuel Oil | D82: Week | E82: 0 | F82: =C82*E82 -> 0 | H82: 0 | I82: =G82*H82 -> 0 | K82: =F82+I82+J82 -> 0
A83: 01 51 05 | B83: Temp HVAC | D83: Week | E83: 0 | F83: =C83*E83 -> 0 | H83: 0 | I83: =G83*H83 -> 0 | K83: =F83+I83+J83 -> 0
A84: 01 51 06 | B84: Temporary Internet | D84: Week | E84: 0 | F84: =C84*E84 -> 0 | H84: 0 | I84: =G84*H84 -> 0 | K84: =F84+I84+J84 -> 0
A85: 01 51 07 | B85: Temporary Water | D85: Week | E85: 0 | F85: =C85*E85 -> 0 | H85: 0 | I85: =G85*H85 -> 0 | K85: =F85+I85+J85 -> 0
J87: Sub Total | K87: =SUM(K79:K86) -> 0
A88: CODE | B88: DESCRIPTION | C88: Materials & Equipment | G88: Labor
A89: 01 52 00 | B89: Construction Facilities | C89: Qty | D89: Unit | E89: U. Price | F89: Sub Total | G89: MHrs | H89: U. Price | I89: Sub Total | J89: Quote | K89: Total
A90: 01 52 01 | B90: Construction Field Office | D90: Month | E90: 750 | F90: =C90*E90 -> 0 | H90: 0 | I90: =G90*H90 -> 0 | K90: =F90+I90+J90 -> 0
A91: 01 52 01 | B91: Field Office One Time Charges | D91: Ea | E91: 1840 | F91: =C91*E91 -> 0 | K91: =F91+I91+J91 -> 0
A92: 01 52 02 | B92: Sanitary Facilities | D92: Week | E92: 50 | F92: =C92*E92 -> 0 | H92: 0 | I92: =G92*H92 -> 0 | K92: =F92+I92+J92 -> 0
A93: 01 52 03 | B93: Drawing Reprographics | C93: =SUM('Estimate Summary'!H17:H61)/1000 -> 598.98224 | D93: M | E93: 0.55 | F93: =C93*E93 -> 329.44023 | H93: 0 | I93: =G93*H93 -> 0 | K93: =F93+I93+J93 -> 329.44023
A94: 01 52 04 | B94: First-Aid / Safety | C94: =J6 -> 13 | D94: Week | E94: 125 | F94: =C94*E94 -> 1625 | H94: 0 | I94: =G94*H94 -> 0 | K94: =F94+I94+J94 -> 1625
A95: 01 52 05 | B95: Job Sign | C95: 1 | D95: Ea | E95: 200 | F95: =C95*E95 -> 200 | H95: 0 | I95: =G95*H95 -> 0 | K95: =F95+I95+J95 -> 200
J97: Sub Total | K97: =SUM(K90:K96) -> 2154.4402
A98: CODE | B98: DESCRIPTION | C98: Materials & Equipment | G98: Labor
A99: 01 54 00 | B99: Construction Aids | C99: Qty | D99: Unit | E99: U. Price | F99: Sub Total | G99: MHrs | H99: U. Price | I99: Sub Total | J99: Quote | K99: Total
A100: 01 54 01 | B100: Scaffolding / Staging | D100: LS | E100: 0 | F100: =C100*E100 -> 0 | H100: 0 | I100: =G100*H100 -> 0 | K100: =F100+I100+J100 -> 0
A101: 01 54 02 | B101: Rentals | D101: LS | E101: 0 | F101: =C101*E101 -> 0 | H101: 0 | I101: =G101*H101 -> 0 | K101: =F101+I101+J101 -> 0
A102: 01 54 03 | B102: Small Tools | C102: ='Estimate Summary'!E62 -> 0 | D102: Allow | E102: 0 | F102: =C102*E102 -> 0 | H102: 0 | I102: =G102*H102 -> 0 | K102: =F102+I102+J102 -> 0
A103: 01 54 04 | B103: Technology (Procore, Smartbid, On-screen, Imaginit, Sage 300) | C103: =SUM('Estimate Summary'!H17:H63)/1000 -> 598.98224 | D103: /$1000 | E103: 2.33 | F103: =C103*E103 -> 1395.6286 | H103: 0 | I103: =G103*H103 -> 0 | K103: =F103+I103+J103 -> 1395.6286
J105: Sub Total | K105: =SUM(K100:K104) -> 1395.6286
A106: CODE | B106: DESCRIPTION | C106: Materials & Equipment | G106: Labor
A107: 01 55 00 | B107: Winter Conditions | C107: Qty | D107: Unit | E107: U. Price | F107: Sub Total | G107: MHrs | H107: U. Price | I107: Sub Total | J107: Quote | K107: Total
A109: 01 55 01 | B109: Frost Fighters | D109: month | E109: 602 | F109: =C109*E109 -> 0 | K109: =F109 -> 0
A110: 01 55 02 | B110: Tarps (10) | D110: ea | E110: 73 | F110: =C110*E110 -> 0 | K110: =F110 -> 0
A111: 01 55 03 | B111: Fans | D111: month | E111: 355 | F111: =C111*E111 -> 0 | K111: =F111 -> 0
A112: 01 55 04 | B112: Fuel Cube | D112: month | E112: 609 | F112: =C112*E112 -> 0 | K112: =F112 -> 0
A113: 01 55 05 | B113: Delivery | D113: ea | E113: 98 | F113: =C113*E113 -> 0 | K113: =F113 -> 0
A114: 01 55 06 | B114: Pickup | D114: ea | E114: 98 | F114: =C114*E114 -> 0 | K114: =F114 -> 0
B115: Quantity of Fuel
C116: Tank Size | D116: L/Hr | E116: Running (Hours / Day) | F116: Litres / Day | G116: Duration (Days)
...

Sheet 2
C1: ='Estimate Summary'!C1:H1 -> 0
G5: Existing Conditions | J5: Schedule
D6: ='Estimate Summary'!C11 -> Area: | E6: ='Estimate Summary'!D11 -> 1747 | F6: ='Estimate Summary'!E11 -> Sq. Ft. | J6: ='1'!J6 -> 13 | K6: Weeks
A11: CODE | B11: DESCRIPTION | C11: Materials & Equipment | G11: Labor | L11: Sub Contractor | M11: Quote Total | N11: Additional Quote Info
A12: 02 00 00 | B12: Existing Conditions | C12: Qty | D12: Unit | E12: U. Price | F12: Sub Total | G12: MHrs | H12: U. Price | I12: Sub Total | J12: Quote | K12: Total
A13: 02 41 00 | B13: Demolition | C13: =E6 -> 1747 | D13: SF | E13: 5 | F13: 0 | H13: 0 | I13: =G13*H13 -> 0 | J13: =M13 -> 10086 | K13: =F13+I13+J13 -> 10086 | L13: Branco | M13: 10086 | N13: Duct demo has been removed
D14: LS | E14: 0 | F14: =C14*E14 -> 0 | H14: 0 | I14: =G14*H14 -> 0 | K14: =F14+I14+J14 -> 0 | L14: Branco | M14: 150 | N14: per hole
B15: Additional 18 holes | D15: LS | E15: 0 | F15: =C15*E15 -> 0 | H15: 0 | I15: =G15*H15 -> 0 | J15: =M14*38 -> 5700 | K15: =F15+I15+J15 -> 5700 | L15: Branco | M15: =M14*38 -> 5700
D16: LS | E16: 0 | F16: =C16*E16 -> 0 | H16: 0 | I16: =G16*H16 -> 0 | K16: =F16+I16+J16 -> 0 | L16: Enviro | M16: 15900
D17: LS | E17: 0 | F17: =C17*E17 -> 0 | H17: 0 | I17: =G17*H17 -> 0 | K17: =F17+I17+J17 -> 0 | L17: Enviro | M17: 100 | N17: per hole
D18: LS | E18: 0 | F18: =C18*E18 -> 0 | H18: 0 | I18: =G18*H18 -> 0 | K18: =F18+I18+J18 -> 0 | L18: Inflector | M18: 15230
D19: LS | E19: 0 | F19: =C19*E19 -> 0 | H19: 0 | I19: =G19*H19 -> 0 | K19: =F19+I19+J19 -> 0
D20: LS | E20: 0 | F20: =C20*E20 -> 0 | H20: 0 | I20: =G20*H20 -> 0 | K20: =F20+I20+J20 -> 0 | L20: Mountain View Dental | M20: 11.94
D21: LS | E21: 0 | F21: =C21*E21 -> 0 | H21: 0 | I21: =G21*H21 -> 0 | K21: =F21+I21+J21 -> 0
D22: LS | E22: 0 | F22: =C22*E22 -> 0 | H22: 0 | I22: =G22*H22 -> 0 | K22: =F22+I22+J22 -> 0
D23: LS | E23: 0 | F23: =C23*E23 -> 0 | H23: 0 | I23: =G23*H23 -> 0 | K23: =F23+I23+J23 -> 0 | M23: =17286-K26 -> 1500
D24: LS | E24: 0 | F24: =C24*E24 -> 0 | H24: 0 | I24: =G24*H24 -> 0 | K24: =F24+I24+J24 -> 0
J26: Sub Total | K26: =SUM(K13:K25) -> 15786
A27: CODE | B27: DESCRIPTION | C27: Materials & Equipment | G27: Labor
A28: 02 82 00 | B28: Asbestos Remediation | C28: Qty | D28: Unit | E28: U. Price | F28: Sub Total | G28: MHrs | H28: U. Price | I28: Sub Total | J28: Quote | K28: Total
D29: LS | E29: 0 | F29: =C29*E29 -> 0 | H29: 0 | I29: =G29*H29 -> 0 | K29: =F29+I29+J29 -> 0
D30: LS | E30: 0 | F30: =C30*E30 -> 0 | H30: 0 | I30: =G30*H30 -> 0 | K30: =F30+I30+J30 -> 0
D31: LS | E31: 0 | F31: =C31*E31 -> 0 | H31: 0 | I31: =G31*H31 -> 0 | K31: =F31+I31+J31 -> 0
D32: LS | E32: 0 | F32: =C32*E32 -> 0 | H32: 0 | I32: =G32*H32 -> 0 | K32: =F32+I32+J32 -> 0
D33: LS | E33: 0 | F33: =C33*E33 -> 0 | H33: 0 | I33: =G33*H33 -> 0 | K33: =F33+I33+J33 -> 0
D34: LS | E34: 0 | F34: =C34*E34 -> 0 | H34: 0 | I34: =G34*H34 -> 0 | K34: =F34+I34+J34 -> 0
D35: LS | E35: 0 | F35: =C35*E35 -> 0 | H35: 0 | I35: =G35*H35 -> 0 | K35: =F35+I35+J35 -> 0
J37: Sub Total | K37: =SUM(K29:K36) -> 0
A38: CODE | B38: DESCRIPTION | C38: Materials & Equipment | G38: Labor
A39: 02 83 00 | B39: Trenching | C39: Qty | D39: Unit | E39: U. Price | F39: Sub Total | G39: MHrs | H39: U. Price | I39: Sub Total | J39: Quote | K39: Total
D40: LS | E40: 0 | F40: =C40*E40 -> 0 | H40: 0 | I40: =G40*H40 -> 0 | K40: =F40+I40+J40 -> 0
B41: Sanitary Trenching | D41: ft | E41: 95 | F41: =C41*E41 -> 0 | H41: 0 | I41: =G41*H41 -> 0 | K41: =F41+I41+J41 -> 0
D42: LS | E42: 0 | F42: =C42*E42 -> 0 | H42: 0 | I42: =G42*H42 -> 0 | K42: =F42+I42+J42 -> 0
B43: Core Drilling | C43: 24 | D43: EA | E43: 120 | F43: 0 | H43: 0 | I43: =G43*H43 -> 0 | K43: =F43+I43+J43 -> 0
B44: X Ray Allowance | C44: 1 | D44: LS | E44: 1500 | F44: =C44*E44 -> 1500 | H44: 0 | I44: =G44*H44 -> 0 | K44: =F44+I44+J44 -> 1500
D45: LS | E45: 0 | F45: =C45*E45 -> 0 | H45: 0 | I45: =G45*H45 -> 0 | K45: =F45+I45+J45 -> 0
D46: LS | E46: 0 | F46: =C46*E46 -> 0 | H46: 0 | I46: =G46*H46 -> 0 | K46: =F46+I46+J46 -> 0
J48: Sub Total | K48: =SUM(K40:K47) -> 1500
F49: Material Total | G49: Total Hours | I49: Labor Total | J49: Contractor Total | K49: TOTAL
A50: $ / Sq.Ft | B50: TOTAL DIVISION 2
A51: =K51/E6 -> 9.8946766 | F51: =SUM(F13:F25,F40:F47,F29:F35) -> 1500 | G51: =SUM(G13:G25,G40:G47,G29:G35) -> 0 | I51: =SUM(I13:I25,I40:I47,I29:I35) -> 0 | J51: =SUM(J13:J25,J40:J47,J29:J35) -> 15786 | K51: =SUM(K48,K26,K37) -> 17286

Sheet 3
C1: ='Estimate Summary'!C1:H1 -> 0
G5: Concrete | J5: Schedule
D6: ='Estimate Summary'!C11 -> Area: | E6: ='Estimate Summary'!D11 -> 1747 | F6: ='Estimate Summary'!E11 -> Sq. Ft. | J6: ='1'!J6 -> 13 | K6: Weeks
A11: CODE | B11: DESCRIPTION | C11: Materials & Equipment | G11: Labor | L11: Sub Contractor | M11: Quote Total | N11: Additional Quote Info
A12: 03 11 00 | B12: Concrete Forming | C12: Qty | D12: Unit | E12: U. Price | F12: Sub Total | G12: MHrs | H12: U. Price | I12: Sub Total | J12: Quote | K12: Total
A13: 03 11 01 | B13: Contractor Quote | K13: =F13+I13+J13 -> 0
A14: 03 11 02.1 | B14: Footings | D14: ft | E14: 25 | F14: =C14*E14 -> 0 | H14: 0 | I14: =G14*H14 -> 0 | K14: =F14+I14+J14 -> 0
A15: 03 11 02.2 | B15: Walls | D15: ft | E15: 45 | F15: =C15*E15 -> 0 | H15: 0 | I15: =G15*H15 -> 0 | K15: =F15+I15+J15 -> 0
A16: 03 11 02.3 | B16: Piers | D16: ea | E16: 150 | F16: =C16*E16 -> 0 | H16: 0 | I16: =G16*H16 -> 0 | K16: =F16+I16+J16 -> 0
D17: LS | E17: 0 | F17: =C17*E17 -> 0 | H17: 0 | I17: =G17*H17 -> 0 | K17: =F17+I17+J17 -> 0
D18: LS | E18: 0 | F18: =C18*E18 -> 0 | H18: 0 | I18: =G18*H18 -> 0 | K18: =F18+I18+J18 -> 0
D19: LS | E19: 0 | F19: =C19*E19 -> 0 | H19: 0 | I19: =G19*H19 -> 0 | K19: =F19+I19+J19 -> 0
D20: LS | E20: 0 | F20: =C20*E20 -> 0 | H20: 0 | I20: =G20*H20 -> 0 | K20: =F20+I20+J20 -> 0
J26: Sub Total | K26: =SUM(K13:K25) -> 0
A27: CODE | B27: DESCRIPTION | C27: Materials & Equipment | G27: Labor
A28: 03 20 00 | B28: Concrete Reinforcing | C28: Qty | D28: Unit | E28: U. Price | F28: Sub Total | G28: MHrs | H28: U. Price | I28: Sub Total | J28: Quote | K28: Total
A29: 03 20 01 | B29: Contractor Quote | K29: =F29+I29+J29 -> 0 | T29: Type | U29: Width | W29: Height
A30: 03 20 02 | B30: Rebar | D30: LS | E30: 0 | F30: =C30*E30 -> 0 | H30: 0 | I30: =G30*H30 -> 0 | K30: =F30+I30+J30 -> 0 | U30: A | V30: B | W30: D | X30: Quantity | Y30: Volume m3
A31: 03 20 03 | B31: Mesh | D31: LS | E31: 0 | F31: =C31*E31 -> 0 | H31: 0 | I31: =G31*H31 -> 0 | K31: =F31+I31+J31 -> 0 | S31: Footings | T31: 1 | Y31: =U31*V31*W31*0.0000163871*X31 -> 0
D32: LS | E32: 0 | F32: =C32*E32 -> 0 | H32: 0 | I32: =G32*H32 -> 0 | K32: =F32+I32+J32 -> 0 | T32: 2 | Y32: =U32*V32*W32*0.0000163871*X32 -> 0
D33: LS | E33: 0 | F33: =C33*E33 -> 0 | H33: 0 | I33: =G33*H33 -> 0 | K33: =F33+I33+J33 -> 0 | U33: Length (FT) | V33: Width (ft) | W33: Height (ft)
D34: LS | E34: 0 | F34: =C34*E34 -> 0 | H34: 0 | I34: =G34*H34 -> 0 | K34: =F34+I34+J34 -> 0 | S34: Strip Footing | Y34: =U34*V34*W34*0.028 -> 0
D35: LS | E35: 0 | F35: =C35*E35 -> 0 | H35: 0 | I35: =G35*H35 -> 0 | K35: =F35+I35+J35 -> 0 | S35: Walls | Y35: =U35*V35*W35*0.028 -> 0
S36: Piers | Y36: =U36*V36*W36*0.028*X36 -> 0
J37: Sub Total | K37: =SUM(K29:K36) -> 0 | U37: Area (SF) | W37: Thickness (ft)
A38: CODE | B38: DESCRIPTION | C38: Materials & Equipment | G38: Labor | S38: Slab - ground floor | Y38: =U38*W38*0.028 -> 0
A39: 03 30 00 | B39: Cast-in-Place Concrete | C39: Qty | D39: Unit | E39: U. Price | F39: Sub Total | G39: MHrs | H39: U. Price | I39: Sub Total | J39: Quote | K39: Total | S39: Slab - 2nd floor | Y39: =U39*W39*0.028 -> 0
A40: 03 30 01 | B40: Slab Volume | C40: =Y44 -> 0 | D40: m3 | E40: 0 | F40: =C40*E40 -> 0 | H40: 0 | I40: =G40*H40 -> 0 | K40: =F40+I40+J40 -> 0
A41: 03 30 02 | B41: Footing Volume | C41: =Y45 -> 0 | D41: m3 | E41: 0 | F41: =C41*E41 -> 0 | H41: 0 | I41: =G41*H41 -> 0 | K41: =F41+I41+J41 -> 0 | S41: Exterior Pads | Y41: =U41*W41*0.028 -> 0
A42: 03 30 03 | B42: Foundation Wall Volume | C42: =Y46 -> 0 | D42: m3 | E42: 0 | F42: =C42*E42 -> 0 | H42: 0 | I42: =G42*H42 -> 0 | K42: =F42+I42+J42 -> 0
A43: 03 30 04 | B43: Exterior Concrete Volume | C43: =Y47 -> 0 | D43: m3 | E43: 0 | F43: =C43*E43 -> 0 | H43: 0 | I43: =G43*H43 -> 0 | K43: =F43+I43+J43 -> 0
D44: LS | E44: 0 | F44: =C44*E44 -> 0 | H44: 0 | I44: =G44*H44 -> 0 | K44: =F44+I44+J44 -> 0 | W44: Total Volume - Slab | Y44: =Y38+Y39 -> 0
A45: 03 30 04 | B45: Pump | C45: =SUM(C40:C43) -> 0 | D45: m3 | E45: 3 | F45: =C45*E45 -> 0 | H45: 0 | I45: =G45*H45 -> 0 | K45: =F45+I45+J45 -> 0 | W45: Total Volume - Footing | Y45: =Y31+Y32+Y34 -> 0
J46: Sub Total | K46: =SUM(K40:K45) -> 0 | W46: Total Volume - Walls | Y46: =Y35+Y36 -> 0
A47: CODE | B47: DESCRIPTION | C47: Materials & Equipment | G47: Labor | W47: Total Volume - Exterior | Y47: =Y41 -> 0
A48: 03 35 00 | B48: Concrete Finishing | C48: Qty | D48: Unit | E48: U. Price | F48: Sub Total | G48: MHrs | H48: U. Price | I48: Sub Total | J48: Quote | K48: Total
D49: LS | E49: 0 | F49: =C49*E49 -> 0 | H49: 0 | I49: =G49*H49 -> 0 | K49: =F49+I49+J49 -> 0
B50: Slab Finishing - Ground Floor | C50: =U38 -> 0 | D50: sf | E50: 1 | F50: =C50*E50 -> 0 | H50: 0 | I50: =G50*H50 -> 0 | K50: =F50+I50+J50 -> 0
B51: Slab Finishing - 2nd Floor | C51: =U39 -> 0 | D51: sf | E51: 1 | F51: =C51*E51 -> 0 | H51: 0 | I51: =G51*H51 -> 0 | K51: =F51+I51+J51 -> 0
D52: LS | E52: 0 | F52: =C52*E52 -> 0 | H52: 0 | I52: =G52*H52 -> 0 | K52: =F52+I52+J52 -> 0
D53: LS | E53: 0 | F53: =C53*E53 -> 0 | H53: 0 | I53: =G53*H53 -> 0 | K53: =F53+I53+J53 -> 0
J55: Sub Total | K55: =SUM(K49:K54) -> 0
A56: CODE | B56: DESCRIPTION | C56: Materials & Equipment | G56: Labor
A57: 03 40 00 | B57: Precast Concrete | C57: Qty | D57: Unit | E57: U. Price | F57: Sub Total | G57: MHrs | H57: U. Price | I57: Sub Total | J57: Quote | K57: Total
D58: LS | E58: 0 | F58: =C58*E58 -> 0 | H58: 0 | I58: =G58*H58 -> 0 | K58: =F58+I58+J58 -> 0
D59: LS | E59: 0 | F59: =C59*E59 -> 0 | H59: 0 | I59: =G59*H59 -> 0 | K59: =F59+I59+J59 -> 0
D60: LS | E60: 0 | F60: =C60*E60 -> 0 | H60: 0 | I60: =G60*H60 -> 0 | K60: =F60+I60+J60 -> 0
D61: LS | E61: 0 | F61: =C61*E61 -> 0 | H61: 0 | I61: =G61*H61 -> 0 | K61: =F61+I61+J61 -> 0
D62: LS | E62: 0 | F62: =C62*E62 -> 0 | H62: 0 | I62: =G62*H62 -> 0 | K62: =F62+I62+J62 -> 0
D63: LS | E63: 0 | F63: =C63*E63 -> 0 | H63: 0 | I63: =G63*H63 -> 0 | K63: =F63+I63+J63 -> 0
D64: LS | E64: 0 | F64: =C64*E64 -> 0 | H64: 0 | I64: =G64*H64 -> 0 | K64: =F64+I64+J64 -> 0
J66: Sub Total | K66: =SUM(K58:K65) -> 0
A67: CODE | B67: DESCRIPTION | C67: Materials & Equipment | G67: Labor
A68: 03 60 00 | B68: Foundation Materials | C68: Qty | D68: Unit | E68: U. Price | F68: Sub Total | G68: MHrs | H68: U. Price | I68: Sub Total | J68: Quote | K68: Total
A69: 03 60 01 | B69: Insulation | D69: sheet | E69: 18.95 | F69: =C69*E69 -> 0 | H69: 0 | I69: =G69*H69 -> 0 | K69: =F69+I69+J69 -> 0
A70: 03 60 02 | B70: Vapour Barrier | D70: rolls | E70: 100 | F70: =C70*E70 -> 0 | H70: 0 | I70: =G70*H70 -> 0 | K70: =F70+I70+J70 -> 0
D71: LS | E71: 0 | F71: =C71*E71 -> 0 | H71: 0 | I71: =G71*H71 -> 0 | K71: =F71+I71+J71 -> 0
D72: LS | E72: 0 | F72: =C72*E72 -> 0 | H72: 0 | I72: =G72*H72 -> 0 | K72: =F72+I72+J72 -> 0
D73: LS | E73: 0 | F73: =C73*E73 -> 0 | H73: 0 | I73: =G73*H73 -> 0 | K73: =F73+I73+J73 -> 0
J75: Sub Total | K75: =SUM(K69:K74) -> 0
F76: Material Total | G76: Total Hours | I76: Labor Total | J76: Contractor Total | K76: TOTAL
A77: $ / Sq.Ft | B77: TOTAL DIVISION 3
A78: =K78/E6 -> 0 | F78: =SUM(F69:F74,F58:F65,F49:F54,F40:F45,F29:F36,F13:F25) -> 0 | G78: =SUM(G69:G74,G58:G65,G49:G54,G40:G45,G29:G36,G13:G24) -> 0 | I78: =SUM(I69:I74,I58:I65,I49:I54,I40:I45,I29:I36,I13:I25) -> 0 | J78: =SUM(J69:J74,J58:J64,J49:J54,J40:J45,J29:J36,J13:J25) -> 0 | K78: =SUM(K75,K66,K55,K46,K37,K26) -> 0

Sheet 4
C1: ='Estimate Summary'!C1:H1 -> 0
G5: Masonry | J5: Schedule
D6: ='Estimate Summary'!C11 -> Area: | E6: ='Estimate Summary'!D11 -> 1747 | F6: ='Estimate Summary'!E11 -> Sq. Ft. | J6: ='1'!J6 -> 13 | K6: Weeks
A11: CODE | B11: DESCRIPTION | C11: Materials & Equipment | G11: Labor | L11: Sub Contractor | M11: Quote Total | N11: Additional Quote Info
A12: 04 20 00 | B12: Unit Masonry | C12: Qty | D12: Unit | E12: U. Price | F12: Sub Total | G12: MHrs | H12: U. Price | I12: Sub Total | J12: Quote | K12: Total
D13: LS | E13: 0 | F13: =C13*E13 -> 0 | H13: 0 | I13: =G13*H13 -> 0 | K13: =F13+I13+J13 -> 0
D14: LS | E14: 0 | F14: =C14*E14 -> 0 | H14: 0 | I14: =G14*H14 -> 0 | K14: =F14+I14+J14 -> 0
D15: LS | E15: 0 | F15: =C15*E15 -> 0 | H15: 0 | I15: =G15*H15 -> 0 | K15: =F15+I15+J15 -> 0
D16: LS | E16: 0 | F16: =C16*E16 -> 0 | H16: 0 | I16: =G16*H16 -> 0 | K16: =F16+I16+J16 -> 0
D17: LS | E17: 0 | F17: =C17*E17 -> 0 | H17: 0 | I17: =G17*H17 -> 0 | K17: =F17+I17+J17 -> 0
D18: LS | E18: 0 | F18: =C18*E18 -> 0 | H18: 0 | I18: =G18*H18 -> 0 | K18: =F18+I18+J18 -> 0
D19: LS | E19: 0 | F19: =C19*E19 -> 0 | H19: 0 | I19: =G19*H19 -> 0 | K19: =F19+I19+J19 -> 0
D20: LS | E20: 0 | F20: =C20*E20 -> 0 | H20: 0 | I20: =G20*H20 -> 0 | K20: =F20+I20+J20 -> 0
D21: LS | E21: 0 | F21: =C21*E21 -> 0 | H21: 0 | I21: =G21*H21 -> 0 | K21: =F21+I21+J21 -> 0
D22: LS | E22: 0 | F22: =C22*E22 -> 0 | H22: 0 | I22: =G22*H22 -> 0 | K22: =F22+I22+J22 -> 0
D23: LS | E23: 0 | F23: =C23*E23 -> 0 | H23: 0 | I23: =G23*H23 -> 0 | K23: =F23+I23+J23 -> 0
D24: LS | E24: 0 | F24: =C24*E24 -> 0 | H24: 0 | I24: =G24*H24 -> 0 | K24: =F24+I24+J24 -> 0
J26: Sub Total | K26: =SUM(K13:K25) -> 0
A27: CODE | B27: DESCRIPTION | C27: Materials & Equipment | G27: Labor
A28: 04 43 00 | B28: Stone Masonry | C28: Qty | D28: Unit | E28: U. Price | F28: Sub Total | G28: MHrs | H28: U. Price | I28: Sub Total | J28: Quote | K28: Total
D29: LS | E29: 0 | F29: =C29*E29 -> 0 | H29: 0 | I29: =G29*H29 -> 0 | K29: =F29+I29+J29 -> 0
D30: LS | E30: 0 | F30: =C30*E30 -> 0 | H30: 0 | I30: =G30*H30 -> 0 | K30: =F30+I30+J30 -> 0
D31: LS | E31: 0 | F31: =C31*E31 -> 0 | H31: 0 | I31: =G31*H31 -> 0 | K31: =F31+I31+J31 -> 0
D32: LS | E32: 0 | F32: =C32*E32 -> 0 | H32: 0 | I32: =G32*H32 -> 0 | K32: =F32+I32+J32 -> 0
D33: LS | E33: 0 | F33: =C33*E33 -> 0 | H33: 0 | I33: =G33*H33 -> 0 | K33: =F33+I33+J33 -> 0
D34: LS | E34: 0 | F34: =C34*E34 -> 0 | H34: 0 | I34: =G34*H34 -> 0 | K34: =F34+I34+J34 -> 0
D35: LS | E35: 0 | F35: =C35*E35 -> 0 | H35: 0 | I35: =G35*H35 -> 0 | K35: =F35+I35+J35 -> 0
J37: Sub Total | K37: =SUM(K29:K36) -> 0
A38: CODE | B38: DESCRIPTION | C38: Materials & Equipment | G38: Labor
C39: Qty | D39: Unit | E39: U. Price | F39: Sub Total | G39: MHrs | H39: U. Price | I39: Sub Total | J39: Quote | K39: Total
D40: LS | E40: 0 | F40: =C40*E40 -> 0 | H40: 0 | I40: =G40*H40 -> 0 | K40: =F40+I40+J40 -> 0
D41: LS | E41: 0 | F41: =C41*E41 -> 0 | H41: 0 | I41: =G41*H41 -> 0 | K41: =F41+I41+J41 -> 0
D42: LS | E42: 0 | F42: =C42*E42 -> 0 | H42: 0 | I42: =G42*H42 -> 0 | K42: =F42+I42+J42 -> 0
J45: Sub Total | K45: =SUM(K40:K44) -> 0
A46: CODE | B46: DESCRIPTION | C46: Materials & Equipment | G46: Labor
C47: Qty | D47: Unit | E47: U. Price | F47: Sub Total | G47: MHrs | H47: U. Price | I47: Sub Total | J47: Quote | K47: Total
D48: LS | E48: 0 | F48: =C48*E48 -> 0 | H48: 0 | I48: =G48*H48 -> 0 | K48: =F48+I48+J48 -> 0
D49: LS | E49: 0 | F49: =C49*E49 -> 0 | H49: 0 | I49: =G49*H49 -> 0 | K49: =F49+I49+J49 -> 0
D50: LS | E50: 0 | F50: =C50*E50 -> 0 | H50: 0 | I50: =G50*H50 -> 0 | K50: =F50+I50+J50 -> 0
D51: LS | E51: 0 | F51: =C51*E51 -> 0 | H51: 0 | I51: =G51*H51 -> 0 | K51: =F51+I51+J51 -> 0
D52: LS | E52: 0 | F52: =C52*E52 -> 0 | H52: 0 | I52: =G52*H52 -> 0 | K52: =F52+I52+J52 -> 0
J54: Sub Total | K54: =SUM(K48:K53) -> 0
A55: CODE | B55: DESCRIPTION | C55: Materials & Equipment | G55: Labor
C56: Qty | D56: Unit | E56: U. Price | F56: Sub Total | G56: MHrs | H56: U. Price | I56: Sub Total | J56: Quote | K56: Total
D57: LS | E57: 0 | F57: =C57*E57 -> 0 | H57: 0 | I57: =G57*H57 -> 0 | K57: =F57+I57+J57 -> 0
D58: LS | E58: 0 | F58: =C58*E58 -> 0 | H58: 0 | I58: =G58*H58 -> 0 | K58: =F58+I58+J58 -> 0
D59: LS | E59: 0 | F59: =C59*E59 -> 0 | H59: 0 | I59: =G59*H59 -> 0 | K59: =F59+I59+J59 -> 0
D60: LS | E60: 0 | F60: =C60*E60 -> 0 | H60: 0 | I60: =G60*H60 -> 0 | K60: =F60+I60+J60 -> 0
D61: LS | E61: 0 | F61: =C61*E61 -> 0 | H61: 0 | I61: =G61*H61 -> 0 | K61: =F61+I61+J61 -> 0
D62: LS | E62: 0 | F62: =C62*E62 -> 0 | H62: 0 | I62: =G62*H62 -> 0 | K62: =F62+I62+J62 -> 0
D63: LS | E63: 0 | F63: =C63*E63 -> 0 | H63: 0 | I63: =G63*H63 -> 0 | K63: =F63+I63+J63 -> 0
J65: Sub Total | K65: =SUM(K57:K64) -> 0
F66: Material Total | G66: Total Hours | I66: Labor Total | J66: Contractor Total | K66: TOTAL
A67: $ / Sq.Ft | B67: TOTAL DIVISION 4
A68: =K68/E6 -> 0 | F68: =SUM(F57:F64,F48:F53,F40:F44,F29:F36,F13:F25) -> 0 | G68: =SUM(G57:G64,G48:G53,G40:G44,G29:G36,G13:G25) -> 0 | I68: =SUM(I57:I64,I48:I53,I40:I44,I29:I36,I13:I25) -> 0 | J68: =SUM(J57:J64,J48:J53,J40:J44,J29:J36,J13:J25) -> 0 | K68: =K65+K54+K45+K37+K26 -> 0

Sheet 5
C1: ='Estimate Summary'!C1:H1 -> 0
G5: Metals | J5: Schedule
D6: ='Estimate Summary'!C11 -> Area: | E6: ='Estimate Summary'!D11 -> 1747 | F6: ='Estimate Summary'!E11 -> Sq. Ft. | J6: ='1'!J6 -> 13 | K6: Weeks
A11: CODE | B11: DESCRIPTION | C11: Materials & Equipment | G11: Labor | L11: Sub Contractor | M11: Quote Total | N11: Additional Quote Info
A12: 05 12 00 | B12: Structural Steel Framing | C12: Qty | D12: Unit | E12: U. Price | F12: Sub Total | G12: MHrs | H12: U. Price | I12: Sub Total | J12: Quote | K12: Total
D13: LS | E13: 0 | F13: =C13*E13 -> 0 | H13: 0 | I13: =G13*H13 -> 0 | K13: =F13+I13+J13 -> 0
D14: LS | E14: 0 | F14: =C14*E14 -> 0 | H14: 0 | I14: =G14*H14 -> 0 | K14: =F14+I14+J14 -> 0
D15: LS | E15: 0 | F15: =C15*E15 -> 0 | H15: 0 | I15: =G15*H15 -> 0 | K15: =F15+I15+J15 -> 0
D16: LS | E16: 0 | F16: =C16*E16 -> 0 | H16: 0 | I16: =G16*H16 -> 0 | K16: =F16+I16+J16 -> 0
D17: LS | E17: 0 | F17: =C17*E17 -> 0 | H17: 0 | I17: =G17*H17 -> 0 | K17: =F17+I17+J17 -> 0
D18: LS | E18: 0 | F18: =C18*E18 -> 0 | H18: 0 | I18: =G18*H18 -> 0 | K18: =F18+I18+J18 -> 0
D19: LS | E19: 0 | F19: =C19*E19 -> 0 | H19: 0 | I19: =G19*H19 -> 0 | K19: =F19+I19+J19 -> 0
D20: LS | E20: 0 | F20: =C20*E20 -> 0 | H20: 0 | I20: =G20*H20 -> 0 | K20: =F20+I20+J20 -> 0
D21: LS | E21: 0 | F21: =C21*E21 -> 0 | H21: 0 | I21: =G21*H21 -> 0 | K21: =F21+I21+J21 -> 0
D22: LS | E22: 0 | F22: =C22*E22 -> 0 | H22: 0 | I22: =G22*H22 -> 0 | K22: =F22+I22+J22 -> 0
D23: LS | E23: 0 | F23: =C23*E23 -> 0 | H23: 0 | I23: =G23*H23 -> 0 | K23: =F23+I23+J23 -> 0
D24: LS | E24: 0 | F24: =C24*E24 -> 0 | H24: 0 | I24: =G24*H24 -> 0 | K24: =F24+I24+J24 -> 0
J26: Sub Total | K26: =SUM(K13:K25) -> 0
A27: CODE | B27: DESCRIPTION | C27: Materials & Equipment | G27: Labor
A28: 05 20 00 | B28: Metal Joists | C28: Qty | D28: Unit | E28: U. Price | F28: Sub Total | G28: MHrs | H28: U. Price | I28: Sub Total | J28: Quote | K28: Total
D29: LS | E29: 0 | F29: =C29*E29 -> 0 | H29: 0 | I29: =G29*H29 -> 0 | K29: =F29+I29+J29 -> 0
D30: LS | E30: 0 | F30: =C30*E30 -> 0 | H30: 0 | I30: =G30*H30 -> 0 | K30: =F30+I30+J30 -> 0
D31: LS | E31: 0 | F31: =C31*E31 -> 0 | H31: 0 | I31: =G31*H31 -> 0 | K31: =F31+I31+J31 -> 0
D32: LS | E32: 0 | F32: =C32*E32 -> 0 | H32: 0 | I32: =G32*H32 -> 0 | K32: =F32+I32+J32 -> 0
D33: LS | E33: 0 | F33: =C33*E33 -> 0 | H33: 0 | I33: =G33*H33 -> 0 | K33: =F33+I33+J33 -> 0
D34: LS | E34: 0 | F34: =C34*E34 -> 0 | H34: 0 | I34: =G34*H34 -> 0 | K34: =F34+I34+J34 -> 0
D35: LS | E35: 0 | F35: =C35*E35 -> 0 | H35: 0 | I35: =G35*H35 -> 0 | K35: =F35+I35+J35 -> 0
J37: Sub Total | K37: =SUM(K29:K36) -> 0
A38: CODE | B38: DESCRIPTION | C38: Materials & Equipment | G38: Labor
A39: 05 30 00 | B39: Metal Decking | C39: Qty | D39: Unit | E39: U. Price | F39: Sub Total | G39: MHrs | H39: U. Price | I39: Sub Total | J39: Quote | K39: Total
D40: LS | E40: 0 | F40: =C40*E40 -> 0 | H40: 0 | I40: =G40*H40 -> 0 | K40: =F40+I40+J40 -> 0
D41: LS | E41: 0 | F41: =C41*E41 -> 0 | H41: 0 | I41: =G41*H41 -> 0 | K41: =F41+I41+J41 -> 0
D42: LS | E42: 0 | F42: =C42*E42 -> 0 | H42: 0 | I42: =G42*H42 -> 0 | K42: =F42+I42+J42 -> 0
J45: Sub Total | K45: =SUM(K40:K44) -> 0
A46: CODE | B46: DESCRIPTION | C46: Materials & Equipment | G46: Labor
A47: 05 51 00 | B47: Metal Stairs | C47: Qty | D47: Unit | E47: U. Price | F47: Sub Total | G47: MHrs | H47: U. Price | I47: Sub Total | J47: Quote | K47: Total
D48: LS | E48: 0 | F48: =C48*E48 -> 0 | H48: 0 | I48: =G48*H48 -> 0 | K48: =F48+I48+J48 -> 0
D49: LS | E49: 0 | F49: =C49*E49 -> 0 | H49: 0 | I49: =G49*H49 -> 0 | K49: =F49+I49+J49 -> 0
D50: LS | E50: 0 | F50: =C50*E50 -> 0 | H50: 0 | I50: =G50*H50 -> 0 | K50: =F50+I50+J50 -> 0
D51: LS | E51: 0 | F51: =C51*E51 -> 0 | H51: 0 | I51: =G51*H51 -> 0 | K51: =F51+I51+J51 -> 0
D52: LS | E52: 0 | F52: =C52*E52 -> 0 | H52: 0 | I52: =G52*H52 -> 0 | K52: =F52+I52+J52 -> 0
J54: Sub Total | K54: =SUM(K48:K53) -> 0
A55: CODE | B55: DESCRIPTION | C55: Materials & Equipment | G55: Labor
A56: 05 52 00 | B56: Metal Railings | C56: Qty | D56: Unit | E56: U. Price | F56: Sub Total | G56: MHrs | H56: U. Price | I56: Sub Total | J56: Quote | K56: Total
D57: LS | E57: 0 | F57: =C57*E57 -> 0 | H57: 0 | I57: =G57*H57 -> 0 | K57: =F57+I57+J57 -> 0
D58: LS | E58: 0 | F58: =C58*E58 -> 0 | H58: 0 | I58: =G58*H58 -> 0 | K58: =F58+I58+J58 -> 0
D59: LS | E59: 0 | F59: =C59*E59 -> 0 | H59: 0 | I59: =G59*H59 -> 0 | K59: =F59+I59+J59 -> 0
D60: LS | E60: 0 | F60: =C60*E60 -> 0 | H60: 0 | I60: =G60*H60 -> 0 | K60: =F60+I60+J60 -> 0
D61: LS | E61: 0 | F61: =C61*E61 -> 0 | H61: 0 | I61: =G61*H61 -> 0 | K61: =F61+I61+J61 -> 0
D62: LS | E62: 0 | F62: =C62*E62 -> 0 | H62: 0 | I62: =G62*H62 -> 0 | K62: =F62+I62+J62 -> 0
D63: LS | E63: 0 | F63: =C63*E63 -> 0 | H63: 0 | I63: =G63*H63 -> 0 | K63: =F63+I63+J63 -> 0
J65: Sub Total | K65: =SUM(K57:K64) -> 0
A66: CODE | B66: DESCRIPTION | C66: Materials & Equipment | G66: Labor
A67: 05 59 00 | B67: Metal Specialties | C67: Qty | D67: Unit | E67: U. Price | F67: Sub Total | G67: MHrs | H67: U. Price | I67: Sub Total | J67: Quote | K67: Total
D68: LS | E68: 0 | F68: =C68*E68 -> 0 | H68: 0 | I68: =G68*H68 -> 0 | K68: =F68+I68+J68 -> 0
D69: LS | E69: 0 | F69: =C69*E69 -> 0 | H69: 0 | I69: =G69*H69 -> 0 | K69: =F69+I69+J69 -> 0
D70: LS | E70: 0 | F70: =C70*E70 -> 0 | H70: 0 | I70: =G70*H70 -> 0 | K70: =F70+I70+J70 -> 0
D71: LS | E71: 0 | F71: =C71*E71 -> 0 | H71: 0 | I71: =G71*H71 -> 0 | K71: =F71+I71+J71 -> 0
D72: LS | E72: 0 | F72: =C72*E72 -> 0 | H72: 0 | I72: =G72*H72 -> 0 | K72: =F72+I72+J72 -> 0
J74: Sub Total | K74: =SUM(K68:K73) -> 0
F75: Material Total | G75: Total Hours | I75: Labor Total | J75: Contractor Total | K75: TOTAL
A76: $ / Sq.Ft | B76: TOTAL DIVISION 5
A77: =K77/E6 -> 0 | F77: =SUM(F68:F73,F57:F64,F48:F53,F40:F44,F29:F36,F13:F25) -> 0 | G77: =SUM(G68:G73,G57:G64,G48:G53,G40:G44,G29:G36,G13:G24) -> 0 | I77: =SUM(I68:I73,I57:I64,I48:I53,I40:I44,I29:I36,I13:I25) -> 0 | J77: =SUM(J68:J73,J57:J63,J48:J53,J40:J44,J29:J36,J13:J25) -> 0 | K77: =SUM(,K74,K65,K54,K45,K37,K26) -> 0

Sheet 6
C1: ='Estimate Summary'!C1:H1 -> 0
G5: Wood & Plastics | J5: Schedule
D6: ='Estimate Summary'!C11 -> Area: | E6: ='Estimate Summary'!D11 -> 1747 | F6: ='Estimate Summary'!E11 -> Sq. Ft. | J6: ='1'!J6 -> 13 | K6: Weeks
A9: CODE | B9: DESCRIPTION | C9: Materials & Equipment | G9: Labor | L9: Sub Contractor | M9: Quote Total | N9: Additional Quote Info
A10: 06 11 00 | B10: Framing Labour | C10: Qty | D10: Unit | E10: U. Price | F10: Sub Total | G10: MHrs | H10: U. Price | I10: Sub Total | J10: Quote | K10: Total
H11: 0 | I11: =G11*H11 -> 0 | K11: =F11+I11+J11 -> 0
G12: 20 | H12: 65 | I12: =G12*H12 -> 1300 | K12: =F12+I12+J12 -> 1300
H13: 0 | I13: =G13*H13 -> 0 | K13: =F13+I13+J13 -> 0
H14: 0 | I14: =G14*H14 -> 0 | K14: =F14+I14+J14 -> 0
H15: 0 | I15: =G15*H15 -> 0 | K15: =F15+I15+J15 -> 0
H16: 0 | I16: =G16*H16 -> 0 | K16: =F16+I16+J16 -> 0
H17: 0 | I17: =G17*H17 -> 0 | K17: =F17+I17+J17 -> 0
J19: Sub Total | K19: =SUM(K11:K18) -> 1300
A20: 06 20 00 | B20: Framing Materials | C20: Qty | D20: Unit | E20: U. Price | F20: Sub Total | J20: Quote | K20: Total
B22: 2x4 Stud (utility room stacked equipment) | C22: 32 | D22: ft | E22: 0.61 | F22: =C22*E22 -> 19.52 | K22: =F22+I22+J22 -> 19.52
B23: 2x6 Stud | D23: ft | E23: 0.81 | F23: =C23*E23 -> 0 | K23: =F23+I23+J23 -> 0
B24: 4x4 (utility room stacked equipment) | C24: 15 | D24: ft | E24: 1.24 | F24: =C24*E24 -> 18.6 | K24: =F24+I24+J24 -> 18.6
B25: 2x10 | D25: ft | E25: 1.61 | F25: =C25*E25 -> 0 | K25: =F25+I25+J25 -> 0
B26: 1x3 | D26: ft | E26: 0.25 | F26: =C26*E26 -> 0 | K26: =F26+I26+J26 -> 0
B27: 1x4 | D27: ft | E27: 0.37 | F27: =C27*E27 -> 0 | K27: =F27+I27+J27 -> 0
B28: PLYWOOD | K28: =F28+I28+J28 -> 0
B29: 1/2" Standard | D29: EA | E29: 66.98 | F29: =C29*E29 -> 0 | K29: =F29+I29+J29 -> 0
B30: 5/8" Standard | D30: EA | E30: 43.69 | F30: =C30*E30 -> 0 | K30: =F30+I30+J30 -> 0
B31: 3/4" Standard | C31: 16 | D31: EA | E31: 87.98 | F31: =C31*E31 -> 1407.68 | K31: =F31+I31+J31 -> 1407.68
B32: Fasteners and consumables | C32: 1 | D32: LS | E32: 550 | F32: =C32*E32 -> 550 | K32: =F32+I32+J32 -> 550
B33: 5/8" OSB T&G | D33: EA | E33: 22.74 | F33: =C33*E33 -> 0 | K33: =F33+I33+J33 -> 0
J36: Sub Total | K36: =SUM(K21:K35) -> 1995.8
A37: CODE | B37: DESCRIPTION | C37: Materials & Equipment | G37: Labor
A38: 06 22 00 | B38: Millwork | C38: Qty | D38: Unit | E38: U. Price | F38: Sub Total | G38: MHrs | H38: U. Price | I38: Sub Total | J38: Quote | K38: Total
B39: Reception Desk | C39: 23 | D39: LF | E39: 400 | F39: 0 | H39: 0 | I39: =G39*H39 -> 0 | J39: =M39 -> 180875 | K39: =F39+I39+J39 -> 180875 | L39: Foxwoods | M39: 180875 | N39: Stainless steel counter included
B40: Hygene Rooms | C40: =15+14+14 -> 43 | D40: LF | E40: 400 | F40: 0 | H40: 0 | I40: =G40*H40 -> 0 | K40: =F40+I40+J40 -> 0 | L40: Foxwoods | M40: 164700 | N40: Alternate spec
B41: Lab & Storage | C41: 20 | D41: LF | E41: 400 | F41: 0 | H41: 0 | I41: =G41*H41 -> 0 | K41: =F41+I41+J41 -> 0 | L41: Lux KBS | M41: 315000
B42: Staff Room | C42: 8 | D42: LF | E42: 400 | F42: 0 | H42: 0 | I42: =G42*H42 -> 0 | K42: =F42+I42+J42 -> 0 | L42: Lux KBS | M42: 254000 | N42: Revised
B43: Workstations | C43: 17 | D43: LF | E43: 400 | F43: 0 | H43: 0 | I43: =G43*H43 -> 0 | K43: =F43+I43+J43 -> 0 | L43: Procase | N43: To send quote this week
B44: Sterilization | C44: 14 | D44: LF | E44: 400 | F44: 0 | H44: 0 | I44: =G44*H44 -> 0 | K44: =F44+I44+J44 -> 0
B45: OP Rooms | C45: =13+15+13+12 -> 53 | D45: LF | E45: 400 | F45: 0 | H45: 0 | I45: =G45*H45 -> 0 | K45: =F45+I45+J45 -> 0
B46: Washrooms | C46: 9 | D46: LF | E46: 400 | F46: 0 | H46: 0 | I46: =G46*H46 -> 0 | K46: =F46+I46+J46 -> 0
B47: Imaging | C47: 3 | D47: LF | E47: 400 | F47: 0 | H47: 0 | I47: =G47*H47 -> 0 | K47: =F47+I47+J47 -> 0
B48: Sterilization | D48: LF | E48: 0 | F48: =C48*E48 -> 0 | H48: 0 | I48: =G48*H48 -> 0 | K48: =F48+I48+J48 -> 0
D49: LS | E49: 0 | F49: =C49*E49 -> 0 | H49: 0 | I49: =G49*H49 -> 0 | K49: =F49+I49+J49 -> 0 | L49: Mountain view Dental | M49: 128488.12 | N49: 2052sf
L50: Tusk dental | M50: 45262 | N50: 1300sf
J51: Sub Total | K51: =SUM(K39:K50) -> 180875
A52: CODE | B52: DESCRIPTION | C52: Materials & Equipment | G52: Labor
A53: 06 41 00 | B53: Architechtural Wood Casework | C53: Qty | D53: Unit | E53: U. Price | F53: Sub Total | G53: MHrs | H53: U. Price | I53: Sub Total | J53: Quote | K53: Total
D54: LS | E54: 0 | F54: =C54*E54 -> 0 | H54: 0 | I54: =G54*H54 -> 0 | K54: =F54+I54+J54 -> 0
D55: LS | E55: 0 | F55: =C55*E55 -> 0 | H55: 0 | I55: =G55*H55 -> 0 | K55: =F55+I55+J55 -> 0
D56: LS | E56: 0 | F56: =C56*E56 -> 0 | H56: 0 | I56: =G56*H56 -> 0 | K56: =F56+I56+J56 -> 0
J59: Sub Total | K59: =SUM(K54:K58) -> 0
A60: CODE | B60: DESCRIPTION | C60: Materials & Equipment | G60: Labor
A61: 06 42 00 | B61: Wood Paneling | C61: Qty | D61: Unit | E61: U. Price | F61: Sub Total | G61: MHrs | H61: U. Price | I61: Sub Total | J61: Quote | K61: Total
D62: LS | E62: 0 | F62: =C62*E62 -> 0 | H62: 0 | I62: =G62*H62 -> 0 | K62: =F62+I62+J62 -> 0
D63: LS | E63: 0 | F63: =C63*E63 -> 0 | H63: 0 | I63: =G63*H63 -> 0 | K63: =F63+I63+J63 -> 0
D64: LS | E64: 0 | F64: =C64*E64 -> 0 | H64: 0 | I64: =G64*H64 -> 0 | K64: =F64+I64+J64 -> 0
D65: LS | E65: 0 | F65: =C65*E65 -> 0 | H65: 0 | I65: =G65*H65 -> 0 | K65: =F65+I65+J65 -> 0
D66: LS | E66: 0 | F66: =C66*E66 -> 0 | H66: 0 | I66: =G66*H66 -> 0 | K66: =F66+I66+J66 -> 0
J68: Sub Total | K68: =SUM(K62:K67) -> 0
A69: CODE | B69: DESCRIPTION | C69: Materials & Equipment | G69: Labor
A70: 06 43 00 | B70: Wood Stairs and Railings | C70: Qty | D70: Unit | E70: U. Price | F70: Sub Total | G70: MHrs | H70: U. Price | I70: Sub Total | J70: Quote | K70: Total
D71: LS | E71: 0 | F71: =C71*E71 -> 0 | H71: 0 | I71: =G71*H71 -> 0 | K71: =F71+I71+J71 -> 0
D72: LS | E72: 0 | F72: =C72*E72 -> 0 | H72: 0 | I72: =G72*H72 -> 0 | K72: =F72+I72+J72 -> 0
D73: LS | E73: 0 | F73: =C73*E73 -> 0 | H73: 0 | I73: =G73*H73 -> 0 | K73: =F73+I73+J73 -> 0
D74: LS | E74: 0 | F74: =C74*E74 -> 0 | H74: 0 | I74: =G74*H74 -> 0 | K74: =F74+I74+J74 -> 0
D75: LS | E75: 0 | F75: =C75*E75 -> 0 | H75: 0 | I75: =G75*H75 -> 0 | K75: =F75+I75+J75 -> 0
D76: LS | E76: 0 | F76: =C76*E76 -> 0 | H76: 0 | I76: =G76*H76 -> 0 | K76: =F76+I76+J76 -> 0
D77: LS | E77: 0 | F77: =C77*E77 -> 0 | H77: 0 | I77: =G77*H77 -> 0 | K77: =F77+I77+J77 -> 0
J79: Sub Total | K79: =SUM(K71:K78) -> 0
A80: CODE | B80: DESCRIPTION | C80: Materials & Equipment | G80: Labor
A81: 06 46 00 | B81: Wood Trim | C81: Qty | D81: Unit | E81: U. Price | F81: Sub Total | G81: MHrs | H81: U. Price | I81: Sub Total | J81: Quote | K81: Total
D82: LS | E82: 0 | F82: =C82*E82 -> 0 | H82: 0 | I82: =G82*H82 -> 0 | K82: =F82+I82+J82 -> 0
D83: LS | E83: 0 | F83: =C83*E83 -> 0 | H83: 0 | I83: =G83*H83 -> 0 | K83: =F83+I83+J83 -> 0
D84: LS | E84: 0 | F84: =C84*E84 -> 0 | H84: 0 | I84: =G84*H84 -> 0 | K84: =F84+I84+J84 -> 0
D85: LS | E85: 0 | F85: =C85*E85 -> 0 | H85: 0 | I85: =G85*H85 -> 0 | K85: =F85+I85+J85 -> 0
D86: LS | E86: 0 | F86: =C86*E86 -> 0 | H86: 0 | I86: =G86*H86 -> 0 | K86: =F86+I86+J86 -> 0
J88: Sub Total | K88: =SUM(K82:K87) -> 0
A89: CODE | B89: DESCRIPTION | C89: Materials & Equipment | G89: Labor
A90: 06 48 00 | B90: Wood Frames | C90: Qty | D90: Unit | E90: U. Price | F90: Sub Total | G90: MHrs | H90: U. Price | I90: Sub Total | J90: Quote | K90: Total
D91: LS | E91: 0 | F91: =C91*E91 -> 0 | H91: 0 | I91: =G91*H91 -> 0 | K91: =F91+I91+J91 -> 0
D92: LS | E92: 0 | F92: =C92*E92 -> 0 | H92: 0 | I92: =G92*H92 -> 0 | K92: =F92+I92+J92 -> 0
D93: LS | E93: 0 | F93: =C93*E93 -> 0 | H93: 0 | I93: =G93*H93 -> 0 | K93: =F93+I93+J93 -> 0
J95: Sub Total | K95: =SUM(K91:K94) -> 0
F96: Material Total | G96: Total Hours | I96: Labor Total | J96: Contractor Total | K96: TOTAL
A97: $ / Sq.Ft | B97: TOTAL DIVISION 6
A98: =K98/E6 -> 105.42118 | F98: =SUM(F91:F94,F82:F87,F71:F77,F62:F67,F54:F58,F39:F50,F21:F35,F11:F17) -> 1995.8 | G98: =SUM(G91:G94,G82:G87,G71:G77,G62:G67,G54:G58,G39:G50,G21:G35,G11:G17) -> 20 | I98: =SUM(I91:I94,I82:I87,I71:I77,I62:I67,I54:I58,I39:I50,I21:I35,I11:I17) -> 1300 | J98: =SUM(J91:J94,J82:J87,J71:J77,J62:J67,J54:J58,J39:J50,J21:J35,J11:J17) -> 180875 | K98: =SUM(K95,K88,K79,K68,K59,K51,K36,K19) -> 184170.8

Sheet 7
C1: ='Estimate Summary'!C1:H1 -> 0
G5: Thermal & Moisture Protection | J5: Schedule
D6: ='Estimate Summary'!C11 -> Area: | E6: ='Estimate Summary'!D11 -> 1747 | F6: ='Estimate Summary'!E11 -> Sq. Ft. | J6: ='1'!J6 -> 13 | K6: Weeks
A9: CODE | B9: DESCRIPTION | C9: Materials & Equipment | G9: Labor | L9: Sub Contractor | M9: Quote Total | N9: Additional Quote Info
A10: 07 21 00 | B10: Thermal Insulation | C10: Qty | D10: Unit | E10: U. Price | F10: Sub Total | G10: MHrs | H10: U. Price | I10: Sub Total | J10: Quote | K10: Total
A11: 07 21 16 | B11: Blanket Insulation | D11: LS | E11: 0 | F11: =C11*E11 -> 0 | H11: 0 | I11: =G11*H11 -> 0 | K11: =F11+I11+J11 -> 0
A12: 07 21 26 | B12: Blown Insulation | D12: LS | E12: 0 | F12: =C12*E12 -> 0 | H12: 0 | I12: =G12*H12 -> 0 | K12: =F12+I12+J12 -> 0
A13: 07 21 29 | B13: Sprayed Insulation | D13: LS | E13: 0 | F13: =C13*E13 -> 0 | H13: 0 | I13: =G13*H13 -> 0 | K13: =F13+I13+J13 -> 0
D14: LS | E14: 0 | F14: =C14*E14 -> 0 | H14: 0 | I14: =G14*H14 -> 0 | K14: =F14+I14+J14 -> 0
J16: Sub Total | K16: =SUM(K11:K15) -> 0
A17: CODE | B17: DESCRIPTION | C17: Materials & Equipment | G17: Labor
A18: 07 24 00 | B18: EIFS | C18: Qty | D18: Unit | E18: U. Price | F18: Sub Total | G18: MHrs | H18: U. Price | I18: Sub Total | J18: Quote | K18: Total
D19: LS | E19: 0 | F19: =C19*E19 -> 0 | H19: 0 | I19: =G19*H19 -> 0 | K19: =F19+I19+J19 -> 0
D20: LS | E20: 0 | F20: =C20*E20 -> 0 | H20: 0 | I20: =G20*H20 -> 0 | K20: =F20+I20+J20 -> 0
D21: LS | E21: 0 | F21: =C21*E21 -> 0 | H21: 0 | I21: =G21*H21 -> 0 | K21: =F21+I21+J21 -> 0
J22: Sub Total | K22: =SUM(K19:K21) -> 0
A23: CODE | B23: DESCRIPTION | C23: Materials & Equipment | G23: Labor
A24: 07 31 00 | B24: Shingles | C24: Qty | D24: Unit | E24: U. Price | F24: Sub Total | G24: MHrs | H24: U. Price | I24: Sub Total | J24: Quote | K24: Total
D25: LS | E25: 0 | F25: =C25*E25 -> 0 | H25: 0 | I25: =G25*H25 -> 0 | K25: =F25+I25+J25 -> 0
D26: LS | E26: 0 | F26: =C26*E26 -> 0 | H26: 0 | I26: =G26*H26 -> 0 | K26: =F26+I26+J26 -> 0
J27: Sub Total | K27: =SUM(K25:K26) -> 0
A28: CODE | B28: DESCRIPTION | C28: Materials & Equipment | G28: Labor
A29: 07 42 00 | B29: Wall Panels | C29: Qty | D29: Unit | E29: U. Price | F29: Sub Total | G29: MHrs | H29: U. Price | I29: Sub Total | J29: Quote | K29: Total
D30: LS | E30: 0 | F30: =C30*E30 -> 0 | H30: 0 | I30: =G30*H30 -> 0 | K30: =F30+I30+J30 -> 0
D31: LS | E31: 0 | F31: =C31*E31 -> 0 | H31: 0 | I31: =G31*H31 -> 0 | K31: =F31+I31+J31 -> 0
D32: LS | E32: 0 | F32: =C32*E32 -> 0 | H32: 0 | I32: =G32*H32 -> 0 | K32: =F32+I32+J32 -> 0
J33: Sub Total | K33: =SUM(K30:K32) -> 0
A34: CODE | B34: DESCRIPTION | C34: Materials & Equipment | G34: Labor
A35: 07 46 00 | B35: Siding | C35: Qty | D35: Unit | E35: U. Price | F35: Sub Total | G35: MHrs | H35: U. Price | I35: Sub Total | J35: Quote | K35: Total
D36: LS | E36: 0 | F36: =C36*E36 -> 0 | H36: 0 | I36: =G36*H36 -> 0 | K36: =F36+I36+J36 -> 0
D37: LS | E37: 0 | F37: =C37*E37 -> 0 | H37: 0 | I37: =G37*H37 -> 0 | K37: =F37+I37+J37 -> 0
D38: LS | E38: 0 | F38: =C38*E38 -> 0 | H38: 0 | I38: =G38*H38 -> 0 | K38: =F38+I38+J38 -> 0
J39: Sub Total | K39: =SUM(K36:K38) -> 0
A40: CODE | B40: DESCRIPTION | C40: Materials & Equipment | G40: Labor
A41: 07 52 00 | B41: Modified Bituminous Membrane Roofing | C41: Qty | D41: Unit | E41: U. Price | F41: Sub Total | G41: MHrs | H41: U. Price | I41: Sub Total | J41: Quote | K41: Total
D42: LS | E42: 0 | F42: =C42*E42 -> 0 | H42: 0 | I42: =G42*H42 -> 0 | K42: =F42+I42+J42 -> 0
D43: LS | E43: 0 | F43: =C43*E43 -> 0 | H43: 0 | I43: =G43*H43 -> 0 | K43: =F43+I43+J43 -> 0
D44: LS | E44: 0 | F44: =C44*E44 -> 0 | H44: 0 | I44: =G44*H44 -> 0 | K44: =F44+I44+J44 -> 0
J45: Sub Total | K45: =SUM(K42:K44) -> 0
A46: CODE | B46: DESCRIPTION | C46: Materials & Equipment | G46: Labor
A47: 07 53 00 | B47: Elastomeric Membrane Roofing | C47: Qty | D47: Unit | E47: U. Price | F47: Sub Total | G47: MHrs | H47: U. Price | I47: Sub Total | J47: Quote | K47: Total
D48: LS | E48: 0 | F48: =C48*E48 -> 0 | H48: 0 | I48: =G48*H48 -> 0 | K48: =F48+I48+J48 -> 0
D49: LS | E49: 0 | F49: =C49*E49 -> 0 | H49: 0 | I49: =G49*H49 -> 0 | K49: =F49+I49+J49 -> 0
J50: Sub Total | K50: =SUM(K48:K49) -> 0
A51: CODE | B51: DESCRIPTION | C51: Materials & Equipment | G51: Labor
A52: 07 62 00 | B52: Sheet Metal Flashing and Trim | C52: Qty | D52: Unit | E52: U. Price | F52: Sub Total | G52: MHrs | H52: U. Price | I52: Sub Total | J52: Quote | K52: Total
D53: LS | E53: 0 | F53: =C53*E53 -> 0 | H53: 0 | I53: =G53*H53 -> 0 | K53: =F53+I53+J53 -> 0
D54: LS | E54: 0 | F54: =C54*E54 -> 0 | H54: 0 | I54: =G54*H54 -> 0 | K54: =F54+I54+J54 -> 0
J55: Sub Total | K55: =SUM(K53:K54) -> 0
A56: CODE | B56: DESCRIPTION | C56: Materials & Equipment | G56: Labor
A57: 07 63 00 | B57: Sheet Metal Roofing Specialties | C57: Qty | D57: Unit | E57: U. Price | F57: Sub Total | G57: MHrs | H57: U. Price | I57: Sub Total | J57: Quote | K57: Total
D58: LS | E58: 0 | F58: =C58*E58 -> 0 | H58: 0 | I58: =G58*H58 -> 0 | K58: =F58+I58+J58 -> 0
D59: LS | E59: 0 | F59: =C59*E59 -> 0 | H59: 0 | I59: =G59*H59 -> 0 | K59: =F59+I59+J59 -> 0
J60: Sub Total | K60: =SUM(K58:K59) -> 0
A61: CODE | B61: DESCRIPTION | C61: Materials & Equipment | G61: Labor
A62: 07 64 00 | B62: Sheet Metal Wall Cladding | C62: Qty | D62: Unit | E62: U. Price | F62: Sub Total | G62: MHrs | H62: U. Price | I62: Sub Total | J62: Quote | K62: Total
D63: LS | E63: 0 | F63: =C63*E63 -> 0 | H63: 0 | I63: =G63*H63 -> 0 | K63: =F63+I63+J63 -> 0
D64: LS | E64: 0 | F64: =C64*E64 -> 0 | H64: 0 | I64: =G64*H64 -> 0 | K64: =F64+I64+J64 -> 0
D65: LS | E65: 0 | F65: =C65*E65 -> 0 | H65: 0 | I65: =G65*H65 -> 0 | K65: =F65+I65+J65 -> 0
J66: Sub Total | K66: =SUM(K63:K65) -> 0
A67: CODE | B67: DESCRIPTION | C67: Materials & Equipment | G67: Labor
A68: 07 72 00 | B68: Roof Accessories | C68: Qty | D68: Unit | E68: U. Price | F68: Sub Total | G68: MHrs | H68: U. Price | I68: Sub Total | J68: Quote | K68: Total
A69: 07 72 26 | B69: Ridge Vents | D69: LS | E69: 0 | F69: =C69*E69 -> 0 | H69: 0 | I69: =G69*H69 -> 0 | K69: =F69+I69+J69 -> 0
A70: 07 72 33 | B70: Roof Hatches | D70: LS | E70: 0 | F70: =C70*E70 -> 0 | H70: 0 | I70: =G70*H70 -> 0 | K70: =F70+I70+J70 -> 0
D71: LS | E71: 0 | F71: =C71*E71 -> 0 | H71: 0 | I71: =G71*H71 -> 0 | K71: =F71+I71+J71 -> 0
J72: Sub Total | K72: =SUM(K69:K71) -> 0
A73: CODE | B73: DESCRIPTION | C73: Materials & Equipment | G73: Labor
A74: 07 81 00 | B74: Applied Fireproofing | C74: Qty | D74: Unit | E74: U. Price | F74: Sub Total | G74: MHrs | H74: U. Price | I74: Sub Total | J74: Quote | K74: Total
A75: 07 84 00 | B75: Firestopping | D75: LS | E75: 0 | F75: =C75*E75 -> 0 | H75: 0 | I75: =G75*H75 -> 0 | J75: =M75 -> 8446 | K75: =F75+I75+J75 -> 8446 | L75: Premium | M75: 8446
D76: LS | E76: 0 | F76: =C76*E76 -> 0 | H76: 0 | I76: =G76*H76 -> 0 | K76: =F76+I76+J76 -> 0
J78: Sub Total | K78: =SUM(K75:K77) -> 8446
A79: CODE | B79: DESCRIPTION | C79: Materials & Equipment | G79: Labor
A80: 07 90 00 | B80: Joint Protection | C80: Qty | D80: Unit | E80: U. Price | F80: Sub Total | G80: MHrs | H80: U. Price | I80: Sub Total | J80: Quote | K80: Total
D81: LS | E81: 0 | F81: =C81*E81 -> 0 | H81: 0 | I81: =G81*H81 -> 0 | K81: =F81+I81+J81 -> 0
D82: LS | E82: 0 | F82: =C82*E82 -> 0 | H82: 0 | I82: =G82*H82 -> 0 | K82: =F82+I82+J82 -> 0
J84: Sub Total | K84: =SUM(K81:K83) -> 0
A85: CODE | B85: DESCRIPTION | C85: Materials & Equipment | G85: Labor
C86: Qty | D86: Unit | E86: U. Price | F86: Sub Total | G86: MHrs | H86: U. Price | I86: Sub Total | J86: Quote | K86: Total
D87: LS | E87: 0 | F87: =C87*E87 -> 0 | H87: 0 | I87: =G87*H87 -> 0 | K87: =F87+I87+J87 -> 0
D88: LS | E88: 0 | F88: =C88*E88 -> 0 | H88: 0 | I88: =G88*H88 -> 0 | K88: =F88+I88+J88 -> 0
J90: Sub Total | K90: =SUM(K87:K89) -> 0
F91: Material Total | G91: Total Hours | I91: Labor Total | J91: Contractor Total | K91: TOTAL
A92: $ / Sq.Ft | B92: TOTAL DIVISION 7
A93: =K94/E6 -> 0 | F93: =SUM(F87:F89,F81:F83,F75:F77,F69:F71,F63:F65,F58:F59,F53:F54,F48:F49,F42:F44,F36:F38,F30:F32,F25:F26,F19:F21,F11:F15) -> 0 | G93: =SUM(G87:G89,G81:G83,G75:G77,G69:G71,G63:G65,G58:G59,G53:G54,G48:G49,G42:G44,G36:G38,G30:G32,G25:G26,G19:G21,G11:G15) -> 0 | I93: =SUM(I87:I89,I81:I83,I75:I77,I69:I71,I63:I65,I58:I59,I53:I54,I48:I49,I42:I44,I36:I38,I30:I32,I25:I26,I19:I21,I11:I15) -> 0 | J93: =SUM(J87:J89,J81:J83,J75:J77,J69:J71,J63:J65,J58:J59,J53:J54,J48:J49,J42:J44,J36:J38,J30:J32,J25:J26,J19:J21,J11:J15) -> 8446 | K93: =K90+K84+K78+K72+K66+K60+K55+K50+K45+K39+K33+K27+K22+K16 -> 8446

Sheet 8
C1: ='Estimate Summary'!C1:H1 -> 0
G5: Openings | J5: Schedule
D6: ='Estimate Summary'!C11 -> Area: | E6: ='Estimate Summary'!D11 -> 1747 | F6: ='Estimate Summary'!E11 -> Sq. Ft. | J6: ='1'!J6 -> 13 | K6: Weeks
A11: CODE | B11: DESCRIPTION | C11: Materials & Equipment | G11: Labor | L11: Sub Contractor | M11: Quote Total | N11: Additional Quote Info
A12: 08 11 00 | B12: Metal Doors and Frames | C12: Qty | D12: Unit | E12: U. Price | F12: Sub Total | G12: MHrs | H12: U. Price | I12: Sub Total | J12: Quote | K12: Total
A13: 08 11 13 | B13: Hollow Metal Frames and Solid Core Wood Door Swing | C13: 5 | D13: EA | E13: 1500 | F13: 0 | G13: =7*4 -> 28 | H13: 65 | I13: =G13*H13 -> 1820 | J13: =M15 -> 18665 | K13: =F13+I13+J13 -> 20485 | L13: Advantage | M13: 21000
A14: 08 11 16 | B14: Hollow Metal Frames and Solid Core Wood Pocket Door | C14: 1 | D14: EA | E14: 1000 | F14: 0 | H14: 0 | I14: =G14*H14 -> 0 | K14: =F14+I14+J14 -> 0 | L14: DCP
B15: Hollow Metal Frames and Solid Core Wood slide Door | C15: 1 | D15: EA | E15: 1200 | F15: 0 | H15: 0 | I15: =G15*H15 -> 0 | K15: =F15+I15+J15 -> 0 | L15: Coastal | M15: 18665
D16: LS | E16: 0 | F16: =C16*E16 -> 0 | H16: 0 | I16: =G16*H16 -> 0 | K16: =F16+I16+J16 -> 0
J18: Sub Total | K18: =SUM(K13:K17) -> 20485
A19: CODE | B19: DESCRIPTION | C19: Materials & Equipment | G19: Labor
A20: 08 14 00 | B20: Wood Doors | C20: Qty | D20: Unit | E20: U. Price | F20: Sub Total | G20: MHrs | H20: U. Price | I20: Sub Total | J20: Quote | K20: Total
D21: LS | E21: 0 | F21: =C21*E21 -> 0 | H21: 0 | I21: =G21*H21 -> 0 | K21: =F21+I21+J21 -> 0
D22: LS | E22: 0 | F22: =C22*E22 -> 0 | H22: 0 | I22: =G22*H22 -> 0 | K22: =F22+I22+J22 -> 0
D23: LS | E23: 0 | F23: =C23*E23 -> 0 | H23: 0 | I23: =G23*H23 -> 0 | K23: =F23+I23+J23 -> 0
J24: Sub Total | K24: =SUM(K21:K23) -> 0
A25: CODE | B25: DESCRIPTION | C25: Materials & Equipment | G25: Labor
A26: 08 31 00 | B26: Access Doors and Panels | C26: Qty | D26: Unit | E26: U. Price | F26: Sub Total | G26: MHrs | H26: U. Price | I26: Sub Total | J26: Quote | K26: Total
D27: LS | E27: 0 | F27: =C27*E27 -> 0 | H27: 0 | I27: =G27*H27 -> 0 | K27: =F27+I27+J27 -> 0
D28: LS | E28: 0 | F28: =C28*E28 -> 0 | H28: 0 | I28: =G28*H28 -> 0 | K28: =F28+I28+J28 -> 0
J29: Sub Total | K29: =SUM(K27:K28) -> 0
A30: CODE | B30: DESCRIPTION | C30: Materials & Equipment | G30: Labor
A31: 08 32 00 | B31: Sliding Gates | C31: Qty | D31: Unit | E31: U. Price | F31: Sub Total | G31: MHrs | H31: U. Price | I31: Sub Total | J31: Quote | K31: Total
D32: LS | E32: 0 | F32: =C32*E32 -> 0 | H32: 0 | I32: =G32*H32 -> 0 | K32: =F32+I32+J32 -> 0
D33: LS | E33: 0 | F33: =C33*E33 -> 0 | H33: 0 | I33: =G33*H33 -> 0 | K33: =F33+I33+J33 -> 0
D34: LS | E34: 0 | F34: =C34*E34 -> 0 | H34: 0 | I34: =G34*H34 -> 0 | K34: =F34+I34+J34 -> 0
J35: Sub Total | K35: =SUM(K32:K34) -> 0
A36: CODE | B36: DESCRIPTION | C36: Materials & Equipment | G36: Labor
A37: 08 33 00 | B37: Coiling Doors and Drilles | C37: Qty | D37: Unit | E37: U. Price | F37: Sub Total | G37: MHrs | H37: U. Price | I37: Sub Total | J37: Quote | K37: Total
D38: LS | E38: 0 | F38: =C38*E38 -> 0 | H38: 0 | I38: =G38*H38 -> 0 | K38: =F38+I38+J38 -> 0
D39: LS | E39: 0 | F39: =C39*E39 -> 0 | H39: 0 | I39: =G39*H39 -> 0 | K39: =F39+I39+J39 -> 0
D40: LS | E40: 0 | F40: =C40*E40 -> 0 | H40: 0 | I40: =G40*H40 -> 0 | K40: =F40+I40+J40 -> 0
J41: Sub Total | K41: =SUM(K38:K40) -> 0
A42: CODE | B42: DESCRIPTION | C42: Materials & Equipment | G42: Labor
A43: 08 34 00 | B43: Special Function Doors | C43: Qty | D43: Unit | E43: U. Price | F43: Sub Total | G43: MHrs | H43: U. Price | I43: Sub Total | J43: Quote | K43: Total
B44: Closet door | C44: 1 | D44: EA | E44: 900 | F44: 0 | H44: 0 | I44: =G44*H44 -> 0 | K44: =F44+I44+J44 -> 0
D45: LS | E45: 0 | F45: =C45*E45 -> 0 | H45: 0 | I45: =G45*H45 -> 0 | K45: =F45+I45+J45 -> 0
D46: LS | E46: 0 | F46: =C46*E46 -> 0 | H46: 0 | I46: =G46*H46 -> 0 | K46: =F46+I46+J46 -> 0
J47: Sub Total | K47: =SUM(K44:K46) -> 0
A48: CODE | B48: DESCRIPTION | C48: Materials & Equipment | G48: Labor
A49: 08 38 00 | B49: Traffic Doors | C49: Qty | D49: Unit | E49: U. Price | F49: Sub Total | G49: MHrs | H49: U. Price | I49: Sub Total | J49: Quote | K49: Total
D50: LS | E50: 0 | F50: =C50*E50 -> 0 | H50: 0 | I50: =G50*H50 -> 0 | K50: =F50+I50+J50 -> 0
D51: LS | E51: 0 | F51: =C51*E51 -> 0 | H51: 0 | I51: =G51*H51 -> 0 | K51: =F51+I51+J51 -> 0
J52: Sub Total | K52: =SUM(K50:K51) -> 0
A53: CODE | B53: DESCRIPTION | C53: Materials & Equipment | G53: Labor
A54: 08 41 00 | B54: Entrances and Storefronts | C54: Qty | D54: Unit | E54: U. Price | F54: Sub Total | G54: MHrs | H54: U. Price | I54: Sub Total | J54: Quote | K54: Total
D55: LS | E55: 0 | F55: =C55*E55 -> 0 | H55: 0 | I55: =G55*H55 -> 0 | K55: =F55+I55+J55 -> 0
D56: LS | E56: 0 | F56: =C56*E56 -> 0 | H56: 0 | I56: =G56*H56 -> 0 | K56: =F56+I56+J56 -> 0
J57: Sub Total | K57: =SUM(K55:K56) -> 0
A58: CODE | B58: DESCRIPTION | C58: Materials & Equipment | G58: Labor
A59: 08 44 00 | B59: Curtain Wall and Glazed Assemblies | C59: Qty | D59: Unit | E59: U. Price | F59: Sub Total | G59: MHrs | H59: U. Price | I59: Sub Total | J59: Quote | K59: Total
D60: LS | E60: 0 | F60: =C60*E60 -> 0 | H60: 0 | I60: =G60*H60 -> 0 | K60: =F60+I60+J60 -> 0
D61: LS | E61: 0 | F61: =C61*E61 -> 0 | H61: 0 | I61: =G61*H61 -> 0 | K61: =F61+I61+J61 -> 0
J62: Sub Total | K62: =SUM(K60:K61) -> 0
A63: CODE | B63: DESCRIPTION | C63: Materials & Equipment | G63: Labor
A64: 08 50 00 | B64: Windows | C64: Qty | D64: Unit | E64: U. Price | F64: Sub Total | G64: MHrs | H64: U. Price | I64: Sub Total | J64: Quote | K64: Total
A65: 08 51 00 | B65: Metal Windows | D65: LS | E65: 0 | F65: =C65*E65 -> 0 | H65: 0 | I65: =G65*H65 -> 0 | K65: =F65+I65+J65 -> 0
A66: 08 52 00 | B66: Wood Windows | D66: LS | E66: 0 | F66: =C66*E66 -> 0 | H66: 0 | I66: =G66*H66 -> 0 | K66: =F66+I66+J66 -> 0
A67: 08 53 00 | B67: Plastic Windows | D67: LS | E67: 0 | F67: =C67*E67 -> 0 | H67: 0 | I67: =G67*H67 -> 0 | K67: =F67+I67+J67 -> 0
A68: 08 54 00 | B68: Composite Windows | D68: LS | E68: 0 | F68: =C68*E68 -> 0 | H68: 0 | I68: =G68*H68 -> 0 | K68: =F68+I68+J68 -> 0
J69: Sub Total | K69: =SUM(K65:K68) -> 0
A70: CODE | B70: DESCRIPTION | C70: Materials & Equipment | G70: Labor
A71: 08 70 00 | B71: Hardware | C71: Qty | D71: Unit | E71: U. Price | F71: Sub Total | G71: MHrs | H71: U. Price | I71: Sub Total | J71: Quote | K71: Total
D72: LS | E72: 0 | F72: =C72*E72 -> 0 | H72: 0 | I72: =G72*H72 -> 0 | K72: =F72+I72+J72 -> 0
D73: LS | E73: 0 | F73: =C73*E73 -> 0 | H73: 0 | I73: =G73*H73 -> 0 | K73: =F73+I73+J73 -> 0
J75: Sub Total | K75: =SUM(K72:K74) -> 0
A76: CODE | B76: DESCRIPTION | C76: Materials & Equipment | G76: Labor
A77: 08 81 00 | B77: Glass Glazing | C77: Qty | D77: Unit | E77: U. Price | F77: Sub Total | G77: MHrs | H77: U. Price | I77: Sub Total | J77: Quote | K77: Total
B78: Glazing | C78: 581 | D78: SF | E78: 55 | F78: 0 | H78: 0 | I78: =G78*H78 -> 0 | J78: =M78 -> 1195 | K78: =F78+I78+J78 -> 1195 | L78: FCG | M78: 1195
B79: Frosted Film | C79: 4 | D79: EA | E79: 120 | F79: =C79*E79 -> 480 | H79: 0 | I79: =G79*H79 -> 0 | J79: =M80 -> 550 | K79: =F79+I79+J79 -> 1030 | L79: Economy | M79: 1450
L80: Economy | M80: 550 | N80: Film
J81: Sub Total | K81: =SUM(K78:K80) -> 2225
A82: CODE | B82: DESCRIPTION | C82: Materials & Equipment | G82: Labor
A83: 08 83 00 | B83: Mirrors | C83: Qty | D83: Unit | E83: U. Price | F83: Sub Total | G83: MHrs | H83: U. Price | I83: Sub Total | J83: Quote | K83: Total
D84: LS | E84: 0 | F84: =C84*E84 -> 0 | H84: 0 | I84: =G84*H84 -> 0 | K84: =F84+I84+J84 -> 0
D85: LS | E85: 0 | F85: =C85*E85 -> 0 | H85: 0 | I85: =G85*H85 -> 0 | K85: =F85+I85+J85 -> 0
J87: Sub Total | K87: =SUM(K84:K86) -> 0
A88: CODE | B88: DESCRIPTION | C88: Materials & Equipment | G88: Labor
A89: 08 87 00 | B89: Glazing Surface Films | C89: Qty | D89: Unit | E89: U. Price | F89: Sub Total | G89: MHrs | H89: U. Price | I89: Sub Total | J89: Quote | K89: Total
D90: LS | E90: 0 | F90: =C90*E90 -> 0 | H90: 0 | I90: =G90*H90 -> 0 | K90: =F90+I90+J90 -> 0
D91: LS | E91: 0 | F91: =C91*E91 -> 0 | H91: 0 | I91: =G91*H91 -> 0 | K91: =F91+I91+J91 -> 0
J93: Sub Total | K93: =SUM(K90:K92) -> 0
A94: CODE | B94: DESCRIPTION | C94: Materials & Equipment | G94: Labor
A95: 08 91 00 | B95: Louvers | C95: Qty | D95: Unit | E95: U. Price | F95: Sub Total | G95: MHrs | H95: U. Price | I95: Sub Total | J95: Quote | K95: Total
D96: LS | E96: 0 | F96: =C96*E96 -> 0 | H96: 0 | I96: =G96*H96 -> 0 | K96: =F96+I96+J96 -> 0
D97: LS | E97: 0 | F97: =C97*E97 -> 0 | H97: 0 | I97: =G97*H97 -> 0 | K97: =F97+I97+J97 -> 0
J99: Sub Total | K99: =SUM(K96:K98) -> 0
A100: CODE | B100: DESCRIPTION | C100: Materials & Equipment | G100: Labor
C101: Qty | D101: Unit | E101: U. Price | F101: Sub Total | G101: MHrs | H101: U. Price | I101: Sub Total | J101: Quote | K101: Total
D102: LS | E102: 0 | F102: =C102*E102 -> 0 | H102: 0 | I102: =G102*H102 -> 0 | K102: =F102+I102+J102 -> 0
D103: LS | E103: 0 | F103: =C103*E103 -> 0 | H103: 0 | I103: =G103*H103 -> 0 | K103: =F103+I103+J103 -> 0
J105: Sub Total | K105: =SUM(K102:K104) -> 0
F106: Material Total | G106: Total Hours | I106: Labor Total | J106: Contractor Total | K106: TOTAL
A107: $ / Sq.Ft | B107: TOTAL DIVISION 8
A108: =K109/E6 -> 0 | F108: =SUM(F102:F104,F96:F98,F90:F92,F84:F86,F78:F80,F72:F74,F65:F68,F60:F61,F55:F56,F50:F51,F44:F46,F38:F40,F32:F34,F27:F28,F21:F23,F13:F17) -> 480 | G108: =SUM(G102:G104,G96:G98,G90:G92,G84:G86,G78:G80,G72:G74,G65:G68,G60:G61,G55:G56,G50:G51,G44:G46,G38:G40,G32:G34,G27:G28,G21:G23,G13:G17) -> 28 | I108: =SUM(I102:I104,I96:I98,I90:I92,I84:I86,I78:I80,I72:I74,I65:I68,I60:I61,I55:I56,I50:I51,I44:I46,I38:I40,I32:I34,I27:I28,I21:I23,I13:I17) -> 1820 | J108: =SUM(J102:J104,J96:J98,J90:J92,J84:J86,J78:J80,J72:J74,J65:J68,J60:J61,J55:J56,J50:J51,J44:J46,J38:J40,J32:J34,J27:J28,J21:J23,J13:J17) -> 20410 | K108: =SUM(K105,K99,K93,K87,K81,K75,K69,K18,K24,K29,K35,K41,K47,K52,K57,K62) -> 22710

Sheet 9
C1: ='Estimate Summary'!C1:H1 -> 0
G5: Finishes | J5: Schedule
D6: ='Estimate Summary'!C11 -> Area: | E6: ='Estimate Summary'!D11 -> 1747 | F6: ='Estimate Summary'!E11 -> Sq. Ft. | J6: ='1'!J6 -> 13 | K6: Weeks
A9: CODE | B9: DESCRIPTION | C9: Materials & Equipment | G9: Labor | L9: Sub Contractor | M9: Quote Total | N9: Additional Quote Info
A10: 09 20 00 | B10: Plaster and Gypsum Board | C10: Qty | D10: Unit | E10: U. Price | F10: Sub Total | G10: MHrs | H10: U. Price | I10: Sub Total | J10: Quote | K10: Total
B11: Interior Drywall | C11: 5097 | D11: SF | E11: 7 | F11: 0 | H11: 0 | I11: =G11*H11 -> 0 | J11: =M15 -> 61750 | K11: =F11+I11+J11 -> 61750 | L11: Arsenault | M11: 82720 | N11: Includes plywood for millwork and washroom accessories
B12: Demising Wall - 1hr - 1 layer of gypsum board over existing wall | C12: 1748 | D12: SF | E12: 10 | F12: 0 | H12: 0 | I12: =G12*H12 -> 0 | K12: =F12+I12+J12 -> 0 | L12: Arsenault | M12: 19160 | N12: All walls to underside of deck
B13: Extra for wall to underside of deck - Office, Staff lounge and equipment room | D13: SF | E13: 0 | F13: =C13*E13 -> 0 | H13: 0 | I13: =G13*H13 -> 0 | K13: =F13+I13+J13 -> 0 | L13: Fundy | M13: 66800 | N13: Backing NIC
C14: =E6 -> 1747 | D14: SF | E14: 0 | F14: =C14*E14 -> 0 | H14: 0 | I14: =G14*H14 -> 0 | K14: =F14+I14+J14 -> 0 | L14: Fundy | M14: 6800 | N14: Credit for walls to be 10'
D15: SF | E15: 0 | F15: =C15*E15 -> 0 | H15: 0 | I15: =G15*H15 -> 0 | K15: =F15+I15+J15 -> 0 | L15: premium | M15: 61750 | N15: Backing included, except for walls not indicated on drawing
D16: SF | E16: 0 | F16: =C16*E16 -> 0 | H16: 0 | I16: =G16*H16 -> 0 | K16: =F16+I16+J16 -> 0 | L16: premium | M16: 8500 | N16: Option price for all walls to underside of deck
J18: Sub Total | K18: =SUM(K11:K17) -> 61750
A19: CODE | B19: DESCRIPTION | C19: Materials & Equipment | G19: Labor
A20: 09 30 00 | B20: Tiling | C20: Qty | D20: Unit | E20: U. Price | F20: Sub Total | G20: MHrs | H20: U. Price | I20: Sub Total | J20: Quote | K20: Total
B21: Washroom tile | C21: 201 | D21: SF | E21: 8 | F21: 0 | H21: 0 | I21: =G21*H21 -> 0 | K21: =F21+I21+J21 -> 0
D22: SF | E22: 0 | F22: =C22*E22 -> 0 | H22: 0 | I22: =G22*H22 -> 0 | K22: =F22+I22+J22 -> 0
D23: SF | E23: 0 | F23: =C23*E23 -> 0 | H23: 0 | I23: =G23*H23 -> 0 | K23: =F23+I23+J23 -> 0
D24: SF | E24: 0 | F24: =C24*E24 -> 0 | H24: 0 | I24: =G24*H24 -> 0 | K24: =F24+I24+J24 -> 0
J26: Sub Total | K26: =SUM(K21:K25) -> 0
A27: CODE | B27: DESCRIPTION | C27: Materials & Equipment | G27: Labor
A28: 09 50 00 | B28: Ceiling | C28: Qty | D28: Unit | E28: U. Price | F28: Sub Total | G28: MHrs | H28: U. Price | I28: Sub Total | J28: Quote | K28: Total
B29: Acoustic ceiling | C29: =E6 -> 1747 | D29: SF | E29: 6 | F29: 0 | H29: 0 | I29: =G29*H29 -> 0 | K29: =F29+I29+J29 -> 0
D30: SF | E30: 0 | F30: =C30*E30 -> 0 | H30: 0 | I30: =G30*H30 -> 0 | K30: =F30+I30+J30 -> 0
J32: Sub Total | K32: =SUM(K29:K31) -> 0
A33: CODE | B33: DESCRIPTION | C33: Materials & Equipment | G33: Labor
A34: 09 60 00 | B34: Flooring | C34: Qty | D34: Unit | E34: U. Price | F34: Sub Total | G34: MHrs | H34: U. Price | I34: Sub Total | J34: Quote | K34: Total
A35: 09 61 00 | B35: Concrete Floor Polishing | D35: SF | E35: 0 | F35: =C35*E35 -> 0 | H35: 0 | I35: =G35*H35 -> 0 | K35: =F35+I35+J35 -> 0 | L35: Coastal/Primo | M35: 28200
D36: SF | E36: 0 | F36: =C36*E36 -> 0 | H36: 0 | I36: =G36*H36 -> 0 | K36: =F36+I36+J36 -> 0 | L36: Ritchie's | M36: 24500
A37: 09 62 00 | B37: Specialty Flooring | D37: SF | E37: 0 | F37: =C37*E37 -> 0 | H37: 0 | I37: =G37*H37 -> 0 | K37: =F37+I37+J37 -> 0 | L37: Domus | M37: 22675
A38: 09 64 00 | B38: Wood Flooring | D38: SF | E38: 0 | F38: =C38*E38 -> 0 | H38: 0 | I38: =G38*H38 -> 0 | K38: =F38+I38+J38 -> 0 | L38: FRS | M38: 27471
A39: 09 65 00 | B39: Flooring | C39: =E6 -> 1747 | D39: SF | E39: 12 | F39: 0 | H39: 0 | I39: =G39*H39 -> 0 | J39: =M37 -> 22675 | K39: =F39+I39+J39 -> 22675
A40: 09 67 00 | B40: Floor Prep | C40: =C39 -> 1747 | D40: SF | E40: 2 | F40: =C40*E40 -> 3494 | H40: 0 | I40: =G40*H40 -> 0 | K40: =F40+I40+J40 -> 3494
A41: 09 68 00 | B41: Carpet Tile | D41: SF | E41: 0 | F41: =C41*E41 -> 0 | H41: 0 | I41: =G41*H41 -> 0 | K41: =F41+I41+J41 -> 0
L45: Sackville smiles | M45: 5.18
J47: Sub Total | K47: =SUM(K35:K46) -> 26169 | L47: Mountain view Dental | M47: 16.07 | N47: Epoxy, stair thread and VCT
A48: CODE | B48: DESCRIPTION | C48: Materials & Equipment | G48: Labor
A49: 09 72 00 | B49: Wall Coverings | C49: Qty | D49: Unit | E49: U. Price | F49: Sub Total | G49: MHrs | H49: U. Price | I49: Sub Total | J49: Quote | K49: Total
D50: SF | E50: 0 | F50: =C50*E50 -> 0 | H50: 0 | I50: =G50*H50 -> 0 | K50: =F50+I50+J50 -> 0
D51: SF | E51: 0 | F51: =C51*E51 -> 0 | H51: 0 | I51: =G51*H51 -> 0 | K51: =F51+I51+J51 -> 0
J53: Sub Total | K53: =SUM(K50:K52) -> 0
A54: CODE | B54: DESCRIPTION | C54: Materials & Equipment | G54: Labor
A55: 09 91 00 | B55: Painting | C55: Qty | D55: Unit | E55: U. Price | F55: Sub Total | G55: MHrs | H55: U. Price | I55: Sub Total | J55: Quote | K55: Total
A56: 09 91 13 | B56: Interior Painting | D56: SF | E56: 0 | F56: =C56*E56 -> 0 | H56: 0 | I56: =G56*H56 -> 0 | J56: =M56 -> 9192.44 | K56: =F56+I56+J56 -> 9192.44 | L56: Coats | M56: 9192.44
A57: 09 91 23 | B57: 1st Flr Painting | C57: =E6 -> 1747 | D57: SF | E57: 6.46 | F57: 0 | H57: 0 | I57: =G57*H57 -> 0 | J57: =M57 -> 3000 | K57: =F57+I57+J57 -> 3000 | L57: Coats | M57: 3000
L58: LJD Paintworks
L59: PaintGenix
L60: Paint2Perfection | M60: 13040
J62: Sub Total | K62: =SUM(K56:K61) -> 12192.44
F63: Material Total | G63: Total Hours | I63: Labor Total | J63: Contractor Total | K63: TOTAL
A64: $ / Sq.Ft | B64: TOTAL DIVISION 9
A65: =K66/'Estimate Summary'!E6 -> #VALUE! | F65: =SUM(F56:F61,F35:F46,F29:F31,F21:F25,F11:F17,F50:F52) -> 3494 | G65: =SUM(G56:G61,G35:G46,G29:G31,G21:G25,G11:G17) -> 0 | I65: =SUM(I56:I61,I35:I46,I29:I31,I21:I25,I11:I17,I50:I52) -> 0 | J65: =SUM(J56:J61,J35:J46,J29:J31,J21:J25,J11:J17,J50:J52) -> 96617.44 | K65: =K62+K53+K47+K32+K26+K18 -> 100111.44

Sheet 10
C1: ='Estimate Summary'!C1:H1 -> 0
G5: Specalties | J5: Schedule
D6: ='Estimate Summary'!C11 -> Area: | E6: ='Estimate Summary'!D11 -> 1747 | F6: ='Estimate Summary'!E11 -> Sq. Ft. | J6: ='1'!J6 -> 13 | K6: Weeks
A9: CODE | B9: DESCRIPTION | C9: Materials & Equipment | G9: Labor | L9: Sub Contractor | M9: Quote Total | N9: Additional Quote Info
A10: 10 11 00 | B10: Visual Display Units | C10: Qty | D10: Unit | E10: U. Price | F10: Sub Total | G10: MHrs | H10: U. Price | I10: Sub Total | J10: Quote | K10: Total
D11: LS | E11: 0 | F11: =C11*E11 -> 0 | H11: 0 | I11: =G11*H11 -> 0 | K11: =F11+I11+J11 -> 0
D12: LS | E12: 0 | F12: =C12*E12 -> 0 | H12: 0 | I12: =G12*H12 -> 0 | K12: =F12+I12+J12 -> 0
D13: LS | E13: 0 | F13: =C13*E13 -> 0 | H13: 0 | I13: =G13*H13 -> 0 | K13: =F13+I13+J13 -> 0
D14: LS | E14: 0 | F14: =C14*E14 -> 0 | H14: 0 | I14: =G14*H14 -> 0 | K14: =F14+I14+J14 -> 0
D15: LS | E15: 0 | F15: =C15*E15 -> 0 | H15: 0 | I15: =G15*H15 -> 0 | K15: =F15+I15+J15 -> 0
J17: Sub Total | K17: =SUM(K11:K16) -> 0
A18: CODE | B18: DESCRIPTION | C18: Materials & Equipment | G18: Labor
A19: 10 14 00 | B19: Signage | C19: Qty | D19: Unit | E19: U. Price | F19: Sub Total | G19: MHrs | H19: U. Price | I19: Sub Total | J19: Quote | K19: Total
D20: LS | E20: 0 | F20: =C20*E20 -> 0 | H20: 0 | I20: =G20*H20 -> 0 | K20: =F20+I20+J20 -> 0
D21: LS | E21: 0 | F21: =C21*E21 -> 0 | H21: 0 | I21: =G21*H21 -> 0 | K21: =F21+I21+J21 -> 0
D22: LS | E22: 0 | F22: =C22*E22 -> 0 | H22: 0 | I22: =G22*H22 -> 0 | K22: =F22+I22+J22 -> 0
D23: LS | E23: 0 | F23: =C23*E23 -> 0 | H23: 0 | I23: =G23*H23 -> 0 | K23: =F23+I23+J23 -> 0
J25: Sub Total | K25: =SUM(K20:K24) -> 0
A26: CODE | B26: DESCRIPTION | C26: Materials & Equipment | G26: Labor
A27: 10 20 00 | B27: Interior Specialties | C27: Qty | D27: Unit | E27: U. Price | F27: Sub Total | G27: MHrs | H27: U. Price | I27: Sub Total | J27: Quote | K27: Total
A28: 10 21 00 | B28: Mirror | C28: =6/3 -> 2 | D28: EA | E28: 1159 | F28: 0 | G28: 26 | H28: 65 | I28: =G28*H28 -> 1690 | J28: =M30 -> 10000 | K28: =F28+I28+J28 -> 11690 | L28: Advantage | M28: 5500 | N28: No Coat Hooks, Paper holder and change table
A29: 10 21 13 | B29: Paper tower dispenser | D29: LS | E29: 0 | F29: =C29*E29 -> 0 | H29: 0 | I29: =G29*H29 -> 0 | K29: =F29+I29+J29 -> 0 | L29: Div 10 | M29: 9300
A30: 10 22 00 | B30: Soap dispenser | D30: LS | E30: 0 | F30: =C30*E30 -> 0 | H30: 0 | I30: =G30*H30 -> 0 | K30: =F30+I30+J30 -> 0 | L30: Rodney | M30: 10000
A31: 10 22 19 | B31: Grab bar | D31: LS | E31: 0 | F31: =C31*E31 -> 0 | H31: 0 | I31: =G31*H31 -> 0 | K31: =F31+I31+J31 -> 0
A32: 10 22 39 | B32: Coat Hooks | D32: LS | E32: 0 | F32: =C32*E32 -> 0 | H32: 0 | I32: =G32*H32 -> 0 | K32: =F32+I32+J32 -> 0
A33: 10 22 43 | B33: Toilet tissue dispenser | D33: LS | E33: 0 | F33: =C33*E33 -> 0 | H33: 0 | I33: =G33*H33 -> 0 | K33: =F33+I33+J33 -> 0
A34: 10 28 00 | B34: Baby change table | C34: 2 | D34: LS | E34: =M34/3 -> 1833.3333 | F34: 0 | G34: 20 | H34: 65 | I34: 0 | K34: =F34+I34+J34 -> 0 | L34: Sackville smiles | M34: 5500 | N34: 3 Washrooms
J38: Sub Total | K38: =SUM(K28:K37) -> 11690
A39: CODE | B39: DESCRIPTION | C39: Materials & Equipment | G39: Labor
A40: 10 44 00 | B40: Fire Protection Specialties | C40: Qty | D40: Unit | E40: U. Price | F40: Sub Total | G40: MHrs | H40: U. Price | I40: Sub Total | J40: Quote | K40: Total
A41: 10 44 16 | B41: Fire Extinguishers | D41: LS | E41: 0 | F41: =C41*E41 -> 0 | H41: 0 | I41: =G41*H41 -> 0 | K41: =F41+I41+J41 -> 0
D42: LS | E42: 0 | F42: =C42*E42 -> 0 | H42: 0 | I42: =G42*H42 -> 0 | K42: =F42+I42+J42 -> 0
J44: Sub Total | K44: =SUM(K41:K43) -> 0
A45: CODE | B45: DESCRIPTION | C45: Materials & Equipment | G45: Labor
A46: 10 51 00 | B46: Lockers | C46: Qty | D46: Unit | E46: U. Price | F46: Sub Total | G46: MHrs | H46: U. Price | I46: Sub Total | J46: Quote | K46: Total
D47: LS | E47: 0 | F47: =C47*E47 -> 0 | H47: 0 | I47: =G47*H47 -> 0 | K47: =F47+I47+J47 -> 0
D48: LS | E48: 0 | F48: =C48*E48 -> 0 | H48: 0 | I48: =G48*H48 -> 0 | K48: =F48+I48+J48 -> 0
D49: LS | E49: 0 | F49: =C49*E49 -> 0 | H49: 0 | I49: =G49*H49 -> 0 | K49: =F49+I49+J49 -> 0
J51: Sub Total | K51: =SUM(K47:K50) -> 0
A52: CODE | B52: DESCRIPTION | C52: Materials & Equipment | G52: Labor
A53: 10 57 00 | B53: Wardrobe and Closet Specialties | C53: Qty | D53: Unit | E53: U. Price | F53: Sub Total | G53: MHrs | H53: U. Price | I53: Sub Total | J53: Quote | K53: Total
D54: LS | E54: 0 | F54: =C54*E54 -> 0 | H54: 0 | I54: =G54*H54 -> 0 | K54: =F54+I54+J54 -> 0
D55: LS | E55: 0 | F55: =C55*E55 -> 0 | H55: 0 | I55: =G55*H55 -> 0 | K55: =F55+I55+J55 -> 0
J57: Sub Total | K57: =SUM(K54:K56) -> 0
A58: CODE | B58: DESCRIPTION | C58: Materials & Equipment | G58: Labor
A59: 10 70 00 | B59: Exterior Specialties | C59: Qty | D59: Unit | E59: U. Price | F59: Sub Total | G59: MHrs | H59: U. Price | I59: Sub Total | J59: Quote | K59: Total
A60: 10 73 00 | B60: Protective Covers | D60: LS | E60: 0 | F60: =C60*E60 -> 0 | H60: 0 | I60: =G60*H60 -> 0 | K60: =F60+I60+J60 -> 0
A61: 10 73 16 | B61: Canopies | D61: LS | E61: 0 | F61: =C61*E61 -> 0 | H61: 0 | I61: =G61*H61 -> 0 | K61: =F61+I61+J61 -> 0
A62: 10 75 00 | B62: Flagpoles
J63: Sub Total | K63: =SUM(K60:K62) -> 0
A64: CODE | B64: DESCRIPTION | C64: Materials & Equipment | G64: Labor
C65: Qty | D65: Unit | E65: U. Price | F65: Sub Total | G65: MHrs | H65: U. Price | I65: Sub Total | J65: Quote | K65: Total
D66: LS | E66: 0 | F66: =C66*E66 -> 0 | H66: 0 | I66: =G66*H66 -> 0 | K66: =F66+I66+J66 -> 0
D67: LS | E67: 0 | F67: =C67*E67 -> 0 | H67: 0 | I67: =G67*H67 -> 0 | K67: =F67+I67+J67 -> 0
D68: LS | E68: 0 | F68: =C68*E68 -> 0 | H68: 0 | I68: =G68*H68 -> 0 | K68: =F68+I68+J68 -> 0
D69: LS | E69: 0 | F69: =C69*E69 -> 0 | H69: 0 | I69: =G69*H69 -> 0 | K69: =F69+I69+J69 -> 0
J71: Sub Total | K71: =SUM(K66:K70) -> 0
F72: Material Total | G72: Total Hours | I72: Labor Total | J72: Contractor Total | K72: TOTAL
A73: $ / Sq.Ft | B73: TOTAL DIVISION 10
A74: =K75/E6 -> 0 | F74: =SUM(F66:F70,F60:F62,F54:F56,F47:F50,F41:F43,F28:F37,F20:F24,F11:F16) -> 0 | G74: =SUM(G66:G70,G60:G62,G54:G56,G47:G50,G41:G43,G28:G37,G20:G24,G11:G16) -> 46 | I74: =SUM(I66:I70,I60:I62,I54:I56,I47:I50,I41:I43,I28:I37,I20:I24,I11:I16) -> 1690 | J74: =SUM(J66:J70,J60:J62,J54:J56,J47:J50,J41:J43,J28:J37,J20:J24,J11:J16) -> 10000 | K74: =K71+K63+K57+K51+K44+K38+K25+K17 -> 11690

Sheet 11
C1: ='Estimate Summary'!C1:H1 -> 0
G5: Equipment | J5: Schedule
D6: ='Estimate Summary'!C11 -> Area: | E6: ='Estimate Summary'!D11 -> 1747 | F6: ='Estimate Summary'!E11 -> Sq. Ft. | J6: ='1'!J6 -> 13 | K6: Weeks
A9: CODE | B9: DESCRIPTION | C9: Materials & Equipment | G9: Labor | L9: Sub Contractor | M9: Quote Total | N9: Additional Quote Info
A10: 11 11 00 | B10: Vehicle Service Equipment | C10: Qty | D10: Unit | E10: U. Price | F10: Sub Total | G10: MHrs | H10: U. Price | I10: Sub Total | J10: Quote | K10: Total
D11: LS | E11: 0 | F11: =C11*E11 -> 0 | H11: 0 | I11: =G11*H11 -> 0 | K11: =F11+I11+J11 -> 0
D12: LS | E12: 0 | F12: =C12*E12 -> 0 | H12: 0 | I12: =G12*H12 -> 0 | K12: =F12+I12+J12 -> 0
D13: LS | E13: 0 | F13: =C13*E13 -> 0 | H13: 0 | I13: =G13*H13 -> 0 | K13: =F13+I13+J13 -> 0
D14: LS | E14: 0 | F14: =C14*E14 -> 0 | H14: 0 | I14: =G14*H14 -> 0 | K14: =F14+I14+J14 -> 0
D15: LS | E15: 0 | F15: =C15*E15 -> 0 | H15: 0 | I15: =G15*H15 -> 0 | K15: =F15+I15+J15 -> 0
D16: LS | E16: 0 | F16: =C16*E16 -> 0 | H16: 0 | I16: =G16*H16 -> 0 | K16: =F16+I16+J16 -> 0
D17: LS | E17: 0 | F17: =C17*E17 -> 0 | H17: 0 | I17: =G17*H17 -> 0 | K17: =F17+I17+J17 -> 0
D18: LS | E18: 0 | F18: =C18*E18 -> 0 | H18: 0 | I18: =G18*H18 -> 0 | K18: =F18+I18+J18 -> 0
D19: LS | E19: 0 | F19: =C19*E19 -> 0 | H19: 0 | I19: =G19*H19 -> 0 | K19: =F19+I19+J19 -> 0
D20: LS | E20: 0 | F20: =C20*E20 -> 0 | H20: 0 | I20: =G20*H20 -> 0 | K20: =F20+I20+J20 -> 0
D21: LS | E21: 0 | F21: =C21*E21 -> 0 | H21: 0 | I21: =G21*H21 -> 0 | K21: =F21+I21+J21 -> 0
D22: LS | E22: 0 | F22: =C22*E22 -> 0 | H22: 0 | I22: =G22*H22 -> 0 | K22: =F22+I22+J22 -> 0
J24: Sub Total | K24: =SUM(K11:K23) -> 0
A25: CODE | B25: DESCRIPTION | C25: Materials & Equipment | G25: Labor
A26: 11 13 00 | B26: Loading Dock Equipment | C26: Qty | D26: Unit | E26: U. Price | F26: Sub Total | G26: MHrs | H26: U. Price | I26: Sub Total | J26: Quote | K26: Total
D27: LS | E27: 0 | F27: =C27*E27 -> 0 | H27: 0 | I27: =G27*H27 -> 0 | K27: =F27+I27+J27 -> 0
D28: LS | E28: 0 | F28: =C28*E28 -> 0 | H28: 0 | I28: =G28*H28 -> 0 | K28: =F28+I28+J28 -> 0
D29: LS | E29: 0 | F29: =C29*E29 -> 0 | H29: 0 | I29: =G29*H29 -> 0 | K29: =F29+I29+J29 -> 0
D30: LS | E30: 0 | F30: =C30*E30 -> 0 | H30: 0 | I30: =G30*H30 -> 0 | K30: =F30+I30+J30 -> 0
D31: LS | E31: 0 | F31: =C31*E31 -> 0 | H31: 0 | I31: =G31*H31 -> 0 | K31: =F31+I31+J31 -> 0
D32: LS | E32: 0 | F32: =C32*E32 -> 0 | H32: 0 | I32: =G32*H32 -> 0 | K32: =F32+I32+J32 -> 0
D33: LS | E33: 0 | F33: =C33*E33 -> 0 | H33: 0 | I33: =G33*H33 -> 0 | K33: =F33+I33+J33 -> 0
J35: Sub Total | K35: =SUM(K27:K34) -> 0
A36: CODE | B36: DESCRIPTION | C36: Materials & Equipment | G36: Labor
A37: 11 30 00 | B37: Residential Equipment | C37: Qty | D37: Unit | E37: U. Price | F37: Sub Total | G37: MHrs | H37: U. Price | I37: Sub Total | J37: Quote | K37: Total
A38: 11 30 13 | B38: Residential Appliances | D38: LS | E38: 0 | F38: =C38*E38 -> 0 | H38: 0 | I38: =G38*H38 -> 0 | K38: =F38+I38+J38 -> 0
D39: LS | E39: 0 | F39: =C39*E39 -> 0 | H39: 0 | I39: =G39*H39 -> 0 | K39: =F39+I39+J39 -> 0
D40: LS | E40: 0 | F40: =C40*E40 -> 0 | H40: 0 | I40: =G40*H40 -> 0 | K40: =F40+I40+J40 -> 0
J43: Sub Total | K43: =SUM(K38:K42) -> 0
A44: CODE | B44: DESCRIPTION | C44: Materials & Equipment | G44: Labor
A45: 11 41 00 | B45: Food Storage Equipment | C45: Qty | D45: Unit | E45: U. Price | F45: Sub Total | G45: MHrs | H45: U. Price | I45: Sub Total | J45: Quote | K45: Total
A46: 11 41 23 | B46: Walk-In Coolers | D46: LS | E46: 0 | F46: =C46*E46 -> 0 | H46: 0 | I46: =G46*H46 -> 0 | K46: =F46+I46+J46 -> 0
D47: LS | E47: 0 | F47: =C47*E47 -> 0 | H47: 0 | I47: =G47*H47 -> 0 | K47: =F47+I47+J47 -> 0
D48: LS | E48: 0 | F48: =C48*E48 -> 0 | H48: 0 | I48: =G48*H48 -> 0 | K48: =F48+I48+J48 -> 0
D49: LS | E49: 0 | F49: =C49*E49 -> 0 | H49: 0 | I49: =G49*H49 -> 0 | K49: =F49+I49+J49 -> 0
D50: LS | E50: 0 | F50: =C50*E50 -> 0 | H50: 0 | I50: =G50*H50 -> 0 | K50: =F50+I50+J50 -> 0
J52: Sub Total | K52: =SUM(K46:K51) -> 0
A53: CODE | B53: DESCRIPTION | C53: Materials & Equipment | G53: Labor
A54: 11 48 00 | B54: Food service Cleaning and Disposal Equipment | C54: Qty | D54: Unit | E54: U. Price | F54: Sub Total | G54: MHrs | H54: U. Price | I54: Sub Total | J54: Quote | K54: Total
A55: 11 48 13 | B55: Commercial Dishwasher | D55: LS | E55: 0 | F55: =C55*E55 -> 0 | H55: 0 | I55: =G55*H55 -> 0 | K55: =F55+I55+J55 -> 0
D56: LS | E56: 0 | F56: =C56*E56 -> 0 | H56: 0 | I56: =G56*H56 -> 0 | K56: =F56+I56+J56 -> 0
D57: LS | E57: 0 | F57: =C57*E57 -> 0 | H57: 0 | I57: =G57*H57 -> 0 | K57: =F57+I57+J57 -> 0
D58: LS | E58: 0 | F58: =C58*E58 -> 0 | H58: 0 | I58: =G58*H58 -> 0 | K58: =F58+I58+J58 -> 0
D59: LS | E59: 0 | F59: =C59*E59 -> 0 | H59: 0 | I59: =G59*H59 -> 0 | K59: =F59+I59+J59 -> 0
D60: LS | E60: 0 | F60: =C60*E60 -> 0 | H60: 0 | I60: =G60*H60 -> 0 | K60: =F60+I60+J60 -> 0
D61: LS | E61: 0 | F61: =C61*E61 -> 0 | H61: 0 | I61: =G61*H61 -> 0 | K61: =F61+I61+J61 -> 0
J63: Sub Total | K63: =SUM(K55:K62) -> 0
A64: CODE | B64: DESCRIPTION | C64: Materials & Equipment | G64: Labor
A65: 11 52 00 | B65: Audio-Visual Equipment | C65: Qty | D65: Unit | E65: U. Price | F65: Sub Total | G65: MHrs | H65: U. Price | I65: Sub Total | J65: Quote | K65: Total
D66: LS | E66: 0 | F66: =C66*E66 -> 0 | H66: 0 | I66: =G66*H66 -> 0 | K66: =F66+I66+J66 -> 0
D67: LS | E67: 0 | F67: =C67*E67 -> 0 | H67: 0 | I67: =G67*H67 -> 0 | K67: =F67+I67+J67 -> 0
D68: LS | E68: 0 | F68: =C68*E68 -> 0 | H68: 0 | I68: =G68*H68 -> 0 | K68: =F68+I68+J68 -> 0
D69: LS | E69: 0 | F69: =C69*E69 -> 0 | H69: 0 | I69: =G69*H69 -> 0 | K69: =F69+I69+J69 -> 0
D70: LS | E70: 0 | F70: =C70*E70 -> 0 | H70: 0 | I70: =G70*H70 -> 0 | K70: =F70+I70+J70 -> 0
J72: Sub Total | K72: =SUM(K66:K71) -> 0
A73: CODE | B73: DESCRIPTION | C73: Materials & Equipment | G73: Labor
A74: 11 53 00 | B74: Laboratory Equipment | C74: Qty | D74: Unit | E74: U. Price | F74: Sub Total | G74: MHrs | H74: U. Price | I74: Sub Total | J74: Quote | K74: Total
D75: LS | E75: 0 | F75: =C75*E75 -> 0 | H75: 0 | I75: =G75*H75 -> 0 | K75: =F75+I75+J75 -> 0
D76: LS | E76: 0 | F76: =C76*E76 -> 0 | H76: 0 | I76: =G76*H76 -> 0 | K76: =F76+I76+J76 -> 0
D77: LS | E77: 0 | F77: =C77*E77 -> 0 | H77: 0 | I77: =G77*H77 -> 0 | K77: =F77+I77+J77 -> 0
J79: Sub Total | K79: =SUM(K75:K78) -> 0
A80: CODE | B80: DESCRIPTION | C80: Materials & Equipment | G80: Labor
C81: Qty | D81: Unit | E81: U. Price | F81: Sub Total | G81: MHrs | H81: U. Price | I81: Sub Total | J81: Quote | K81: Total
D82: LS | E82: 0 | F82: =C82*E82 -> 0 | H82: 0 | I82: =G82*H82 -> 0 | K82: =F82+I82+J82 -> 0
D83: LS | E83: 0 | F83: =C83*E83 -> 0 | H83: 0 | I83: =G83*H83 -> 0 | K83: =F83+I83+J83 -> 0
D84: LS | E84: 0 | F84: =C84*E84 -> 0 | H84: 0 | I84: =G84*H84 -> 0 | K84: =F84+I84+J84 -> 0
D85: LS | E85: 0 | F85: =C85*E85 -> 0 | H85: 0 | I85: =G85*H85 -> 0 | K85: =F85+I85+J85 -> 0
D86: LS | E86: 0 | F86: =C86*E86 -> 0 | H86: 0 | I86: =G86*H86 -> 0 | K86: =F86+I86+J86 -> 0
J88: Sub Total | K88: =SUM(K82:K87) -> 0
A89: CODE | B89: DESCRIPTION | C89: Materials & Equipment | G89: Labor
C90: Qty | D90: Unit | E90: U. Price | F90: Sub Total | G90: MHrs | H90: U. Price | I90: Sub Total | J90: Quote | K90: Total
D91: LS | E91: 0 | F91: =C91*E91 -> 0 | H91: 0 | I91: =G91*H91 -> 0 | K91: =F91+I91+J91 -> 0
D92: LS | E92: 0 | F92: =C92*E92 -> 0 | H92: 0 | I92: =G92*H92 -> 0 | K92: =F92+I92+J92 -> 0
D93: LS | E93: 0 | F93: =C93*E93 -> 0 | H93: 0 | I93: =G93*H93 -> 0 | K93: =F93+I93+J93 -> 0
D94: LS | E94: 0 | F94: =C94*E94 -> 0 | H94: 0 | I94: =G94*H94 -> 0 | K94: =F94+I94+J94 -> 0
J96: Sub Total | K96: =SUM(K91:K95) -> 0
F97: Material Total | G97: Total Hours | I97: Labor Total | J97: Contractor Total | K97: TOTAL
A98: $ / Sq.Ft | B98: TOTAL DIVISION 11
A99: =K99/E6 -> 0 | F99: =SUM(F91:F95,F82:F87,F75:F78,F66:F71,F55:F61,F46:F51,F38:F42,F27:F34,F11:F23) -> 0 | G99: =SUM(G91:G95,G82:G87,G75:G78,G66:G71,G55:G61,G46:G51,G38:G42,G27:G34,G11:G23) -> 0 | I99: =SUM(I91:I95,I82:I87,I75:I78,I66:I71,I55:I61,I46:I51,I38:I42,I27:I34,I11:I23) -> 0 | J99: =SUM(J91:J95,J82:J87,J75:J78,J66:J71,J55:J61,J46:J51,J38:J42,J27:J34,J11:J23) -> 0 | K99: =SUM(K96,K88,K79,K72,K63,K52,K43,K35,K24) -> 0

Sheet 12
C1: ='Estimate Summary'!C1:H1 -> 0
G5: Furnishing | J5: Schedule
D6: ='Estimate Summary'!C11 -> Area: | E6: ='Estimate Summary'!D11 -> 1747 | F6: ='Estimate Summary'!E11 -> Sq. Ft. | J6: ='1'!J6 -> 13 | K6: Weeks
A9: CODE | B9: DESCRIPTION | C9: Materials & Equipment | G9: Labor | L9: Sub Contractor | M9: Quote Total | N9: Additional Quote Info
A10: 12 20 00 | B10: Window Treatments | C10: Qty | D10: Unit | E10: U. Price | F10: Sub Total | G10: MHrs | H10: U. Price | I10: Sub Total | J10: Quote | K10: Total
D11: LS | E11: 0 | F11: =C11*E11 -> 0 | H11: 0 | I11: =G11*H11 -> 0 | K11: =F11+I11+J11 -> 0
D12: LS | E12: 0 | F12: =C12*E12 -> 0 | H12: 0 | I12: =G12*H12 -> 0 | K12: =F12+I12+J12 -> 0
D13: LS | E13: 0 | F13: =C13*E13 -> 0 | H13: 0 | I13: =G13*H13 -> 0 | K13: =F13+I13+J13 -> 0
D14: LS | E14: 0 | F14: =C14*E14 -> 0 | H14: 0 | I14: =G14*H14 -> 0 | K14: =F14+I14+J14 -> 0
D15: LS | E15: 0 | F15: =C15*E15 -> 0 | H15: 0 | I15: =G15*H15 -> 0 | K15: =F15+I15+J15 -> 0
D16: LS | E16: 0 | F16: =C16*E16 -> 0 | H16: 0 | I16: =G16*H16 -> 0 | K16: =F16+I16+J16 -> 0
D17: LS | E17: 0 | F17: =C17*E17 -> 0 | H17: 0 | I17: =G17*H17 -> 0 | K17: =F17+I17+J17 -> 0
D18: LS | E18: 0 | F18: =C18*E18 -> 0 | H18: 0 | I18: =G18*H18 -> 0 | K18: =F18+I18+J18 -> 0
D19: LS | E19: 0 | F19: =C19*E19 -> 0 | H19: 0 | I19: =G19*H19 -> 0 | K19: =F19+I19+J19 -> 0
D20: LS | E20: 0 | F20: =C20*E20 -> 0 | H20: 0 | I20: =G20*H20 -> 0 | K20: =F20+I20+J20 -> 0
D21: LS | E21: 0 | F21: =C21*E21 -> 0 | H21: 0 | I21: =G21*H21 -> 0 | K21: =F21+I21+J21 -> 0
D22: LS | E22: 0 | F22: =C22*E22 -> 0 | H22: 0 | I22: =G22*H22 -> 0 | K22: =F22+I22+J22 -> 0
J24: Sub Total | K24: =SUM(K11:K23) -> 0
A25: CODE | B25: DESCRIPTION | C25: Materials & Equipment | G25: Labor
A26: 12 21 00 | B26: Window Blinds | C26: Qty | D26: Unit | E26: U. Price | F26: Sub Total | G26: MHrs | H26: U. Price | I26: Sub Total | J26: Quote | K26: Total
B27: Window Blinds | C27: 76 | D27: LF | E27: 0 | F27: =C27*E27 -> 0 | H27: 0 | I27: =G27*H27 -> 0 | K27: =F27+I27+J27 -> 0 | L27: Sackville smiles | M27: 2016
D28: LS | E28: 0 | F28: =C28*E28 -> 0 | H28: 0 | I28: =G28*H28 -> 0 | K28: =F28+I28+J28 -> 0 | L28: Sackville smiles | M28: 141 | N28: Unit price-3 ft wide
D29: LS | E29: 0 | F29: =C29*E29 -> 0 | H29: 0 | I29: =G29*H29 -> 0 | K29: =F29+I29+J29 -> 0 | M29: =M28/3 -> 47
D30: LS | E30: 0 | F30: =C30*E30 -> 0 | H30: 0 | I30: =G30*H30 -> 0 | K30: =F30+I30+J30 -> 0
D31: LS | E31: 0 | F31: =C31*E31 -> 0 | H31: 0 | I31: =G31*H31 -> 0 | K31: =F31+I31+J31 -> 0
D32: LS | E32: 0 | F32: =C32*E32 -> 0 | H32: 0 | I32: =G32*H32 -> 0 | K32: =F32+I32+J32 -> 0
D33: LS | E33: 0 | F33: =C33*E33 -> 0 | H33: 0 | I33: =G33*H33 -> 0 | K33: =F33+I33+J33 -> 0
J35: Sub Total | K35: =SUM(K27:K34) -> 0
A36: CODE | B36: DESCRIPTION | C36: Materials & Equipment | G36: Labor
A37: 12 30 00 | B37: Casework | C37: Qty | D37: Unit | E37: U. Price | F37: Sub Total | G37: MHrs | H37: U. Price | I37: Sub Total | J37: Quote | K37: Total
D38: LS | E38: 0 | F38: =C38*E38 -> 0 | H38: 0 | I38: =G38*H38 -> 0 | K38: =F38+I38+J38 -> 0
D39: LS | E39: 0 | F39: =C39*E39 -> 0 | H39: 0 | I39: =G39*H39 -> 0 | K39: =F39+I39+J39 -> 0
D40: LS | E40: 0 | F40: =C40*E40 -> 0 | H40: 0 | I40: =G40*H40 -> 0 | K40: =F40+I40+J40 -> 0
J43: Sub Total | K43: =SUM(K38:K42) -> 0
A44: CODE | B44: DESCRIPTION | C44: Materials & Equipment | G44: Labor
A45: 12 32 00 | B45: Manufactured Wood Casework | C45: Qty | D45: Unit | E45: U. Price | F45: Sub Total | G45: MHrs | H45: U. Price | I45: Sub Total | J45: Quote | K45: Total
D46: LS | E46: 0 | F46: =C46*E46 -> 0 | H46: 0 | I46: =G46*H46 -> 0 | K46: =F46+I46+J46 -> 0
D47: LS | E47: 0 | F47: =C47*E47 -> 0 | H47: 0 | I47: =G47*H47 -> 0 | K47: =F47+I47+J47 -> 0
D48: LS | E48: 0 | F48: =C48*E48 -> 0 | H48: 0 | I48: =G48*H48 -> 0 | K48: =F48+I48+J48 -> 0
D49: LS | E49: 0 | F49: =C49*E49 -> 0 | H49: 0 | I49: =G49*H49 -> 0 | K49: =F49+I49+J49 -> 0
D50: LS | E50: 0 | F50: =C50*E50 -> 0 | H50: 0 | I50: =G50*H50 -> 0 | K50: =F50+I50+J50 -> 0
J52: Sub Total | K52: =SUM(K46:K51) -> 0
A53: CODE | B53: DESCRIPTION | C53: Materials & Equipment | G53: Labor
A54: 12 35 00 | B54: Specialty Casework | C54: Qty | D54: Unit | E54: U. Price | F54: Sub Total | G54: MHrs | H54: U. Price | I54: Sub Total | J54: Quote | K54: Total
D55: LS | E55: 0 | F55: =C55*E55 -> 0 | H55: 0 | I55: =G55*H55 -> 0 | K55: =F55+I55+J55 -> 0
D56: LS | E56: 0 | F56: =C56*E56 -> 0 | H56: 0 | I56: =G56*H56 -> 0 | K56: =F56+I56+J56 -> 0
D57: LS | E57: 0 | F57: =C57*E57 -> 0 | H57: 0 | I57: =G57*H57 -> 0 | K57: =F57+I57+J57 -> 0
D58: LS | E58: 0 | F58: =C58*E58 -> 0 | H58: 0 | I58: =G58*H58 -> 0 | K58: =F58+I58+J58 -> 0
D59: LS | E59: 0 | F59: =C59*E59 -> 0 | H59: 0 | I59: =G59*H59 -> 0 | K59: =F59+I59+J59 -> 0
D60: LS | E60: 0 | F60: =C60*E60 -> 0 | H60: 0 | I60: =G60*H60 -> 0 | K60: =F60+I60+J60 -> 0
D61: LS | E61: 0 | F61: =C61*E61 -> 0 | H61: 0 | I61: =G61*H61 -> 0 | K61: =F61+I61+J61 -> 0
J63: Sub Total | K63: =SUM(K55:K62) -> 0
A64: CODE | B64: DESCRIPTION | C64: Materials & Equipment | G64: Labor
A65: 12 36 00 | B65: Countertops | C65: Qty | D65: Unit | E65: U. Price | F65: Sub Total | G65: MHrs | H65: U. Price | I65: Sub Total | J65: Quote | K65: Total
D66: LS | E66: 0 | F66: =C66*E66 -> 0 | H66: 0 | I66: =G66*H66 -> 0 | K66: =F66+I66+J66 -> 0
D67: LS | E67: 0 | F67: =C67*E67 -> 0 | H67: 0 | I67: =G67*H67 -> 0 | K67: =F67+I67+J67 -> 0
D68: LS | E68: 0 | F68: =C68*E68 -> 0 | H68: 0 | I68: =G68*H68 -> 0 | K68: =F68+I68+J68 -> 0
D69: LS | E69: 0 | F69: =C69*E69 -> 0 | H69: 0 | I69: =G69*H69 -> 0 | K69: =F69+I69+J69 -> 0
D70: LS | E70: 0 | F70: =C70*E70 -> 0 | H70: 0 | I70: =G70*H70 -> 0 | K70: =F70+I70+J70 -> 0
J72: Sub Total | K72: =SUM(K66:K71) -> 0
A73: CODE | B73: DESCRIPTION | C73: Materials & Equipment | G73: Labor
C74: Qty | D74: Unit | E74: U. Price | F74: Sub Total | G74: MHrs | H74: U. Price | I74: Sub Total | J74: Quote | K74: Total
D75: LS | E75: 0 | F75: =C75*E75 -> 0 | H75: 0 | I75: =G75*H75 -> 0 | K75: =F75+I75+J75 -> 0
D76: LS | E76: 0 | F76: =C76*E76 -> 0 | H76: 0 | I76: =G76*H76 -> 0 | K76: =F76+I76+J76 -> 0
D77: LS | E77: 0 | F77: =C77*E77 -> 0 | H77: 0 | I77: =G77*H77 -> 0 | K77: =F77+I77+J77 -> 0
J79: Sub Total | K79: =SUM(K75:K78) -> 0
A80: CODE | B80: DESCRIPTION | C80: Materials & Equipment | G80: Labor
C81: Qty | D81: Unit | E81: U. Price | F81: Sub Total | G81: MHrs | H81: U. Price | I81: Sub Total | J81: Quote | K81: Total
D82: LS | E82: 0 | F82: =C82*E82 -> 0 | H82: 0 | I82: =G82*H82 -> 0 | K82: =F82+I82+J82 -> 0
D83: LS | E83: 0 | F83: =C83*E83 -> 0 | H83: 0 | I83: =G83*H83 -> 0 | K83: =F83+I83+J83 -> 0
D84: LS | E84: 0 | F84: =C84*E84 -> 0 | H84: 0 | I84: =G84*H84 -> 0 | K84: =F84+I84+J84 -> 0
D85: LS | E85: 0 | F85: =C85*E85 -> 0 | H85: 0 | I85: =G85*H85 -> 0 | K85: =F85+I85+J85 -> 0
D86: LS | E86: 0 | F86: =C86*E86 -> 0 | H86: 0 | I86: =G86*H86 -> 0 | K86: =F86+I86+J86 -> 0
J88: Sub Total | K88: =SUM(K82:K87) -> 0
A89: CODE | B89: DESCRIPTION | C89: Materials & Equipment | G89: Labor
C90: Qty | D90: Unit | E90: U. Price | F90: Sub Total | G90: MHrs | H90: U. Price | I90: Sub Total | J90: Quote | K90: Total
D91: LS | E91: 0 | F91: =C91*E91 -> 0 | H91: 0 | I91: =G91*H91 -> 0 | K91: =F91+I91+J91 -> 0
D92: LS | E92: 0 | F92: =C92*E92 -> 0 | H92: 0 | I92: =G92*H92 -> 0 | K92: =F92+I92+J92 -> 0
D93: LS | E93: 0 | F93: =C93*E93 -> 0 | H93: 0 | I93: =G93*H93 -> 0 | K93: =F93+I93+J93 -> 0
D94: LS | E94: 0 | F94: =C94*E94 -> 0 | H94: 0 | I94: =G94*H94 -> 0 | K94: =F94+I94+J94 -> 0
J96: Sub Total | K96: =SUM(K91:K95) -> 0
F97: Material Total | G97: Total Hours | I97: Labor Total | J97: Contractor Total | K97: TOTAL
A98: $ / Sq.Ft | B98: TOTAL DIVISION 12
A99: =K99/E6 -> 0 | F99: =SUM(F91:F95,F82:F87,F75:F78,F66:F71,F55:F61,F46:F51,F38:F42,F27:F34,F11:F23) -> 0 | G99: =SUM(G91:G95,G82:G87,G75:G78,G66:G71,G55:G61,G46:G51,G38:G42,G27:G34,G11:G23) -> 0 | I99: =SUM(I91:I95,I82:I87,I75:I78,I66:I71,I55:I61,I46:I51,I38:I42,I27:I34,I11:I23) -> 0 | J99: =SUM(J91:J95,J82:J87,J75:J78,J66:J71,J55:J61,J46:J51,J38:J42,J27:J34,J11:J23) -> 0 | K99: =SUM(K96,K88,K79,K72,K63,K52,K43,K35,K24) -> 0

Sheet 13
C1: ='Estimate Summary'!C1:H1 -> 0
G5: Special Construction | J5: Schedule
D6: ='Estimate Summary'!C11 -> Area: | E6: ='Estimate Summary'!D11 -> 1747 | F6: ='Estimate Summary'!E11 -> Sq. Ft. | J6: ='1'!J6 -> 13 | K6: Weeks
A9: CODE | B9: DESCRIPTION | C9: Materials & Equipment | G9: Labor | L9: Sub Contractor | M9: Quote Total | N9: Additional Quote Info
C10: Qty | D10: Unit | E10: U. Price | F10: Sub Total | G10: MHrs | H10: U. Price | I10: Sub Total | J10: Quote | K10: Total
D11: LS | E11: 0 | F11: =C11*E11 -> 0 | H11: 0 | I11: =G11*H11 -> 0 | K11: =F11+I11+J11 -> 0
D12: LS | E12: 0 | F12: =C12*E12 -> 0 | H12: 0 | I12: =G12*H12 -> 0 | K12: =F12+I12+J12 -> 0
D13: LS | E13: 0 | F13: =C13*E13 -> 0 | H13: 0 | I13: =G13*H13 -> 0 | K13: =F13+I13+J13 -> 0
D14: LS | E14: 0 | F14: =C14*E14 -> 0 | H14: 0 | I14: =G14*H14 -> 0 | K14: =F14+I14+J14 -> 0
D15: LS | E15: 0 | F15: =C15*E15 -> 0 | H15: 0 | I15: =G15*H15 -> 0 | K15: =F15+I15+J15 -> 0
D16: LS | E16: 0 | F16: =C16*E16 -> 0 | H16: 0 | I16: =G16*H16 -> 0 | K16: =F16+I16+J16 -> 0
D17: LS | E17: 0 | F17: =C17*E17 -> 0 | H17: 0 | I17: =G17*H17 -> 0 | K17: =F17+I17+J17 -> 0
D18: LS | E18: 0 | F18: =C18*E18 -> 0 | H18: 0 | I18: =G18*H18 -> 0 | K18: =F18+I18+J18 -> 0
D19: LS | E19: 0 | F19: =C19*E19 -> 0 | H19: 0 | I19: =G19*H19 -> 0 | K19: =F19+I19+J19 -> 0
D20: LS | E20: 0 | F20: =C20*E20 -> 0 | H20: 0 | I20: =G20*H20 -> 0 | K20: =F20+I20+J20 -> 0
D21: LS | E21: 0 | F21: =C21*E21 -> 0 | H21: 0 | I21: =G21*H21 -> 0 | K21: =F21+I21+J21 -> 0
D22: LS | E22: 0 | F22: =C22*E22 -> 0 | H22: 0 | I22: =G22*H22 -> 0 | K22: =F22+I22+J22 -> 0
J24: Sub Total | K24: =SUM(K11:K23) -> 0
A25: CODE | B25: DESCRIPTION | C25: Materials & Equipment | G25: Labor
C26: Qty | D26: Unit | E26: U. Price | F26: Sub Total | G26: MHrs | H26: U. Price | I26: Sub Total | J26: Quote | K26: Total
D27: LS | E27: 0 | F27: =C27*E27 -> 0 | H27: 0 | I27: =G27*H27 -> 0 | K27: =F27+I27+J27 -> 0
D28: LS | E28: 0 | F28: =C28*E28 -> 0 | H28: 0 | I28: =G28*H28 -> 0 | K28: =F28+I28+J28 -> 0
D29: LS | E29: 0 | F29: =C29*E29 -> 0 | H29: 0 | I29: =G29*H29 -> 0 | K29: =F29+I29+J29 -> 0
D30: LS | E30: 0 | F30: =C30*E30 -> 0 | H30: 0 | I30: =G30*H30 -> 0 | K30: =F30+I30+J30 -> 0
D31: LS | E31: 0 | F31: =C31*E31 -> 0 | H31: 0 | I31: =G31*H31 -> 0 | K31: =F31+I31+J31 -> 0
D32: LS | E32: 0 | F32: =C32*E32 -> 0 | H32: 0 | I32: =G32*H32 -> 0 | K32: =F32+I32+J32 -> 0
D33: LS | E33: 0 | F33: =C33*E33 -> 0 | H33: 0 | I33: =G33*H33 -> 0 | K33: =F33+I33+J33 -> 0
J35: Sub Total | K35: =SUM(K27:K34) -> 0
A36: CODE | B36: DESCRIPTION | C36: Materials & Equipment | G36: Labor
C37: Qty | D37: Unit | E37: U. Price | F37: Sub Total | G37: MHrs | H37: U. Price | I37: Sub Total | J37: Quote | K37: Total
D38: LS | E38: 0 | F38: =C38*E38 -> 0 | H38: 0 | I38: =G38*H38 -> 0 | K38: =F38+I38+J38 -> 0
D39: LS | E39: 0 | F39: =C39*E39 -> 0 | H39: 0 | I39: =G39*H39 -> 0 | K39: =F39+I39+J39 -> 0
D40: LS | E40: 0 | F40: =C40*E40 -> 0 | H40: 0 | I40: =G40*H40 -> 0 | K40: =F40+I40+J40 -> 0
J43: Sub Total | K43: =SUM(K38:K42) -> 0
A44: CODE | B44: DESCRIPTION | C44: Materials & Equipment | G44: Labor
C45: Qty | D45: Unit | E45: U. Price | F45: Sub Total | G45: MHrs | H45: U. Price | I45: Sub Total | J45: Quote | K45: Total
D46: LS | E46: 0 | F46: =C46*E46 -> 0 | H46: 0 | I46: =G46*H46 -> 0 | K46: =F46+I46+J46 -> 0
D47: LS | E47: 0 | F47: =C47*E47 -> 0 | H47: 0 | I47: =G47*H47 -> 0 | K47: =F47+I47+J47 -> 0
D48: LS | E48: 0 | F48: =C48*E48 -> 0 | H48: 0 | I48: =G48*H48 -> 0 | K48: =F48+I48+J48 -> 0
D49: LS | E49: 0 | F49: =C49*E49 -> 0 | H49: 0 | I49: =G49*H49 -> 0 | K49: =F49+I49+J49 -> 0
D50: LS | E50: 0 | F50: =C50*E50 -> 0 | H50: 0 | I50: =G50*H50 -> 0 | K50: =F50+I50+J50 -> 0
J52: Sub Total | K52: =SUM(K46:K51) -> 0
A53: CODE | B53: DESCRIPTION | C53: Materials & Equipment | G53: Labor
C54: Qty | D54: Unit | E54: U. Price | F54: Sub Total | G54: MHrs | H54: U. Price | I54: Sub Total | J54: Quote | K54: Total
D55: LS | E55: 0 | F55: =C55*E55 -> 0 | H55: 0 | I55: =G55*H55 -> 0 | K55: =F55+I55+J55 -> 0
D56: LS | E56: 0 | F56: =C56*E56 -> 0 | H56: 0 | I56: =G56*H56 -> 0 | K56: =F56+I56+J56 -> 0
D57: LS | E57: 0 | F57: =C57*E57 -> 0 | H57: 0 | I57: =G57*H57 -> 0 | K57: =F57+I57+J57 -> 0
D58: LS | E58: 0 | F58: =C58*E58 -> 0 | H58: 0 | I58: =G58*H58 -> 0 | K58: =F58+I58+J58 -> 0
D59: LS | E59: 0 | F59: =C59*E59 -> 0 | H59: 0 | I59: =G59*H59 -> 0 | K59: =F59+I59+J59 -> 0
D60: LS | E60: 0 | F60: =C60*E60 -> 0 | H60: 0 | I60: =G60*H60 -> 0 | K60: =F60+I60+J60 -> 0
D61: LS | E61: 0 | F61: =C61*E61 -> 0 | H61: 0 | I61: =G61*H61 -> 0 | K61: =F61+I61+J61 -> 0
J63: Sub Total | K63: =SUM(K55:K62) -> 0
A64: CODE | B64: DESCRIPTION | C64: Materials & Equipment | G64: Labor
C65: Qty | D65: Unit | E65: U. Price | F65: Sub Total | G65: MHrs | H65: U. Price | I65: Sub Total | J65: Quote | K65: Total
D66: LS | E66: 0 | F66: =C66*E66 -> 0 | H66: 0 | I66: =G66*H66 -> 0 | K66: =F66+I66+J66 -> 0
D67: LS | E67: 0 | F67: =C67*E67 -> 0 | H67: 0 | I67: =G67*H67 -> 0 | K67: =F67+I67+J67 -> 0
D68: LS | E68: 0 | F68: =C68*E68 -> 0 | H68: 0 | I68: =G68*H68 -> 0 | K68: =F68+I68+J68 -> 0
D69: LS | E69: 0 | F69: =C69*E69 -> 0 | H69: 0 | I69: =G69*H69 -> 0 | K69: =F69+I69+J69 -> 0
D70: LS | E70: 0 | F70: =C70*E70 -> 0 | H70: 0 | I70: =G70*H70 -> 0 | K70: =F70+I70+J70 -> 0
J72: Sub Total | K72: =SUM(K66:K71) -> 0
A73: CODE | B73: DESCRIPTION | C73: Materials & Equipment | G73: Labor
C74: Qty | D74: Unit | E74: U. Price | F74: Sub Total | G74: MHrs | H74: U. Price | I74: Sub Total | J74: Quote | K74: Total
D75: LS | E75: 0 | F75: =C75*E75 -> 0 | H75: 0 | I75: =G75*H75 -> 0 | K75: =F75+I75+J75 -> 0
D76: LS | E76: 0 | F76: =C76*E76 -> 0 | H76: 0 | I76: =G76*H76 -> 0 | K76: =F76+I76+J76 -> 0
D77: LS | E77: 0 | F77: =C77*E77 -> 0 | H77: 0 | I77: =G77*H77 -> 0 | K77: =F77+I77+J77 -> 0
J79: Sub Total | K79: =SUM(K75:K78) -> 0
A80: CODE | B80: DESCRIPTION | C80: Materials & Equipment | G80: Labor
C81: Qty | D81: Unit | E81: U. Price | F81: Sub Total | G81: MHrs | H81: U. Price | I81: Sub Total | J81: Quote | K81: Total
D82: LS | E82: 0 | F82: =C82*E82 -> 0 | H82: 0 | I82: =G82*H82 -> 0 | K82: =F82+I82+J82 -> 0
D83: LS | E83: 0 | F83: =C83*E83 -> 0 | H83: 0 | I83: =G83*H83 -> 0 | K83: =F83+I83+J83 -> 0
D84: LS | E84: 0 | F84: =C84*E84 -> 0 | H84: 0 | I84: =G84*H84 -> 0 | K84: =F84+I84+J84 -> 0
D85: LS | E85: 0 | F85: =C85*E85 -> 0 | H85: 0 | I85: =G85*H85 -> 0 | K85: =F85+I85+J85 -> 0
D86: LS | E86: 0 | F86: =C86*E86 -> 0 | H86: 0 | I86: =G86*H86 -> 0 | K86: =F86+I86+J86 -> 0
J88: Sub Total | K88: =SUM(K82:K87) -> 0
A89: CODE | B89: DESCRIPTION | C89: Materials & Equipment | G89: Labor
C90: Qty | D90: Unit | E90: U. Price | F90: Sub Total | G90: MHrs | H90: U. Price | I90: Sub Total | J90: Quote | K90: Total
D91: LS | E91: 0 | F91: =C91*E91 -> 0 | H91: 0 | I91: =G91*H91 -> 0 | K91: =F91+I91+J91 -> 0
D92: LS | E92: 0 | F92: =C92*E92 -> 0 | H92: 0 | I92: =G92*H92 -> 0 | K92: =F92+I92+J92 -> 0
D93: LS | E93: 0 | F93: =C93*E93 -> 0 | H93: 0 | I93: =G93*H93 -> 0 | K93: =F93+I93+J93 -> 0
D94: LS | E94: 0 | F94: =C94*E94 -> 0 | H94: 0 | I94: =G94*H94 -> 0 | K94: =F94+I94+J94 -> 0
J96: Sub Total | K96: =SUM(K91:K95) -> 0
F97: Material Total | G97: Total Hours | I97: Labor Total | J97: Contractor Total | K97: TOTAL
A98: $ / Sq.Ft | B98: TOTAL DIVISION 13
A99: =K99/E6 -> 0 | F99: =SUM(F91:F95,F82:F87,F75:F78,F66:F71,F55:F61,F46:F51,F38:F42,F27:F34,F11:F23) -> 0 | G99: =SUM(G91:G95,G82:G87,G75:G78,G66:G71,G55:G61,G46:G51,G38:G42,G27:G34,G11:G23) -> 0 | I99: =SUM(I91:I95,I82:I87,I75:I78,I66:I71,I55:I61,I46:I51,I38:I42,I27:I34,I11:I23) -> 0 | J99: =SUM(J91:J95,J82:J87,J75:J78,J66:J71,J55:J61,J46:J51,J38:J42,J27:J34,J11:J23) -> 0 | K99: =SUM(K96,K88,K79,K72,K63,K52,K43,K35,K24) -> 0

Sheet 14
C1: ='Estimate Summary'!C1:H1 -> 0
G5: Conveying Equipment | J5: Schedule
D6: ='Estimate Summary'!C11 -> Area: | E6: ='Estimate Summary'!D11 -> 1747 | F6: ='Estimate Summary'!E11 -> Sq. Ft. | J6: ='1'!J6 -> 13 | K6: Weeks
A9: CODE | B9: DESCRIPTION | C9: Materials & Equipment | G9: Labor | L9: Sub Contractor | M9: Quote Total | N9: Additional Quote Info
A10: 14 20 00 | B10: Elevators | C10: Qty | D10: Unit | E10: U. Price | F10: Sub Total | G10: MHrs | H10: U. Price | I10: Sub Total | J10: Quote | K10: Total
D11: LS | E11: 0 | F11: =C11*E11 -> 0 | H11: 0 | I11: =G11*H11 -> 0 | K11: =F11+I11+J11 -> 0
D12: LS | E12: 0 | F12: =C12*E12 -> 0 | H12: 0 | I12: =G12*H12 -> 0 | K12: =F12+I12+J12 -> 0
D13: LS | E13: 0 | F13: =C13*E13 -> 0 | H13: 0 | I13: =G13*H13 -> 0 | K13: =F13+I13+J13 -> 0
D14: LS | E14: 0 | F14: =C14*E14 -> 0 | H14: 0 | I14: =G14*H14 -> 0 | K14: =F14+I14+J14 -> 0
D15: LS | E15: 0 | F15: =C15*E15 -> 0 | H15: 0 | I15: =G15*H15 -> 0 | K15: =F15+I15+J15 -> 0
D16: LS | E16: 0 | F16: =C16*E16 -> 0 | H16: 0 | I16: =G16*H16 -> 0 | K16: =F16+I16+J16 -> 0
D17: LS | E17: 0 | F17: =C17*E17 -> 0 | H17: 0 | I17: =G17*H17 -> 0 | K17: =F17+I17+J17 -> 0
D18: LS | E18: 0 | F18: =C18*E18 -> 0 | H18: 0 | I18: =G18*H18 -> 0 | K18: =F18+I18+J18 -> 0
D19: LS | E19: 0 | F19: =C19*E19 -> 0 | H19: 0 | I19: =G19*H19 -> 0 | K19: =F19+I19+J19 -> 0
D20: LS | E20: 0 | F20: =C20*E20 -> 0 | H20: 0 | I20: =G20*H20 -> 0 | K20: =F20+I20+J20 -> 0
D21: LS | E21: 0 | F21: =C21*E21 -> 0 | H21: 0 | I21: =G21*H21 -> 0 | K21: =F21+I21+J21 -> 0
D22: LS | E22: 0 | F22: =C22*E22 -> 0 | H22: 0 | I22: =G22*H22 -> 0 | K22: =F22+I22+J22 -> 0
J24: Sub Total | K24: =SUM(K11:K23) -> 0
A25: CODE | B25: DESCRIPTION | C25: Materials & Equipment | G25: Labor
A26: 14 40 00 | B26: Lifts | C26: Qty | D26: Unit | E26: U. Price | F26: Sub Total | G26: MHrs | H26: U. Price | I26: Sub Total | J26: Quote | K26: Total
D27: LS | E27: 0 | F27: =C27*E27 -> 0 | H27: 0 | I27: =G27*H27 -> 0 | K27: =F27+I27+J27 -> 0
D28: LS | E28: 0 | F28: =C28*E28 -> 0 | H28: 0 | I28: =G28*H28 -> 0 | K28: =F28+I28+J28 -> 0
D29: LS | E29: 0 | F29: =C29*E29 -> 0 | H29: 0 | I29: =G29*H29 -> 0 | K29: =F29+I29+J29 -> 0
D30: LS | E30: 0 | F30: =C30*E30 -> 0 | H30: 0 | I30: =G30*H30 -> 0 | K30: =F30+I30+J30 -> 0
D31: LS | E31: 0 | F31: =C31*E31 -> 0 | H31: 0 | I31: =G31*H31 -> 0 | K31: =F31+I31+J31 -> 0
D32: LS | E32: 0 | F32: =C32*E32 -> 0 | H32: 0 | I32: =G32*H32 -> 0 | K32: =F32+I32+J32 -> 0
D33: LS | E33: 0 | F33: =C33*E33 -> 0 | H33: 0 | I33: =G33*H33 -> 0 | K33: =F33+I33+J33 -> 0
J35: Sub Total | K35: =SUM(K27:K34) -> 0
A36: CODE | B36: DESCRIPTION | C36: Materials & Equipment | G36: Labor
A37: 14 42 00 | B37: Wheelchair Lifts | C37: Qty | D37: Unit | E37: U. Price | F37: Sub Total | G37: MHrs | H37: U. Price | I37: Sub Total | J37: Quote | K37: Total
D38: LS | E38: 0 | F38: =C38*E38 -> 0 | H38: 0 | I38: =G38*H38 -> 0 | K38: =F38+I38+J38 -> 0
D39: LS | E39: 0 | F39: =C39*E39 -> 0 | H39: 0 | I39: =G39*H39 -> 0 | K39: =F39+I39+J39 -> 0
D40: LS | E40: 0 | F40: =C40*E40 -> 0 | H40: 0 | I40: =G40*H40 -> 0 | K40: =F40+I40+J40 -> 0
J43: Sub Total | K43: =SUM(K38:K42) -> 0
A44: CODE | B44: DESCRIPTION | C44: Materials & Equipment | G44: Labor
C45: Qty | D45: Unit | E45: U. Price | F45: Sub Total | G45: MHrs | H45: U. Price | I45: Sub Total | J45: Quote | K45: Total
D46: LS | E46: 0 | F46: =C46*E46 -> 0 | H46: 0 | I46: =G46*H46 -> 0 | K46: =F46+I46+J46 -> 0
D47: LS | E47: 0 | F47: =C47*E47 -> 0 | H47: 0 | I47: =G47*H47 -> 0 | K47: =F47+I47+J47 -> 0
D48: LS | E48: 0 | F48: =C48*E48 -> 0 | H48: 0 | I48: =G48*H48 -> 0 | K48: =F48+I48+J48 -> 0
D49: LS | E49: 0 | F49: =C49*E49 -> 0 | H49: 0 | I49: =G49*H49 -> 0 | K49: =F49+I49+J49 -> 0
D50: LS | E50: 0 | F50: =C50*E50 -> 0 | H50: 0 | I50: =G50*H50 -> 0 | K50: =F50+I50+J50 -> 0
J52: Sub Total | K52: =SUM(K46:K51) -> 0
A53: CODE | B53: DESCRIPTION | C53: Materials & Equipment | G53: Labor
C54: Qty | D54: Unit | E54: U. Price | F54: Sub Total | G54: MHrs | H54: U. Price | I54: Sub Total | J54: Quote | K54: Total
D55: LS | E55: 0 | F55: =C55*E55 -> 0 | H55: 0 | I55: =G55*H55 -> 0 | K55: =F55+I55+J55 -> 0
D56: LS | E56: 0 | F56: =C56*E56 -> 0 | H56: 0 | I56: =G56*H56 -> 0 | K56: =F56+I56+J56 -> 0
D57: LS | E57: 0 | F57: =C57*E57 -> 0 | H57: 0 | I57: =G57*H57 -> 0 | K57: =F57+I57+J57 -> 0
D58: LS | E58: 0 | F58: =C58*E58 -> 0 | H58: 0 | I58: =G58*H58 -> 0 | K58: =F58+I58+J58 -> 0
D59: LS | E59: 0 | F59: =C59*E59 -> 0 | H59: 0 | I59: =G59*H59 -> 0 | K59: =F59+I59+J59 -> 0
D60: LS | E60: 0 | F60: =C60*E60 -> 0 | H60: 0 | I60: =G60*H60 -> 0 | K60: =F60+I60+J60 -> 0
D61: LS | E61: 0 | F61: =C61*E61 -> 0 | H61: 0 | I61: =G61*H61 -> 0 | K61: =F61+I61+J61 -> 0
J63: Sub Total | K63: =SUM(K55:K62) -> 0
A64: CODE | B64: DESCRIPTION | C64: Materials & Equipment | G64: Labor
C65: Qty | D65: Unit | E65: U. Price | F65: Sub Total | G65: MHrs | H65: U. Price | I65: Sub Total | J65: Quote | K65: Total
D66: LS | E66: 0 | F66: =C66*E66 -> 0 | H66: 0 | I66: =G66*H66 -> 0 | K66: =F66+I66+J66 -> 0
D67: LS | E67: 0 | F67: =C67*E67 -> 0 | H67: 0 | I67: =G67*H67 -> 0 | K67: =F67+I67+J67 -> 0
D68: LS | E68: 0 | F68: =C68*E68 -> 0 | H68: 0 | I68: =G68*H68 -> 0 | K68: =F68+I68+J68 -> 0
D69: LS | E69: 0 | F69: =C69*E69 -> 0 | H69: 0 | I69: =G69*H69 -> 0 | K69: =F69+I69+J69 -> 0
D70: LS | E70: 0 | F70: =C70*E70 -> 0 | H70: 0 | I70: =G70*H70 -> 0 | K70: =F70+I70+J70 -> 0
J72: Sub Total | K72: =SUM(K66:K71) -> 0
A73: CODE | B73: DESCRIPTION | C73: Materials & Equipment | G73: Labor
C74: Qty | D74: Unit | E74: U. Price | F74: Sub Total | G74: MHrs | H74: U. Price | I74: Sub Total | J74: Quote | K74: Total
D75: LS | E75: 0 | F75: =C75*E75 -> 0 | H75: 0 | I75: =G75*H75 -> 0 | K75: =F75+I75+J75 -> 0
D76: LS | E76: 0 | F76: =C76*E76 -> 0 | H76: 0 | I76: =G76*H76 -> 0 | K76: =F76+I76+J76 -> 0
D77: LS | E77: 0 | F77: =C77*E77 -> 0 | H77: 0 | I77: =G77*H77 -> 0 | K77: =F77+I77+J77 -> 0
J79: Sub Total | K79: =SUM(K75:K78) -> 0
A80: CODE | B80: DESCRIPTION | C80: Materials & Equipment | G80: Labor
C81: Qty | D81: Unit | E81: U. Price | F81: Sub Total | G81: MHrs | H81: U. Price | I81: Sub Total | J81: Quote | K81: Total
D82: LS | E82: 0 | F82: =C82*E82 -> 0 | H82: 0 | I82: =G82*H82 -> 0 | K82: =F82+I82+J82 -> 0
D83: LS | E83: 0 | F83: =C83*E83 -> 0 | H83: 0 | I83: =G83*H83 -> 0 | K83: =F83+I83+J83 -> 0
D84: LS | E84: 0 | F84: =C84*E84 -> 0 | H84: 0 | I84: =G84*H84 -> 0 | K84: =F84+I84+J84 -> 0
D85: LS | E85: 0 | F85: =C85*E85 -> 0 | H85: 0 | I85: =G85*H85 -> 0 | K85: =F85+I85+J85 -> 0
D86: LS | E86: 0 | F86: =C86*E86 -> 0 | H86: 0 | I86: =G86*H86 -> 0 | K86: =F86+I86+J86 -> 0
J88: Sub Total | K88: =SUM(K82:K87) -> 0
A89: CODE | B89: DESCRIPTION | C89: Materials & Equipment | G89: Labor
C90: Qty | D90: Unit | E90: U. Price | F90: Sub Total | G90: MHrs | H90: U. Price | I90: Sub Total | J90: Quote | K90: Total
D91: LS | E91: 0 | F91: =C91*E91 -> 0 | H91: 0 | I91: =G91*H91 -> 0 | K91: =F91+I91+J91 -> 0
D92: LS | E92: 0 | F92: =C92*E92 -> 0 | H92: 0 | I92: =G92*H92 -> 0 | K92: =F92+I92+J92 -> 0
D93: LS | E93: 0 | F93: =C93*E93 -> 0 | H93: 0 | I93: =G93*H93 -> 0 | K93: =F93+I93+J93 -> 0
D94: LS | E94: 0 | F94: =C94*E94 -> 0 | H94: 0 | I94: =G94*H94 -> 0 | K94: =F94+I94+J94 -> 0
J96: Sub Total | K96: =SUM(K91:K95) -> 0
F97: Material Total | G97: Total Hours | I97: Labor Total | J97: Contractor Total | K97: TOTAL
A98: $ / Sq.Ft | B98: TOTAL DIVISION 14
A99: =K99/E6 -> 0 | F99: =SUM(F91:F95,F82:F87,F75:F78,F66:F71,F55:F61,F46:F51,F38:F42,F27:F34,F11:F23) -> 0 | G99: =SUM(G91:G95,G82:G87,G75:G78,G66:G71,G55:G61,G46:G51,G38:G42,G27:G34,G11:G23) -> 0 | I99: =SUM(I91:I95,I82:I87,I75:I78,I66:I71,I55:I61,I46:I51,I38:I42,I27:I34,I11:I23) -> 0 | J99: =SUM(J91:J95,J82:J87,J75:J78,J66:J71,J55:J61,J46:J51,J38:J42,J27:J34,J11:J23) -> 0 | K99: =SUM(K96,K88,K79,K72,K63,K52,K43,K35,K24) -> 0

Sheet 21
C1: ='Estimate Summary'!C1:H1 -> 0
G5: Fire Suppression | J5: Schedule
D6: ='Estimate Summary'!C11 -> Area: | E6: ='Estimate Summary'!D11 -> 1747 | F6: ='Estimate Summary'!E11 -> Sq. Ft. | J6: ='1'!J6 -> 13 | K6: Weeks
A9: CODE | B9: DESCRIPTION | C9: Materials & Equipment | G9: Labor | L9: Sub Contractor | M9: Quote Total | N9: Additional Quote Info
A10: 21 10 00 | B10: Water-Based Fire-Suppression System | C10: Qty | D10: Unit | E10: U. Price | F10: Sub Total | G10: MHrs | H10: U. Price | I10: Sub Total | J10: Quote | K10: Total
B11: Sprinkler Readjustment | C11: =E6 -> 1747 | D11: SF | E11: 3.5 | F11: 0 | H11: 0 | I11: =G11*H11 -> 0 | J11: =M13 -> 6938 | K11: =F11+I11+J11 -> 6938 | L11: B&G | M11: 29600
D12: LS | E12: 0 | F12: =C12*E12 -> 0 | H12: 0 | I12: =G12*H12 -> 0 | K12: =F12+I12+J12 -> 0 | L12: Mutch Fire | M12: 7920 | N12: They have done couple of maintenance in the building
D13: LS | E13: 0 | F13: =C13*E13 -> 0 | H13: 0 | I13: =G13*H13 -> 0 | K13: =F13+I13+J13 -> 0 | L13: Viking | M13: 6938 | N13: Night work NIC
D14: LS | E14: 0 | F14: =C14*E14 -> 0 | H14: 0 | I14: =G14*H14 -> 0 | K14: =F14+I14+J14 -> 0 | L14: Vipond | M14: 13990
D15: LS | E15: 0 | F15: =C15*E15 -> 0 | H15: 0 | I15: =G15*H15 -> 0 | K15: =F15+I15+J15 -> 0 | L15: Deploy | M15: 32500
D16: LS | E16: 0 | F16: =C16*E16 -> 0 | H16: 0 | I16: =G16*H16 -> 0 | K16: =F16+I16+J16 -> 0
D17: LS | E17: 0 | F17: =C17*E17 -> 0 | H17: 0 | I17: =G17*H17 -> 0 | K17: =F17+I17+J17 -> 0
D18: LS | E18: 0 | F18: =C18*E18 -> 0 | H18: 0 | I18: =G18*H18 -> 0 | K18: =F18+I18+J18 -> 0
D19: LS | E19: 0 | F19: =C19*E19 -> 0 | H19: 0 | I19: =G19*H19 -> 0 | K19: =F19+I19+J19 -> 0
D20: LS | E20: 0 | F20: =C20*E20 -> 0 | H20: 0 | I20: =G20*H20 -> 0 | K20: =F20+I20+J20 -> 0
D21: LS | E21: 0 | F21: =C21*E21 -> 0 | H21: 0 | I21: =G21*H21 -> 0 | K21: =F21+I21+J21 -> 0
D22: LS | E22: 0 | F22: =C22*E22 -> 0 | H22: 0 | I22: =G22*H22 -> 0 | K22: =F22+I22+J22 -> 0
J24: Sub Total | K24: =SUM(K11:K23) -> 6938
A25: CODE | B25: DESCRIPTION | C25: Materials & Equipment | G25: Labor
C26: Qty | D26: Unit | E26: U. Price | F26: Sub Total | G26: MHrs | H26: U. Price | I26: Sub Total | J26: Quote | K26: Total
D27: LS | E27: 0 | F27: =C27*E27 -> 0 | H27: 0 | I27: =G27*H27 -> 0 | K27: =F27+I27+J27 -> 0
D28: LS | E28: 0 | F28: =C28*E28 -> 0 | H28: 0 | I28: =G28*H28 -> 0 | K28: =F28+I28+J28 -> 0
D29: LS | E29: 0 | F29: =C29*E29 -> 0 | H29: 0 | I29: =G29*H29 -> 0 | K29: =F29+I29+J29 -> 0
D30: LS | E30: 0 | F30: =C30*E30 -> 0 | H30: 0 | I30: =G30*H30 -> 0 | K30: =F30+I30+J30 -> 0
D31: LS | E31: 0 | F31: =C31*E31 -> 0 | H31: 0 | I31: =G31*H31 -> 0 | K31: =F31+I31+J31 -> 0
D32: LS | E32: 0 | F32: =C32*E32 -> 0 | H32: 0 | I32: =G32*H32 -> 0 | K32: =F32+I32+J32 -> 0
D33: LS | E33: 0 | F33: =C33*E33 -> 0 | H33: 0 | I33: =G33*H33 -> 0 | K33: =F33+I33+J33 -> 0
J35: Sub Total | K35: =SUM(K27:K34) -> 0
A36: CODE | B36: DESCRIPTION | C36: Materials & Equipment | G36: Labor
C37: Qty | D37: Unit | E37: U. Price | F37: Sub Total | G37: MHrs | H37: U. Price | I37: Sub Total | J37: Quote | K37: Total
D38: LS | E38: 0 | F38: =C38*E38 -> 0 | H38: 0 | I38: =G38*H38 -> 0 | K38: =F38+I38+J38 -> 0
D39: LS | E39: 0 | F39: =C39*E39 -> 0 | H39: 0 | I39: =G39*H39 -> 0 | K39: =F39+I39+J39 -> 0
D40: LS | E40: 0 | F40: =C40*E40 -> 0 | H40: 0 | I40: =G40*H40 -> 0 | K40: =F40+I40+J40 -> 0
J43: Sub Total | K43: =SUM(K38:K42) -> 0
A44: CODE | B44: DESCRIPTION | C44: Materials & Equipment | G44: Labor
C45: Qty | D45: Unit | E45: U. Price | F45: Sub Total | G45: MHrs | H45: U. Price | I45: Sub Total | J45: Quote | K45: Total
D46: LS | E46: 0 | F46: =C46*E46 -> 0 | H46: 0 | I46: =G46*H46 -> 0 | K46: =F46+I46+J46 -> 0
D47: LS | E47: 0 | F47: =C47*E47 -> 0 | H47: 0 | I47: =G47*H47 -> 0 | K47: =F47+I47+J47 -> 0
D48: LS | E48: 0 | F48: =C48*E48 -> 0 | H48: 0 | I48: =G48*H48 -> 0 | K48: =F48+I48+J48 -> 0
D49: LS | E49: 0 | F49: =C49*E49 -> 0 | H49: 0 | I49: =G49*H49 -> 0 | K49: =F49+I49+J49 -> 0
D50: LS | E50: 0 | F50: =C50*E50 -> 0 | H50: 0 | I50: =G50*H50 -> 0 | K50: =F50+I50+J50 -> 0
J52: Sub Total | K52: =SUM(K46:K51) -> 0
A53: CODE | B53: DESCRIPTION | C53: Materials & Equipment | G53: Labor
C54: Qty | D54: Unit | E54: U. Price | F54: Sub Total | G54: MHrs | H54: U. Price | I54: Sub Total | J54: Quote | K54: Total
D55: LS | E55: 0 | F55: =C55*E55 -> 0 | H55: 0 | I55: =G55*H55 -> 0 | K55: =F55+I55+J55 -> 0
D56: LS | E56: 0 | F56: =C56*E56 -> 0 | H56: 0 | I56: =G56*H56 -> 0 | K56: =F56+I56+J56 -> 0
D57: LS | E57: 0 | F57: =C57*E57 -> 0 | H57: 0 | I57: =G57*H57 -> 0 | K57: =F57+I57+J57 -> 0
D58: LS | E58: 0 | F58: =C58*E58 -> 0 | H58: 0 | I58: =G58*H58 -> 0 | K58: =F58+I58+J58 -> 0
D59: LS | E59: 0 | F59: =C59*E59 -> 0 | H59: 0 | I59: =G59*H59 -> 0 | K59: =F59+I59+J59 -> 0
D60: LS | E60: 0 | F60: =C60*E60 -> 0 | H60: 0 | I60: =G60*H60 -> 0 | K60: =F60+I60+J60 -> 0
D61: LS | E61: 0 | F61: =C61*E61 -> 0 | H61: 0 | I61: =G61*H61 -> 0 | K61: =F61+I61+J61 -> 0
J63: Sub Total | K63: =SUM(K55:K62) -> 0
A64: CODE | B64: DESCRIPTION | C64: Materials & Equipment | G64: Labor
C65: Qty | D65: Unit | E65: U. Price | F65: Sub Total | G65: MHrs | H65: U. Price | I65: Sub Total | J65: Quote | K65: Total
D66: LS | E66: 0 | F66: =C66*E66 -> 0 | H66: 0 | I66: =G66*H66 -> 0 | K66: =F66+I66+J66 -> 0
D67: LS | E67: 0 | F67: =C67*E67 -> 0 | H67: 0 | I67: =G67*H67 -> 0 | K67: =F67+I67+J67 -> 0
D68: LS | E68: 0 | F68: =C68*E68 -> 0 | H68: 0 | I68: =G68*H68 -> 0 | K68: =F68+I68+J68 -> 0
D69: LS | E69: 0 | F69: =C69*E69 -> 0 | H69: 0 | I69: =G69*H69 -> 0 | K69: =F69+I69+J69 -> 0
D70: LS | E70: 0 | F70: =C70*E70 -> 0 | H70: 0 | I70: =G70*H70 -> 0 | K70: =F70+I70+J70 -> 0
J72: Sub Total | K72: =SUM(K66:K71) -> 0
A73: CODE | B73: DESCRIPTION | C73: Materials & Equipment | G73: Labor
C74: Qty | D74: Unit | E74: U. Price | F74: Sub Total | G74: MHrs | H74: U. Price | I74: Sub Total | J74: Quote | K74: Total
D75: LS | E75: 0 | F75: =C75*E75 -> 0 | H75: 0 | I75: =G75*H75 -> 0 | K75: =F75+I75+J75 -> 0
D76: LS | E76: 0 | F76: =C76*E76 -> 0 | H76: 0 | I76: =G76*H76 -> 0 | K76: =F76+I76+J76 -> 0
D77: LS | E77: 0 | F77: =C77*E77 -> 0 | H77: 0 | I77: =G77*H77 -> 0 | K77: =F77+I77+J77 -> 0
J79: Sub Total | K79: =SUM(K75:K78) -> 0
A80: CODE | B80: DESCRIPTION | C80: Materials & Equipment | G80: Labor
C81: Qty | D81: Unit | E81: U. Price | F81: Sub Total | G81: MHrs | H81: U. Price | I81: Sub Total | J81: Quote | K81: Total
D82: LS | E82: 0 | F82: =C82*E82 -> 0 | H82: 0 | I82: =G82*H82 -> 0 | K82: =F82+I82+J82 -> 0
D83: LS | E83: 0 | F83: =C83*E83 -> 0 | H83: 0 | I83: =G83*H83 -> 0 | K83: =F83+I83+J83 -> 0
D84: LS | E84: 0 | F84: =C84*E84 -> 0 | H84: 0 | I84: =G84*H84 -> 0 | K84: =F84+I84+J84 -> 0
D85: LS | E85: 0 | F85: =C85*E85 -> 0 | H85: 0 | I85: =G85*H85 -> 0 | K85: =F85+I85+J85 -> 0
D86: LS | E86: 0 | F86: =C86*E86 -> 0 | H86: 0 | I86: =G86*H86 -> 0 | K86: =F86+I86+J86 -> 0
J88: Sub Total | K88: =SUM(K82:K87) -> 0
A89: CODE | B89: DESCRIPTION | C89: Materials & Equipment | G89: Labor
C90: Qty | D90: Unit | E90: U. Price | F90: Sub Total | G90: MHrs | H90: U. Price | I90: Sub Total | J90: Quote | K90: Total
D91: LS | E91: 0 | F91: =C91*E91 -> 0 | H91: 0 | I91: =G91*H91 -> 0 | K91: =F91+I91+J91 -> 0
D92: LS | E92: 0 | F92: =C92*E92 -> 0 | H92: 0 | I92: =G92*H92 -> 0 | K92: =F92+I92+J92 -> 0
D93: LS | E93: 0 | F93: =C93*E93 -> 0 | H93: 0 | I93: =G93*H93 -> 0 | K93: =F93+I93+J93 -> 0
D94: LS | E94: 0 | F94: =C94*E94 -> 0 | H94: 0 | I94: =G94*H94 -> 0 | K94: =F94+I94+J94 -> 0
J96: Sub Total | K96: =SUM(K91:K95) -> 0
F97: Material Total | G97: Total Hours | I97: Labor Total | J97: Contractor Total | K97: TOTAL
A98: $ / Sq.Ft | B98: TOTAL DIVISION 21
A99: =K99/E6 -> 3.9713795 | F99: =SUM(F91:F95,F82:F87,F75:F78,F66:F71,F55:F61,F46:F51,F38:F42,F27:F34,F11:F23) -> 0 | G99: =SUM(G91:G95,G82:G87,G75:G78,G66:G71,G55:G61,G46:G51,G38:G42,G27:G34,G11:G23) -> 0 | I99: =SUM(I91:I95,I82:I87,I75:I78,I66:I71,I55:I61,I46:I51,I38:I42,I27:I34,I11:I23) -> 0 | J99: =SUM(J91:J95,J82:J87,J75:J78,J66:J71,J55:J61,J46:J51,J38:J42,J27:J34,J11:J23) -> 6938 | K99: =SUM(K96,K88,K79,K72,K63,K52,K43,K35,K24) -> 6938

Sheet 22
C1: ='Estimate Summary'!C1:H1 -> 0
G5: Plumbing | J5: Schedule
D6: ='Estimate Summary'!C11 -> Area: | E6: ='Estimate Summary'!D11 -> 1747 | F6: ='Estimate Summary'!E11 -> Sq. Ft. | J6: ='1'!J6 -> 13 | K6: Weeks
A9: CODE | B9: DESCRIPTION | C9: Materials & Equipment | G9: Labor | L9: Sub Contractor | M9: Quote Total | N9: Additional Quote Info
A10: 22 10 00 | B10: Plumbing Piping | C10: Qty | D10: Unit | E10: U. Price | F10: Sub Total | G10: MHrs | H10: U. Price | I10: Sub Total | J10: Quote | K10: Total
B11: Plumbing, compressed air, vaccum | C11: 14 | D11: Fx | E11: 4333.33 | F11: 0 | H11: 0 | I11: =G11*H11 -> 0 | K11: =F11+I11+J11 -> 0 | L11: Ermen | M11: 129800
D12: LS | E12: 0 | F12: =C12*E12 -> 0 | H12: 0 | I12: =G12*H12 -> 0 | K12: =F12+I12+J12 -> 0 | L12: Franco | M12: 195500
C13: =E6 -> 1747 | D13: SF | E13: =26.67*1.1 -> 29.337 | F13: 0 | H13: 0 | I13: =G13*H13 -> 0 | J13: =M11 -> 129800 | K13: =F13+I13+J13 -> 129800 | L13: George's | M13: 137260
D14: LS | E14: 0 | F14: =C14*E14 -> 0 | H14: 0 | I14: =G14*H14 -> 0 | K14: =F14+I14+J14 -> 0 | L14: Moncton Plumbing
D15: LS | E15: 0 | F15: =C15*E15 -> 0 | H15: 0 | I15: =G15*H15 -> 0 | K15: =F15+I15+J15 -> 0 | L15: Premiere
D16: LS | E16: 0 | F16: =C16*E16 -> 0 | H16: 0 | I16: =G16*H16 -> 0 | K16: =F16+I16+J16 -> 0
D17: LS | E17: 0 | F17: =C17*E17 -> 0 | H17: 0 | I17: =G17*H17 -> 0 | K17: =F17+I17+J17 -> 0
D18: LS | E18: 0 | F18: =C18*E18 -> 0 | H18: 0 | I18: =G18*H18 -> 0 | K18: =F18+I18+J18 -> 0
D19: LS | E19: 0 | F19: =C19*E19 -> 0 | H19: 0 | I19: =G19*H19 -> 0 | K19: =F19+I19+J19 -> 0
D20: LS | E20: 0 | F20: =C20*E20 -> 0 | H20: 0 | I20: =G20*H20 -> 0 | K20: =F20+I20+J20 -> 0
D21: LS | E21: 0 | F21: =C21*E21 -> 0 | H21: 0 | I21: =G21*H21 -> 0 | K21: =F21+I21+J21 -> 0 | L21: Sackville smiles | M21: 5993.33 | N21: Per fixtures
D22: LS | E22: 0 | F22: =C22*E22 -> 0 | H22: 0 | I22: =G22*H22 -> 0 | K22: =F22+I22+J22 -> 0 | L22: Mountain View Dental | M22: 4333.33
L23: Mountain View Dental | M23: 26.67 | N23: per sf
J24: Sub Total | K24: =SUM(K11:K23) -> 129800
A25: CODE | B25: DESCRIPTION | C25: Materials & Equipment | G25: Labor
A26: 22 30 00 | B26: Plumbing Equipment | C26: Qty | D26: Unit | E26: U. Price | F26: Sub Total | G26: MHrs | H26: U. Price | I26: Sub Total | J26: Quote | K26: Total
A27: 22 33 00 | B27: Electric Domestic Water Heaters | D27: LS | E27: 0 | F27: =C27*E27 -> 0 | H27: 0 | I27: =G27*H27 -> 0 | K27: =F27+I27+J27 -> 0
A28: 22 34 00 | B28: Fuel-Fired Domestic Water Heaters | D28: LS | E28: 0 | F28: =C28*E28 -> 0 | H28: 0 | I28: =G28*H28 -> 0 | K28: =F28+I28+J28 -> 0
D29: LS | E29: 0 | F29: =C29*E29 -> 0 | H29: 0 | I29: =G29*H29 -> 0 | K29: =F29+I29+J29 -> 0
D30: LS | E30: 0 | F30: =C30*E30 -> 0 | H30: 0 | I30: =G30*H30 -> 0 | K30: =F30+I30+J30 -> 0
D31: LS | E31: 0 | F31: =C31*E31 -> 0 | H31: 0 | I31: =G31*H31 -> 0 | K31: =F31+I31+J31 -> 0
D32: LS | E32: 0 | F32: =C32*E32 -> 0 | H32: 0 | I32: =G32*H32 -> 0 | K32: =F32+I32+J32 -> 0
D33: LS | E33: 0 | F33: =C33*E33 -> 0 | H33: 0 | I33: =G33*H33 -> 0 | K33: =F33+I33+J33 -> 0
J35: Sub Total | K35: =SUM(K27:K34) -> 0
A36: CODE | B36: DESCRIPTION | C36: Materials & Equipment | G36: Labor
A37: 22 40 00 | B37: Plumbing Fixtures | C37: Qty | D37: Unit | E37: U. Price | F37: Sub Total | G37: MHrs | H37: U. Price | I37: Sub Total | J37: Quote | K37: Total
D38: LS | E38: 0 | F38: =C38*E38 -> 0 | H38: 0 | I38: =G38*H38 -> 0 | K38: =F38+I38+J38 -> 0
D39: LS | E39: 0 | F39: =C39*E39 -> 0 | H39: 0 | I39: =G39*H39 -> 0 | K39: =F39+I39+J39 -> 0
D40: LS | E40: 0 | F40: =C40*E40 -> 0 | H40: 0 | I40: =G40*H40 -> 0 | K40: =F40+I40+J40 -> 0
D41: LS | E41: 0 | F41: =C41*E41 -> 0 | H41: 0 | I41: =G41*H41 -> 0 | K41: =F41+I41+J41 -> 0
D42: LS | E42: 0 | F42: =C42*E42 -> 0 | H42: 0 | I42: =G42*H42 -> 0 | K42: =F42+I42+J42 -> 0
D43: LS | E43: 0 | F43: =C43*E43 -> 0 | H43: 0 | I43: =G43*H43 -> 0 | K43: =F43+I43+J43 -> 0
D44: LS | E44: 0 | F44: =C44*E44 -> 0 | H44: 0 | I44: =G44*H44 -> 0 | K44: =F44+I44+J44 -> 0
J46: Sub Total | K46: =SUM(K38:K45) -> 0
A47: CODE | B47: DESCRIPTION | C47: Materials & Equipment | G47: Labor
A48: 22 42 00 | B48: Commercial Plumbing Fixtures | C48: Qty | D48: Unit | E48: U. Price | F48: Sub Total | G48: MHrs | H48: U. Price | I48: Sub Total | J48: Quote | K48: Total
A49: 22 42 13 | B49: Commercial Water Closets, Urinals, and Bidets | D49: LS | E49: 0 | F49: =C49*E49 -> 0 | H49: 0 | I49: =G49*H49 -> 0 | K49: =F49+I49+J49 -> 0
A50: 22 42 13.13 | B50: Commercial Water Closets | D50: LS | E50: 0 | F50: =C50*E50 -> 0 | H50: 0 | I50: =G50*H50 -> 0 | K50: =F50+I50+J50 -> 0
A51: 22 42 13.16 | B51: Commercial Urinals | D51: LS | E51: 0 | F51: =C51*E51 -> 0 | H51: 0 | I51: =G51*H51 -> 0 | K51: =F51+I51+J51 -> 0
A52: 22 42 16 | B52: Commercial Lavatories and Sinks | D52: LS | E52: 0 | F52: =C52*E52 -> 0 | H52: 0 | I52: =G52*H52 -> 0 | K52: =F52+I52+J52 -> 0
A53: 22 42 16.13 | B53: Commercial Lavatories | D53: LS | E53: 0 | F53: =C53*E53 -> 0 | H53: 0 | I53: =G53*H53 -> 0 | K53: =F53+I53+J53 -> 0
A54: 22 42 16.16 | B54: Commercial Sinks | D54: LS | E54: 0 | F54: =C54*E54 -> 0 | H54: 0 | I54: =G54*H54 -> 0 | K54: =F54+I54+J54 -> 0
A55: 22 42 19 | B55: Commercial Bathtubs | D55: LS | E55: 0 | F55: =C55*E55 -> 0 | H55: 0 | I55: =G55*H55 -> 0 | K55: =F55+I55+J55 -> 0
A56: 22 42 23 | B56: Commercial Showers | D56: LS | E56: 0 | F56: =C56*E56 -> 0 | H56: 0 | I56: =G56*H56 -> 0 | K56: =F56+I56+J56 -> 0
A57: 22 42 26 | B57: Commercial Disposers | D57: LS | E57: 0 | F57: =C57*E57 -> 0 | H57: 0 | I57: =G57*H57 -> 0 | K57: =F57+I57+J57 -> 0
A58: 22 42 29 | B58: Shampoo Bowls | D58: LS | E58: 0 | F58: =C58*E58 -> 0 | H58: 0 | I58: =G58*H58 -> 0 | K58: =F58+I58+J58 -> 0
A59: 22 42 33 | B59: Wash Fountains | D59: LS | E59: 0 | F59: =C59*E59 -> 0 | H59: 0 | I59: =G59*H59 -> 0 | K59: =F59+I59+J59 -> 0
A60: 22 42 36 | B60: Commercial Laundry Trays | D60: LS | E60: 0 | F60: =C60*E60 -> 0 | H60: 0 | I60: =G60*H60 -> 0 | K60: =F60+I60+J60 -> 0
... A62: 22 42 43 | B62: Flushometers | D62: LS | E62: 0 | F62: =C62*E62 -> 0 | H62: 0 | I62: =G62*H62 -> 0 | K62: =F62+I62+J62 -> 0
D63: LS | E63: 0 | F63: =C63*E63 -> 0 | H63: 0 | I63: =G63*H63 -> 0 | K63: =F63+I63+J63 -> 0
D64: LS | E64: 0 | F64: =C64*E64 -> 0 | H64: 0 | I64: =G64*H64 -> 0 | K64: =F64+I64+J64 -> 0
D65: LS | E65: 0 | F65: =C65*E65 -> 0 | H65: 0 | I65: =G65*H65 -> 0 | K65: =F65+I65+J65 -> 0
J67: Sub Total | K67: =SUM(K49:K66) -> 0
A68: CODE | B68: DESCRIPTION | C68: Materials & Equipment | G68: Labor
A69: 22 45 00 | B69: Emergency Plumbing Fixtures | C69: Qty | D69: Unit | E69: U. Price | F69: Sub Total | G69: MHrs | H69: U. Price | I69: Sub Total | J69: Quote | K69: Total
A70: 22 45 13 | B70: Emergency Showers | D70: LS | E70: 0 | F70: =C70*E70 -> 0 | H70: 0 | I70: =G70*H70 -> 0 | K70: =F70+I70+J70 -> 0
A71: 22 45 16 | B71: Eyewash Station | D71: LS | E71: 0 | F71: =C71*E71 -> 0 | H71: 0 | I71: =G71*H71 -> 0 | K71: =F71+I71+J71 -> 0
D72: LS | E72: 0 | F72: =C72*E72 -> 0 | H72: 0 | I72: =G72*H72 -> 0 | K72: =F72+I72+J72 -> 0
J74: Sub Total | K74: =SUM(K70:K73) -> 0
A75: CODE | B75: DESCRIPTION | C75: Materials & Equipment | G75: Labor
A76: 22 47 00 | B76: Drinking Fountains and Water Coolers | C76: Qty | D76: Unit | E76: U. Price | F76: Sub Total | G76: MHrs | H76: U. Price | I76: Sub Total | J76: Quote | K76: Total
D77: LS | E77: 0 | F77: =C77*E77 -> 0 | H77: 0 | I77: =G77*H77 -> 0 | K77: =F77+I77+J77 -> 0
D78: LS | E78: 0 | F78: =C78*E78 -> 0 | H78: 0 | I78: =G78*H78 -> 0 | K78: =F78+I78+J78 -> 0
D79: LS | E79: 0 | F79: =C79*E79 -> 0 | H79: 0 | I79: =G79*H79 -> 0 | K79: =F79+I79+J79 -> 0
D80: LS | E80: 0 | F80: =C80*E80 -> 0 | H80: 0 | I80: =G80*H80 -> 0 | K80: =F80+I80+J80 -> 0
D81: LS | E81: 0 | F81: =C81*E81 -> 0 | H81: 0 | I81: =G81*H81 -> 0 | K81: =F81+I81+J81 -> 0
J83: Sub Total | K83: =SUM(K77:K82) -> 0
A84: CODE | B84: DESCRIPTION | C84: Materials & Equipment | G84: Labor
C85: Qty | D85: Unit | E85: U. Price | F85: Sub Total | G85: MHrs | H85: U. Price | I85: Sub Total | J85: Quote | K85: Total
D86: LS | E86: 0 | F86: =C86*E86 -> 0 | H86: 0 | I86: =G86*H86 -> 0 | K86: =F86+I86+J86 -> 0
D87: LS | E87: 0 | F87: =C87*E87 -> 0 | H87: 0 | I87: =G87*H87 -> 0 | K87: =F87+I87+J87 -> 0
D88: LS | E88: 0 | F88: =C88*E88 -> 0 | H88: 0 | I88: =G88*H88 -> 0 | K88: =F88+I88+J88 -> 0
D89: LS | E89: 0 | F89: =C89*E89 -> 0 | H89: 0 | I89: =G89*H89 -> 0 | K89: =F89+I89+J89 -> 0
J91: Sub Total | K91: =SUM(K86:K90) -> 0
F92: Material Total | G92: Total Hours | I92: Labor Total | J92: Contractor Total | K92: TOTAL
A93: $ / Sq.Ft | B93: TOTAL DIVISION 22
A94: =K94/E6 -> 74.298798 | F94: =SUM(F77:F82,F70:F73,F49:F66,F38:F45,F27:F34,F11:F23) -> 0 | G94: =SUM(G77:G82,G70:G73,G49:G66,G38:G45,G27:G34,G11:G23) -> 0 | I94: =SUM(I77:I82,I70:I73,I49:I66,I38:I45,I27:I34,I11:I23) -> 0 | J94: =SUM(J77:J82,J70:J73,J49:J66,J38:J45,J27:J34,J11:J23) -> 129800 | K94: =K91+K83+K74+K67+K46+K35+K24 -> 129800

Sheet 23
C1: ='Estimate Summary'!C1:H1 -> 0
G5: HVAC | J5: Schedule
D6: ='Estimate Summary'!C11 -> Area: | E6: ='Estimate Summary'!D11 -> 1747 | F6: ='Estimate Summary'!E11 -> Sq. Ft. | J6: ='1'!J6 -> 13 | K6: Weeks
A9: CODE | B9: DESCRIPTION | C9: Materials & Equipment | G9: Labor | L9: Sub Contractor | M9: Quote Total | N9: Additional Quote Info
A10: 23 07 00 | B10: HVAC Insulation | C10: Qty | D10: Unit | E10: U. Price | F10: Sub Total | G10: MHrs | H10: U. Price | I10: Sub Total | J10: Quote | K10: Total
B11: HVAC Installation | C11: =E6 -> 1747 | D11: SF | E11: 12 | F11: 0 | H11: 0 | I11: =G11*H11 -> 0 | J11: =M14 -> 36130 | K11: =F11+I11+J11 -> 36130 | L11: BSM | M11: 55115
D12: LS | E12: 0 | F12: =C12*E12 -> 0 | H12: 0 | I12: =G12*H12 -> 0 | J12: =M15 -> 900 | K12: =F12+I12+J12 -> 900 | L12: ConAir | M12: 38800
D13: LS | E13: 0 | F13: =C13*E13 -> 0 | H13: 0 | I13: =G13*H13 -> 0 | K13: =F13+I13+J13 -> 0 | L13: ECR | M13: 49225
D14: LS | E14: 0 | F14: =C14*E14 -> 0 | H14: 0 | I14: =G14*H14 -> 0 | K14: =F14+I14+J14 -> 0 | L14: Sica | M14: 36130
D15: LS | E15: 0 | F15: =C15*E15 -> 0 | H15: 0 | I15: =G15*H15 -> 0 | K15: =F15+I15+J15 -> 0 | L15: Sica | M15: 900 | N15: Duct leakage Test
D16: LS | E16: 0 | F16: =C16*E16 -> 0 | H16: 0 | I16: =G16*H16 -> 0 | K16: =F16+I16+J16 -> 0
J18: Sub Total | K18: =SUM(K11:K17) -> 37030
A19: CODE | B19: DESCRIPTION | C19: Materials & Equipment | G19: Labor
A20: 23 08 00 | B20: Commissioning of HVAC | C20: Qty | D20: Unit | E20: U. Price | F20: Sub Total | G20: MHrs | H20: U. Price | I20: Sub Total | J20: Quote | K20: Total
D21: LS | E21: 0 | F21: =C21*E21 -> 0 | H21: 0 | I21: =G21*H21 -> 0 | K21: =F21+I21+J21 -> 0
D22: LS | E22: 0 | F22: =C22*E22 -> 0 | H22: 0 | I22: =G22*H22 -> 0 | K22: =F22+I22+J22 -> 0
D23: LS | E23: 0 | F23: =C23*E23 -> 0 | H23: 0 | I23: =G23*H23 -> 0 | K23: =F23+I23+J23 -> 0
J25: Sub Total | K25: =SUM(K21:K24) -> 0
A26: CODE | B26: DESCRIPTION | C26: Materials & Equipment | G26: Labor
A27: 23 09 00 | B27: Instrumentation and Control for HVAC | C27: Qty | D27: Unit | E27: U. Price | F27: Sub Total | G27: MHrs | H27: U. Price | I27: Sub Total | J27: Quote | K27: Total
D28: LS | E28: 0 | F28: =C28*E28 -> 0 | H28: 0 | I28: =G28*H28 -> 0 | K28: =F28+I28+J28 -> 0
D29: LS | E29: 0 | F29: =C29*E29 -> 0 | H29: 0 | I29: =G29*H29 -> 0 | K29: =F29+I29+J29 -> 0
J31: Sub Total | K31: =SUM(K28:K30) -> 0
A32: CODE | B32: DESCRIPTION | C32: Materials & Equipment | G32: Labor
A33: 23 11 00 | B33: Facility Fuel piping | C33: Qty | D33: Unit | E33: U. Price | F33: Sub Total | G33: MHrs | H33: U. Price | I33: Sub Total | J33: Quote | K33: Total
A34: 23 11 23 | B34: Facility Natural Gas Piping | D34: LS | E34: 0 | F34: =C34*E34 -> 0 | H34: 0 | I34: =G34*H34 -> 0 | K34: =F34+I34+J34 -> 0
D35: LS | E35: 0 | F35: =C35*E35 -> 0 | H35: 0 | I35: =G35*H35 -> 0 | K35: =F35+I35+J35 -> 0
D36: LS | E36: 0 | F36: =C36*E36 -> 0 | H36: 0 | I36: =G36*H36 -> 0 | K36: =F36+I36+J36 -> 0
J38: Sub Total | K38: =SUM(K34:K37) -> 0
A39: CODE | B39: DESCRIPTION | C39: Materials & Equipment | G39: Labor
A40: 23 13 00 | B40: Facility Fuel Storage | C40: Qty | D40: Unit | E40: U. Price | F40: Sub Total | G40: MHrs | H40: U. Price | I40: Sub Total | J40: Quote | K40: Total
D41: LS | E41: 0 | F41: =C41*E41 -> 0 | H41: 0 | I41: =G41*H41 -> 0 | K41: =F41+I41+J41 -> 0
D42: LS | E42: 0 | F42: =C42*E42 -> 0 | H42: 0 | I42: =G42*H42 -> 0 | K42: =F42+I42+J42 -> 0
D43: LS | E43: 0 | F43: =C43*E43 -> 0 | H43: 0 | I43: =G43*H43 -> 0 | K43: =F43+I43+J43 -> 0
D44: LS | E44: 0 | F44: =C44*E44 -> 0 | H44: 0 | I44: =G44*H44 -> 0 | K44: =F44+I44+J44 -> 0
J46: Sub Total | K46: =SUM(K41:K45) -> 0
A47: CODE | B47: DESCRIPTION | C47: Materials & Equipment | G47: Labor
A48: 23 20 00 | B48: HVAC Piping and Pumps | C48: Qty | D48: Unit | E48: U. Price | F48: Sub Total | G48: MHrs | H48: U. Price | I48: Sub Total | J48: Quote | K48: Total
D49: LS | E49: 0 | F49: =C49*E49 -> 0 | H49: 0 | I49: =G49*H49 -> 0 | K49: =F49+I49+J49 -> 0
D50: LS | E50: 0 | F50: =C50*E50 -> 0 | H50: 0 | I50: =G50*H50 -> 0 | K50: =F50+I50+J50 -> 0
D51: LS | E51: 0 | F51: =C51*E51 -> 0 | H51: 0 | I51: =G51*H51 -> 0 | K51: =F51+I51+J51 -> 0
J53: Sub Total | K53: =SUM(K49:K52) -> 0
A54: CODE | B54: DESCRIPTION | C54: Materials & Equipment | G54: Labor
A55: 23 23 00 | B55: Refrigerant Piping | C55: Qty | D55: Unit | E55: U. Price | F55: Sub Total | G55: MHrs | H55: U. Price | I55: Sub Total | J55: Quote | K55: Total
D56: LS | E56: 0 | F56: =C56*E56 -> 0 | H56: 0 | I56: =G56*H56 -> 0 | K56: =F56+I56+J56 -> 0
J58: Sub Total | K58: =SUM(K56:K57) -> 0
A59: CODE | B59: DESCRIPTION | C59: Materials & Equipment | G59: Labor
A60: 23 30 00 | B60: HVAC Air Distribution | C60: Qty | D60: Unit | E60: U. Price | F60: Sub Total | G60: MHrs | H60: U. Price | I60: Sub Total | J60: Quote | K60: Total
A61: 23 31 00 | B61: HVAC Ducts and Casings | D61: LS | E61: 0 | F61: =C61*E61 -> 0 | H61: 0 | I61: =G61*H61 -> 0 | K61: =F61+I61+J61 -> 0
A62: 23 31 12 | B62: Metal Ducts | D62: LS | E62: 0 | F62: =C62*E62 -> 0 | H62: 0 | I62: =G62*H62 -> 0 | K62: =F62+I62+J62 -> 0
A63: 23 31 12.13 | B63: Rectangular Metal Ducts | D63: LS | E63: 0 | F63: =C63*E63 -> 0 | H63: 0 | I63: =G63*H63 -> 0 | K63: =F63+I63+J63 -> 0
A64: 23 31 12.16 | B64: Round and Flat-Oval Spiral Ducts | D64: LS | E64: 0 | F64: =C64*E64 -> 0 | H64: 0 | I64: =G64*H64 -> 0 | K64: =F64+I64+J64 -> 0
A65: 23 33 00 | B65: Air Duct Accessories | D65: LS | E65: 0 | F65: =C65*E65 -> 0 | H65: 0 | I65: =G65*H65 -> 0 | K65: =F65+I65+J65 -> 0
A66: 23 33 46 | B66: Flexible Ducts | D66: LS | E66: 0 | F66: =C66*E66 -> 0 | H66: 0 | I66: =G66*H66 -> 0 | K66: =F66+I66+J66 -> 0
A67: 23 34 00 | B67: HVAC Fans | D67: LS | E67: 0 | F67: =C67*E67 -> 0 | H67: 0 | I67: =G67*H67 -> 0 | K67: =F67+I67+J67 -> 0
A68: 23 38 00 | B68: Ventilation Hoods | D68: LS | E68: 0 | F68: =C68*E68 -> 0 | H68: 0 | I68: =G68*H68 -> 0 | K68: =F68+I68+J68 -> 0
D69: LS | E69: 0 | F69: =C69*E69 -> 0 | H69: 0 | I69: =G69*H69 -> 0 | K69: =F69+I69+J69 -> 0
D70: LS | E70: 0 | F70: =C70*E70 -> 0 | H70: 0 | I70: =G70*H70 -> 0 | K70: =F70+I70+J70 -> 0
D71: LS | E71: 0 | F71: =C71*E71 -> 0 | H71: 0 | I71: =G71*H71 -> 0 | K71: =F71+I71+J71 -> 0
J73: Sub Total | K73: =SUM(K61:K72) -> 0
A74: CODE | B74: DESCRIPTION | C74: Materials & Equipment | G74: Labor
A75: 23 70 00 | B75: Central HVAC Equipment | C75: Qty | D75: Unit | E75: U. Price | F75: Sub Total | G75: MHrs | H75: U. Price | I75: Sub Total | J75: Quote | K75: Total
A76: 23 74 00 | B76: Packaged Outdoor HVAC Equipment | D76: LS | E76: 0 | F76: =C76*E76 -> 0 | H76: 0 | I76: =G76*H76 -> 0 | K76: =F76+I76+J76 -> 0
D77: LS | E77: 0 | F77: =C77*E77 -> 0 | H77: 0 | I77: =G77*H77 -> 0 | K77: =F77+I77+J77 -> 0
J79: Sub Total | K79: =SUM(K76:K78) -> 0
A80: CODE | B80: DESCRIPTION | C80: Materials & Equipment | G80: Labor
A81: 23 83 00 | B81: Radiant Heating Units | C81: Qty | D81: Unit | E81: U. Price | F81: Sub Total | G81: MHrs | H81: U. Price | I81: Sub Total | J81: Quote | K81: Total
D82: LS | E82: 0 | F82: =C82*E82 -> 0 | H82: 0 | I82: =G82*H82 -> 0 | K82: =F82+I82+J82 -> 0
D83: LS | E83: 0 | F83: =C83*E83 -> 0 | H83: 0 | I83: =G83*H83 -> 0 | K83: =F83+I83+J83 -> 0
J85: Sub Total | K85: =SUM(K82:K84) -> 0
A86: CODE | B86: DESCRIPTION | C86: Materials & Equipment | G86: Labor
A87: 23 84 00 | B87: Humidity Control Equipment | C87: Qty | D87: Unit | E87: U. Price | F87: Sub Total | G87: MHrs | H87: U. Price | I87: Sub Total | J87: Quote | K87: Total
D88: LS | E88: 0 | F88: =C88*E88 -> 0 | H88: 0 | I88: =G88*H88 -> 0 | K88: =F88+I88+J88 -> 0
D89: LS | E89: 0 | F89: =C89*E89 -> 0 | H89: 0 | I89: =G89*H89 -> 0 | K89: =F89+I89+J89 -> 0
J91: Sub Total | K91: =SUM(K88:K90) -> 0
A92: CODE | B92: DESCRIPTION | C92: Materials & Equipment | G92: Labor
C93: Qty | D93: Unit | E93: U. Price | F93: Sub Total | G93: MHrs | H93: U. Price | I93: Sub Total | J93: Quote | K93: Total
D94: LS | E94: 0 | F94: =C94*E94 -> 0 | H94: 0 | I94: =G94*H94 -> 0 | K94: =F94+I94+J94 -> 0
D95: LS | E95: 0 | F95: =C95*E95 -> 0 | H95: 0 | I95: =G95*H95 -> 0 | K95: =F95+I95+J95 -> 0
D96: LS | E96: 0 | F96: =C96*E96 -> 0 | H96: 0 | I96: =G96*H96 -> 0 | K96: =F96+I96+J96 -> 0
D97: LS | E97: 0 | F97: =C97*E97 -> 0 | H97: 0 | I97: =G97*H97 -> 0 | K97: =F97+I97+J97 -> 0
J99: Sub Total | K99: =SUM(K94:K98) -> 0
F100: Material Total | G100: Total Hours | I100: Labor Total | J100: Contractor Total | K100: TOTAL
A101: $ / Sq.Ft | B101: TOTAL DIVISION 23
A102: =K102/E6 -> 21.196337 | F102: =SUM(F94:F98,F88:F90,F82:F84,F76:F78,F61:F72,F56:F57,F49:F52,F41:F45,F34:F37,F28:F30,F21:F24,F11:F17) -> 0 | G102: =SUM(G94:G98,G88:G90,G82:G84,G76:G78,G61:G72,G56:G57,G49:G52,G41:G45,G34:G37,G28:G30,G21:G24,G11:G17) -> 0 | I102: =SUM(I94:I98,I88:I90,I82:I84,I76:I78,I61:I72,I56:I57,I49:I52,I41:I45,I34:I37,I28:I30,I21:I24,I11:I17) -> 0 | J102: =SUM(J94:J98,J88:J90,J82:J84,J76:J78,J61:J72,J56:J57,J49:J52,J41:J45,J34:J37,J28:J30,J21:J24,J11:J17) -> 37030 | K102: =K99+K91+K85+K79+K73+K58+K53+K46+K38+K31+K25+K18 -> 37030

Sheet 25
C1: ='Estimate Summary'!C1:H1 -> 0
G5: Controls | J5: Schedule
D6: ='Estimate Summary'!C11 -> Area: | E6: ='Estimate Summary'!D11 -> 1747 | F6: ='Estimate Summary'!E11 -> Sq. Ft. | J6: ='1'!J6 -> 13 | K6: Weeks
A9: CODE | B9: DESCRIPTION | C9: Materials & Equipment | G9: Labor | L9: Sub Contractor | M9: Quote Total | N9: Additional Quote Info
A10: 25 00 00 | B10: Integrated Automation | C10: Qty | D10: Unit | E10: U. Price | F10: Sub Total | G10: MHrs | H10: U. Price | I10: Sub Total | J10: Quote | K10: Total
D11: LS | E11: 0 | F11: =C11*E11 -> 0 | H11: 0 | I11: =G11*H11 -> 0 | K11: =F11+I11+J11 -> 0
D12: LS | E12: 0 | F12: =C12*E12 -> 0 | H12: 0 | I12: =G12*H12 -> 0 | K12: =F12+I12+J12 -> 0
D13: LS | E13: 0 | F13: =C13*E13 -> 0 | H13: 0 | I13: =G13*H13 -> 0 | K13: =F13+I13+J13 -> 0
D14: LS | E14: 0 | F14: =C14*E14 -> 0 | H14: 0 | I14: =G14*H14 -> 0 | K14: =F14+I14+J14 -> 0
D15: LS | E15: 0 | F15: =C15*E15 -> 0 | H15: 0 | I15: =G15*H15 -> 0 | K15: =F15+I15+J15 -> 0
D16: LS | E16: 0 | F16: =C16*E16 -> 0 | H16: 0 | I16: =G16*H16 -> 0 | K16: =F16+I16+J16 -> 0
D17: LS | E17: 0 | F17: =C17*E17 -> 0 | H17: 0 | I17: =G17*H17 -> 0 | K17: =F17+I17+J17 -> 0
D18: LS | E18: 0 | F18: =C18*E18 -> 0 | H18: 0 | I18: =G18*H18 -> 0 | K18: =F18+I18+J18 -> 0
D19: LS | E19: 0 | F19: =C19*E19 -> 0 | H19: 0 | I19: =G19*H19 -> 0 | K19: =F19+I19+J19 -> 0
D20: LS | E20: 0 | F20: =C20*E20 -> 0 | H20: 0 | I20: =G20*H20 -> 0 | K20: =F20+I20+J20 -> 0
D21: LS | E21: 0 | F21: =C21*E21 -> 0 | H21: 0 | I21: =G21*H21 -> 0 | K21: =F21+I21+J21 -> 0
D22: LS | E22: 0 | F22: =C22*E22 -> 0 | H22: 0 | I22: =G22*H22 -> 0 | K22: =F22+I22+J22 -> 0
J24: Sub Total | K24: =SUM(K11:K23) -> 0
A25: CODE | B25: DESCRIPTION | C25: Materials & Equipment | G25: Labor
C26: Qty | D26: Unit | E26: U. Price | F26: Sub Total | G26: MHrs | H26: U. Price | I26: Sub Total | J26: Quote | K26: Total
D27: LS | E27: 0 | F27: =C27*E27 -> 0 | H27: 0 | I27: =G27*H27 -> 0 | K27: =F27+I27+J27 -> 0
D28: LS | E28: 0 | F28: =C28*E28 -> 0 | H28: 0 | I28: =G28*H28 -> 0 | K28: =F28+I28+J28 -> 0
D29: LS | E29: 0 | F29: =C29*E29 -> 0 | H29: 0 | I29: =G29*H29 -> 0 | K29: =F29+I29+J29 -> 0
D30: LS | E30: 0 | F30: =C30*E30 -> 0 | H30: 0 | I30: =G30*H30 -> 0 | K30: =F30+I30+J30 -> 0
D31: LS | E31: 0 | F31: =C31*E31 -> 0 | H31: 0 | I31: =G31*H31 -> 0 | K31: =F31+I31+J31 -> 0
D32: LS | E32: 0 | F32: =C32*E32 -> 0 | H32: 0 | I32: =G32*H32 -> 0 | K32: =F32+I32+J32 -> 0
D33: LS | E33: 0 | F33: =C33*E33 -> 0 | H33: 0 | I33: =G33*H33 -> 0 | K33: =F33+I33+J33 -> 0
J35: Sub Total | K35: =SUM(K27:K34) -> 0
A36: CODE | B36: DESCRIPTION | C36: Materials & Equipment | G36: Labor
C37: Qty | D37: Unit | E37: U. Price | F37: Sub Total | G37: MHrs | H37: U. Price | I37: Sub Total | J37: Quote | K37: Total
D38: LS | E38: 0 | F38: =C38*E38 -> 0 | H38: 0 | I38: =G38*H38 -> 0 | K38: =F38+I38+J38 -> 0
D39: LS | E39: 0 | F39: =C39*E39 -> 0 | H39: 0 | I39: =G39*H39 -> 0 | K39: =F39+I39+J39 -> 0
D40: LS | E40: 0 | F40: =C40*E40 -> 0 | H40: 0 | I40: =G40*H40 -> 0 | K40: =F40+I40+J40 -> 0
J43: Sub Total | K43: =SUM(K38:K42) -> 0
A44: CODE | B44: DESCRIPTION | C44: Materials & Equipment | G44: Labor
C45: Qty | D45: Unit | E45: U. Price | F45: Sub Total | G45: MHrs | H45: U. Price | I45: Sub Total | J45: Quote | K45: Total
D46: LS | E46: 0 | F46: =C46*E46 -> 0 | H46: 0 | I46: =G46*H46 -> 0 | K46: =F46+I46+J46 -> 0
D47: LS | E47: 0 | F47: =C47*E47 -> 0 | H47: 0 | I47: =G47*H47 -> 0 | K47: =F47+I47+J47 -> 0
D48: LS | E48: 0 | F48: =C48*E48 -> 0 | H48: 0 | I48: =G48*H48 -> 0 | K48: =F48+I48+J48 -> 0
D49: LS | E49: 0 | F49: =C49*E49 -> 0 | H49: 0 | I49: =G49*H49 -> 0 | K49: =F49+I49+J49 -> 0
J51: Sub Total | K51: =SUM(K46:K50) -> 0
F52: Material Total | G52: Total Hours | I52: Labor Total | J52: Contractor Total | K52: TOTAL
A53: $ / Sq.Ft | B53: TOTAL DIVISION 25
A54: =K54/E6 -> 0 | F54: =SUM(F46:F50,F38:F42,F27:F34,F11:F23) -> 0 | G54: =SUM(G46:G50,G38:G42,G27:G34,G11:G23) -> 0 | I54: =SUM(I46:I50,I38:I42,I27:I34,I11:I23) -> 0 | J54: =SUM(J46:J50,J38:J42,J27:J34,J11:J23) -> 0 | K54: =K51+K43+K35+K24 -> 0

Sheet 26
C1: ='Estimate Summary'!C1:H1 -> 0
G5: Electrical | J5: Schedule
D6: ='Estimate Summary'!C11 -> Area: | E6: ='Estimate Summary'!D11 -> 1747 | F6: ='Estimate Summary'!E11 -> Sq. Ft. | J6: ='1'!J6 -> 13 | K6: Weeks
L8: sub | M8: qty | N8: units | O8: unit $ | P8: ext
A11: CODE | B11: DESCRIPTION | C11: Materials & Equipment | G11: Labor | L11: Sub Contractor | M11: Quote Total | N11: Additional Quote Info
A12: 26 09 00 | B12: Instrumentation and Controls for Electrical Systems | C12: Qty | D12: Unit | E12: U. Price | F12: Sub Total | G12: MHrs | H12: U. Price | I12: Sub Total | J12: Quote | K12: Total
A13: 26 09 13 | B13: Electrical distribution and lighting | C13: =E6 -> 1747 | D13: SF | E13: =27.63*1.1 -> 30.393 | F13: 0 | H13: 0 | I13: =G13*H13 -> 0 | J13: =M16 -> 80800 | K13: =F13+I13+J13 -> 80800 | L13: AL's Electric | M13: 209700
D14: LS | E14: 0 | F14: =C14*E14 -> 0 | H14: 0 | I14: =G14*H14 -> 0 | K14: =F14+I14+J14 -> 0 | L14: Amplify
D15: LS | E15: 0 | F15: =C15*E15 -> 0 | H15: 0 | I15: =G15*H15 -> 0 | K15: =F15+I15+J15 -> 0 | L15: Melco | M15: 89050 | N15: Excludes backbone data cabling, typically done by Rogers or Bell.
D16: LS | E16: 0 | F16: =C16*E16 -> 0 | H16: 0 | I16: =G16*H16 -> 0 | K16: =F16+I16+J16 -> 0 | L16: Melco | M16: 80800 | N16: Cost saving option. Downsized the fuse from 200 to 125A.
D17: LS | E17: 0 | F17: =C17*E17 -> 0 | H17: 0 | I17: =G17*H17 -> 0 | K17: =F17+I17+J17 -> 0 | L17: Power
D18: LS | E18: 0 | F18: =C18*E18 -> 0 | H18: 0 | I18: =G18*H18 -> 0 | K18: =F18+I18+J18 -> 0 | L18: Forward Electric
D19: LS | E19: 0 | F19: =C19*E19 -> 0 | H19: 0 | I19: =G19*H19 -> 0 | K19: =F19+I19+J19 -> 0 | L19: Lakeview | M19: 113795.85 | N19: Excludes backbone data cabling, security
D20: LS | E20: 0 | F20: =C20*E20 -> 0 | H20: 0 | I20: =G20*H20 -> 0 | K20: =F20+I20+J20 -> 0
D21: LS | E21: 0 | F21: =C21*E21 -> 0 | H21: 0 | I21: =G21*H21 -> 0 | K21: =F21+I21+J21 -> 0
D22: LS | E22: 0 | F22: =C22*E22 -> 0 | H22: 0 | I22: =G22*H22 -> 0 | K22: =F22+I22+J22 -> 0
D23: LS | E23: 0 | F23: =C23*E23 -> 0 | H23: 0 | I23: =G23*H23 -> 0 | K23: =F23+I23+J23 -> 0
D24: LS | E24: 0 | F24: =C24*E24 -> 0 | H24: 0 | I24: =G24*H24 -> 0 | K24: =F24+I24+J24 -> 0
L25: Sackville smiles | M25: 64.81
J26: Sub Total | K26: =SUM(K13:K25) -> 80800 | L26: Mountain View Dental | M26: 27.63 | N26: per sf
A27: CODE | B27: DESCRIPTION | C27: Materials & Equipment | G27: Labor
A28: 26 10 00 | B28: Medium-Voltage Electrical Distribution | C28: Qty | D28: Unit | E28: U. Price | F28: Sub Total | G28: MHrs | H28: U. Price | I28: Sub Total | J28: Quote | K28: Total
A29: 26 11 00 | B29: Substations | D29: LS | E29: 0 | F29: =C29*E29 -> 0 | H29: 0 | I29: =G29*H29 -> 0 | K29: =F29+I29+J29 -> 0
A30: 26 12 00 | B30: Medium Voltage Transformer | D30: LS | E30: 0 | F30: =C30*E30 -> 0 | H30: 0 | I30: =G30*H30 -> 0 | K30: =F30+I30+J30 -> 0
A31: 26 13 00 | B31: Medium Voltage Switchgear | D31: LS | E31: 0 | F31: =C31*E31 -> 0 | H31: 0 | I31: =G31*H31 -> 0 | K31: =F31+I31+J31 -> 0
A32: 26 16 00 | B32: Medium-Voltage Metering | D32: LS | E32: 0 | F32: =C32*E32 -> 0 | H32: 0 | I32: =G32*H32 -> 0 | K32: =F32+I32+J32 -> 0
A33: 26 18 00 | B33: Medium-Voltage Circuit Protection Devices | D33: LS | E33: 0 | F33: =C33*E33 -> 0 | H33: 0 | I33: =G33*H33 -> 0 | K33: =F33+I33+J33 -> 0
D34: LS | E34: 0 | F34: =C34*E34 -> 0 | H34: 0 | I34: =G34*H34 -> 0 | K34: =F34+I34+J34 -> 0
D35: LS | E35: 0 | F35: =C35*E35 -> 0 | H35: 0 | I35: =G35*H35 -> 0 | K35: =F35+I35+J35 -> 0
J37: Sub Total | K37: =SUM(K29:K36) -> 0
A38: CODE | B38: DESCRIPTION | C38: Materials & Equipment | G38: Labor
A39: 26 50 00 | B39: Lighting | C39: Qty | D39: Unit | E39: U. Price | F39: Sub Total | G39: MHrs | H39: U. Price | I39: Sub Total | J39: Quote | K39: Total
A40: 26 51 00 | B40: Interior Lighting | D40: LS | E40: 0 | F40: =C40*E40 -> 0 | H40: 0 | I40: =G40*H40 -> 0 | K40: =F40+I40+J40 -> 0
A41: 26 52 00 | B41: Safety Lighting | D41: LS | E41: 0 | F41: =C41*E41 -> 0 | H41: 0 | I41: =G41*H41 -> 0 | K41: =F41+I41+J41 -> 0
A42: 26 56 00 | B42: Exterior Lighting | D42: LS | E42: 0 | F42: =C42*E42 -> 0 | H42: 0 | I42: =G42*H42 -> 0 | K42: =F42+I42+J42 -> 0
J45: Sub Total | K45: =SUM(K40:K44) -> 0
A46: CODE | B46: DESCRIPTION | C46: Materials & Equipment | G46: Labor
C47: Qty | D47: Unit | E47: U. Price | F47: Sub Total | G47: MHrs | H47: U. Price | I47: Sub Total | J47: Quote | K47: Total
D48: LS | E48: 0 | F48: =C48*E48 -> 0 | H48: 0 | I48: =G48*H48 -> 0 | K48: =F48+I48+J48 -> 0
D49: LS | E49: 0 | F49: =C49*E49 -> 0 | H49: 0 | I49: =G49*H49 -> 0 | K49: =F49+I49+J49 -> 0
D50: LS | E50: 0 | F50: =C50*E50 -> 0 | H50: 0 | I50: =G50*H50 -> 0 | K50: =F50+I50+J50 -> 0
D51: LS | E51: 0 | F51: =C51*E51 -> 0 | H51: 0 | I51: =G51*H51 -> 0 | K51: =F51+I51+J51 -> 0
D52: LS | E52: 0 | F52: =C52*E52 -> 0 | H52: 0 | I52: =G52*H52 -> 0 | K52: =F52+I52+J52 -> 0
J54: Sub Total | K54: =SUM(K48:K53) -> 0
F55: Material Total | G55: Total Hours | I55: Labor Total | J55: Contractor Total | K55: TOTAL
A56: $ / Sq.Ft | B56: TOTAL DIVISION 26
A57: =K57/E6 -> 46.250716 | F57: =SUM(F48:F53,F40:F44,F29:F36,F13:F25) -> 0 | G57: =SUM(G48:G53,G40:G44,G29:G36,G13:G25) -> 0 | I57: =SUM(I48:I53,I40:I44,I29:I36,I13:I25) -> 0 | J57: =SUM(J48:J53,J40:J44,J29:J36,J13:J25) -> 80800 | K57: =SUM(K54,K45,K37,K26) -> 80800

Sheet 27
C1: ='Estimate Summary'!C1:H1 -> 0
G5: Communications | J5: Schedule
D6: ='Estimate Summary'!C11 -> Area: | E6: ='Estimate Summary'!D11 -> 1747 | F6: ='Estimate Summary'!E11 -> Sq. Ft. | J6: ='1'!J6 -> 13 | K6: Weeks
A9: CODE | B9: DESCRIPTION | C9: Materials & Equipment | G9: Labor | L9: Sub Contractor | M9: Quote Total | N9: Additional Quote Info
A10: 27 10 00 | B10: Structured Cabling | C10: Qty | D10: Unit | E10: U. Price | F10: Sub Total | G10: MHrs | H10: U. Price | I10: Sub Total | J10: Quote | K10: Total
B11: Structured Cabling | C11: =E6 -> 1747 | D11: SF | E11: 4.85 | F11: 0 | H11: 0 | I11: =G11*H11 -> 0 | K11: =F11+I11+J11 -> 0 | L11: Mountain View Dental | M11: 4.85
D12: LS | E12: 0 | F12: =C12*E12 -> 0 | H12: 0 | I12: =G12*H12 -> 0 | K12: =F12+I12+J12 -> 0
D13: LS | E13: 0 | F13: =C13*E13 -> 0 | H13: 0 | I13: =G13*H13 -> 0 | K13: =F13+I13+J13 -> 0
D14: LS | E14: 0 | F14: =C14*E14 -> 0 | H14: 0 | I14: =G14*H14 -> 0 | K14: =F14+I14+J14 -> 0
D15: LS | E15: 0 | F15: =C15*E15 -> 0 | H15: 0 | I15: =G15*H15 -> 0 | K15: =F15+I15+J15 -> 0
D16: LS | E16: 0 | F16: =C16*E16 -> 0 | H16: 0 | I16: =G16*H16 -> 0 | K16: =F16+I16+J16 -> 0
D17: LS | E17: 0 | F17: =C17*E17 -> 0 | H17: 0 | I17: =G17*H17 -> 0 | K17: =F17+I17+J17 -> 0
D18: LS | E18: 0 | F18: =C18*E18 -> 0 | H18: 0 | I18: =G18*H18 -> 0 | K18: =F18+I18+J18 -> 0
D19: LS | E19: 0 | F19: =C19*E19 -> 0 | H19: 0 | I19: =G19*H19 -> 0 | K19: =F19+I19+J19 -> 0
D20: LS | E20: 0 | F20: =C20*E20 -> 0 | H20: 0 | I20: =G20*H20 -> 0 | K20: =F20+I20+J20 -> 0
D21: LS | E21: 0 | F21: =C21*E21 -> 0 | H21: 0 | I21: =G21*H21 -> 0 | K21: =F21+I21+J21 -> 0
D22: LS | E22: 0 | F22: =C22*E22 -> 0 | H22: 0 | I22: =G22*H22 -> 0 | K22: =F22+I22+J22 -> 0
J24: Sub Total | K24: =SUM(K11:K23) -> 0
A25: CODE | B25: DESCRIPTION | C25: Materials & Equipment | G25: Labor
A26: 27 20 00 | B26: Data Communications | C26: Qty | D26: Unit | E26: U. Price | F26: Sub Total | G26: MHrs | H26: U. Price | I26: Sub Total | J26: Quote | K26: Total
A27: 27 21 00 | B27: Data Communications Network Equipment | D27: LS | E27: 0 | F27: =C27*E27 -> 0 | H27: 0 | I27: =G27*H27 -> 0 | K27: =F27+I27+J27 -> 0
A28: 27 22 00 | B28: Data Communications Hardware | D28: LS | E28: 0 | F28: =C28*E28 -> 0 | H28: 0 | I28: =G28*H28 -> 0 | K28: =F28+I28+J28 -> 0
D29: LS | E29: 0 | F29: =C29*E29 -> 0 | H29: 0 | I29: =G29*H29 -> 0 | K29: =F29+I29+J29 -> 0
D30: LS | E30: 0 | F30: =C30*E30 -> 0 | H30: 0 | I30: =G30*H30 -> 0 | K30: =F30+I30+J30 -> 0
D31: LS | E31: 0 | F31: =C31*E31 -> 0 | H31: 0 | I31: =G31*H31 -> 0 | K31: =F31+I31+J31 -> 0
D32: LS | E32: 0 | F32: =C32*E32 -> 0 | H32: 0 | I32: =G32*H32 -> 0 | K32: =F32+I32+J32 -> 0
D33: LS | E33: 0 | F33: =C33*E33 -> 0 | H33: 0 | I33: =G33*H33 -> 0 | K33: =F33+I33+J33 -> 0
J35: Sub Total | K35: =SUM(K27:K34) -> 0
A36: CODE | B36: DESCRIPTION | C36: Materials & Equipment | G36: Labor
A37: 27 30 00 | B37: Voice Communications | C37: Qty | D37: Unit | E37: U. Price | F37: Sub Total | G37: MHrs | H37: U. Price | I37: Sub Total | J37: Quote | K37: Total
D38: LS | E38: 0 | F38: =C38*E38 -> 0 | H38: 0 | I38: =G38*H38 -> 0 | K38: =F38+I38+J38 -> 0
D39: LS | E39: 0 | F39: =C39*E39 -> 0 | H39: 0 | I39: =G39*H39 -> 0 | K39: =F39+I39+J39 -> 0
D40: LS | E40: 0 | F40: =C40*E40 -> 0 | H40: 0 | I40: =G40*H40 -> 0 | K40: =F40+I40+J40 -> 0
J43: Sub Total | K43: =SUM(K38:K42) -> 0
A44: CODE | B44: DESCRIPTION | C44: Materials & Equipment | G44: Labor
A45: 27 40 00 | B45: Audio-Voice Communications | C45: Qty | D45: Unit | E45: U. Price | F45: Sub Total | G45: MHrs | H45: U. Price | I45: Sub Total | J45: Quote | K45: Total
D46: LS | E46: 0 | F46: =C46*E46 -> 0 | H46: 0 | I46: =G46*H46 -> 0 | K46: =F46+I46+J46 -> 0
D47: LS | E47: 0 | F47: =C47*E47 -> 0 | H47: 0 | I47: =G47*H47 -> 0 | K47: =F47+I47+J47 -> 0
D48: LS | E48: 0 | F48: =C48*E48 -> 0 | H48: 0 | I48: =G48*H48 -> 0 | K48: =F48+I48+J48 -> 0
D49: LS | E49: 0 | F49: =C49*E49 -> 0 | H49: 0 | I49: =G49*H49 -> 0 | K49: =F49+I49+J49 -> 0
D50: LS | E50: 0 | F50: =C50*E50 -> 0 | H50: 0 | I50: =G50*H50 -> 0 | K50: =F50+I50+J50 -> 0
J52: Sub Total | K52: =SUM(K46:K51) -> 0
A53: CODE | B53: DESCRIPTION | C53: Materials & Equipment | G53: Labor
A54: 27 50 00 | B54: Distributed Communications and Monitoring Systems | C54: Qty | D54: Unit | E54: U. Price | F54: Sub Total | G54: MHrs | H54: U. Price | I54: Sub Total | J54: Quote | K54: Total
D55: LS | E55: 0 | F55: =C55*E55 -> 0 | H55: 0 | I55: =G55*H55 -> 0 | K55: =F55+I55+J55 -> 0
D56: LS | E56: 0 | F56: =C56*E56 -> 0 | H56: 0 | I56: =G56*H56 -> 0 | K56: =F56+I56+J56 -> 0
D57: LS | E57: 0 | F57: =C57*E57 -> 0 | H57: 0 | I57: =G57*H57 -> 0 | K57: =F57+I57+J57 -> 0
D58: LS | E58: 0 | F58: =C58*E58 -> 0 | H58: 0 | I58: =G58*H58 -> 0 | K58: =F58+I58+J58 -> 0
D59: LS | E59: 0 | F59: =C59*E59 -> 0 | H59: 0 | I59: =G59*H59 -> 0 | K59: =F59+I59+J59 -> 0
D60: LS | E60: 0 | F60: =C60*E60 -> 0 | H60: 0 | I60: =G60*H60 -> 0 | K60: =F60+I60+J60 -> 0
D61: LS | E61: 0 | F61: =C61*E61 -> 0 | H61: 0 | I61: =G61*H61 -> 0 | K61: =F61+I61+J61 -> 0
J63: Sub Total | K63: =SUM(K55:K62) -> 0
A64: CODE | B64: DESCRIPTION | C64: Materials & Equipment | G64: Labor
C65: Qty | D65: Unit | E65: U. Price | F65: Sub Total | G65: MHrs | H65: U. Price | I65: Sub Total | J65: Quote | K65: Total
D66: LS | E66: 0 | F66: =C66*E66 -> 0 | H66: 0 | I66: =G66*H66 -> 0 | K66: =F66+I66+J66 -> 0
D67: LS | E67: 0 | F67: =C67*E67 -> 0 | H67: 0 | I67: =G67*H67 -> 0 | K67: =F67+I67+J67 -> 0
D68: LS | E68: 0 | F68: =C68*E68 -> 0 | H68: 0 | I68: =G68*H68 -> 0 | K68: =F68+I68+J68 -> 0
D69: LS | E69: 0 | F69: =C69*E69 -> 0 | H69: 0 | I69: =G69*H69 -> 0 | K69: =F69+I69+J69 -> 0
D70: LS | E70: 0 | F70: =C70*E70 -> 0 | H70: 0 | I70: =G70*H70 -> 0 | K70: =F70+I70+J70 -> 0
J72: Sub Total | K72: =SUM(K66:K71) -> 0
A73: CODE | B73: DESCRIPTION | C73: Materials & Equipment | G73: Labor
C74: Qty | D74: Unit | E74: U. Price | F74: Sub Total | G74: MHrs | H74: U. Price | I74: Sub Total | J74: Quote | K74: Total
D75: LS | E75: 0 | F75: =C75*E75 -> 0 | H75: 0 | I75: =G75*H75 -> 0 | K75: =F75+I75+J75 -> 0
D76: LS | E76: 0 | F76: =C76*E76 -> 0 | H76: 0 | I76: =G76*H76 -> 0 | K76: =F76+I76+J76 -> 0
D77: LS | E77: 0 | F77: =C77*E77 -> 0 | H77: 0 | I77: =G77*H77 -> 0 | K77: =F77+I77+J77 -> 0
J79: Sub Total | K79: =SUM(K75:K78) -> 0
A80: CODE | B80: DESCRIPTION | C80: Materials & Equipment | G80: Labor
C81: Qty | D81: Unit | E81: U. Price | F81: Sub Total | G81: MHrs | H81: U. Price | I81: Sub Total | J81: Quote | K81: Total
D82: LS | E82: 0 | F82: =C82*E82 -> 0 | H82: 0 | I82: =G82*H82 -> 0 | K82: =F82+I82+J82 -> 0
D83: LS | E83: 0 | F83: =C83*E83 -> 0 | H83: 0 | I83: =G83*H83 -> 0 | K83: =F83+I83+J83 -> 0
D84: LS | E84: 0 | F84: =C84*E84 -> 0 | H84: 0 | I84: =G84*H84 -> 0 | K84: =F84+I84+J84 -> 0
D85: LS | E85: 0 | F85: =C85*E85 -> 0 | H85: 0 | I85: =G85*H85 -> 0 | K85: =F85+I85+J85 -> 0
D86: LS | E86: 0 | F86: =C86*E86 -> 0 | H86: 0 | I86: =G86*H86 -> 0 | K86: =F86+I86+J86 -> 0
J88: Sub Total | K88: =SUM(K82:K87) -> 0
A89: CODE | B89: DESCRIPTION | C89: Materials & Equipment | G89: Labor
C90: Qty | D90: Unit | E90: U. Price | F90: Sub Total | G90: MHrs | H90: U. Price | I90: Sub Total | J90: Quote | K90: Total
D91: LS | E91: 0 | F91: =C91*E91 -> 0 | H91: 0 | I91: =G91*H91 -> 0 | K91: =F91+I91+J91 -> 0
D92: LS | E92: 0 | F92: =C92*E92 -> 0 | H92: 0 | I92: =G92*H92 -> 0 | K92: =F92+I92+J92 -> 0
D93: LS | E93: 0 | F93: =C93*E93 -> 0 | H93: 0 | I93: =G93*H93 -> 0 | K93: =F93+I93+J93 -> 0
D94: LS | E94: 0 | F94: =C94*E94 -> 0 | H94: 0 | I94: =G94*H94 -> 0 | K94: =F94+I94+J94 -> 0
J96: Sub Total | K96: =SUM(K91:K95) -> 0
F97: Material Total | G97: Total Hours | I97: Labor Total | J97: Contractor Total | K97: TOTAL
A98: $ / Sq.Ft | B98: TOTAL DIVISION 27
A99: =K99/E6 -> 0 | F99: =SUM(F91:F95,F82:F87,F75:F78,F66:F71,F55:F61,F46:F51,F38:F42,F27:F34,F11:F23) -> 0 | G99: =SUM(G91:G95,G82:G87,G75:G78,G66:G71,G55:G61,G46:G51,G38:G42,G27:G34,G11:G23) -> 0 | I99: =SUM(I91:I95,I82:I87,I75:I78,I66:I71,I55:I61,I46:I51,I38:I42,I27:I34,I11:I23) -> 0 | J99: =SUM(J91:J95,J82:J87,J75:J78,J66:J71,J55:J61,J46:J51,J38:J42,J27:J34,J11:J23) -> 0 | K99: =K96+K88+K79+K72+K63+K52+K43+K35+K24 -> 0

Sheet 28
C1: ='Estimate Summary'!C1:H1 -> 0
G5: Security | J5: Schedule
D6: ='Estimate Summary'!C11 -> Area: | E6: ='Estimate Summary'!D11 -> 1747 | F6: ='Estimate Summary'!E11 -> Sq. Ft. | J6: ='1'!J6 -> 13 | K6: Weeks
A9: CODE | B9: DESCRIPTION | C9: Materials & Equipment | G9: Labor | L9: Sub Contractor | M9: Quote Total | N9: Additional Quote Info
A10: 28 10 00 | B10: Access Control | C10: Qty | D10: Unit | E10: U. Price | F10: Sub Total | G10: MHrs | H10: U. Price | I10: Sub Total | J10: Quote | K10: Total
A11: 28 15 00 | B11: Access Control Hardware Devices | D11: LS | E11: 0 | F11: =C11*E11 -> 0 | H11: 0 | I11: =G11*H11 -> 0 | K11: =F11+I11+J11 -> 0
D12: LS | E12: 0 | F12: =C12*E12 -> 0 | H12: 0 | I12: =G12*H12 -> 0 | K12: =F12+I12+J12 -> 0
D13: LS | E13: 0 | F13: =C13*E13 -> 0 | H13: 0 | I13: =G13*H13 -> 0 | K13: =F13+I13+J13 -> 0
D14: LS | E14: 0 | F14: =C14*E14 -> 0 | H14: 0 | I14: =G14*H14 -> 0 | K14: =F14+I14+J14 -> 0
D15: LS | E15: 0 | F15: =C15*E15 -> 0 | H15: 0 | I15: =G15*H15 -> 0 | K15: =F15+I15+J15 -> 0
D16: LS | E16: 0 | F16: =C16*E16 -> 0 | H16: 0 | I16: =G16*H16 -> 0 | K16: =F16+I16+J16 -> 0
D17: LS | E17: 0 | F17: =C17*E17 -> 0 | H17: 0 | I17: =G17*H17 -> 0 | K17: =F17+I17+J17 -> 0
D18: LS | E18: 0 | F18: =C18*E18 -> 0 | H18: 0 | I18: =G18*H18 -> 0 | K18: =F18+I18+J18 -> 0
D19: LS | E19: 0 | F19: =C19*E19 -> 0 | H19: 0 | I19: =G19*H19 -> 0 | K19: =F19+I19+J19 -> 0
D20: LS | E20: 0 | F20: =C20*E20 -> 0 | H20: 0 | I20: =G20*H20 -> 0 | K20: =F20+I20+J20 -> 0
D21: LS | E21: 0 | F21: =C21*E21 -> 0 | H21: 0 | I21: =G21*H21 -> 0 | K21: =F21+I21+J21 -> 0
D22: LS | E22: 0 | F22: =C22*E22 -> 0 | H22: 0 | I22: =G22*H22 -> 0 | K22: =F22+I22+J22 -> 0
J24: Sub Total | K24: =SUM(K11:K23) -> 0
A25: CODE | B25: DESCRIPTION | C25: Materials & Equipment | G25: Labor
A26: 28 20 00 | B26: Video Surveillance | C26: Qty | D26: Unit | E26: U. Price | F26: Sub Total | G26: MHrs | H26: U. Price | I26: Sub Total | J26: Quote | K26: Total
D27: LS | E27: 0 | F27: =C27*E27 -> 0 | H27: 0 | I27: =G27*H27 -> 0 | K27: =F27+I27+J27 -> 0
D28: LS | E28: 0 | F28: =C28*E28 -> 0 | H28: 0 | I28: =G28*H28 -> 0 | K28: =F28+I28+J28 -> 0
D29: LS | E29: 0 | F29: =C29*E29 -> 0 | H29: 0 | I29: =G29*H29 -> 0 | K29: =F29+I29+J29 -> 0
D30: LS | E30: 0 | F30: =C30*E30 -> 0 | H30: 0 | I30: =G30*H30 -> 0 | K30: =F30+I30+J30 -> 0
D31: LS | E31: 0 | F31: =C31*E31 -> 0 | H31: 0 | I31: =G31*H31 -> 0 | K31: =F31+I31+J31 -> 0
D32: LS | E32: 0 | F32: =C32*E32 -> 0 | H32: 0 | I32: =G32*H32 -> 0 | K32: =F32+I32+J32 -> 0
D33: LS | E33: 0 | F33: =C33*E33 -> 0 | H33: 0 | I33: =G33*H33 -> 0 | K33: =F33+I33+J33 -> 0
J35: Sub Total | K35: =SUM(K27:K34) -> 0
A36: CODE | B36: DESCRIPTION | C36: Materials & Equipment | G36: Labor
A37: 28 30 00 | B37: Security Detection, Aarm, and Monitoring | C37: Qty | D37: Unit | E37: U. Price | F37: Sub Total | G37: MHrs | H37: U. Price | I37: Sub Total | J37: Quote | K37: Total
D38: LS | E38: 0 | F38: =C38*E38 -> 0 | H38: 0 | I38: =G38*H38 -> 0 | K38: =F38+I38+J38 -> 0
D39: LS | E39: 0 | F39: =C39*E39 -> 0 | H39: 0 | I39: =G39*H39 -> 0 | K39: =F39+I39+J39 -> 0
D40: LS | E40: 0 | F40: =C40*E40 -> 0 | H40: 0 | I40: =G40*H40 -> 0 | K40: =F40+I40+J40 -> 0
J43: Sub Total | K43: =SUM(K38:K42) -> 0
A44: CODE | B44: DESCRIPTION | C44: Materials & Equipment | G44: Labor
A45: 28 40 00 | B45: Life Safety | C45: Qty | D45: Unit | E45: U. Price | F45: Sub Total | G45: MHrs | H45: U. Price | I45: Sub Total | J45: Quote | K45: Total
A46: 28 46 00 | B46: Fire Detection and Alarm | D46: LS | E46: 0 | F46: =C46*E46 -> 0 | H46: 0 | I46: =G46*H46 -> 0 | K46: =F46+I46+J46 -> 0
D47: LS | E47: 0 | F47: =C47*E47 -> 0 | H47: 0 | I47: =G47*H47 -> 0 | K47: =F47+I47+J47 -> 0
D48: LS | E48: 0 | F48: =C48*E48 -> 0 | H48: 0 | I48: =G48*H48 -> 0 | K48: =F48+I48+J48 -> 0
D49: LS | E49: 0 | F49: =C49*E49 -> 0 | H49: 0 | I49: =G49*H49 -> 0 | K49: =F49+I49+J49 -> 0
D50: LS | E50: 0 | F50: =C50*E50 -> 0 | H50: 0 | I50: =G50*H50 -> 0 | K50: =F50+I50+J50 -> 0
J52: Sub Total | K52: =SUM(K46:K51) -> 0
F53: Material Total | G53: Total Hours | I53: Labor Total | J53: Contractor Total | K53: TOTAL
A54: $ / Sq.Ft | B54: TOTAL DIVISION 28
A55: =K55/E6 -> 0 | F55: =SUM(F46:F51,F38:F42,F27:F34,F11:F23) -> 0 | G55: =SUM(G46:G51,G38:G42,G27:G34,G11:G23) -> 0 | I55: =SUM(I46:I51,I38:I42,I27:I34,I11:I23) -> 0 | J55: =SUM(J46:J51,J38:J42,J27:J34,J11:J23) -> 0 | K55: =K52+K43+K35+K24 -> 0

Sheet 31
C1: ='Estimate Summary'!C1:H1 -> 0
G5: Earthwork | J5: Schedule
D6: ='Estimate Summary'!C11 -> Area: | E6: ='Estimate Summary'!D11 -> 1747 | F6: ='Estimate Summary'!E11 -> Sq. Ft. | J6: ='1'!J6 -> 13 | K6: Weeks
A11: CODE | B11: DESCRIPTION | C11: Materials & Equipment | G11: Labor | L11: Sub Contractor | M11: Quote Total | N11: Additional Quote Info
A12: 31 10 00 | B12: Site Clearing | C12: Qty | D12: Unit | E12: U. Price | F12: Sub Total | G12: MHrs | H12: U. Price | I12: Sub Total | J12: Quote | K12: Total
A13: 31 10 00 | B13: Site Clearing | D13: LS | E13: 0 | F13: =C13*E13 -> 0 | H13: 0 | I13: =G13*H13 -> 0 | K13: =F13+I13+J13 -> 0
A14: 31 11 00 | B14: Clearing and Grubbing | D14: LS | E14: 0 | F14: =C14*E14 -> 0 | H14: 0 | I14: =G14*H14 -> 0 | K14: =F14+I14+J14 -> 0
D15: LS | E15: 0 | F15: =C15*E15 -> 0 | H15: 0 | I15: =G15*H15 -> 0 | K15: =F15+I15+J15 -> 0
D16: LS | E16: 0 | F16: =C16*E16 -> 0 | H16: 0 | I16: =G16*H16 -> 0 | K16: =F16+I16+J16 -> 0
D17: LS | E17: 0 | F17: =C17*E17 -> 0 | H17: 0 | I17: =G17*H17 -> 0 | K17: =F17+I17+J17 -> 0
D18: LS | E18: 0 | F18: =C18*E18 -> 0 | H18: 0 | I18: =G18*H18 -> 0 | K18: =F18+I18+J18 -> 0
D19: LS | E19: 0 | F19: =C19*E19 -> 0 | H19: 0 | I19: =G19*H19 -> 0 | K19: =F19+I19+J19 -> 0
D20: LS | E20: 0 | F20: =C20*E20 -> 0 | H20: 0 | I20: =G20*H20 -> 0 | K20: =F20+I20+J20 -> 0
D21: LS | E21: 0 | F21: =C21*E21 -> 0 | H21: 0 | I21: =G21*H21 -> 0 | K21: =F21+I21+J21 -> 0
D22: LS | E22: 0 | F22: =C22*E22 -> 0 | H22: 0 | I22: =G22*H22 -> 0 | K22: =F22+I22+J22 -> 0
D23: LS | E23: 0 | F23: =C23*E23 -> 0 | H23: 0 | I23: =G23*H23 -> 0 | K23: =F23+I23+J23 -> 0
D24: LS | E24: 0 | F24: =C24*E24 -> 0 | H24: 0 | I24: =G24*H24 -> 0 | K24: =F24+I24+J24 -> 0
J26: Sub Total | K26: =SUM(K13:K25) -> 0
A27: CODE | B27: DESCRIPTION | C27: Materials & Equipment | G27: Labor
A28: 31 20 00 | B28: Earth Moving | C28: Qty | D28: Unit | E28: U. Price | F28: Sub Total | G28: MHrs | H28: U. Price | I28: Sub Total | J28: Quote | K28: Total
A29: 31 22 00 | B29: Grading | D29: LS | E29: 0 | F29: =C29*E29 -> 0 | H29: 0 | I29: =G29*H29 -> 0 | K29: =F29+I29+J29 -> 0
A30: 31 22 13 | B30: Rough Grading | D30: LS | E30: 0 | F30: =C30*E30 -> 0 | H30: 0 | I30: =G30*H30 -> 0 | K30: =F30+I30+J30 -> 0
A31: 31 22 16 | B31: Fine Grading | D31: LS | E31: 0 | F31: =C31*E31 -> 0 | H31: 0 | I31: =G31*H31 -> 0 | K31: =F31+I31+J31 -> 0
A32: 31 23 00 | B32: Excavation and Fill | D32: LS | E32: 0 | F32: =C32*E32 -> 0 | H32: 0 | I32: =G32*H32 -> 0 | K32: =F32+I32+J32 -> 0
A33: 31 23 13 | B33: Subgrade Preparation | D33: LS | E33: 0 | F33: =C33*E33 -> 0 | H33: 0 | I33: =G33*H33 -> 0 | K33: =F33+I33+J33 -> 0
A34: 31 23 16 | B34: Excavation and Fill | D34: LS | E34: 0 | F34: =C34*E34 -> 0 | H34: 0 | I34: =G34*H34 -> 0 | K34: =F34+I34+J34 -> 0
A35: 31 23 16.13 | B35: Trenching | D35: LS | E35: 0 | F35: =C35*E35 -> 0 | H35: 0 | I35: =G35*H35 -> 0 | K35: =F35+I35+J35 -> 0
A36: 31 23 16.16 | B36: Structural Excavation for Minor Structures | D36: LS | E36: 0 | F36: =C36*E36 -> 0 | H36: 0 | I36: =G36*H36 -> 0 | K36: =F36+I36+J36 -> 0
A37: 31 23 16.26 | B37: Rock Removal | D37: LS | E37: 0 | F37: =C37*E37 -> 0 | H37: 0 | I37: =G37*H37 -> 0 | K37: =F37+I37+J37 -> 0
A38: 31 23 19 | B38: Dewatering | D38: LS | E38: 0 | F38: =C38*E38 -> 0 | H38: 0 | I38: =G38*H38 -> 0 | K38: =F38+I38+J38 -> 0
A39: 31 23 23 | B39: Fill | D39: LS | E39: 0 | F39: =C39*E39 -> 0 | H39: 0 | I39: =G39*H39 -> 0 | K39: =F39+I39+J39 -> 0
A40: 31 23 23.13 | B40: Backfill | D40: LS | E40: 0 | F40: =C40*E40 -> 0 | H40: 0 | I40: =G40*H40 -> 0 | K40: =F40+I40+J40 -> 0
... A45: 31 25 00 | B45: Erosion nd Sedimentation Controls | D45: LS | E45: 0 | F45: =C45*E45 -> 0 | H45: 0 | I45: =G45*H45 -> 0 | K45: =F45+I45+J45 -> 0
D46: LS | E46: 0 | F46: =C46*E46 -> 0 | H46: 0 | I46: =G46*H46 -> 0 | K46: =F46+I46+J46 -> 0
D47: LS | E47: 0 | F47: =C47*E47 -> 0 | H47: 0 | I47: =G47*H47 -> 0 | K47: =F47+I47+J47 -> 0
J49: Sub Total | K49: =SUM(K29:K48) -> 0
A50: CODE | B50: DESCRIPTION | C50: Materials & Equipment | G50: Labor
A51: 31 37 00 | B51: Riprap | C51: Qty | D51: Unit | E51: U. Price | F51: Sub Total | G51: MHrs | H51: U. Price | I51: Sub Total | J51: Quote | K51: Total
D52: LS | E52: 0 | F52: =C52*E52 -> 0 | H52: 0 | I52: =G52*H52 -> 0 | K52: =F52+I52+J52 -> 0
D53: LS | E53: 0 | F53: =C53*E53 -> 0 | H53: 0 | I53: =G53*H53 -> 0 | K53: =F53+I53+J53 -> 0
D54: LS | E54: 0 | F54: =C54*E54 -> 0 | H54: 0 | I54: =G54*H54 -> 0 | K54: =F54+I54+J54 -> 0
J57: Sub Total | K57: =SUM(K52:K56) -> 0
A58: CODE | B58: DESCRIPTION | C58: Materials & Equipment | G58: Labor
A59: 31 70 00 | B59: Tunneling | C59: Qty | D59: Unit | E59: U. Price | F59: Sub Total | G59: MHrs | H59: U. Price | I59: Sub Total | J59: Quote | K59: Total
D60: LS | E60: 0 | F60: =C60*E60 -> 0 | H60: 0 | I60: =G60*H60 -> 0 | K60: =F60+I60+J60 -> 0
D61: LS | E61: 0 | F61: =C61*E61 -> 0 | H61: 0 | I61: =G61*H61 -> 0 | K61: =F61+I61+J61 -> 0
D62: LS | E62: 0 | F62: =C62*E62 -> 0 | H62: 0 | I62: =G62*H62 -> 0 | K62: =F62+I62+J62 -> 0
D63: LS | E63: 0 | F63: =C63*E63 -> 0 | H63: 0 | I63: =G63*H63 -> 0 | K63: =F63+I63+J63 -> 0
D64: LS | E64: 0 | F64: =C64*E64 -> 0 | H64: 0 | I64: =G64*H64 -> 0 | K64: =F64+I64+J64 -> 0
J66: Sub Total | K66: =SUM(K60:K65) -> 0
F67: Material Total | G67: Total Hours | I67: Labor Total | J67: Contractor Total | K67: TOTAL
A68: $ / Sq.Ft | B68: TOTAL DIVISION 31
A69: =K69/E6 -> 0 | F69: =SUM(F13:F24,F60:F65,F52:F56,F29:F48) -> 0 | G69: =SUM(G13:G24,G60:G65,G52:G56,G29:G48) -> 0 | I69: =SUM(I13:I24,I60:I65,I52:I56,I29:I48) -> 0 | J69: =SUM(J13:J24,J60:J65,J52:J56,J29:J48) -> 0 | K69: =SUM(K66,K57,K49,K26) -> 0

Sheet 32
C1: ='Estimate Summary'!C1:H1 -> 0
G5: Exterior Improvements | J5: Schedule
